Workbook

Sheet COGS Item and GL
A1: Item Name | B1: Account Name | C1: Number | D1: Internal ID Prod | E1: Display Name
A2: Advertisement Expenses | B2: 10166 ADVERTISEMENT EXPENSES | C2: =_xlfn.TEXTBEFORE(B2," ") -> 10166 | D2: =VLOOKUP(C2,Sheet1!C:E,2,FALSE) -> 678 | E2: =VLOOKUP(C2,Sheet1!C:E,3,FALSE) -> 10166 OWN ADVERTISING : ADVERTISEMENT EXPENSES | F2: =VLOOKUP(D2,Sheet3!B:C,2,FALSE) -> Expense
A3: Air Cargo Charges - Events | B3: 1040 Air Cargo Charges - Events | C3: =_xlfn.TEXTBEFORE(B3," ") -> 1040 | D3: =VLOOKUP(C3,Sheet1!C:E,2,FALSE) -> 1254 | E3: =VLOOKUP(C3,Sheet1!C:E,3,FALSE) -> 1040 DIRECT REBILLED COSTS (OTHER THAN MEDIA)A : EVENT MNG ORG CHARGES : Air Cargo Charges - Events | F3: =VLOOKUP(D3,Sheet3!B:C,2,FALSE) -> Cost of Goods Sold
A4: Air Fare | B4: 10149 AIR TRAVEL FARE | C4: =_xlfn.TEXTBEFORE(B4," ") -> 10149 | D4: =VLOOKUP(C4,Sheet1!C:E,2,FALSE) -> 661 | E4: =VLOOKUP(C4,Sheet1!C:E,3,FALSE) -> 10149 TRAVEL COSTS : AIR TRAVEL FARE | F4: =VLOOKUP(D4,Sheet3!B:C,2,FALSE) -> Expense
A5: Air Fare - Events | B5: 1042 Air Fare - Events | C5: =_xlfn.TEXTBEFORE(B5," ") -> 1042 | D5: =VLOOKUP(C5,Sheet1!C:E,2,FALSE) -> 1256 | E5: =VLOOKUP(C5,Sheet1!C:E,3,FALSE) -> 1042 DIRECT REBILLED COSTS (OTHER THAN MEDIA)A : EVENT MNG ORG CHARGES : Air Fare - Events | F5: =VLOOKUP(D5,Sheet3!B:C,2,FALSE) -> Cost of Goods Sold
A6: Air Transport | B6: 10149 AIR TRAVEL FARE | C6: =_xlfn.TEXTBEFORE(B6," ") -> 10149 | D6: =VLOOKUP(C6,Sheet1!C:E,2,FALSE) -> 661 | E6: =VLOOKUP(C6,Sheet1!C:E,3,FALSE) -> 10149 TRAVEL COSTS : AIR TRAVEL FARE | F6: =VLOOKUP(D6,Sheet3!B:C,2,FALSE) -> Expense
A7: Air Travel Fare | B7: 10149 AIR TRAVEL FARE | C7: =_xlfn.TEXTBEFORE(B7," ") -> 10149 | D7: =VLOOKUP(C7,Sheet1!C:E,2,FALSE) -> 661 | E7: =VLOOKUP(C7,Sheet1!C:E,3,FALSE) -> 10149 TRAVEL COSTS : AIR TRAVEL FARE | F7: =VLOOKUP(D7,Sheet3!B:C,2,FALSE) -> Expense
A8: Asset Maintainance Charges | B8: 10113 ASSET MAINTAINANCE CHARGES | C8: =_xlfn.TEXTBEFORE(B8," ") -> 10113 | D8: =VLOOKUP(C8,Sheet1!C:E,2,FALSE) -> 625 | E8: =VLOOKUP(C8,Sheet1!C:E,3,FALSE) -> 10113 REAL PROPERTY SERVICE EXPENSES (EXPENSES) / INCOME : ASSET MAINTAINANCE CHARGES | F8: =VLOOKUP(D8,Sheet3!B:C,2,FALSE) -> Expense
A9: Auditors Remuneration | B9: 10120 AUDITORS REMUNERATION | C9: =_xlfn.TEXTBEFORE(B9," ") -> 10120 | D9: =VLOOKUP(C9,Sheet1!C:E,2,FALSE) -> 632 | E9: =VLOOKUP(C9,Sheet1!C:E,3,FALSE) -> 10120 FEES AND SUBSCRIPTION FEES : AUDITORS REMUNERATION | F9: =VLOOKUP(D9,Sheet3!B:C,2,FALSE) -> Expense
A10: Business Development Charges | B10: 1005 Business Development Charges | C10: =_xlfn.TEXTBEFORE(B10," ") -> 1005 | D10: =VLOOKUP(C10,Sheet1!C:E,2,FALSE) -> 1219 | E10: =VLOOKUP(C10,Sheet1!C:E,3,FALSE) -> 1005 DIRECT REBILLED COSTS (OTHER THAN MEDIA)A : EVENT MNG ORG CHARGES : Business Development Charges | F10: =VLOOKUP(D10,Sheet3!B:C,2,FALSE) -> Cost of Goods Sold
A11: Car Hire Charges - Events | B11: 1043 Car Hire Charges - Events | C11: =_xlfn.TEXTBEFORE(B11," ") -> 1043 | D11: =VLOOKUP(C11,Sheet1!C:E,2,FALSE) -> 1257 | E11: =VLOOKUP(C11,Sheet1!C:E,3,FALSE) -> 1043 DIRECT REBILLED COSTS (OTHER THAN MEDIA)A : EVENT MNG ORG CHARGES : Car Hire Charges - Events | F11: =VLOOKUP(D11,Sheet3!B:C,2,FALSE) -> Cost of Goods Sold
A12: Car Hire Expenses | B12: 10152 CAR HIRE EXPENSES | C12: =_xlfn.TEXTBEFORE(B12," ") -> 10152 | D12: =VLOOKUP(C12,Sheet1!C:E,2,FALSE) -> 664 | E12: =VLOOKUP(C12,Sheet1!C:E,3,FALSE) -> 10152 TRAVEL COSTS : CAR HIRE EXPENSES | F12: =VLOOKUP(D12,Sheet3!B:C,2,FALSE) -> Expense
A13: Car Hire Expenses | B13: 10152 CAR HIRE EXPENSES | C13: =_xlfn.TEXTBEFORE(B13," ") -> 10152 | D13: =VLOOKUP(C13,Sheet1!C:E,2,FALSE) -> 664 | E13: =VLOOKUP(C13,Sheet1!C:E,3,FALSE) -> 10152 TRAVEL COSTS : CAR HIRE EXPENSES | F13: =VLOOKUP(D13,Sheet3!B:C,2,FALSE) -> Expense
... A114: Water Charges | B114: 10117 WATER CHARGES | C114: =_xlfn.TEXTBEFORE(B114," ") -> 10117 | D114: =VLOOKUP(C114,Sheet1!C:E,2,FALSE) -> 629 | E114: =VLOOKUP(C114,Sheet1!C:E,3,FALSE) -> 10117 REAL PROPERTY SERVICE EXPENSES (EXPENSES) / INCOME : WATER CHARGES | F114: =VLOOKUP(D114,Sheet3!B:C,2,FALSE) -> Expense

Sheet Income Item and GL
A1: Item Name | B1: Account Name | C1: Internal ID Prod
A2: Sales | B2: EVENT MNG ORG REVENUE | C2: 535
A3: Event Revenue | B3: EVENT MNG ORG REVENUE : Event Revenue | C3: 1215
A4: Inter Office Revenue | B4: EVENT MNG ORG REVENUE : Inter Office Revenue | C4: 1216
A5: Sponsorship Fees | B5: EVENT MNG ORG REVENUE : Sponsorship Revenue | C5: 1244
A6: MISCELLANEOUS EXPENSES WRITTEN OFF | B6: Miscellaneous Expenses Written Off for Sale | C6: 720

Sheet AP & AR GL
A1: Account Name | B1: Internal ID Prod
A2: Account Receivable | B2: 119
A3: Sundry Debtors | B3: 874
A4: Account Paybles | B4: 111
A5: 10530 Accounts Payble | B5: 1040
A6: Advance to Employee | B6: 1454
A7: Loan to Employee | B7: 850 , 853 , 952

Sheet Sheet1
A1: Internal ID | B1: Name | C1: Number | D1: Internal ID | E1: Display Name | F1: Account Type | G1: Description | H1: Balance | I1: Show in Fixed Assets Management | J1: Employee
A2: 111 | B2: Accounts Payable | D2: 111 | E2: Accounts Payable | F2: Accounts Payable | H2: -1.0137171e+09
A3: 434 | B3: ACCOUNTS PAYABLE | C3: P40000 | D3: 434 | E3: P40000 ACCOUNTS PAYABLE | F3: Accounts Payable | H3: 0
A4: 1040 | B4: ACCOUNTS PAYABLE : ACCOUNTS PAYABLE | C4: 10530 | D4: 1040 | E4: 10530 ACCOUNTS PAYABLE : ACCOUNTS PAYABLE | F4: Accounts Payable | H4: -39605554
A5: 1453 | B5: ACCOUNTS PAYABLE : ACCOUNTS PAYABLE : Credit Card Dues (MIS) | C5: 1251 | D5: 1453 | E5: 1251 ACCOUNTS PAYABLE : ACCOUNTS PAYABLE : Credit Card Dues (MIS) | F5: Accounts Payable | H5: 0
A6: 1333 | B6: ACCOUNTS PAYABLE : ACCOUNTS PAYABLE : Executive Advance For Expenses Payable (Mis) | C6: 1119 | D6: 1333 | E6: 1119 ACCOUNTS PAYABLE : ACCOUNTS PAYABLE : Executive Advance For Expenses Payable (Mis) | F6: Accounts Payable | H6: 9599
A7: 1048 | B7: ACCOUNTS PAYABLE : ADVANCE BILLING | C7: 10538 | D7: 1048 | E7: 10538 ACCOUNTS PAYABLE : ADVANCE BILLING | F7: Accounts Payable | H7: 0
A8: 1046 | B8: ACCOUNTS PAYABLE : DEFERRED LEASE RENT LIABILITY | C8: 10536 | D8: 1046 | E8: 10536 ACCOUNTS PAYABLE : DEFERRED LEASE RENT LIABILITY | F8: Accounts Payable | H8: 0
A9: 1042 | B9: ACCOUNTS PAYABLE : OUTSTANDING LIABILITIES | C9: 10532 | D9: 1042 | E9: 10532 ACCOUNTS PAYABLE : OUTSTANDING LIABILITIES | F9: Accounts Payable | H9: 0
A10: 1044 | B10: ACCOUNTS PAYABLE : PROV. FOR BILLS PAYABLE (SHORT IBS) | C10: 10534 | D10: 1044 | E10: 10534 ACCOUNTS PAYABLE : PROV. FOR BILLS PAYABLE (SHORT IBS) | F10: Accounts Payable | H10: 0
A11: 1045 | B11: ACCOUNTS PAYABLE : PROV. FOR COMMISSION/DISCOUNT PAYBLE | C11: 10535 | D11: 1045 | E11: 10535 ACCOUNTS PAYABLE : PROV. FOR COMMISSION/DISCOUNT PAYBLE | F11: Accounts Payable | H11: 0
A12: 1043 | B12: ACCOUNTS PAYABLE : PROV. FOR MANEGEMENT FEES | C12: 10533 | D12: 1043 | E12: 10533 ACCOUNTS PAYABLE : PROV. FOR MANEGEMENT FEES | F12: Accounts Payable | H12: 0
A13: 1041 | B13: ACCOUNTS PAYABLE : PROVISION AGAINST WORK IN PROGRESS | C13: 10531 | D13: 1041 | E13: 10531 ACCOUNTS PAYABLE : PROVISION AGAINST WORK IN PROGRESS | F13: Accounts Payable | H13: 0
A14: 1047 | B14: ACCOUNTS PAYABLE : SUSPENSE ACCOUNT | C14: 10537 | D14: 1047 | E14: 10537 ACCOUNTS PAYABLE : SUSPENSE ACCOUNT | F14: Accounts Payable | H14: 640316.71
A15: 119 | B15: Accounts Receivable | D15: 119 | E15: Accounts Receivable | F15: Accounts Receivable | H15: 1.5241973e+09
A16: 427 | B16: ACCRUED INTEREST ON BANK BORROWINGS | C16: P16887 | D16: 427 | E16: P16887 ACCRUED INTEREST ON BANK BORROWINGS | F16: Other Current Liability | H16: 0
A17: 1032 | B17: ACCRUED INTEREST ON BANK BORROWINGS : ACCRUED INTEREST ON BANK BORROWINGS | C17: 10522 | D17: 1032 | E17: 10522 ACCRUED INTEREST ON BANK BORROWINGS : ACCRUED INTEREST ON BANK BORROWINGS | F17: Other Current Liability | H17: 0
A18: 338 | B18: ACCRUED INTEREST ON OUTSIDE GROUP > 1YEAR | C18: A26781 | D18: 338 | E18: A26781 ACCRUED INTEREST ON OUTSIDE GROUP > 1YEAR | F18: Other Asset | H18: 0
A19: 1214 | B19: ACCRUED INTEREST ON OUTSIDE GROUP > 1YEAR : ACCRUED INTEREST ON OUTSIDE GROUP > 1YEAR | C19: 10337 | D19: 1214 | E19: 10337 ACCRUED INTEREST ON OUTSIDE GROUP > 1YEAR : ACCRUED INTEREST ON OUTSIDE GROUP > 1YEAR | F19: Other Asset | H19: 0
A20: 337 | B20: ACCRUED INTEREST ON OUTSIDE GROUP < 1YEAR | C20: A26780 | D20: 337 | E20: A26780 ACCRUED INTEREST ON OUTSIDE GROUP < 1YEAR | F20: Other Asset | H20: 0
A21: 1213 | B21: ACCRUED INTEREST ON OUTSIDE GROUP < 1YEAR : ACCRUED INTEREST ON OUTSIDE GROUP < 1YEAR | C21: 10336 | D21: 1213 | E21: 10336 ACCRUED INTEREST ON OUTSIDE GROUP < 1YEAR : ACCRUED INTEREST ON OUTSIDE GROUP < 1YEAR | F21: Other Asset | H21: 0
A22: 433 | B22: ACCRUED INTEREST ON OUTSIDE GROUP OVERDRAFT | C22: P51980 | D22: 433 | E22: P51980 ACCRUED INTEREST ON OUTSIDE GROUP OVERDRAFT | F22: Other Current Liability | H22: 0
A23: 1039 | B23: ACCRUED INTEREST ON OUTSIDE GROUP OVERDRAFT : ACCRUED INTEREST ON OUTSIDE GROUP OVERDRAFT | C23: 10529 | D23: 1039 | E23: 10529 ACCRUED INTEREST ON OUTSIDE GROUP OVERDRAFT : ACCRUED INTEREST ON OUTSIDE GROUP OVERDRAFT | F23: Other Current Liability | H23: 0
A24: 112 | B24: Accrued Purchases | D24: 112 | E24: Accrued Purchases | F24: Other Current Liability | H24: 0
A25: 440 | B25: ACCRUED SEVERANCES | C25: P42100 | D25: 440 | E25: P42100 ACCRUED SEVERANCES | F25: Other Current Liability | H25: 0
A26: 1071 | B26: ACCRUED SEVERANCES : ACCRUED SEVERANCES | C26: 10561 | D26: 1071 | E26: 10561 ACCRUED SEVERANCES : ACCRUED SEVERANCES | F26: Other Current Liability | H26: 0
A27: 290 | B27: ACQUISITION COSTS ON INVESTMENTS | C27: R66300 | D27: 290 | E27: R66300 ACQUISITION COSTS ON INVESTMENTS | F27: Expense | H27: 0
A28: 774 | B28: ACQUISITION COSTS ON INVESTMENTS : LOSSES ON FINANCIAL RECEIV AND INVEST SECURITIES | C28: 10262 | D28: 774 | E28: 10262 ACQUISITION COSTS ON INVESTMENTS : LOSSES ON FINANCIAL RECEIV AND INVEST SECURITIES | F28: Expense | H28: 0 | I28: Depreciation Expense,Disposal Cost Account,Write Down Account,Write Off Account
A29: 403 | B29: ACTUARIAL GAINS AND LOSSES | C29: P10602 | D29: 403 | E29: P10602 ACTUARIAL GAINS AND LOSSES | F29: Equity | H29: 0
A30: 1008 | B30: ACTUARIAL GAINS AND LOSSES : ACTUARIAL GAINS AND LOSSES | C30: 10498 | D30: 1008 | E30: 10498 ACTUARIAL GAINS AND LOSSES : ACTUARIAL GAINS AND LOSSES | F30: Equity | H30: 0
A31: 435 | B31: ADVANCE PAYMENTS FROM CLIENTS | C31: P40110 | D31: 435 | E31: P40110 ADVANCE PAYMENTS FROM CLIENTS | F31: Other Current Liability | H31: 0
A32: 1049 | B32: ADVANCE PAYMENTS FROM CLIENTS : ADVANCE RECEIVED FROM DEBTORS | C32: 10539 | D32: 1049 | E32: 10539 ADVANCE PAYMENTS FROM CLIENTS : ADVANCE RECEIVED FROM DEBTORS | F32: Other Current Liability | H32: 0
A33: 2387 | B33: Advance received from debtors | D33: 2387 | E33: Advance received from debtors | F33: Other Current Liability | H33: -3.2819298e+08
A34: 118 | B34: Advances Paid | D34: 118 | E34: Advances Paid | F34: Other Current Asset | H34: -210364
A35: 357 | B35: ADVANCES TO SUPPLIERS | C35: A40910 | D35: 357 | E35: A40910 ADVANCES TO SUPPLIERS | F35: Other Current Liability | H35: 0
A36: 873 | B36: ADVANCES TO SUPPLIERS : ADVANCES TO SUPPLIERS | C36: 10363 | D36: 873 | E36: 10363 ADVANCES TO SUPPLIERS : ADVANCES TO SUPPLIERS | F36: Other Current Liability | H36: 76124396
A37: 378 | B37: ALLOWANCE FOR ADV.SUPPLIERS | C37: A49091 | D37: 378 | E37: A49091 ALLOWANCE FOR ADV.SUPPLIERS | F37: Other Current Asset | H37: 0
A38: 956 | B38: ALLOWANCE FOR ADV.SUPPLIERS : ALLOWANCE FOR ADV.SUPPLIERS | C38: 10446 | D38: 956 | E38: 10446 ALLOWANCE FOR ADV.SUPPLIERS : ALLOWANCE FOR ADV.SUPPLIERS | F38: Other Current Asset | H38: 0
A39: 381 | B39: ALLOWANCE FOR DEFERRED TAX ASSET - DEFERRED DEDUCT. EXP. | C39: A49445 | D39: 381 | E39: A49445 ALLOWANCE FOR DEFERRED TAX ASSET - DEFERRED DEDUCT. EXP. | F39: Other Current Asset | H39: 0
A40: 960 | B40: ALLOWANCE FOR DEFERRED TAX ASSET - DEFERRED DEDUCT. EXP. : ALLOWANCE FOR DEFERRED TAX ASSET - DEFERRED DEDUCT. EXP. | C40: 10450 | D40: 960 | E40: 10450 ALLOWANCE FOR DEFERRED TAX ASSET - DEFERRED DEDUCT. EXP. : ALLOWANCE FOR DEFERRED TAX ASSET - DEFERRED DEDUCT. EXP. | F40: Other Current Asset | H40: 0
A41: 380 | B41: ALLOWANCE FOR DEFERRED TAX ASSET - TAX LOSSES | C41: A49441 | D41: 380 | E41: A49441 ALLOWANCE FOR DEFERRED TAX ASSET - TAX LOSSES | F41: Other Current Asset | H41: 0
A42: 959 | B42: ALLOWANCE FOR DEFERRED TAX ASSET - TAX LOSSES : ALLOWANCE FOR DEFERRED TAX ASSET - TAX LOSSES | C42: 10449 | D42: 959 | E42: 10449 ALLOWANCE FOR DEFERRED TAX ASSET - TAX LOSSES : ALLOWANCE FOR DEFERRED TAX ASSET - TAX LOSSES | F42: Other Current Asset | H42: 0
A43: 259 | B43: AMORT/DEPREC OF INTANGIBLE ASSETS | C43: R68114 | D43: 259 | E43: R68114 AMORT/DEPREC OF INTANGIBLE ASSETS | F43: Expense | H43: 0
A44: 717 | B44: AMORT/DEPREC OF INTANGIBLE ASSETS : DEPRECIATION - INTANGIBLE ASSETS | C44: 10205 | D44: 717 | E44: 10205 AMORT/DEPREC OF INTANGIBLE ASSETS : DEPRECIATION - INTANGIBLE ASSETS | F44: Expense | H44: 282482 | I44: Depreciation Expense,Disposal Cost Account,Write Down Account,Write Off Account
A45: 258 | B45: AMORT/DEPREC OF TANGIBLE ASSETS | C45: R68111 | D45: 258 | E45: R68111 AMORT/DEPREC OF TANGIBLE ASSETS | F45: Expense | H45: 0
A46: 710 | B46: AMORT/DEPREC OF TANGIBLE ASSETS : DEPRECIATION - COMPUTERS | C46: 10198 | D46: 710 | E46: 10198 AMORT/DEPREC OF TANGIBLE ASSETS : DEPRECIATION - COMPUTERS | F46: Expense | H46: 16495177 | I46: Depreciation Expense,Disposal Cost Account,Write Down Account,Write Off Account
A47: 712 | B47: AMORT/DEPREC OF TANGIBLE ASSETS : DEPRECIATION - F&F | C47: 10200 | D47: 712 | E47: 10200 AMORT/DEPREC OF TANGIBLE ASSETS : DEPRECIATION - F&F | F47: Expense | H47: 254208 | I47: Depreciation Expense,Disposal Cost Account,Write Down Account,Write Off Account
A48: 716 | B48: AMORT/DEPREC OF TANGIBLE ASSETS : DEPRECIATION - LEASED VEHICLES | C48: 10204 | D48: 716 | E48: 10204 AMORT/DEPREC OF TANGIBLE ASSETS : DEPRECIATION - LEASED VEHICLES | F48: Expense | H48: 0 | I48: Depreciation Expense,Disposal Cost Account,Write Down Account,Write Off Account
A49: 715 | B49: AMORT/DEPREC OF TANGIBLE ASSETS : DEPRECIATION - LEASEDHOLD IMPROVEMENTS | C49: 10203 | D49: 715 | E49: 10203 AMORT/DEPREC OF TANGIBLE ASSETS : DEPRECIATION - LEASEDHOLD IMPROVEMENTS | F49: Expense | H49: 444815 | I49: Depreciation Expense,Disposal Cost Account,Write Down Account,Write Off Account
A50: 711 | B50: AMORT/DEPREC OF TANGIBLE ASSETS : DEPRECIATION - OFFICE EQPMT | C50: 10199 | D50: 711 | E50: 10199 AMORT/DEPREC OF TANGIBLE ASSETS : DEPRECIATION - OFFICE EQPMT | F50: Expense | H50: 1151869 | I50: Depreciation Expense,Disposal Cost Account,Write Down Account,Write Off Account
A51: 714 | B51: AMORT/DEPREC OF TANGIBLE ASSETS : DEPRECIATION - SOFTWARE | C51: 10202 | D51: 714 | E51: 10202 AMORT/DEPREC OF TANGIBLE ASSETS : DEPRECIATION - SOFTWARE | F51: Expense | H51: 6450 | I51: Depreciation Expense,Disposal Cost Account,Write Down Account,Write Off Account
A52: 713 | B52: AMORT/DEPREC OF TANGIBLE ASSETS : DEPRECIATION - VEHICLES | C52: 10201 | D52: 713 | E52: 10201 AMORT/DEPREC OF TANGIBLE ASSETS : DEPRECIATION - VEHICLES | F52: Expense | H52: 0 | I52: Depreciation Expense,Disposal Cost Account,Write Down Account,Write Off Account
A53: 260 | B53: AMORTIZATION OF DEFERRED EXPENSES | C53: R68120 | D53: 260 | E53: R68120 AMORTIZATION OF DEFERRED EXPENSES | F53: Expense | H53: 0
A54: 718 | B54: AMORTIZATION OF DEFERRED EXPENSES : AMORTIZATION OF DEFERRED EXPENSES | C54: 10206 | D54: 718 | E54: 10206 AMORTIZATION OF DEFERRED EXPENSES : AMORTIZATION OF DEFERRED EXPENSES | F54: Expense | H54: 0 | I54: Depreciation Expense,Disposal Cost Account,Write Down Account,Write Off Account
A55: 363 | B55: ASSETS, WITHHOLDING TAX | C55: A44255 | D55: 363 | E55: A44255 ASSETS, WITHHOLDING TAX | F55: Other Current Asset | H55: 0
A56: 886 | B56: ASSETS, WITHHOLDING TAX : ADVANCE TAX | C56: 10376 | D56: 886 | E56: 10376 ASSETS, WITHHOLDING TAX : ADVANCE TAX | F56: Other Current Asset | H56: 0
A57: 887 | B57: ASSETS, WITHHOLDING TAX : MAT ASSET / LIABILITY | C57: 10377 | D57: 887 | E57: 10377 ASSETS, WITHHOLDING TAX : MAT ASSET / LIABILITY | F57: Other Current Asset | H57: 0
A58: 888 | B58: ASSETS, WITHHOLDING TAX : PROVISION FOR INCOME TAX | C58: 10378 | D58: 888 | E58: 10378 ASSETS, WITHHOLDING TAX : PROVISION FOR INCOME TAX | F58: Other Current Asset | H58: 0
A59: 2328 | B59: ASSETS, WITHHOLDING TAX : PROVISION FOR INCOME TAX : Provision for Income Tax AY 2024-25 | C59: 1274 | D59: 2328 | E59: 1274 ASSETS, WITHHOLDING TAX : PROVISION FOR INCOME TAX : Provision for Income Tax AY 2024-25 | F59: Other Current Asset | H59: 0
A60: 2330 | B60: ASSETS, WITHHOLDING TAX : PROVISION FOR INCOME TAX : Provision for Income Tax AY 2025-26 | C60: 1275 | D60: 2330 | E60: 1275 ASSETS, WITHHOLDING TAX : PROVISION FOR INCOME TAX : Provision for Income Tax AY 2025-26 | F60: Other Current Asset | H60: -66670110
A61: 2403 | B61: ASSETS, WITHHOLDING TAX : PROVISION FOR INCOME TAX : Provision for Income Tax AY 2026-27 | C61: 1320 | D61: 2403 | E61: 1320 ASSETS, WITHHOLDING TAX : PROVISION FOR INCOME TAX : Provision for Income Tax AY 2026-27 | F61: Other Current Asset | H61: -72711000
A62: 884 | B62: ASSETS, WITHHOLDING TAX : TDS ON DIVIDEND | C62: 10374 | D62: 884 | E62: 10374 ASSETS, WITHHOLDING TAX : TDS ON DIVIDEND | F62: Other Current Asset | H62: 0
A63: 882 | B63: ASSETS, WITHHOLDING TAX : TDS ON INTEREST | C63: 10372 | D63: 882 | E63: 10372 ASSETS, WITHHOLDING TAX : TDS ON INTEREST | F63: Other Current Asset | H63: 0
A64: 883 | B64: ASSETS, WITHHOLDING TAX : TDS ON RENT INCOME | C64: 10373 | D64: 883 | E64: 10373 ASSETS, WITHHOLDING TAX : TDS ON RENT INCOME | F64: Other Current Asset | H64: 0
A65: 885 | B65: ASSETS, WITHHOLDING TAX : TDS SUSPENSE ACCOUNT | C65: 10375 | D65: 885 | E65: 10375 ASSETS, WITHHOLDING TAX : TDS SUSPENSE ACCOUNT | F65: Other Current Asset | H65: 0
A66: 255 | B66: BAD DEBTS WRITTEN OFF | C66: R65400 | D66: 255 | E66: R65400 BAD DEBTS WRITTEN OFF | F66: Expense | H66: 0
A67: 698 | B67: BAD DEBTS WRITTEN OFF : BAD DEBTS (WRITTEN OFF) | C67: 10186 | D67: 698 | E67: 10186 BAD DEBTS WRITTEN OFF : BAD DEBTS (WRITTEN OFF) | F67: Expense | H67: 0 | I67: Depreciation Expense,Disposal Cost Account,Write Down Account,Write Off Account
A68: 422 | B68: BANK BORROWINGS > 1 YEAR | C68: P16401 | D68: 422 | E68: P16401 BANK BORROWINGS > 1 YEAR | F68: Long Term Liability | H68: 0
A69: 1026 | B69: BANK BORROWINGS > 1 YEAR : LONG TERM LOAN | C69: 10516 | D69: 1026 | E69: 10516 BANK BORROWINGS > 1 YEAR : LONG TERM LOAN | F69: Long Term Liability | H69: 0
A70: 421 | B70: BANK BORROWINGS < 1 YEAR | C70: P16400 | D70: 421 | E70: P16400 BANK BORROWINGS < 1 YEAR | F70: Other Current Liability | H70: 0
A71: 1025 | B71: BANK BORROWINGS < 1 YEAR : SHORT TERM LOAN | C71: 10515 | D71: 1025 | E71: 10515 BANK BORROWINGS < 1 YEAR : SHORT TERM LOAN | F71: Other Current Liability | H71: 0
A72: 243 | B72: BANK CHARGES | C72: R62700 | D72: 243 | E72: R62700 BANK CHARGES | F72: Expense | H72: 0
A73: 646 | B73: BANK CHARGES : BANK CHARGES | C73: 10134 | D73: 646 | E73: 10134 BANK CHARGES : BANK CHARGES | F73: Expense | H73: 5.9 | I73: Depreciation Expense,Disposal Cost Account,Write Down Account,Write Off Account
A74: 647 | B74: BANK CHARGES : CREDIT CARD CHARGES | C74: 10135 | D74: 647 | E74: 10135 BANK CHARGES : CREDIT CARD CHARGES | F74: Expense | H74: 0
A75: 1267 | B75: BANK CHARGES : CREDIT CARD CHARGES : Card Maintenance Expenses | C75: 1053 | D75: 1267 | E75: 1053 BANK CHARGES : CREDIT CARD CHARGES : Card Maintenance Expenses | F75: Expense | H75: 68304.1 | I75: Depreciation Expense,Disposal Cost Account,Write Down Account,Write Off Account
A76: 648 | B76: BANK CHARGES : TRANSACTION EXPENSES | C76: 10136 | D76: 648 | E76: 10136 BANK CHARGES : TRANSACTION EXPENSES | F76: Expense | H76: 14122 | I76: Depreciation Expense,Disposal Cost Account,Write Down Account,Write Off Account
A77: 2022 | B77: BANK OVERDRAFTS (OUTSIDE GROUP) | C77: P51910 | D77: 2022 | E77: P51910 BANK OVERDRAFTS (OUTSIDE GROUP) | F77: Bank | H77: 0
A78: 2038 | B78: BANK OVERDRAFTS (OUTSIDE GROUP) : BANK OVERDRAFTS (OUTSIDE GROUP) | C78: 10528 | D78: 2038 | E78: 10528 BANK OVERDRAFTS (OUTSIDE GROUP) : BANK OVERDRAFTS (OUTSIDE GROUP) | F78: Bank | H78: 0
A79: 2054 | B79: BANK OVERDRAFTS (OUTSIDE GROUP) : BANK OVERDRAFTS (OUTSIDE GROUP) : BNP 09009120333 00114 | C79: 1117 | D79: 2054 | E79: 1117 BANK OVERDRAFTS (OUTSIDE GROUP) : BANK OVERDRAFTS (OUTSIDE GROUP) : BNP 09009120333 00114 | F79: Bank | H79: 1.5601015e+08
A80: 2055 | B80: BANK OVERDRAFTS (OUTSIDE GROUP) : BANK OVERDRAFTS (OUTSIDE GROUP) : Deutsche Bank Od A/C No.100025436730028 | C80: 1118 | D80: 2055 | E80: 1118 BANK OVERDRAFTS (OUTSIDE GROUP) : BANK OVERDRAFTS (OUTSIDE GROUP) : Deutsche Bank Od A/C No.100025436730028 | F80: Bank | H80: 83379.28
A81: 439 | B81: BONUSES | C81: P42080 | D81: 439 | E81: P42080 BONUSES | F81: Other Current Liability | H81: 0
A82: 232 | B82: BONUSES (WITHOUT SOCIAL CONTRIBUTIONS) | C82: R64110 | D82: 232 | E82: R64110 BONUSES (WITHOUT SOCIAL CONTRIBUTIONS) | F82: Expense | H82: 0
A83: 607 | B83: BONUSES (WITHOUT SOCIAL CONTRIBUTIONS) : BONUS ON EBIT ACHIEVEMENT | C83: 10095 | D83: 607 | E83: 10095 BONUSES (WITHOUT SOCIAL CONTRIBUTIONS) : BONUS ON EBIT ACHIEVEMENT | F83: Expense | H83: 16445192 | I83: Depreciation Expense,Disposal Cost Account,Write Down Account,Write Off Account
A84: 1070 | B84: BONUSES : BONUS POOL | C84: 10560 | D84: 1070 | E84: 10560 BONUSES : BONUS POOL | F84: Other Current Liability | H84: 0
A85: 1069 | B85: BONUSES : INCENTIVE PAYABLE TO STAFF | C85: 10559 | D85: 1069 | E85: 10559 BONUSES : INCENTIVE PAYABLE TO STAFF | F85: Other Current Liability | H85: 0
A86: 279 | B86: BOOK VALUE OF OTHER FINANCIAL ASSETS SOLD | C86: R67580 | D86: 279 | E86: R67580 BOOK VALUE OF OTHER FINANCIAL ASSETS SOLD | F86: Expense | H86: 0
A87: 745 | B87: BOOK VALUE OF OTHER FINANCIAL ASSETS SOLD : GROSS VALUE OF OTHER FINANCIAL ASSETS SOLD | C87: 10233 | D87: 745 | E87: 10233 BOOK VALUE OF OTHER FINANCIAL ASSETS SOLD : GROSS VALUE OF OTHER FINANCIAL ASSETS SOLD | F87: Expense | H87: 0 | I87: Depreciation Expense,Disposal Cost Account,Write Down Account,Write Off Account
A88: 744 | B88: BOOK VALUE OF OTHER FINANCIAL ASSETS SOLD : SECURITY RECEIVABLE | C88: 10232 | D88: 744 | E88: 10232 BOOK VALUE OF OTHER FINANCIAL ASSETS SOLD : SECURITY RECEIVABLE | F88: Expense | H88: 0 | I88: Depreciation Expense,Disposal Cost Account,Write Down Account,Write Off Account
A89: 325 | B89: BUILDINGS FIXTURES AND FITTINGS ON FREEHOLD LAND | C89: A21650 | D89: 325 | E89: A21650 BUILDINGS FIXTURES AND FITTINGS ON FREEHOLD LAND | F89: Fixed Asset | H89: 0
A90: 825 | B90: BUILDINGS FIXTURES AND FITTINGS ON FREEHOLD LAND : BUILDINGS FIXTURES AND FITTINGS ON FREEHOLD LAND | C90: 10313 | D90: 825 | E90: 10313 BUILDINGS FIXTURES AND FITTINGS ON FREEHOLD LAND : BUILDINGS FIXTURES AND FITTINGS ON FREEHOLD LAND | F90: Fixed Asset | H90: 0 | I90: Asset Account,Depreciation Account,Write Down Account,Write Off Account
A91: 324 | B91: BUILDINGS FIXTURES AND FITTINGS ON NON FREEHOLD LAND | C91: A21600 | D91: 324 | E91: A21600 BUILDINGS FIXTURES AND FITTINGS ON NON FREEHOLD LAND | F91: Fixed Asset | H91: 0
A92: 824 | B92: BUILDINGS FIXTURES AND FITTINGS ON NON FREEHOLD LAND : FURNITURE & FIXTURES | C92: 10312 | D92: 824 | E92: 10312 BUILDINGS FIXTURES AND FITTINGS ON NON FREEHOLD LAND : FURNITURE & FIXTURES | F92: Fixed Asset | H92: 0 | I92: Asset Account,Depreciation Account,Write Down Account,Write Off Account
A93: 823 | B93: BUILDINGS FIXTURES AND FITTINGS ON NON FREEHOLD LAND : LEASEHOLD IMPROVEMENTS | C93: 10311 | D93: 823 | E93: 10311 BUILDINGS FIXTURES AND FITTINGS ON NON FREEHOLD LAND : LEASEHOLD IMPROVEMENTS | F93: Fixed Asset | H93: 4895412 | I93: Asset Account,Depreciation Account,Write Down Account,Write Off Account
A94: 2398 | B94: BUILDINGS FIXTURES AND FITTINGS ON NON FREEHOLD LAND : LEASEHOLD IMPROVEMENTS : Leasehold Improvements GL | C94: 1315 | D94: 2398 | E94: 1315 BUILDINGS FIXTURES AND FITTINGS ON NON FREEHOLD LAND : LEASEHOLD IMPROVEMENTS : Leasehold Improvements GL | F94: Fixed Asset | H94: 2719556
A95: 2021 | B95: CASH AT BANK (OUTSIDE GROUP) | C95: A51000 | D95: 2021 | E95: A51000 CASH AT BANK (OUTSIDE GROUP) | F95: Bank | H95: 0
A96: 2032 | B96: CASH AT BANK (OUTSIDE GROUP) : ANZ BANK | C96: 10471 | D96: 2032 | E96: 10471 CASH AT BANK (OUTSIDE GROUP) : ANZ BANK | F96: Bank | H96: 0
A97: 2033 | B97: CASH AT BANK (OUTSIDE GROUP) : AXIS BANK | C97: 10472 | D97: 2033 | E97: 10472 CASH AT BANK (OUTSIDE GROUP) : AXIS BANK | F97: Bank | H97: 0
A98: 2024 | B98: CASH AT BANK (OUTSIDE GROUP) : BNP PARIBAS | C98: 10463 | D98: 2024 | E98: 10463 CASH AT BANK (OUTSIDE GROUP) : BNP PARIBAS | F98: Bank | H98: 0
A99: 2041 | B99: CASH AT BANK (OUTSIDE GROUP) : BNP PARIBAS : Bnp Dividend A/C 09009 121310 001 48 | C99: 1104 | D99: 2041 | E99: 1104 CASH AT BANK (OUTSIDE GROUP) : BNP PARIBAS : Bnp Dividend A/C 09009 121310 001 48 | F99: Bank | H99: 0
A100: 2027 | B100: CASH AT BANK (OUTSIDE GROUP) : CENTRAL BANK OF INDIA | C100: 10466 | D100: 2027 | E100: 10466 CASH AT BANK (OUTSIDE GROUP) : CENTRAL BANK OF INDIA | F100: Bank | H100: 0
...

Sheet Sheet2
A1: Internal ID Prod
A2: 678
A3: 1254
A4: 661
A5: 1256
A6: 661
A7: 661
A8: 625
A9: 632
A10: 1219
A11: 1257
A12: 664
A13: 664
... A127: 952

Sheet Sheet3
A1: Internal ID | B1: Internal ID | C1: Account Type | D1: Name | E1: Display Name | F1: Account Type | G1: Description | H1: Balance | I1: Show in Fixed Assets Management | J1: Employee
A2: 111 | B2: 111 | C2: Accounts Payable | D2: Accounts Payable | E2: Accounts Payable | F2: Accounts Payable | H2: -1.0136452e+09
A3: 434 | B3: 434 | C3: Accounts Payable | D3: ACCOUNTS PAYABLE | E3: P40000 ACCOUNTS PAYABLE | F3: Accounts Payable | H3: 0
A4: 1040 | B4: 1040 | C4: Accounts Payable | D4: ACCOUNTS PAYABLE : ACCOUNTS PAYABLE | E4: 10530 ACCOUNTS PAYABLE : ACCOUNTS PAYABLE | F4: Accounts Payable | H4: -39780508
A5: 1453 | B5: 1453 | C5: Accounts Payable | D5: ACCOUNTS PAYABLE : ACCOUNTS PAYABLE : Credit Card Dues (MIS) | E5: 1251 ACCOUNTS PAYABLE : ACCOUNTS PAYABLE : Credit Card Dues (MIS) | F5: Accounts Payable | H5: 0
A6: 1333 | B6: 1333 | C6: Accounts Payable | D6: ACCOUNTS PAYABLE : ACCOUNTS PAYABLE : Executive Advance For Expenses Payable (Mis) | E6: 1119 ACCOUNTS PAYABLE : ACCOUNTS PAYABLE : Executive Advance For Expenses Payable (Mis) | F6: Accounts Payable | H6: 9599
A7: 1048 | B7: 1048 | C7: Accounts Payable | D7: ACCOUNTS PAYABLE : ADVANCE BILLING | E7: 10538 ACCOUNTS PAYABLE : ADVANCE BILLING | F7: Accounts Payable | H7: 0
A8: 1046 | B8: 1046 | C8: Accounts Payable | D8: ACCOUNTS PAYABLE : DEFERRED LEASE RENT LIABILITY | E8: 10536 ACCOUNTS PAYABLE : DEFERRED LEASE RENT LIABILITY | F8: Accounts Payable | H8: 0
A9: 1042 | B9: 1042 | C9: Accounts Payable | D9: ACCOUNTS PAYABLE : OUTSTANDING LIABILITIES | E9: 10532 ACCOUNTS PAYABLE : OUTSTANDING LIABILITIES | F9: Accounts Payable | H9: 0
A10: 1044 | B10: 1044 | C10: Accounts Payable | D10: ACCOUNTS PAYABLE : PROV. FOR BILLS PAYABLE (SHORT IBS) | E10: 10534 ACCOUNTS PAYABLE : PROV. FOR BILLS PAYABLE (SHORT IBS) | F10: Accounts Payable | H10: 0
A11: 1045 | B11: 1045 | C11: Accounts Payable | D11: ACCOUNTS PAYABLE : PROV. FOR COMMISSION/DISCOUNT PAYBLE | E11: 10535 ACCOUNTS PAYABLE : PROV. FOR COMMISSION/DISCOUNT PAYBLE | F11: Accounts Payable | H11: 0
A12: 1043 | B12: 1043 | C12: Accounts Payable | D12: ACCOUNTS PAYABLE : PROV. FOR MANEGEMENT FEES | E12: 10533 ACCOUNTS PAYABLE : PROV. FOR MANEGEMENT FEES | F12: Accounts Payable | H12: 0
A13: 1041 | B13: 1041 | C13: Accounts Payable | D13: ACCOUNTS PAYABLE : PROVISION AGAINST WORK IN PROGRESS | E13: 10531 ACCOUNTS PAYABLE : PROVISION AGAINST WORK IN PROGRESS | F13: Accounts Payable | H13: 0
... A27: 290 | B27: 290 | C27: Expense | D27: ACQUISITION COSTS ON INVESTMENTS | E27: R66300 ACQUISITION COSTS ON INVESTMENTS | F27: Expense | H27: 0
A28: 774 | B28: 774 | C28: Expense | D28: ACQUISITION COSTS ON INVESTMENTS : LOSSES ON FINANCIAL RECEIV AND INVEST SECURITIES | E28: 10262 ACQUISITION COSTS ON INVESTMENTS : LOSSES ON FINANCIAL RECEIV AND INVEST SECURITIES | F28: Expense | H28: 0 | I28: Depreciation Expense,Disposal Cost Account,Write Down Account,Write Off Account
A29: 403 | B29: 403 | C29: Equity | D29: ACTUARIAL GAINS AND LOSSES | E29: P10602 ACTUARIAL GAINS AND LOSSES | F29: Equity | H29: 0
A30: 1008 | B30: 1008 | C30: Equity | D30: ACTUARIAL GAINS AND LOSSES : ACTUARIAL GAINS AND LOSSES | E30: 10498 ACTUARIAL GAINS AND LOSSES : ACTUARIAL GAINS AND LOSSES | F30: Equity | H30: 0
A31: 435 | B31: 435 | C31: Other Current Liability | D31: ADVANCE PAYMENTS FROM CLIENTS | E31: P40110 ADVANCE PAYMENTS FROM CLIENTS | F31: Other Current Liability | H31: 0
A32: 1049 | B32: 1049 | C32: Other Current Liability | D32: ADVANCE PAYMENTS FROM CLIENTS : ADVANCE RECEIVED FROM DEBTORS | E32: 10539 ADVANCE PAYMENTS FROM CLIENTS : ADVANCE RECEIVED FROM DEBTORS | F32: Other Current Liability | H32: 0
A33: 2387 | B33: 2387 | C33: Other Current Liability | D33: Advance received from debtors | E33: Advance received from debtors | F33: Other Current Liability | H33: -3.4158146e+08
A34: 118 | B34: 118 | C34: Other Current Asset | D34: Advances Paid | E34: Advances Paid | F34: Other Current Asset | H34: -210364
A35: 357 | B35: 357 | C35: Other Current Liability | D35: ADVANCES TO SUPPLIERS | E35: A40910 ADVANCES TO SUPPLIERS | F35: Other Current Liability | H35: 0
A36: 873 | B36: 873 | C36: Other Current Liability | D36: ADVANCES TO SUPPLIERS : ADVANCES TO SUPPLIERS | E36: 10363 ADVANCES TO SUPPLIERS : ADVANCES TO SUPPLIERS | F36: Other Current Liability | H36: 76124396
A37: 378 | B37: 378 | C37: Other Current Asset | D37: ALLOWANCE FOR ADV.SUPPLIERS | E37: A49091 ALLOWANCE FOR ADV.SUPPLIERS | F37: Other Current Asset | H37: 0
A38: 956 | B38: 956 | C38: Other Current Asset | D38: ALLOWANCE FOR ADV.SUPPLIERS : ALLOWANCE FOR ADV.SUPPLIERS | E38: 10446 ALLOWANCE FOR ADV.SUPPLIERS : ALLOWANCE FOR ADV.SUPPLIERS | F38: Other Current Asset | H38: 0
A39: 381 | B39: 381 | C39: Other Current Asset | D39: ALLOWANCE FOR DEFERRED TAX ASSET - DEFERRED DEDUCT. EXP. | E39: A49445 ALLOWANCE FOR DEFERRED TAX ASSET - DEFERRED DEDUCT. EXP. | F39: Other Current Asset | H39: 0
A40: 960 | B40: 960 | C40: Other Current Asset | D40: ALLOWANCE FOR DEFERRED TAX ASSET - DEFERRED DEDUCT. EXP. : ALLOWANCE FOR DEFERRED TAX ASSET - DEFERRED DEDUCT. EXP. | E40: 10450 ALLOWANCE FOR DEFERRED TAX ASSET - DEFERRED DEDUCT. EXP. : ALLOWANCE FOR DEFERRED TAX ASSET - DEFERRED DEDUCT. EXP. | F40: Other Current Asset | H40: 0
... A43: 259 | B43: 259 | C43: Expense | D43: AMORT/DEPREC OF INTANGIBLE ASSETS | E43: R68114 AMORT/DEPREC OF INTANGIBLE ASSETS | F43: Expense | H43: 0
A44: 717 | B44: 717 | C44: Expense | D44: AMORT/DEPREC OF INTANGIBLE ASSETS : DEPRECIATION - INTANGIBLE ASSETS | E44: 10205 AMORT/DEPREC OF INTANGIBLE ASSETS : DEPRECIATION - INTANGIBLE ASSETS | F44: Expense | H44: 282482 | I44: Depreciation Expense,Disposal Cost Account,Write Down Account,Write Off Account
A45: 258 | B45: 258 | C45: Expense | D45: AMORT/DEPREC OF TANGIBLE ASSETS | E45: R68111 AMORT/DEPREC OF TANGIBLE ASSETS | F45: Expense | H45: 0
A46: 710 | B46: 710 | C46: Expense | D46: AMORT/DEPREC OF TANGIBLE ASSETS : DEPRECIATION - COMPUTERS | E46: 10198 AMORT/DEPREC OF TANGIBLE ASSETS : DEPRECIATION - COMPUTERS | F46: Expense | H46: 16495177 | I46: Depreciation Expense,Disposal Cost Account,Write Down Account,Write Off Account
A47: 712 | B47: 712 | C47: Expense | D47: AMORT/DEPREC OF TANGIBLE ASSETS : DEPRECIATION - F&F | E47: 10200 AMORT/DEPREC OF TANGIBLE ASSETS : DEPRECIATION - F&F | F47: Expense | H47: 254208 | I47: Depreciation Expense,Disposal Cost Account,Write Down Account,Write Off Account
A48: 716 | B48: 716 | C48: Expense | D48: AMORT/DEPREC OF TANGIBLE ASSETS : DEPRECIATION - LEASED VEHICLES | E48: 10204 AMORT/DEPREC OF TANGIBLE ASSETS : DEPRECIATION - LEASED VEHICLES | F48: Expense | H48: 0 | I48: Depreciation Expense,Disposal Cost Account,Write Down Account,Write Off Account
A49: 715 | B49: 715 | C49: Expense | D49: AMORT/DEPREC OF TANGIBLE ASSETS : DEPRECIATION - LEASEDHOLD IMPROVEMENTS | E49: 10203 AMORT/DEPREC OF TANGIBLE ASSETS : DEPRECIATION - LEASEDHOLD IMPROVEMENTS | F49: Expense | H49: 444815 | I49: Depreciation Expense,Disposal Cost Account,Write Down Account,Write Off Account
A50: 711 | B50: 711 | C50: Expense | D50: AMORT/DEPREC OF TANGIBLE ASSETS : DEPRECIATION - OFFICE EQPMT | E50: 10199 AMORT/DEPREC OF TANGIBLE ASSETS : DEPRECIATION - OFFICE EQPMT | F50: Expense | H50: 1151869 | I50: Depreciation Expense,Disposal Cost Account,Write Down Account,Write Off Account
A51: 714 | B51: 714 | C51: Expense | D51: AMORT/DEPREC OF TANGIBLE ASSETS : DEPRECIATION - SOFTWARE | E51: 10202 AMORT/DEPREC OF TANGIBLE ASSETS : DEPRECIATION - SOFTWARE | F51: Expense | H51: 6450 | I51: Depreciation Expense,Disposal Cost Account,Write Down Account,Write Off Account
A52: 713 | B52: 713 | C52: Expense | D52: AMORT/DEPREC OF TANGIBLE ASSETS : DEPRECIATION - VEHICLES | E52: 10201 AMORT/DEPREC OF TANGIBLE ASSETS : DEPRECIATION - VEHICLES | F52: Expense | H52: 0 | I52: Depreciation Expense,Disposal Cost Account,Write Down Account,Write Off Account
A53: 260 | B53: 260 | C53: Expense | D53: AMORTIZATION OF DEFERRED EXPENSES | E53: R68120 AMORTIZATION OF DEFERRED EXPENSES | F53: Expense | H53: 0
A54: 718 | B54: 718 | C54: Expense | D54: AMORTIZATION OF DEFERRED EXPENSES : AMORTIZATION OF DEFERRED EXPENSES | E54: 10206 AMORTIZATION OF DEFERRED EXPENSES : AMORTIZATION OF DEFERRED EXPENSES | F54: Expense | H54: 0 | I54: Depreciation Expense,Disposal Cost Account,Write Down Account,Write Off Account
A55: 363 | B55: 363 | C55: Other Current Asset | D55: ASSETS, WITHHOLDING TAX | E55: A44255 ASSETS, WITHHOLDING TAX | F55: Other Current Asset | H55: 0
A56: 886 | B56: 886 | C56: Other Current Asset | D56: ASSETS, WITHHOLDING TAX : ADVANCE TAX | E56: 10376 ASSETS, WITHHOLDING TAX : ADVANCE TAX | F56: Other Current Asset | H56: 0
A57: 887 | B57: 887 | C57: Other Current Asset | D57: ASSETS, WITHHOLDING TAX : MAT ASSET / LIABILITY | E57: 10377 ASSETS, WITHHOLDING TAX : MAT ASSET / LIABILITY | F57: Other Current Asset | H57: 0
A58: 888 | B58: 888 | C58: Other Current Asset | D58: ASSETS, WITHHOLDING TAX : PROVISION FOR INCOME TAX | E58: 10378 ASSETS, WITHHOLDING TAX : PROVISION FOR INCOME TAX | F58: Other Current Asset | H58: 0
A59: 2328 | B59: 2328 | C59: Other Current Asset | D59: ASSETS, WITHHOLDING TAX : PROVISION FOR INCOME TAX : Provision for Income Tax AY 2024-25 | E59: 1274 ASSETS, WITHHOLDING TAX : PROVISION FOR INCOME TAX : Provision for Income Tax AY 2024-25 | F59: Other Current Asset | H59: 0
A60: 2330 | B60: 2330 | C60: Other Current Asset | D60: ASSETS, WITHHOLDING TAX : PROVISION FOR INCOME TAX : Provision for Income Tax AY 2025-26 | E60: 1275 ASSETS, WITHHOLDING TAX : PROVISION FOR INCOME TAX : Provision for Income Tax AY 2025-26 | F60: Other Current Asset | H60: -66670110
A61: 2403 | B61: 2403 | C61: Other Current Asset | D61: ASSETS, WITHHOLDING TAX : PROVISION FOR INCOME TAX : Provision for Income Tax AY 2026-27 | E61: 1320 ASSETS, WITHHOLDING TAX : PROVISION FOR INCOME TAX : Provision for Income Tax AY 2026-27 | F61: Other Current Asset | H61: -72711000
A62: 884 | B62: 884 | C62: Other Current Asset | D62: ASSETS, WITHHOLDING TAX : TDS ON DIVIDEND | E62: 10374 ASSETS, WITHHOLDING TAX : TDS ON DIVIDEND | F62: Other Current Asset | H62: 0
A63: 882 | B63: 882 | C63: Other Current Asset | D63: ASSETS, WITHHOLDING TAX : TDS ON INTEREST | E63: 10372 ASSETS, WITHHOLDING TAX : TDS ON INTEREST | F63: Other Current Asset | H63: 0
A64: 883 | B64: 883 | C64: Other Current Asset | D64: ASSETS, WITHHOLDING TAX : TDS ON RENT INCOME | E64: 10373 ASSETS, WITHHOLDING TAX : TDS ON RENT INCOME | F64: Other Current Asset | H64: 0
A65: 885 | B65: 885 | C65: Other Current Asset | D65: ASSETS, WITHHOLDING TAX : TDS SUSPENSE ACCOUNT | E65: 10375 ASSETS, WITHHOLDING TAX : TDS SUSPENSE ACCOUNT | F65: Other Current Asset | H65: 0
A66: 255 | B66: 255 | C66: Expense | D66: BAD DEBTS WRITTEN OFF | E66: R65400 BAD DEBTS WRITTEN OFF | F66: Expense | H66: 0
A67: 698 | B67: 698 | C67: Expense | D67: BAD DEBTS WRITTEN OFF : BAD DEBTS (WRITTEN OFF) | E67: 10186 BAD DEBTS WRITTEN OFF : BAD DEBTS (WRITTEN OFF) | F67: Expense | H67: 0 | I67: Depreciation Expense,Disposal Cost Account,Write Down Account,Write Off Account
A68: 422 | B68: 422 | C68: Long Term Liability | D68: BANK BORROWINGS > 1 YEAR | E68: P16401 BANK BORROWINGS > 1 YEAR | F68: Long Term Liability | H68: 0
A69: 1026 | B69: 1026 | C69: Long Term Liability | D69: BANK BORROWINGS > 1 YEAR : LONG TERM LOAN | E69: 10516 BANK BORROWINGS > 1 YEAR : LONG TERM LOAN | F69: Long Term Liability | H69: 0
A70: 421 | B70: 421 | C70: Other Current Liability | D70: BANK BORROWINGS < 1 YEAR | E70: P16400 BANK BORROWINGS < 1 YEAR | F70: Other Current Liability | H70: 0
A71: 1025 | B71: 1025 | C71: Other Current Liability | D71: BANK BORROWINGS < 1 YEAR : SHORT TERM LOAN | E71: 10515 BANK BORROWINGS < 1 YEAR : SHORT TERM LOAN | F71: Other Current Liability | H71: 0
A72: 243 | B72: 243 | C72: Expense | D72: BANK CHARGES | E72: R62700 BANK CHARGES | F72: Expense | H72: 0
A73: 646 | B73: 646 | C73: Expense | D73: BANK CHARGES : BANK CHARGES | E73: 10134 BANK CHARGES : BANK CHARGES | F73: Expense | H73: 5.9 | I73: Depreciation Expense,Disposal Cost Account,Write Down Account,Write Off Account
A74: 647 | B74: 647 | C74: Expense | D74: BANK CHARGES : CREDIT CARD CHARGES | E74: 10135 BANK CHARGES : CREDIT CARD CHARGES | F74: Expense | H74: 0
A75: 1267 | B75: 1267 | C75: Expense | D75: BANK CHARGES : CREDIT CARD CHARGES : Card Maintenance Expenses | E75: 1053 BANK CHARGES : CREDIT CARD CHARGES : Card Maintenance Expenses | F75: Expense | H75: 68304.1 | I75: Depreciation Expense,Disposal Cost Account,Write Down Account,Write Off Account
A76: 648 | B76: 648 | C76: Expense | D76: BANK CHARGES : TRANSACTION EXPENSES | E76: 10136 BANK CHARGES : TRANSACTION EXPENSES | F76: Expense | H76: 14122 | I76: Depreciation Expense,Disposal Cost Account,Write Down Account,Write Off Account
A77: 2022 | B77: 2022 | C77: Bank | D77: BANK OVERDRAFTS (OUTSIDE GROUP) | E77: P51910 BANK OVERDRAFTS (OUTSIDE GROUP) | F77: Bank | H77: 0
A78: 2038 | B78: 2038 | C78: Bank | D78: BANK OVERDRAFTS (OUTSIDE GROUP) : BANK OVERDRAFTS (OUTSIDE GROUP) | E78: 10528 BANK OVERDRAFTS (OUTSIDE GROUP) : BANK OVERDRAFTS (OUTSIDE GROUP) | F78: Bank | H78: 0
A79: 2054 | B79: 2054 | C79: Bank | D79: BANK OVERDRAFTS (OUTSIDE GROUP) : BANK OVERDRAFTS (OUTSIDE GROUP) : BNP 09009120333 00114 | E79: 1117 BANK OVERDRAFTS (OUTSIDE GROUP) : BANK OVERDRAFTS (OUTSIDE GROUP) : BNP 09009120333 00114 | F79: Bank | H79: 1.7167167e+08
A80: 2055 | B80: 2055 | C80: Bank | D80: BANK OVERDRAFTS (OUTSIDE GROUP) : BANK OVERDRAFTS (OUTSIDE GROUP) : Deutsche Bank Od A/C No.100025436730028 | E80: 1118 BANK OVERDRAFTS (OUTSIDE GROUP) : BANK OVERDRAFTS (OUTSIDE GROUP) : Deutsche Bank Od A/C No.100025436730028 | F80: Bank | H80: 83379.28
A81: 439 | B81: 439 | C81: Other Current Liability | D81: BONUSES | E81: P42080 BONUSES | F81: Other Current Liability | H81: 0
A82: 232 | B82: 232 | C82: Expense | D82: BONUSES (WITHOUT SOCIAL CONTRIBUTIONS) | E82: R64110 BONUSES (WITHOUT SOCIAL CONTRIBUTIONS) | F82: Expense | H82: 0
A83: 607 | B83: 607 | C83: Expense | D83: BONUSES (WITHOUT SOCIAL CONTRIBUTIONS) : BONUS ON EBIT ACHIEVEMENT | E83: 10095 BONUSES (WITHOUT SOCIAL CONTRIBUTIONS) : BONUS ON EBIT ACHIEVEMENT | F83: Expense | H83: 16445192 | I83: Depreciation Expense,Disposal Cost Account,Write Down Account,Write Off Account
A84: 1070 | B84: 1070 | C84: Other Current Liability | D84: BONUSES : BONUS POOL | E84: 10560 BONUSES : BONUS POOL | F84: Other Current Liability | H84: 0
A85: 1069 | B85: 1069 | C85: Other Current Liability | D85: BONUSES : INCENTIVE PAYABLE TO STAFF | E85: 10559 BONUSES : INCENTIVE PAYABLE TO STAFF | F85: Other Current Liability | H85: 0
A86: 279 | B86: 279 | C86: Expense | D86: BOOK VALUE OF OTHER FINANCIAL ASSETS SOLD | E86: R67580 BOOK VALUE OF OTHER FINANCIAL ASSETS SOLD | F86: Expense | H86: 0
A87: 745 | B87: 745 | C87: Expense | D87: BOOK VALUE OF OTHER FINANCIAL ASSETS SOLD : GROSS VALUE OF OTHER FINANCIAL ASSETS SOLD | E87: 10233 BOOK VALUE OF OTHER FINANCIAL ASSETS SOLD : GROSS VALUE OF OTHER FINANCIAL ASSETS SOLD | F87: Expense | H87: 0 | I87: Depreciation Expense,Disposal Cost Account,Write Down Account,Write Off Account
A88: 744 | B88: 744 | C88: Expense | D88: BOOK VALUE OF OTHER FINANCIAL ASSETS SOLD : SECURITY RECEIVABLE | E88: 10232 BOOK VALUE OF OTHER FINANCIAL ASSETS SOLD : SECURITY RECEIVABLE | F88: Expense | H88: 0 | I88: Depreciation Expense,Disposal Cost Account,Write Down Account,Write Off Account
A89: 325 | B89: 325 | C89: Fixed Asset | D89: BUILDINGS FIXTURES AND FITTINGS ON FREEHOLD LAND | E89: A21650 BUILDINGS FIXTURES AND FITTINGS ON FREEHOLD LAND | F89: Fixed Asset | H89: 0
A90: 825 | B90: 825 | C90: Fixed Asset | D90: BUILDINGS FIXTURES AND FITTINGS ON FREEHOLD LAND : BUILDINGS FIXTURES AND FITTINGS ON FREEHOLD LAND | E90: 10313 BUILDINGS FIXTURES AND FITTINGS ON FREEHOLD LAND : BUILDINGS FIXTURES AND FITTINGS ON FREEHOLD LAND | F90: Fixed Asset | H90: 0 | I90: Asset Account,Depreciation Account,Write Down Account,Write Off Account
A91: 324 | B91: 324 | C91: Fixed Asset | D91: BUILDINGS FIXTURES AND FITTINGS ON NON FREEHOLD LAND | E91: A21600 BUILDINGS FIXTURES AND FITTINGS ON NON FREEHOLD LAND | F91: Fixed Asset | H91: 0
A92: 824 | B92: 824 | C92: Fixed Asset | D92: BUILDINGS FIXTURES AND FITTINGS ON NON FREEHOLD LAND : FURNITURE & FIXTURES | E92: 10312 BUILDINGS FIXTURES AND FITTINGS ON NON FREEHOLD LAND : FURNITURE & FIXTURES | F92: Fixed Asset | H92: 0 | I92: Asset Account,Depreciation Account,Write Down Account,Write Off Account
A93: 823 | B93: 823 | C93: Fixed Asset | D93: BUILDINGS FIXTURES AND FITTINGS ON NON FREEHOLD LAND : LEASEHOLD IMPROVEMENTS | E93: 10311 BUILDINGS FIXTURES AND FITTINGS ON NON FREEHOLD LAND : LEASEHOLD IMPROVEMENTS | F93: Fixed Asset | H93: 4895412 | I93: Asset Account,Depreciation Account,Write Down Account,Write Off Account
A94: 2398 | B94: 2398 | C94: Fixed Asset | D94: BUILDINGS FIXTURES AND FITTINGS ON NON FREEHOLD LAND : LEASEHOLD IMPROVEMENTS : Leasehold Improvements GL | E94: 1315 BUILDINGS FIXTURES AND FITTINGS ON NON FREEHOLD LAND : LEASEHOLD IMPROVEMENTS : Leasehold Improvements GL | F94: Fixed Asset | H94: 2719556
A95: 2021 | B95: 2021 | C95: Bank | D95: CASH AT BANK (OUTSIDE GROUP) | E95: A51000 CASH AT BANK (OUTSIDE GROUP) | F95: Bank | H95: 0
A96: 2032 | B96: 2032 | C96: Bank | D96: CASH AT BANK (OUTSIDE GROUP) : ANZ BANK | E96: 10471 CASH AT BANK (OUTSIDE GROUP) : ANZ BANK | F96: Bank | H96: 0
A97: 2033 | B97: 2033 | C97: Bank | D97: CASH AT BANK (OUTSIDE GROUP) : AXIS BANK | E97: 10472 CASH AT BANK (OUTSIDE GROUP) : AXIS BANK | F97: Bank | H97: 0
A98: 2024 | B98: 2024 | C98: Bank | D98: CASH AT BANK (OUTSIDE GROUP) : BNP PARIBAS | E98: 10463 CASH AT BANK (OUTSIDE GROUP) : BNP PARIBAS | F98: Bank | H98: 0
A99: 2041 | B99: 2041 | C99: Bank | D99: CASH AT BANK (OUTSIDE GROUP) : BNP PARIBAS : Bnp Dividend A/C 09009 121310 001 48 | E99: 1104 CASH AT BANK (OUTSIDE GROUP) : BNP PARIBAS : Bnp Dividend A/C 09009 121310 001 48 | F99: Bank | H99: 0
A100: 2027 | B100: 2027 | C100: Bank | D100: CASH AT BANK (OUTSIDE GROUP) : CENTRAL BANK OF INDIA | E100: 10466 CASH AT BANK (OUTSIDE GROUP) : CENTRAL BANK OF INDIA | F100: Bank | H100: 0
A101: 2031 | B101: 2031 | C101: Bank | D101: CASH AT BANK (OUTSIDE GROUP) : CITIBANK | E101: 10470 CASH AT BANK (OUTSIDE GROUP) : CITIBANK | F101: Bank | H101: 0
A102: 2361 | B102: 2361 | C102: Bank | D102: CASH AT BANK (OUTSIDE GROUP) : Credit Card Bank | E102: 10604 CASH AT BANK (OUTSIDE GROUP) : Credit Card Bank | F102: Bank | H102: 0
A103: 2362 | B103: 2362 | C103: Bank | D103: CASH AT BANK (OUTSIDE GROUP) : Credit Card Bank : American Express Centurian Card (CC) | E103: 1281 CASH AT BANK (OUTSIDE GROUP) : Credit Card Bank : American Express Centurian Card (CC) | F103: Bank | H103: -13640627
A104: 2363 | B104: 2363 | C104: Bank | D104: CASH AT BANK (OUTSIDE GROUP) : Credit Card Bank : HDFC Corporate Card (CC) | E104: 1282 CASH AT BANK (OUTSIDE GROUP) : Credit Card Bank : HDFC Corporate Card (CC) | F104: Bank | H104: -2713989
A105: 2364 | B105: 2364 | C105: Bank | D105: CASH AT BANK (OUTSIDE GROUP) : Credit Card Bank : HDFC Corporate Travel Card (CC) | E105: 1283 CASH AT BANK (OUTSIDE GROUP) : Credit Card Bank : HDFC Corporate Travel Card (CC) | F105: Bank | H105: 13780.4
... A137: 309 | B137: 309 | C137: Fixed Asset | D137: CONCESSIONS, SOFTWARE LICENSES, PATENTS, SIMILAR RIGHTS | E137: A20500 CONCESSIONS, SOFTWARE LICENSES, PATENTS, SIMILAR RIGHTS | F137: Fixed Asset | H137: 0
A138: 806 | B138: 806 | C138: Fixed Asset | D138: CONCESSIONS, SOFTWARE LICENSES, PATENTS, SIMILAR RIGHTS : SOFTWARE & LICENSES | E138: 10294 CONCESSIONS, SOFTWARE LICENSES, PATENTS, SIMILAR RIGHTS : SOFTWARE & LICENSES | F138: Fixed Asset | H138: 12471540 | I138: Asset Account,Depreciation Account,Write Down Account,Write Off Account
A139: 2400 | B139: 2400 | C139: Fixed Asset | D139: CONCESSIONS, SOFTWARE LICENSES, PATENTS, SIMILAR RIGHTS : SOFTWARE & LICENSES : Software | E139: 1317 CONCESSIONS, SOFTWARE LICENSES, PATENTS, SIMILAR RIGHTS : SOFTWARE & LICENSES : Software | F139: Fixed Asset | H139: 0
A140: 420 | B140: 420 | C140: Long Term Liability | D140: CONVERTIBLE AND OTHER BONDS > 1 YEAR | E140: P16001 CONVERTIBLE AND OTHER BONDS > 1 YEAR | F140: Long Term Liability | H140: 0
A141: 1024 | B141: 1024 | C141: Long Term Liability | D141: CONVERTIBLE AND OTHER BONDS > 1 YEAR : CONVERTIBLE AND OTHER BONDS > 1 YEAR | E141: 10514 CONVERTIBLE AND OTHER BONDS > 1 YEAR : CONVERTIBLE AND OTHER BONDS > 1 YEAR | F141: Long Term Liability | H141: 0
A142: 419 | B142: 419 | C142: Other Current Liability | D142: CONVERTIBLE AND OTHER BONDS < 1 YEAR | E142: P16000 CONVERTIBLE AND OTHER BONDS < 1 YEAR | F142: Other Current Liability | H142: 0
A143: 1023 | B143: 1023 | C143: Other Current Liability | D143: CONVERTIBLE AND OTHER BONDS < 1 YEAR : CONVERTIBLE AND OTHER BONDS < 1 YEAR | E143: 10513 CONVERTIBLE AND OTHER BONDS < 1 YEAR : CONVERTIBLE AND OTHER BONDS < 1 YEAR | F143: Other Current Liability | H143: 0
A144: 224 | B144: 224 | C144: Cost of Goods Sold | D144: COORDINATION FEES PAID | E144: R60610 COORDINATION FEES PAID | F144: Cost of Goods Sold | H144: 0
A145: 560 | B145: 560 | C145: Cost of Goods Sold | D145: COORDINATION FEES PAID : COORDINATION FEES PAID | E145: 10048 COORDINATION FEES PAID : COORDINATION FEES PAID | F145: Cost of Goods Sold | H145: 0
A146: 300 | B146: 300 | C146: Expense | D146: CORPORATE TAX - AT CURRENT RATE | E146: R69500 CORPORATE TAX - AT CURRENT RATE | F146: Expense | H146: 0
...
