Workbook

Sheet PO with created By ASR
A1: External Id | B1: Voucher No | C1: Date | D1: Vendor raw | E1: Vendor without location | F1: Matched Vendor | G1: Branch | H1: Vch Type | I1: Created By | J1: Project | K1: Type of Expense | L1: Nature of Document | M1: Place of Supply | N1: Subsidiary | O1: Terms | P1: Approval Status | Q1: Department | R1: Line of business | S1: Subsidiary Location | T1: Nexus Override | U1: Nexus | V1: Currency | W1: Item raw | X1: Item Matched | Y1: Quantity Lookup | Z1: Rate Lookup | AA1: Order By (Other Refernence) raw | AB1: Order By (Other Refernence) Matched | AC1: HSN & SAC Code
A2: B/2025/PO/000001 | B2: B/2025/PO/000001 | C2: 45658 | D2: H P Ramareddy-Blr | E2: =_xlfn.TEXTBEFORE(D2,"-") -> H P Ramareddy | F2: 11014 H P Ramareddy | G2: B - Bangalore | H2: Purchase Order-Blr | I2: 1115173 Nagaraju R | K2: Indirect Expense | L2: Invoices for inward supply from unregistered person | N2: 6 | O2: 10 Days | P2: Pending Approval | T2: TRUE | U2: Nexus-Karnataka | V2: Indian Rupee | W2: Office Rent | X2: Rent Office | Y2: 1 | Z2: 245446 | AC2: CGST Input for KT (DT) 9%
A3: B/2025/PO/000002 | B3: B/2025/PO/000002 | C3: 45658 | D3: A Ramareddy (Rent)-Blr | E3: =_xlfn.TEXTBEFORE(D3,"-") -> A Ramareddy (Rent) | F3: 11009 A Ramareddy (Rent) | G3: B - Bangalore | H3: Purchase Order-Blr | I3: 1115173 Nagaraju R | K3: Indirect Expense | L3: Invoices for inward supply from unregistered person | N3: 6 | O3: 10 Days | P3: Pending Approval | T3: TRUE | U3: Nexus-Karnataka | V3: Indian Rupee | W3: Office Rent | X3: Rent Office | Y3: 1 | Z3: 245446 | AC3: CGST Input for KT (DT) 9%
A4: B/2025/PO/000003 | B4: B/2025/PO/000003 | C4: 45658 | D4: H P Ramareddy Utility-Blr | E4: =_xlfn.TEXTBEFORE(D4,"-") -> H P Ramareddy Utility | F4: 11015 H P Ramareddy Utility | G4: B - Bangalore | H4: Purchase Order-Blr | I4: 1115173 Nagaraju R | K4: Indirect Expense | L4: Invoices for inward supply from unregistered person | N4: 6 | O4: 10 Days | P4: Pending Approval | T4: TRUE | U4: Nexus-Karnataka | V4: Indian Rupee | W4: Water Charges | X4: Water Charges | Y4: 1 | Z4: 4000 | AC4: #N/A
A5: B/2025/PO/000004 | B5: B/2025/PO/000004 | C5: 45658 | D5: Renaissance Bengaluru Race Course Hotel (Dharampal Satyapal Ltd)-Blr | E5: =_xlfn.TEXTBEFORE(D5,"-") -> Renaissance Bengaluru Race Course Hotel (Dharampal Satyapal Ltd) | F5: 10403 Renaissance Bengaluru Race Course Hotel (Dharampal Satyapal Ltd) | G5: B - Bangalore | H5: Purchase Order-Blr | I5: 1138596 Yogesh A | J5: SB 22267 | K5: Direct Expense | L5: Invoices for inward supply from unregistered person | N5: 6 | O5: 90 Days | P5: Pending Approval | Q5: BU North | R5: Event Management | S5: Delhi | T5: TRUE | U5: Nexus-Karnataka | V5: Indian Rupee | W5: STAY CHARGES (DE) | X5: Stay Charges - Events | Y5: 1 | Z5: 279000 | AA5: Alok Khanna | AB5: 1137790 Alok Khanna | AC5: CGST Input for KT (DT) 9%
A6: B/2025/PO/000005 | B6: B/2025/PO/000005 | C6: 45658 | D6: H P Ramareddy Utility-Blr | E6: =_xlfn.TEXTBEFORE(D6,"-") -> H P Ramareddy Utility | F6: 11015 H P Ramareddy Utility | G6: B - Bangalore | H6: Purchase Order-Blr | I6: 1115173 Nagaraju R | K6: Indirect Expense | L6: Invoices for inward supply from unregistered person | N6: 6 | O6: 10 Days | P6: Pending Approval | T6: TRUE | U6: Nexus-Karnataka | V6: Indian Rupee | W6: Electricity Expenses | X6: #N/A | Y6: 1 | Z6: 19073 | AC6: #N/A
A7: B/2025/PO/000006 | B7: B/2025/PO/000006 | C7: 45658 | D7: Lynx Security & Detectives Services (P) Ltd-Blr | E7: =_xlfn.TEXTBEFORE(D7,"-") -> Lynx Security & Detectives Services (P) Ltd | F7: 11520 Lynx Security & Detectives Services (P) Ltd | G7: B - Bangalore | H7: Purchase Order-Blr | I7: 1115173 Nagaraju R | K7: Indirect Expense | L7: Invoices for inward supply from unregistered person | N7: 6 | O7: 10 Days | P7: Pending Approval | T7: TRUE | U7: Nexus-Karnataka | V7: Indian Rupee | W7: Security Charges | X7: Security Charges | Y7: 1 | Z7: 48991 | AA7: Anurama V | AB7: 1131024 Anurama V | AC7: CGST Input for KT (DT) 9%
A8: B/2025/PO/000007 | B8: B/2025/PO/000007 | C8: 45658 | D8: Mayur Enterprises-Blr | E8: =_xlfn.TEXTBEFORE(D8,"-") -> Mayur Enterprises | F8: 11521 Mayur Enterprises | G8: B - Bangalore | H8: Purchase Order-Blr | I8: 1115173 Nagaraju R | K8: Indirect Expense | L8: Invoices for inward supply from unregistered person | N8: 6 | O8: 10 Days | P8: Pending Approval | T8: TRUE | U8: Nexus-Karnataka | V8: Indian Rupee | W8: Water Charges | X8: Water Charges | Y8: 1 | Z8: 1610 | AC8: Ineligible CGST Input-Gen
A9: B/2025/PO/000008 | B9: B/2025/PO/000008 | C9: 45658 | D9: K Vishwanath Gouda Rent-Blr | E9: =_xlfn.TEXTBEFORE(D9,"-") -> K Vishwanath Gouda Rent | F9: 11016 K Vishwanath Gouda Rent | G9: B - Bangalore | H9: Purchase Order-Blr | I9: 1115173 Nagaraju R | K9: Indirect Expense | L9: Invoices for inward supply from unregistered person | N9: 6 | O9: 10 Days | P9: Pending Approval | T9: TRUE | U9: Nexus-Karnataka | V9: Indian Rupee | W9: Rent - Storage Room | X9: Rent Storage Room | Y9: 1 | Z9: 27500 | AC9: #N/A
A10: B/2025/PO/000009 | B10: B/2025/PO/000009 | C10: 45658 | D10: K-Corp-Blr | E10: =_xlfn.TEXTBEFORE(D10,"-") -> K | F10: #N/A | G10: B - Bangalore | H10: Purchase Order-Blr | I10: 1115173 Nagaraju R | K10: Indirect Expense | L10: Invoices for inward supply from unregistered person | N10: 6 | O10: 90 Days | P10: Pending Approval | T10: TRUE | U10: Nexus-Karnataka | V10: Indian Rupee | W10: Computer Hire Charges | X10: Computer Hire Charges | Y10: 1 | Z10: 3500 | AC10: CGST Input for KT (DT) 9%
A11: B/2025/PO/000010 | B11: B/2025/PO/000010 | C11: 45658 | D11: Aaa Rental Llp-Mum | E11: =_xlfn.TEXTBEFORE(D11,"-") -> Aaa Rental Llp | F11: 11626 Aaa Rental Llp | G11: B - Bangalore | H11: Purchase Order-Blr | I11: 1115173 Nagaraju R | K11: Indirect Expense | L11: Invoices for inward supply from unregistered person | N11: 6 | O11: 45 Days | P11: Pending Approval | T11: TRUE | U11: Nexus-Karnataka | V11: Indian Rupee | W11: Computer Hire Charges | X11: Computer Hire Charges | Y11: 1 | Z11: 13500 | AA11: Tijo Joseph | AB11: 1128119 Tijo Joseph | AC11: CGST Input for KT (DT) 9%
A12: B/2025/PO/000011 | B12: B/2025/PO/000011 | C12: 45658 | D12: Bharti Airtel Ltd.-Del | E12: =_xlfn.TEXTBEFORE(D12,"-") -> Bharti Airtel Ltd. | F12: #N/A | G12: B - Bangalore | H12: Purchase Order-Blr | I12: 1115173 Nagaraju R | K12: Indirect Expense | L12: Invoices for inward supply from unregistered person | N12: 6 | O12: Immediate | P12: Pending Approval | T12: TRUE | U12: Nexus-Karnataka | V12: Indian Rupee | W12: Internet Expenses | X12: Internet Expenses - Events | Y12: 1 | Z12: 1498 | AA12: Tijo Joseph | AB12: 1128119 Tijo Joseph | AC12: CGST Input for KT (DT) 9%
A13: C/2025/PO/000001 | B13: C/2025/PO/000001 | C13: 45658 | D13: Elsie Mathew-Che | E13: =_xlfn.TEXTBEFORE(D13,"-") -> Elsie Mathew | F13: 11012 Elsie Mathew | G13: C - Chennai | H13: Purchase Order-Che | I13: 1115173 Nagaraju R | K13: Indirect Expense | L13: Invoices for inward supply from unregistered person | N13: 6 | O13: 10 Days | P13: Pending Approval | T13: TRUE | U13: Nexus-Tamil Nadu | V13: Indian Rupee | W13: Office Rent | X13: Rent Office | Y13: 1 | Z13: 73500 | AA13: Aravind Kumar S | AB13: 1044838 Aravind Kumar.S | AC13: #N/A
A14: C/2025/PO/000002 | B14: C/2025/PO/000002 | C14: 45658 | D14: Race View Tower Association-Che | E14: =_xlfn.TEXTBEFORE(D14,"-") -> Race View Tower Association | F14: 11525 Race View Tower Association | G14: C - Chennai | H14: Purchase Order-Che | I14: 1115173 Nagaraju R | K14: Indirect Expense | L14: Invoices for inward supply from unregistered person | N14: 6 | O14: 10 Days | P14: Pending Approval | T14: TRUE | U14: Nexus-Tamil Nadu | V14: Indian Rupee | W14: Office Maintainance Expenses | X14: #N/A | Y14: 1 | Z14: 4000 | AA14: Aravind Kumar S | AB14: 1044838 Aravind Kumar.S | AC14: #N/A
A15: C/2025/PO/000003 | B15: C/2025/PO/000003 | C15: 45658 | D15: Unicare Hospitality Services Pvt Ltd-Che | E15: =_xlfn.TEXTBEFORE(D15,"-") -> Unicare Hospitality Services Pvt Ltd | F15: 12571 Unicare Hospitality Services Pvt Ltd | G15: C - Chennai | H15: Purchase Order-Che | I15: 1115173 Nagaraju R | K15: Indirect Expense | L15: Invoices for inward supply from unregistered person | N15: 6 | O15: 45 Days | P15: Pending Approval | T15: TRUE | U15: Nexus-Tamil Nadu | V15: Indian Rupee | W15: Security Charges | X15: Security Charges | Y15: 1 | Z15: 28273 | AA15: Aravind Kumar S | AB15: 1044838 Aravind Kumar.S | AC15: CGST Input for TN (DT) 9%
A16: B/2025/PO/000012 | B16: B/2025/PO/000012 | C16: 45659 | D16: Siva Sankar Cabs-Blr | E16: =_xlfn.TEXTBEFORE(D16,"-") -> Siva Sankar Cabs | F16: 10089 Siva Sankar Cabs | G16: B - Bangalore | H16: Purchase Order-Blr | I16: 1115173 Nagaraju R | J16: SB 22270 | K16: Direct Expense | L16: Invoices for inward supply from unregistered person | N16: 6 | O16: 30 Days | P16: Pending Approval | Q16: BU South | R16: Event Management | S16: Bangalore | T16: TRUE | U16: Nexus-Karnataka | V16: Indian Rupee | W16: CAR HIRE CHARGES - EVENTS (DE) | X16: CarHireCharges | Y16: 1 | Z16: 9400 | AA16: Thirtha Patil | AB16: 1138809 Thirtha Patil | AC16: #N/A
A17: B/2025/PO/000013 | B17: B/2025/PO/000013 | C17: 45659 | D17: Arun Kumar M -CR | E17: =_xlfn.TEXTBEFORE(D17,"-") -> Arun Kumar M | F17: #N/A | G17: B - Bangalore | H17: Purchase Order-Blr | I17: 1115173 Nagaraju R | J17: SB 22190 | K17: Direct Expense | L17: Invoices for inward supply from unregistered person | N17: 6 | O17: Immediate | P17: Pending Approval | Q17: BU South | R17: Event Management | S17: Bangalore | T17: TRUE | U17: Nexus-Karnataka | V17: Indian Rupee | W17: CONVEYANCE - EVENTS (DE) | X17: Conveyance | Y17: 1 | Z17: 5599 | AA17: Amrita Sawhney | AB17: 1122672 Amrita Sawhney | AC17: #N/A
A18: B/2025/PO/000014 | B18: B/2025/PO/000014 | C18: 45659 | D18: Sky Office Stationers-Blr | E18: =_xlfn.TEXTBEFORE(D18,"-") -> Sky Office Stationers | F18: 12417 Sky Office Stationers | G18: B - Bangalore | H18: Purchase Order-Blr | I18: EBP BlrChe | K18: Indirect Expense | L18: Invoices for inward supply from unregistered person | N18: 6 | O18: 45 Days | P18: Pending Approval | T18: TRUE | U18: Nexus-Karnataka | V18: Indian Rupee | W18: Staff Welfare | X18: Staff Welfare - Others | Y18: 1 | Z18: 2846 | AA18: Anurama V | AB18: 1131024 Anurama V | AC18: Ineligible CGST Input-Gen
A19: C/2025/PO/000004 | B19: C/2025/PO/000004 | C19: 45659 | D19: The Westin Chennai Velachery (MFAR Hotels and Resorts Pvt Ltd)-Che | E19: =_xlfn.TEXTBEFORE(D19,"-") -> The Westin Chennai Velachery (MFAR Hotels and Resorts Pvt Ltd) | F19: 10468 The Westin Chennai Velachery (MFAR Hotels and Resorts Pvt Ltd) | G19: C - Chennai | H19: Purchase Order-Che | I19: 1138596 Yogesh A | J19: SB 22254 | K19: Direct Expense | L19: Invoices for inward supply from unregistered person | N19: 6 | O19: Immediate | P19: Pending Approval | Q19: BU North | R19: Event Management | S19: Delhi | T19: TRUE | U19: Nexus-Tamil Nadu | V19: Indian Rupee | W19: EVENT EXPENSES-GIVE AWAYS | X19: Event Expenses - Giveaways | Y19: 1 | Z19: 69600 | AA19: Harshit Jain | AB19: 1044966 Harshit Jain | AC19: CGST Input for TN (DT) 9%
A20: D/2025/PO/000001 | B20: D/2025/PO/000001 | C20: 45659 | D20: Jarvas Smart Solutions Pvt Ltd-Del | E20: =_xlfn.TEXTBEFORE(D20,"-") -> Jarvas Smart Solutions Pvt Ltd | F20: 12882 Jarvas Smart Solutions Pvt Ltd | G20: D - Delhi | H20: Purchase Order-Del | I20: 1138596 Yogesh A | J20: SB 22159 | K20: Direct Expense | L20: Invoices for inward supply from unregistered person | N20: 6 | O20: 45 Days | P20: Pending Approval | Q20: BU North | R20: Event Management | S20: Delhi | T20: TRUE | U20: Nexus-Delhi | V20: Indian Rupee | W20: STAGE & SET EXPENSES (DE) | X20: Stage & Set Expenses - Events | Y20: 1 | Z20: 3787500 | AA20: Ravi Kiroula | AB20: 1128186 Ravi Kiroula | AC20: IGST Input for DL (DT) 18%
A21: D/2025/PO/000002 | B21: D/2025/PO/000002 | C21: 45659 | D21: Rishi Computers-Del | E21: =_xlfn.TEXTBEFORE(D21,"-") -> Rishi Computers | F21: 12343 Rishi Computers | G21: D - Delhi | H21: Purchase Order-Del | I21: 1135026 Gaurav Khurana | K21: Indirect Expense | L21: Invoices for inward supply from unregistered person | N21: 6 | O21: 45 Days | P21: Pending Approval | T21: TRUE | U21: Nexus-Delhi | V21: Indian Rupee | W21: Laptop Dell(P) | X21: #N/A | Y21: 6 | Z21: 81000 | AA21: Abhishek | AB21: 1140231 Abhishek Jadhav | AC21: CGST Input for DL (DT) 9%
A22: D/2025/PO/000003 | B22: D/2025/PO/000003 | C22: 45659 | D22: Rishi Computers-Del | E22: =_xlfn.TEXTBEFORE(D22,"-") -> Rishi Computers | F22: 12343 Rishi Computers | G22: D - Delhi | H22: Purchase Order-Del | I22: 1135026 Gaurav Khurana | K22: Indirect Expense | L22: Invoices for inward supply from unregistered person | N22: 6 | O22: 45 Days | P22: Pending Approval | T22: TRUE | U22: Nexus-Delhi | V22: Indian Rupee | W22: Computer | X22: #N/A | Y22: 2 | Z22: 315000 | AA22: Abhishek | AB22: 1140231 Abhishek Jadhav | AC22: CGST Input for DL (DT) 9%
A23: D/2025/PO/000004 | B23: D/2025/PO/000004 | C23: 45659 | D23: Saksham Signs Pvt Ltd-Del | E23: =_xlfn.TEXTBEFORE(D23,"-") -> Saksham Signs Pvt Ltd | F23: 12886 Saksham Signs Pvt Ltd | G23: D - Delhi | H23: Purchase Order-Del | I23: 1138596 Yogesh A | J23: SB 22159 | K23: Direct Expense | L23: Invoices for inward supply from unregistered person | N23: 6 | O23: 45 Days | P23: Pending Approval | Q23: BU North | R23: Event Management | S23: Delhi | T23: TRUE | U23: Nexus-Delhi | V23: Indian Rupee | W23: STAGE & SET EXPENSES (DE) | X23: Stage & Set Expenses - Events | Y23: 1 | Z23: 491000 | AA23: Ravi Kiroula | AB23: 1128186 Ravi Kiroula | AC23: IGST Input for DL (DT) 18%
A24: D/2025/PO/000005 | B24: D/2025/PO/000005 | C24: 45659 | D24: Gurdeep Kaur-Del | E24: =_xlfn.TEXTBEFORE(D24,"-") -> Gurdeep Kaur | F24: 11103 Gurdeep Kaur | G24: D - Delhi | H24: Purchase Order-Del | I24: 1138596 Yogesh A | K24: Indirect Expense | L24: Invoices for inward supply from unregistered person | N24: 6 | O24: 90 Days | P24: Pending Approval | T24: TRUE | U24: Nexus-Delhi | V24: Indian Rupee | W24: Computer Hire Charges | X24: Computer Hire Charges | Y24: 1 | Z24: 28000 | AA24: Gurpreet Singh | AB24: 1044881 Gurpreet Singh Khani | AC24: CGST Input for DL (DT) 9%
A25: D/2025/PO/000006 | B25: D/2025/PO/000006 | C25: 45659 | D25: Gurdeep Kaur-Del | E25: =_xlfn.TEXTBEFORE(D25,"-") -> Gurdeep Kaur | F25: 11103 Gurdeep Kaur | G25: D - Delhi | H25: Purchase Order-Del | I25: 1138596 Yogesh A | K25: Indirect Expense | L25: Invoices for inward supply from unregistered person | N25: 6 | O25: 90 Days | P25: Pending Approval | T25: TRUE | U25: Nexus-Delhi | V25: Indian Rupee | W25: Computer Hire Charges | X25: Computer Hire Charges | Y25: 1 | Z25: 22000 | AA25: Gurpreet Singh | AB25: 1044881 Gurpreet Singh Khani | AC25: CGST Input for DL (DT) 9%
A26: D/2025/PO/000007 | B26: D/2025/PO/000007 | C26: 45659 | D26: Aaa Rental Llp-Mum | E26: =_xlfn.TEXTBEFORE(D26,"-") -> Aaa Rental Llp | F26: 11626 Aaa Rental Llp | G26: D - Delhi | H26: Purchase Order-Del | I26: 1138596 Yogesh A | K26: Indirect Expense | L26: Invoices for inward supply from unregistered person | N26: 6 | O26: 45 Days | P26: Pending Approval | T26: TRUE | U26: Nexus-Delhi | V26: Indian Rupee | W26: Computer Hire Charges | X26: Computer Hire Charges | Y26: 1 | Z26: 22000 | AA26: Gurpreet | AB26: 1044881 Gurpreet Singh Khani | AC26: CGST Input for DL (DT) 9%
A27: D/2025/PO/000008 | B27: D/2025/PO/000008 | C27: 45659 | D27: Aaa Rental Llp-Mum | E27: =_xlfn.TEXTBEFORE(D27,"-") -> Aaa Rental Llp | F27: 11626 Aaa Rental Llp | G27: D - Delhi | H27: Purchase Order-Del | I27: 1138596 Yogesh A | K27: Indirect Expense | L27: Invoices for inward supply from unregistered person | N27: 6 | O27: 45 Days | P27: Pending Approval | T27: TRUE | U27: Nexus-Delhi | V27: Indian Rupee | W27: Computer Hire Charges | X27: Computer Hire Charges | Y27: 2 | Z27: 21000 | AA27: Gurpreet | AB27: 1044881 Gurpreet Singh Khani | AC27: CGST Input for DL (DT) 9%
A28: D/2025/PO/000009 | B28: D/2025/PO/000009 | C28: 45659 | D28: Aaa Rental Llp-Mum | E28: =_xlfn.TEXTBEFORE(D28,"-") -> Aaa Rental Llp | F28: 11626 Aaa Rental Llp | G28: D - Delhi | H28: Purchase Order-Del | I28: 1138596 Yogesh A | K28: Indirect Expense | L28: Invoices for inward supply from unregistered person | N28: 6 | O28: 45 Days | P28: Pending Approval | T28: TRUE | U28: Nexus-Delhi | V28: Indian Rupee | W28: Computer Hire Charges | X28: Computer Hire Charges | Y28: 1 | Z28: 19000 | AA28: Gurpreet | AB28: 1044881 Gurpreet Singh Khani | AC28: CGST Input for DL (DT) 9%
A29: A/2025/PO/000001 | B29: A/2025/PO/000001 | C29: 45659 | D29: Ekatra Collective Pvt Ltd-Mum | E29: =_xlfn.TEXTBEFORE(D29,"-") -> Ekatra Collective Pvt Ltd | F29: 12858 Ekatra Collective Pvt Ltd | G29: A - Mumbai | H29: Purchase Order-Mum | I29: 1138574 Swapnil Bangal | J29: SB 22256 | K29: Direct Expense | L29: Invoices for inward supply from unregistered person | N29: 6 | O29: 45 Days | P29: Pending Approval | Q29: BU South | R29: Event Management | S29: Chennai | T29: FALSE | U29: Nexus-Maharashtra | V29: Indian Rupee | W29: EVENT EXPENSES-GIVE AWAYS | X29: Event Expenses - Giveaways | Y29: 1 | Z29: 13259.16 | AA29: Clinton Jesuraja | AB29: 1044969 Clinton J | AC29: IGST Input for MH 12%
A30: A/2025/PO/000002 | B30: A/2025/PO/000002 | C30: 45659 | D30: Noaman Digital Partnership Firm-Mum | E30: =_xlfn.TEXTBEFORE(D30,"-") -> Noaman Digital Partnership Firm | F30: #N/A | G30: A - Mumbai | H30: Purchase Order-Mum | I30: 1138574 Swapnil Bangal | J30: SB 22123 | K30: Direct Expense | L30: Invoices for inward supply from unregistered person | N30: 6 | O30: 45 Days | P30: Pending Approval | Q30: BU West | R30: Event Management | S30: Mumbai | T30: FALSE | U30: Nexus-Maharashtra | V30: Indian Rupee | W30: PRINTING & STATIONERY - EVENTS | X30: Printing & Stationery - Events | Y30: 1 | Z30: 11793 | AA30: Aftab Shaikh | AB30: 1133492 Aftab Mobin Shaikh | AC30: CGST Input for MH (DT) 9%
A31: A/2025/PO/000003 | B31: A/2025/PO/000003 | C31: 45659 | D31: Turbonet Systems Pvt Ltd-Mum | E31: =_xlfn.TEXTBEFORE(D31,"-") -> Turbonet Systems Pvt Ltd | F31: 12560 Turbonet Systems Pvt Ltd | G31: A - Mumbai | H31: Purchase Order-Mum | I31: 1138574 Swapnil Bangal | J31: SB 22212 | K31: Direct Expense | L31: Invoices for inward supply from unregistered person | N31: 6 | O31: 45 Days | P31: Pending Approval | Q31: BU West | R31: Event Management | S31: Mumbai | T31: FALSE | U31: Nexus-Maharashtra | V31: Indian Rupee | W31: Courier Charges - Events | X31: Courier Charges - Events | Y31: 1 | Z31: 7000 | AA31: Neetuprakash Poojary | AB31: 1044835 Neetu Prakash Poojary | AC31: CGST Input for MH (DT) 9%
A32: A/2025/PO/000004 | B32: A/2025/PO/000004 | C32: 45659 | D32: Jaguar Security Services Pvt Ltd-Mum | E32: =_xlfn.TEXTBEFORE(D32,"-") -> Jaguar Security Services Pvt Ltd | F32: 12046 Jaguar Security Services Pvt Ltd | G32: A - Mumbai | H32: Purchase Order-Mum | I32: 1138574 Swapnil Bangal | J32: SB 21718 | K32: Direct Expense | L32: Invoices for inward supply from unregistered person | N32: 6 | O32: 45 Days | P32: Pending Approval | T32: FALSE | U32: Nexus-Maharashtra | V32: Indian Rupee | W32: SECURITY CHARGES - EVENTS | X32: Security Charges - Events | Y32: 1 | Z32: 165000 | AA32: Hari Bailwal | AB32: 1044898 Hari Bailwal | AC32: IGST Input for MH (DT) 18%
A33: C/2025/PO/000005 | B33: C/2025/PO/000005 | C33: 45660 | D33: Tata Teleservices Ltd-Blr | E33: =_xlfn.TEXTBEFORE(D33,"-") -> Tata Teleservices Ltd | F33: 10964 Tata Teleservices Ltd | G33: C - Chennai | H33: Purchase Order-Che | I33: 1115173 Nagaraju R | K33: Indirect Expense | L33: Invoices for inward supply from unregistered person | N33: 6 | O33: 15 Days | P33: Pending Approval | T33: TRUE | U33: Nexus-Tamil Nadu | V33: Indian Rupee | W33: Internet Expenses | X33: Internet Expenses - Events | Y33: 1 | Z33: 62500 | AA33: Amir Merchant | AB33: 1044800 Amir Merchant | AC33: CGST Input for TN (DT) 9%
A34: D/2025/PO/000010 | B34: D/2025/PO/000010 | C34: 45660 | D34: Goldline Security Systems-Del | E34: =_xlfn.TEXTBEFORE(D34,"-") -> Goldline Security Systems | F34: 12880 Goldline Security Systems | G34: D - Delhi | H34: Purchase Order-Del | I34: 1135026 Gaurav Khurana | K34: Indirect Expense | L34: Invoices for inward supply from unregistered person | N34: 6 | O34: 45 Days | P34: Pending Approval | T34: TRUE | U34: Nexus-Delhi | V34: Indian Rupee | W34: Fire Alarm (Office Equipment) | X34: #N/A | Y34: 1 | Z34: 116703 | AA34: Pankaj | AB34: 1044903 Pankaj Kumar Mishra | AC34: CGST Input for DL (DT) 9%
A35: D/2025/PO/000010 | B35: D/2025/PO/000010 | C35: 45660 | D35: Goldline Security Systems-Del | E35: =_xlfn.TEXTBEFORE(D35,"-") -> Goldline Security Systems | F35: 12880 Goldline Security Systems | G35: D - Delhi | H35: Purchase Order-Del | I35: 1135026 Gaurav Khurana | K35: Indirect Expense | L35: Invoices for inward supply from unregistered person | N35: 6 | O35: 45 Days | P35: Pending Approval | T35: TRUE | U35: Nexus-Delhi | V35: Indian Rupee | W35: Fire Alarm (Office Equipment) | X35: #N/A | Y35: 1 | Z35: 116703 | AA35: Pankaj | AB35: 1044903 Pankaj Kumar Mishra | AC35: CGST Input for DL (DT) 9%
A36: D/2025/PO/000011 | B36: D/2025/PO/000011 | C36: 45660 | D36: Goldline Security Systems-Del | E36: =_xlfn.TEXTBEFORE(D36,"-") -> Goldline Security Systems | F36: 12880 Goldline Security Systems | G36: D - Delhi | H36: Purchase Order-Del | I36: 1135026 Gaurav Khurana | K36: Indirect Expense | L36: Invoices for inward supply from unregistered person | N36: 6 | O36: 45 Days | P36: Pending Approval | T36: TRUE | U36: Nexus-Delhi | V36: Indian Rupee | W36: Office Maintainance Expenses | X36: #N/A | Y36: 1 | Z36: 68802 | AA36: Pankaj | AB36: 1044903 Pankaj Kumar Mishra | AC36: CGST Input for DL (DT) 9%
A37: D/2025/PO/000012 | B37: D/2025/PO/000012 | C37: 45660 | D37: Wanderers Adventure Sports Pvt Ltd-Del | E37: =_xlfn.TEXTBEFORE(D37,"-") -> Wanderers Adventure Sports Pvt Ltd | F37: 10103 Wanderers Adventure Sports Pvt Ltd | G37: D - Delhi | H37: Purchase Order-Del | I37: 1044835 Neetu Prakash Poojary | J37: SB 22159 | K37: Direct Expense | L37: Invoices for inward supply from unregistered person | N37: 6 | O37: 90 Days | P37: Pending Approval | Q37: BU North | R37: Event Management | S37: Delhi | T37: TRUE | U37: Nexus-Delhi | V37: Indian Rupee | W37: EVENT EXPENSES /OTHERS | X37: Event Expenses - Others | Y37: 1 | Z37: 138013 | AA37: SONIA | AB37: 1114836 Sonia Thakur | AC37: CGST Input for DL (DT) 9%
A38: D/2025/PO/000013 | B38: D/2025/PO/000013 | C38: 45660 | D38: Studio Merchandise Pvt Ltd-Del | E38: =_xlfn.TEXTBEFORE(D38,"-") -> Studio Merchandise Pvt Ltd | F38: 12464 Studio Merchandise Pvt Ltd | G38: D - Delhi | H38: Purchase Order-Del | I38: 1138596 Yogesh A | J38: SB 22120 | K38: Direct Expense | L38: Invoices for inward supply from unregistered person | N38: 6 | O38: 45 Days | P38: Pending Approval | Q38: BU North | R38: Event Management | S38: Delhi | T38: TRUE | U38: Nexus-Delhi | V38: Indian Rupee | W38: EVENT EXPENSES-GIVE AWAYS | X38: Event Expenses - Giveaways | Y38: 1 | Z38: 147300 | AA38: Varun Sondhi | AB38: 1129995 Varun Sodhi | AC38: CGST Input for DL (DT) 9%
A39: A/2025/PO/000005 | B39: A/2025/PO/000005 | C39: 45660 | D39: Fairfield By Marriott Mumbai (Associated Hospitality Pvt Ltd)-Mum | E39: =_xlfn.TEXTBEFORE(D39,"-") -> Fairfield By Marriott Mumbai (Associated Hospitality Pvt Ltd) | F39: 11911 Fairfield By Marriott Mumbai (Associated Hospitality Pvt Ltd) | G39: A - Mumbai | H39: Purchase Order-Mum | I39: 1138596 Yogesh A | J39: SB 22120 | K39: Direct Expense | L39: Invoices for inward supply from unregistered person | N39: 6 | O39: Immediate | P39: Pending Approval | Q39: BU North | R39: Event Management | S39: Delhi | T39: FALSE | U39: Nexus-Maharashtra | V39: Indian Rupee | W39: STAY CHARGES (DE) | X39: Stay Charges - Events | Y39: 1 | Z39: 41000 | AA39: Alok Khanna | AB39: 1137790 Alok Khanna | AC39: CGST Input for MH (DT) 9%
A40: A/2025/PO/000006 | B40: A/2025/PO/000006 | C40: 45660 | D40: Black Hat Talent Solutions & Consulting Pvt Ltd-Mum | E40: =_xlfn.TEXTBEFORE(D40,"-") -> Black Hat Talent Solutions & Consulting Pvt Ltd | F40: 10572 Black Hat Talent Solutions & Consulting Pvt Ltd | G40: A - Mumbai | H40: Purchase Order-Mum | I40: 1044835 Neetu Prakash Poojary | J40: SB 22196 | K40: Direct Expense | L40: Invoices for inward supply from unregistered person | N40: 6 | O40: 90 Days | P40: Pending Approval | Q40: BU North | R40: Event Management | S40: Delhi | T40: FALSE | U40: Nexus-Maharashtra | V40: Indian Rupee | W40: PERFORMER EXPENSES | X40: Performer Expenses | Y40: 1 | Z40: 540000 | AA40: SHRUTI GUPTA | AB40: 1135015 Shruti Gupta | AC40: CGST Input for MH (DT) 9%
A41: A/2025/PO/000007 | B41: A/2025/PO/000007 | C41: 45660 | D41: Phonographic Performance Limited-Mum | E41: =_xlfn.TEXTBEFORE(D41,"-") -> Phonographic Performance Limited | F41: #N/A | G41: A - Mumbai | H41: Purchase Order-Mum | I41: 1138574 Swapnil Bangal | J41: SB 22267 | K41: Direct Expense | L41: Invoices for inward supply from unregistered person | N41: 6 | O41: 45 Days | P41: Pending Approval | Q41: BU North | R41: Event Management | S41: Delhi | T41: FALSE | U41: Nexus-Maharashtra | V41: Indian Rupee | W41: PERMISSION EXPENSES | X41: Permission Expenses | Y41: 1 | Z41: 55500 | AA41: Mangesh Waghmare | AB41: 1044806 Mangesh Waghmare | AC41: CGST Input for MH (DT) 9%
A42: A/2025/PO/000008 | B42: A/2025/PO/000008 | C42: 45660 | D42: Novex Communications Pvt. Ltd.-Mum | E42: =_xlfn.TEXTBEFORE(D42,"-") -> Novex Communications Pvt. Ltd. | F42: #N/A | G42: A - Mumbai | H42: Purchase Order-Mum | I42: 1138574 Swapnil Bangal | J42: SB 22267 | K42: Direct Expense | L42: Invoices for inward supply from unregistered person | N42: 6 | O42: 45 Days | P42: Pending Approval | Q42: BU North | R42: Event Management | S42: Delhi | T42: FALSE | U42: Nexus-Maharashtra | V42: Indian Rupee | W42: PERMISSION EXPENSES | X42: Permission Expenses | Y42: 1 | Z42: 60000 | AA42: Mangesh Waghmare | AB42: 1044806 Mangesh Waghmare | AC42: CGST Input for MH (DT) 9%
A43: A/2025/PO/000009 | B43: A/2025/PO/000009 | C43: 45660 | D43: The Indian Performing Right Society Ltd.-Mum | E43: =_xlfn.TEXTBEFORE(D43,"-") -> The Indian Performing Right Society Ltd. | F43: #N/A | G43: A - Mumbai | H43: Purchase Order-Mum | I43: 1138574 Swapnil Bangal | J43: SB 22270 | K43: Direct Expense | L43: Invoices for inward supply from unregistered person | N43: 6 | O43: 90 Days | P43: Pending Approval | Q43: BU South | R43: Event Management | S43: Bangalore | T43: FALSE | U43: Nexus-Maharashtra | V43: Indian Rupee | W43: PERMISSION EXPENSES | X43: Permission Expenses | Y43: 1 | Z43: 75000 | AA43: Mangesh Waghmare | AB43: 1044806 Mangesh Waghmare | AC43: CGST Input for MH (DT) 9%
A44: A/2025/PO/000010 | B44: A/2025/PO/000010 | C44: 45660 | D44: Phonographic Performance Limited-Mum | E44: =_xlfn.TEXTBEFORE(D44,"-") -> Phonographic Performance Limited | F44: #N/A | G44: A - Mumbai | H44: Purchase Order-Mum | I44: 1138574 Swapnil Bangal | J44: SB 22270 | K44: Direct Expense | L44: Invoices for inward supply from unregistered person | N44: 6 | O44: 45 Days | P44: Pending Approval | Q44: BU South | R44: Event Management | S44: Bangalore | T44: FALSE | U44: Nexus-Maharashtra | V44: Indian Rupee | W44: PERMISSION EXPENSES | X44: Permission Expenses | Y44: 1 | Z44: 60000 | AA44: Mangesh Waghmare | AB44: 1044806 Mangesh Waghmare | AC44: CGST Input for MH (DT) 9%
A45: A/2025/PO/000011 | B45: A/2025/PO/000011 | C45: 45660 | D45: Novex Communications Pvt. Ltd.-Mum | E45: =_xlfn.TEXTBEFORE(D45,"-") -> Novex Communications Pvt. Ltd. | F45: #N/A | G45: A - Mumbai | H45: Purchase Order-Mum | I45: 1138574 Swapnil Bangal | J45: SB 22270 | K45: Direct Expense | L45: Invoices for inward supply from unregistered person | N45: 6 | O45: 90 Days | P45: Pending Approval | Q45: BU South | R45: Event Management | S45: Bangalore | T45: FALSE | U45: Nexus-Maharashtra | V45: Indian Rupee | W45: PERMISSION EXPENSES | X45: Permission Expenses | Y45: 1 | Z45: 60000 | AA45: Mangesh Waghmare | AB45: 1044806 Mangesh Waghmare | AC45: CGST Input for MH (DT) 9%
A46: A/2025/PO/000012 | B46: A/2025/PO/000012 | C46: 45660 | D46: Rentastic-Mum | E46: =_xlfn.TEXTBEFORE(D46,"-") -> Rentastic | F46: #N/A | G46: A - Mumbai | H46: Purchase Order-Mum | I46: 1115173 Nagaraju R | J46: SB 22270 | K46: Direct Expense | L46: Invoices for inward supply from unregistered person | N46: 6 | O46: 45 Days | P46: Pending Approval | Q46: BU South | R46: Event Management | S46: Bangalore | T46: FALSE | U46: Nexus-Maharashtra | V46: Indian Rupee | W46: STAGE & SET EXPENSES (DE) | X46: Stage & Set Expenses - Events | Y46: 1 | Z46: 24600 | AA46: Thirtha Patil | AB46: 1138809 Thirtha Patil | AC46: CGST Input for MH (DT) 9%
A47: A/2025/PO/000013 | B47: A/2025/PO/000013 | C47: 45660 | D47: Zinque (Sweet Spot) (OTV)-Mum | E47: =_xlfn.TEXTBEFORE(D47,"-") -> Zinque (Sweet Spot) (OTV) | F47: #N/A | G47: A - Mumbai | H47: Purchase Order-Mum | I47: 1138574 Swapnil Bangal | J47: SB 21768 | K47: Direct Expense | L47: Invoices for inward supply from unregistered person | N47: 6 | O47: 90 Days | P47: Pending Approval | T47: FALSE | U47: Nexus-Maharashtra | V47: Indian Rupee | W47: EVENT EXPENSES-GIVE AWAYS | X47: Event Expenses - Giveaways | Y47: 1 | Z47: 29400 | AA47: Aftab Shaikh | AB47: 1133492 Aftab Mobin Shaikh | AC47: CGST Input for MH (DT) 9%
A48: B/2025/PO/000015 | B48: B/2025/PO/000015 | C48: 45663 | D48: The Oberoi Bengaluru-Blr | E48: =_xlfn.TEXTBEFORE(D48,"-") -> The Oberoi Bengaluru | F48: 10455 The Oberoi Bengaluru | G48: B - Bangalore | H48: Purchase Order-Blr | I48: 1138596 Yogesh A | J48: SB 22277 | K48: Direct Expense | L48: Invoices for inward supply from unregistered person | N48: 6 | O48: Immediate | P48: Pending Approval | Q48: BU North | R48: Event Management | S48: Delhi | T48: TRUE | U48: Nexus-Karnataka | V48: Indian Rupee | W48: F&B Charges Events | X48: F&B Charges Events | Y48: 1 | Z48: 348660 | AA48: Alok Khanna | AB48: 1137790 Alok Khanna | AC48: CGST Input for KT (DT) 9%
A49: B/2025/PO/000016 | B49: B/2025/PO/000016 | C49: 45663 | D49: Time Marketing-Blr | E49: =_xlfn.TEXTBEFORE(D49,"-") -> Time Marketing | F49: 12541 Time Marketing | G49: B - Bangalore | H49: Purchase Order-Blr | I49: 1138574 Swapnil Bangal | J49: SB 22276 | K49: Direct Expense | L49: Invoices for inward supply from unregistered person | N49: 6 | O49: 45 Days | P49: Pending Approval | Q49: BU West | R49: Event Management | S49: Mumbai | T49: TRUE | U49: Nexus-Karnataka | V49: Indian Rupee | W49: EVENT EXPENSES-GIVE AWAYS | X49: Event Expenses - Giveaways | Y49: 1 | Z49: 55180 | AA49: Abdul Rehman ? | AB49: 1044827 Abdul Rahman | AC49: CGST Input for KT (DT) 9%
A50: B/2025/PO/000017 | B50: B/2025/PO/000017 | C50: 45663 | D50: Abdul Rehman -CR | E50: =_xlfn.TEXTBEFORE(D50,"-") -> Abdul Rehman | F50: #N/A | G50: B - Bangalore | H50: Purchase Order-Blr | I50: EBP BlrChe | J50: SB 21960 | K50: Direct Expense | L50: Invoices for inward supply from unregistered person | N50: 6 | O50: Immediate | P50: Pending Approval | Q50: BU South | R50: Event Management | S50: Bangalore | T50: TRUE | U50: Nexus-Karnataka | V50: Indian Rupee | W50: CONVEYANCE - EVENTS (DE) | X50: Conveyance | Y50: 1 | Z50: 2610 | AA50: Rahul Deherkar | AB50: 1044803 Rahul Deherkar | AC50: #N/A
A51: B/2025/PO/000018 | B51: B/2025/PO/000018 | C51: 45663 | D51: Abdul Rehman -CR | E51: =_xlfn.TEXTBEFORE(D51,"-") -> Abdul Rehman | F51: #N/A | G51: B - Bangalore | H51: Purchase Order-Blr | I51: EBP BlrChe | J51: SB 21960 | K51: Direct Expense | L51: Invoices for inward supply from unregistered person | N51: 6 | O51: Immediate | P51: Pending Approval | Q51: BU South | R51: Event Management | S51: Bangalore | T51: TRUE | U51: Nexus-Karnataka | V51: Indian Rupee | W51: CONVEYANCE - EVENTS (DE) | X51: Conveyance | Y51: 1 | Z51: 3000 | AA51: Rahul Deherkar | AB51: 1044803 Rahul Deherkar | AC51: #N/A
A52: B/2025/PO/000019 | B52: B/2025/PO/000019 | C52: 45663 | D52: Navyatha Sagar D-Blr | E52: =_xlfn.TEXTBEFORE(D52,"-") -> Navyatha Sagar D | F52: 10766 Navyatha Sagar D | G52: B - Bangalore | H52: Purchase Order-Blr | I52: 1135026 Gaurav Khurana | J52: SB 22267 | K52: Direct Expense | L52: Invoices for inward supply from unregistered person | N52: 6 | O52: 90 Days | P52: Pending Approval | Q52: BU North | R52: Event Management | S52: Delhi | T52: TRUE | U52: Nexus-Karnataka | V52: Indian Rupee | W52: MANPOWER SUPPLY | X52: Manpower Supply | Y52: 1 | Z52: 65000 | AA52: Pravesh | AB52: 1044913 Parvesh Mahalwal | AC52: CGST Input for KT (DT) 9%
A53: B/2025/PO/000020 | B53: B/2025/PO/000020 | C53: 45663 | D53: DJ VJ Joshua-Blr | E53: =_xlfn.TEXTBEFORE(D53,"-") -> DJ VJ Joshua | F53: 12878 DJ VJ Joshua | G53: B - Bangalore | H53: Purchase Order-Blr | I53: 1138596 Yogesh A | J53: SB 22267 | K53: Direct Expense | L53: Invoices for inward supply from unregistered person | N53: 6 | O53: 45 Days | P53: Pending Approval | Q53: BU North | R53: Event Management | S53: Delhi | T53: TRUE | U53: Nexus-Karnataka | V53: Indian Rupee | W53: PERFORMER EXPENSES | X53: Performer Expenses | Y53: 1 | Z53: 60000 | AA53: Parvesh | AB53: 1044913 Parvesh Mahalwal | AC53: CGST Input for KT (DT) 9%
A54: B/2025/PO/000021 | B54: B/2025/PO/000021 | C54: 45663 | D54: Yash Gifts-Blr | E54: =_xlfn.TEXTBEFORE(D54,"-") -> Yash Gifts | F54: 12634 Yash Gifts | G54: B - Bangalore | H54: Purchase Order-Blr | I54: 1138596 Yogesh A | J54: SB 22267 | K54: Direct Expense | L54: Invoices for inward supply from unregistered person | N54: 6 | O54: 45 Days | P54: Pending Approval | Q54: BU North | R54: Event Management | S54: Delhi | T54: TRUE | U54: Nexus-Karnataka | V54: Indian Rupee | W54: EVENT EXPENSES-GIVE AWAYS | X54: Event Expenses - Giveaways | Y54: 1 | Z54: 107762 | AA54: Abdul Rehman | AB54: 1044827 Abdul Rahman | AC54: CGST Input for KT (DT) 9%
A55: B/2025/PO/000022 | B55: B/2025/PO/000022 | C55: 45663 | D55: Sumair Shariff-Blr | E55: =_xlfn.TEXTBEFORE(D55,"-") -> Sumair Shariff | F55: 11436 Sumair Shariff | G55: B - Bangalore | H55: Purchase Order-Blr | I55: 1138596 Yogesh A | J55: SB 22267 | K55: Direct Expense | L55: Invoices for inward supply from unregistered person | N55: 6 | O55: 90 Days | P55: Pending Approval | Q55: BU North | R55: Event Management | S55: Delhi | T55: TRUE | U55: Nexus-Karnataka | V55: Indian Rupee | W55: MANPOWER SUPPLY | X55: Manpower Supply | Y55: 1 | Z55: 21500 | AA55: Abdul Rehman | AB55: 1044827 Abdul Rahman | AC55: #N/A
A56: B/2025/PO/000023 | B56: B/2025/PO/000023 | C56: 45663 | D56: Foundsys Technologies Pvt Ltd-Blr | E56: =_xlfn.TEXTBEFORE(D56,"-") -> Foundsys Technologies Pvt Ltd | F56: 11931 Foundsys Technologies Pvt Ltd | G56: B - Bangalore | H56: Purchase Order-Blr | I56: 1138596 Yogesh A | J56: SB 22266 | K56: Direct Expense | L56: Invoices for inward supply from unregistered person | N56: 6 | O56: 45 Days | P56: Pending Approval | Q56: BU North | R56: Event Management | S56: Delhi | T56: TRUE | U56: Nexus-Karnataka | V56: Indian Rupee | W56: INTERNET EXPENSES - EVENTS | X56: Internet Expenses - Events | Y56: 1 | Z56: 25000 | AA56: Abdhul Rehman | AB56: 1044827 Abdul Rahman | AC56: CGST Input for KT (DT) 9%
A57: B/2025/PO/000024 | B57: B/2025/PO/000024 | C57: 45663 | D57: S R Creations-Blr | E57: =_xlfn.TEXTBEFORE(D57,"-") -> S R Creations | F57: 11428 S R Creations | G57: B - Bangalore | H57: Purchase Order-Blr | I57: 1115173 Nagaraju R | J57: SB 22285 | K57: Direct Expense | L57: Invoices for inward supply from unregistered person | N57: 6 | O57: 90 Days | P57: Pending Approval | Q57: BU South | R57: Event Management | S57: Bangalore | T57: TRUE | U57: Nexus-Karnataka | V57: Indian Rupee | W57: Event Management Charges (DE) | X57: Event Management Charges | Y57: 1 | Z57: 433710 | AA57: Ravish | AB57: 1129362 Ravish Nair | AC57: CGST Input for KT (DT) 9%
A58: B/2025/PO/000025 | B58: B/2025/PO/000025 | C58: 45663 | D58: Abdul Rehman -CR | E58: =_xlfn.TEXTBEFORE(D58,"-") -> Abdul Rehman | F58: #N/A | G58: B - Bangalore | H58: Purchase Order-Blr | I58: EBP BlrChe | J58: SB 22254 | K58: Direct Expense | L58: Invoices for inward supply from unregistered person | N58: 6 | O58: Immediate | P58: Pending Approval | Q58: BU North | R58: Event Management | S58: Delhi | T58: TRUE | U58: Nexus-Karnataka | V58: Indian Rupee | W58: CONVEYANCE - EVENTS (DE) | X58: Conveyance | Y58: 1 | Z58: 1900 | AA58: Rahul Luthra | AB58: 1132253 Rahul Luthra | AC58: #N/A
A59: C/2025/PO/000006 | B59: C/2025/PO/000006 | C59: 45663 | D59: Gala Event Solutions-Che | E59: =_xlfn.TEXTBEFORE(D59,"-") -> Gala Event Solutions | F59: 11939 Gala Event Solutions | G59: C - Chennai | H59: Purchase Order-Che | I59: 1115173 Nagaraju R | J59: SB 22274 | K59: Direct Expense | L59: Invoices for inward supply from unregistered person | N59: 6 | O59: 45 Days | P59: Pending Approval | Q59: BU South | R59: Event Management | S59: Chennai | T59: TRUE | U59: Nexus-Tamil Nadu | V59: Indian Rupee | W59: Event Management Charges (DE) | X59: Event Management Charges | Y59: 1 | Z59: 126940 | AA59: Ashwath Rao | AB59: 1044942 Ashwath Rao | AC59: CGST Input for TN (DT) 9%
A60: C/2025/PO/000007 | B60: C/2025/PO/000007 | C60: 45663 | D60: Clinton J for Expense-CR | E60: =_xlfn.TEXTBEFORE(D60,"-") -> Clinton J for Expense | F60: #N/A | G60: C - Chennai | H60: Purchase Order-Che | I60: 1115173 Nagaraju R | K60: Indirect Expense | L60: Invoices for inward supply from unregistered person | N60: 6 | O60: Immediate | P60: Pending Approval | T60: TRUE | U60: Nexus-Tamil Nadu | V60: Indian Rupee | W60: Train & Bus Fare (General) | X60: Train & Bus Fare - Events | Y60: 1 | Z60: 2950 | AA60: Anchan Bipin | AB60: 1044804 Bipin Anchan | AC60: #N/A
A61: C/2025/PO/000008 | B61: C/2025/PO/000008 | C61: 45663 | D61: Gala Event Solutions-Che | E61: =_xlfn.TEXTBEFORE(D61,"-") -> Gala Event Solutions | F61: 11939 Gala Event Solutions | G61: C - Chennai | H61: Purchase Order-Che | I61: 1138574 Swapnil Bangal | J61: SB 22284 | K61: Direct Expense | L61: Invoices for inward supply from unregistered person | N61: 6 | O61: 45 Days | P61: Pending Approval | Q61: BU South | R61: Event Management | S61: Chennai | T61: TRUE | U61: Nexus-Tamil Nadu | V61: Indian Rupee | W61: Event Management Charges (DE) | X61: Event Management Charges | Y61: 1 | Z61: 20200 | AA61: Praveen Raj | AB61: 1044869 M Praveen Raj | AC61: CGST Input for TN (DT) 9%
A62: D/2025/PO/000014 | B62: D/2025/PO/000014 | C62: 45663 | D62: Benson Trophies And Awards-Del | E62: =_xlfn.TEXTBEFORE(D62,"-") -> Benson Trophies And Awards | F62: 11719 Benson Trophies And Awards | G62: D - Delhi | H62: Purchase Order-Del | I62: 1138596 Yogesh A | J62: SB 22267 | K62: Direct Expense | L62: Invoices for inward supply from unregistered person | N62: 6 | O62: 45 Days | P62: Pending Approval | Q62: BU North | R62: Event Management | S62: Delhi | T62: TRUE | U62: Nexus-Delhi | V62: Indian Rupee | W62: EVENT EXPENSES-GIVE AWAYS | X62: Event Expenses - Giveaways | Y62: 1 | Z62: 147000 | AA62: Ravi Lal | AC62: CGST Input for DL (DT) 9%
A63: D/2025/PO/000015 | B63: D/2025/PO/000015 | C63: 45663 | D63: Digital Emotions Pvt Ltd-Del | E63: =_xlfn.TEXTBEFORE(D63,"-") -> Digital Emotions Pvt Ltd | F63: 11826 Digital Emotions Pvt Ltd | G63: D - Delhi | H63: Purchase Order-Del | I63: 1044835 Neetu Prakash Poojary | J63: SB 22159 | K63: Direct Expense | L63: Invoices for inward supply from unregistered person | N63: 6 | O63: 45 Days | P63: Pending Approval | Q63: BU North | R63: Event Management | S63: Delhi | T63: TRUE | U63: Nexus-Delhi | V63: Indian Rupee | W63: PROFESSIONAL FEES-EVENTS | X63: Professional Fee - Events | Y63: 1 | Z63: 13500 | AA63: Imran Khan | AB63: 1044965 Imran Khan | AC63: IGST Input for DL (DT) 18%
A64: D/2025/PO/000016 | B64: D/2025/PO/000016 | C64: 45663 | D64: Sunil Kumar -CR | E64: =_xlfn.TEXTBEFORE(D64,"-") -> Sunil Kumar | F64: #N/A | G64: D - Delhi | H64: Purchase Order-Del | I64: 1044835 Neetu Prakash Poojary | J64: SB 22254 | K64: Direct Expense | L64: Invoices for inward supply from unregistered person | N64: 6 | O64: Immediate | P64: Pending Approval | Q64: BU North | R64: Event Management | S64: Delhi | T64: TRUE | U64: Nexus-Delhi | V64: Indian Rupee | W64: CONVEYANCE - EVENTS (DE) | X64: Conveyance | Y64: 1 | Z64: 6120 | AA64: SUNIL KUMAR | AB64: 1142277 Sunil Kumar | AC64: #N/A
A65: D/2025/PO/000017 | B65: D/2025/PO/000017 | C65: 45663 | D65: Nitin Kumar ........... -CR | E65: =_xlfn.TEXTBEFORE(D65,"-") -> Nitin Kumar ........... | F65: #N/A | G65: D - Delhi | H65: Purchase Order-Del | I65: 1044835 Neetu Prakash Poojary | J65: SB 22254 | K65: Direct Expense | L65: Invoices for inward supply from unregistered person | N65: 6 | O65: Immediate | P65: Pending Approval | Q65: BU North | R65: Event Management | S65: Delhi | T65: TRUE | U65: Nexus-Delhi | V65: Indian Rupee | W65: CONVEYANCE - EVENTS (DE) | X65: Conveyance | Y65: 1 | Z65: 1224 | AA65: NITIN KUMAR | AB65: 1044976 Nitin Kumar | AC65: #N/A
A66: D/2025/PO/000018 | B66: D/2025/PO/000018 | C66: 45663 | D66: Yogesh Kumar Bansal -CR | E66: =_xlfn.TEXTBEFORE(D66,"-") -> Yogesh Kumar Bansal | F66: #N/A | G66: D - Delhi | H66: Purchase Order-Del | I66: 1044835 Neetu Prakash Poojary | J66: SB 22254 | K66: Direct Expense | L66: Invoices for inward supply from unregistered person | N66: 6 | O66: Immediate | P66: Pending Approval | Q66: BU North | R66: Event Management | S66: Delhi | T66: TRUE | U66: Nexus-Delhi | V66: Indian Rupee | W66: CONVEYANCE - EVENTS (DE) | X66: Conveyance | Y66: 1 | Z66: 2139 | AA66: YOGESH KUMAR BANSAL | AB66: 1130111 Yogesh Kumar Bansal | AC66: #N/A
A67: D/2025/PO/000019 | B67: D/2025/PO/000019 | C67: 45663 | D67: Yogesh Kumar Bansal -CR | E67: =_xlfn.TEXTBEFORE(D67,"-") -> Yogesh Kumar Bansal | F67: #N/A | G67: D - Delhi | H67: Purchase Order-Del | I67: 1044835 Neetu Prakash Poojary | J67: SB 22254 | K67: Direct Expense | L67: Invoices for inward supply from unregistered person | N67: 6 | O67: Immediate | P67: Pending Approval | Q67: BU North | R67: Event Management | S67: Delhi | T67: TRUE | U67: Nexus-Delhi | V67: Indian Rupee | W67: CONVEYANCE - EVENTS (DE) | X67: Conveyance | Y67: 1 | Z67: 941 | AA67: YOGESH KUMAR BANSAL | AB67: 1130111 Yogesh Kumar Bansal | AC67: #N/A
A68: D/2025/PO/000020 | B68: D/2025/PO/000020 | C68: 45663 | D68: Samarth Kapoor -CR | E68: =_xlfn.TEXTBEFORE(D68,"-") -> Samarth Kapoor | F68: #N/A | G68: D - Delhi | H68: Purchase Order-Del | I68: 1044835 Neetu Prakash Poojary | J68: SB 22254 | K68: Direct Expense | L68: Invoices for inward supply from unregistered person | N68: 6 | O68: Immediate | P68: Pending Approval | Q68: BU North | R68: Event Management | S68: Delhi | T68: TRUE | U68: Nexus-Delhi | V68: Indian Rupee | W68: CONVEYANCE - EVENTS (DE) | X68: Conveyance | Y68: 1 | Z68: 2105 | AA68: SAMARTH KAPOOR | AB68: 1139551 Kapoor Samarth | AC68: #N/A
A69: D/2025/PO/000021 | B69: D/2025/PO/000021 | C69: 45663 | D69: Beats Light & Sound Pvt Ltd-Del | E69: =_xlfn.TEXTBEFORE(D69,"-") -> Beats Light & Sound Pvt Ltd | F69: 11717 Beats Light & Sound Pvt Ltd | G69: D - Delhi | H69: Purchase Order-Del | I69: 1138596 Yogesh A | J69: SB 22159 | K69: Direct Expense | L69: Invoices for inward supply from unregistered person | N69: 6 | O69: 45 Days | P69: Pending Approval | Q69: BU North | R69: Event Management | S69: Delhi | T69: TRUE | U69: Nexus-Delhi | V69: Indian Rupee | W69: EQUIPMENTS & TECHNICAL OPERATION CHGS. | X69: Equipment & Technical Operation Charges | Y69: 1 | Z69: 2950000 | AA69: Sonia Thakur | AB69: 1114836 Sonia Thakur | AC69: CGST Input for DL (DT) 9%
A70: D/2025/PO/000022 | B70: D/2025/PO/000022 | C70: 45663 | D70: Shivam Video Pvt.Ltd.-Del | E70: =_xlfn.TEXTBEFORE(D70,"-") -> Shivam Video Pvt.Ltd. | F70: #N/A | G70: D - Delhi | H70: Purchase Order-Del | I70: 1138596 Yogesh A | J70: SB 22159 | K70: Direct Expense | L70: Invoices for inward supply from unregistered person | N70: 6 | O70: 45 Days | P70: Pending Approval | Q70: BU North | R70: Event Management | S70: Delhi | T70: TRUE | U70: Nexus-Delhi | V70: Indian Rupee | W70: EQUIPMENTS & TECHNICAL OPERATION CHGS. | X70: Equipment & Technical Operation Charges | Y70: 1 | Z70: 2650000 | AA70: Sonia | AB70: 1114836 Sonia Thakur | AC70: CGST Input for DL (DT) 9%
A71: D/2025/PO/000023 | B71: D/2025/PO/000023 | C71: 45663 | D71: Ravi.........-CR | E71: =_xlfn.TEXTBEFORE(D71,"-") -> Ravi......... | F71: #N/A | G71: D - Delhi | H71: Purchase Order-Del | I71: 1044835 Neetu Prakash Poojary | J71: SB 22254 | K71: Direct Expense | L71: Invoices for inward supply from unregistered person | N71: 6 | O71: Immediate | P71: Pending Approval | Q71: BU North | R71: Event Management | S71: Delhi | T71: TRUE | U71: Nexus-Delhi | V71: Indian Rupee | W71: CONVEYANCE - EVENTS (DE) | X71: Conveyance | Y71: 1 | Z71: 694 | AA71: RAVI | AC71: #N/A
A72: D/2025/PO/000024 | B72: D/2025/PO/000024 | C72: 45663 | D72: All4One Events-Del | E72: =_xlfn.TEXTBEFORE(D72,"-") -> All4One Events | F72: 11655 All4One Events | G72: D - Delhi | H72: Purchase Order-Del | I72: 1138596 Yogesh A | J72: SB 22159 | K72: Direct Expense | L72: Invoices for inward supply from unregistered person | N72: 6 | O72: 45 Days | P72: Pending Approval | Q72: BU North | R72: Event Management | S72: Delhi | T72: TRUE | U72: Nexus-Delhi | V72: Indian Rupee | W72: MANPOWER SUPPLY | X72: Manpower Supply | Y72: 1 | Z72: 1225000 | AA72: Sonia | AB72: 1114836 Sonia Thakur | AC72: CGST Input for DL (DT) 9%
A73: D/2025/PO/000025 | B73: D/2025/PO/000025 | C73: 45663 | D73: Anurag Jadli -CR | E73: =_xlfn.TEXTBEFORE(D73,"-") -> Anurag Jadli | F73: #N/A | G73: D - Delhi | H73: Purchase Order-Del | I73: 1044835 Neetu Prakash Poojary | J73: SB 22254 | K73: Direct Expense | L73: Invoices for inward supply from unregistered person | N73: 6 | O73: Immediate | P73: Pending Approval | Q73: BU North | R73: Event Management | S73: Delhi | T73: TRUE | U73: Nexus-Delhi | V73: Indian Rupee | W73: CONVEYANCE - EVENTS (DE) | X73: Conveyance | Y73: 1 | Z73: 4564 | AA73: ANURAG JADLI | AB73: 1132963 Anurag Jadli | AC73: #N/A
A74: D/2025/PO/000026 | B74: D/2025/PO/000026 | C74: 45663 | D74: Ask 4 Car Care- Delhi-Del | E74: =_xlfn.TEXTBEFORE(D74,"-") -> Ask 4 Car Care | F74: 11687 Ask 4 Car Care | G74: D - Delhi | H74: Purchase Order-Del | I74: 1138596 Yogesh A | J74: SB 22159 | K74: Direct Expense | L74: Invoices for inward supply from unregistered person | N74: 6 | O74: 45 Days | P74: Pending Approval | Q74: BU North | R74: Event Management | S74: Delhi | T74: TRUE | U74: Nexus-Delhi | V74: Indian Rupee | W74: EVENT EXPENSES /OTHERS | X74: Event Expenses - Others | Y74: 1 | Z74: 366800 | AA74: Sonia | AB74: 1114836 Sonia Thakur | AC74: CGST Input for DL (DT) 9%
A75: D/2025/PO/000027 | B75: D/2025/PO/000027 | C75: 45663 | D75: Shield Guard India Pvt Ltd-Del | E75: =_xlfn.TEXTBEFORE(D75,"-") -> Shield Guard India Pvt Ltd | F75: 12387 Shield Guard India Pvt Ltd | G75: D - Delhi | H75: Purchase Order-Del | I75: 1138596 Yogesh A | J75: SB 22159 | K75: Direct Expense | L75: Invoices for inward supply from unregistered person | N75: 6 | O75: 45 Days | P75: Pending Approval | Q75: BU North | R75: Event Management | S75: Delhi | T75: TRUE | U75: Nexus-Delhi | V75: Indian Rupee | W75: MANPOWER SUPPLY | X75: Manpower Supply | Y75: 1 | Z75: 689800 | AA75: Sonia Thakur | AB75: 1114836 Sonia Thakur | AC75: CGST Input for DL (DT) 9%
A76: D/2025/PO/000028 | B76: D/2025/PO/000028 | C76: 45663 | D76: Kunwar Singh Chauhan -CR | E76: =_xlfn.TEXTBEFORE(D76,"-") -> Kunwar Singh Chauhan | F76: #N/A | G76: D - Delhi | H76: Purchase Order-Del | I76: 1044835 Neetu Prakash Poojary | J76: SB 22158 | K76: Direct Expense | L76: Invoices for inward supply from unregistered person | N76: 6 | O76: Immediate | P76: Pending Approval | Q76: BU North | R76: Event Management | S76: Delhi | T76: TRUE | U76: Nexus-Delhi | V76: Indian Rupee | W76: CONVEYANCE - EVENTS (DE) | X76: Conveyance | Y76: 1 | Z76: 10895 | AA76: KUNWAR SINGH CHAUHAN | AB76: 1141533 Kunwar Singh Chauhan | AC76: #N/A
A77: D/2025/PO/000028 | B77: D/2025/PO/000028 | C77: 45663 | D77: Kunwar Singh Chauhan -CR | E77: =_xlfn.TEXTBEFORE(D77,"-") -> Kunwar Singh Chauhan | F77: #N/A | G77: D - Delhi | H77: Purchase Order-Del | I77: 1044835 Neetu Prakash Poojary | J77: SB 22158 | K77: Direct Expense | L77: Invoices for inward supply from unregistered person | N77: 6 | O77: Immediate | P77: Pending Approval | Q77: BU North | R77: Event Management | S77: Delhi | T77: TRUE | U77: Nexus-Delhi | V77: Indian Rupee | W77: CONVEYANCE - EVENTS (DE) | X77: Conveyance | Y77: 1 | Z77: 10895 | AA77: KUNWAR SINGH CHAUHAN | AB77: 1141533 Kunwar Singh Chauhan | AC77: #N/A
A78: D/2025/PO/000029 | B78: D/2025/PO/000029 | C78: 45663 | D78: Bodhi Tree Entertainment-Del | E78: =_xlfn.TEXTBEFORE(D78,"-") -> Bodhi Tree Entertainment | F78: 11741 Bodhi Tree Entertainment | G78: D - Delhi | H78: Purchase Order-Del | I78: 1138596 Yogesh A | J78: SB 22159 | K78: Direct Expense | L78: Invoices for inward supply from unregistered person | N78: 6 | O78: 45 Days | P78: Pending Approval | Q78: BU North | R78: Event Management | S78: Delhi | T78: TRUE | U78: Nexus-Delhi | V78: Indian Rupee | W78: PHOTOGRAPHY EXPENSES EVENTS | X78: Photography Expenses - Events | Y78: 1 | Z78: 305000 | AA78: Sonia | AB78: 1114836 Sonia Thakur | AC78: CGST Input for DL (DT) 9%
A79: D/2025/PO/000030 | B79: D/2025/PO/000030 | C79: 45663 | D79: Raghav Bhardwaj -CR | E79: =_xlfn.TEXTBEFORE(D79,"-") -> Raghav Bhardwaj | F79: #N/A | G79: D - Delhi | H79: Purchase Order-Del | I79: 1044835 Neetu Prakash Poojary | J79: SB 22158 | K79: Direct Expense | L79: Invoices for inward supply from unregistered person | N79: 6 | O79: Immediate | P79: Pending Approval | Q79: BU North | R79: Event Management | S79: Delhi | T79: TRUE | U79: Nexus-Delhi | V79: Indian Rupee | W79: CONVEYANCE - EVENTS (DE) | X79: Conveyance | Y79: 1 | Z79: 2777 | AA79: RAGHAV BHARDWAJ | AB79: 1135466 Raghav Bhardwaj | AC79: #N/A
A80: D/2025/PO/000030 | B80: D/2025/PO/000030 | C80: 45663 | D80: Raghav Bhardwaj -CR | E80: =_xlfn.TEXTBEFORE(D80,"-") -> Raghav Bhardwaj | F80: #N/A | G80: D - Delhi | H80: Purchase Order-Del | I80: 1044835 Neetu Prakash Poojary | J80: SB 22158 | K80: Direct Expense | L80: Invoices for inward supply from unregistered person | N80: 6 | O80: Immediate | P80: Pending Approval | Q80: BU North | R80: Event Management | S80: Delhi | T80: TRUE | U80: Nexus-Delhi | V80: Indian Rupee | W80: CONVEYANCE - EVENTS (DE) | X80: Conveyance | Y80: 1 | Z80: 2777 | AA80: RAGHAV BHARDWAJ | AB80: 1135466 Raghav Bhardwaj | AC80: #N/A
A81: D/2025/PO/000031 | B81: D/2025/PO/000031 | C81: 45663 | D81: Webcontxt India Pvt Ltd-Del | E81: =_xlfn.TEXTBEFORE(D81,"-") -> Webcontxt India Pvt Ltd | F81: 12615 Webcontxt India Pvt Ltd | G81: D - Delhi | H81: Purchase Order-Del | I81: 1138596 Yogesh A | J81: SB 22159 | K81: Direct Expense | L81: Invoices for inward supply from unregistered person | N81: 6 | O81: 45 Days | P81: Pending Approval | Q81: BU North | R81: Event Management | S81: Delhi | T81: TRUE | U81: Nexus-Delhi | V81: Indian Rupee | W81: PROFESSIONAL FEES-EVENTS | X81: Professional Fee - Events | Y81: 1 | Z81: 700000 | AA81: Sonia | AB81: 1114836 Sonia Thakur | AC81: IGST Input for DL (DT) 18%
A82: D/2025/PO/000032 | B82: D/2025/PO/000032 | C82: 45663 | D82: Vijender -CR | E82: =_xlfn.TEXTBEFORE(D82,"-") -> Vijender | F82: #N/A | G82: D - Delhi | H82: Purchase Order-Del | I82: 1044835 Neetu Prakash Poojary | J82: SB 22158 | K82: Direct Expense | L82: Invoices for inward supply from unregistered person | N82: 6 | O82: Immediate | P82: Pending Approval | Q82: BU North | R82: Event Management | S82: Delhi | T82: TRUE | U82: Nexus-Delhi | V82: Indian Rupee | W82: SITE EXPENSES - EVENTS | X82: Site Expenses - Events | Y82: 1 | Z82: 1870 | AA82: VIJENDER | AB82: 1128882 Vijender H | AC82: #N/A
A83: D/2025/PO/000033 | B83: D/2025/PO/000033 | C83: 45663 | D83: Brief Cab-Del | E83: =_xlfn.TEXTBEFORE(D83,"-") -> Brief Cab | F83: 11745 Brief Cab | G83: D - Delhi | H83: Purchase Order-Del | I83: 1138596 Yogesh A | J83: SB 22159 | K83: Direct Expense | L83: Invoices for inward supply from unregistered person | N83: 6 | O83: 45 Days | P83: Pending Approval | Q83: BU North | R83: Event Management | S83: Delhi | T83: TRUE | U83: Nexus-Delhi | V83: Indian Rupee | W83: PROFESSIONAL FEES-EVENTS | X83: Professional Fee - Events | Y83: 1 | Z83: 280000 | AA83: Sonia | AB83: 1114836 Sonia Thakur | AC83: IGST Input for DL (DT) 18%
A84: D/2025/PO/000034 | B84: D/2025/PO/000034 | C84: 45663 | D84: Keshav Sargur -CR | E84: =_xlfn.TEXTBEFORE(D84,"-") -> Keshav Sargur | F84: #N/A | G84: D - Delhi | H84: Purchase Order-Del | I84: 1044835 Neetu Prakash Poojary | J84: SB 22158 | K84: Direct Expense | L84: Invoices for inward supply from unregistered person | N84: 6 | O84: Immediate | P84: Pending Approval | Q84: BU North | R84: Event Management | S84: Delhi | T84: TRUE | U84: Nexus-Delhi | V84: Indian Rupee | W84: CONVEYANCE - EVENTS (DE) | X84: Conveyance | Y84: 1 | Z84: 652 | AA84: KESHAV SARGUR | AB84: 1137430 Keshav Sargur | AC84: #N/A
A85: D/2025/PO/000035 | B85: D/2025/PO/000035 | C85: 45663 | D85: Minter Cstech Pvt.Ltd.-Del | E85: =_xlfn.TEXTBEFORE(D85,"-") -> Minter Cstech Pvt.Ltd. | F85: #N/A | G85: D - Delhi | H85: Purchase Order-Del | I85: 1138596 Yogesh A | J85: SB 22159 | K85: Direct Expense | L85: Invoices for inward supply from unregistered person | N85: 6 | O85: 45 Days | P85: Pending Approval | Q85: BU North | R85: Event Management | S85: Delhi | T85: TRUE | U85: Nexus-Delhi | V85: Indian Rupee | W85: EQUIPMENTS & TECHNICAL OPERATION CHGS. | X85: Equipment & Technical Operation Charges | Y85: 1 | Z85: 105000 | AA85: Sonia | AB85: 1114836 Sonia Thakur | AC85: CGST Input for DL (DT) 9%
A86: D/2025/PO/000036 | B86: D/2025/PO/000036 | C86: 45663 | D86: Garv Aggarwal -CR | E86: =_xlfn.TEXTBEFORE(D86,"-") -> Garv Aggarwal | F86: #N/A | G86: D - Delhi | H86: Purchase Order-Del | I86: 1044835 Neetu Prakash Poojary | J86: SB 22267 | K86: Direct Expense | L86: Invoices for inward supply from unregistered person | N86: 6 | O86: Immediate | P86: Pending Approval | Q86: BU North | R86: Event Management | S86: Delhi | T86: TRUE | U86: Nexus-Delhi | V86: Indian Rupee | W86: CONVEYANCE - EVENTS (DE) | X86: Conveyance | Y86: 1 | Z86: 5713 | AA86: GARV AGGARWAL | AB86: 1126975 Garv Aggarwal | AC86: #N/A
A87: D/2025/PO/000037 | B87: D/2025/PO/000037 | C87: 45663 | D87: Garv Aggarwal -CR | E87: =_xlfn.TEXTBEFORE(D87,"-") -> Garv Aggarwal | F87: #N/A | G87: D - Delhi | H87: Purchase Order-Del | I87: 1044835 Neetu Prakash Poojary | J87: SB 22267 | K87: Direct Expense | L87: Invoices for inward supply from unregistered person | N87: 6 | O87: Immediate | P87: Pending Approval | Q87: BU North | R87: Event Management | S87: Delhi | T87: TRUE | U87: Nexus-Delhi | V87: Indian Rupee | W87: SITE EXPENSES - EVENTS | X87: Site Expenses - Events | Y87: 1 | Z87: 1142 | AA87: GARV AGGARWAL | AB87: 1126975 Garv Aggarwal | AC87: #N/A
A88: D/2025/PO/000038 | B88: D/2025/PO/000038 | C88: 45663 | D88: Prachi Signal -CR | E88: =_xlfn.TEXTBEFORE(D88,"-") -> Prachi Signal | F88: #N/A | G88: D - Delhi | H88: Purchase Order-Del | I88: 1044835 Neetu Prakash Poojary | J88: SB 22267 | K88: Direct Expense | L88: Invoices for inward supply from unregistered person | N88: 6 | O88: Immediate | P88: Pending Approval | Q88: BU North | R88: Event Management | S88: Delhi | T88: TRUE | U88: Nexus-Delhi | V88: Indian Rupee | W88: SITE EXPENSES - EVENTS | X88: Site Expenses - Events | Y88: 1 | Z88: 100 | AA88: PRACHI SIGNAL | AB88: 1141542 Prachi Singal | AC88: #N/A
A89: D/2025/PO/000039 | B89: D/2025/PO/000039 | C89: 45663 | D89: Garnertech Innovation Pvt Ltd-Del | E89: =_xlfn.TEXTBEFORE(D89,"-") -> Garnertech Innovation Pvt Ltd | F89: 11941 Garnertech Innovation Pvt Ltd | G89: D - Delhi | H89: Purchase Order-Del | I89: 1138596 Yogesh A | J89: SB 22159 | K89: Direct Expense | L89: Invoices for inward supply from unregistered person | N89: 6 | O89: 45 Days | P89: Pending Approval | Q89: BU North | R89: Event Management | S89: Delhi | T89: TRUE | U89: Nexus-Delhi | V89: Indian Rupee | W89: EQUIPMENTS & TECHNICAL OPERATION CHGS. | X89: Equipment & Technical Operation Charges | Y89: 1 | Z89: 200000 | AA89: Sonia | AB89: 1114836 Sonia Thakur | AC89: CGST Input for DL (DT) 9%
A90: D/2025/PO/000040 | B90: D/2025/PO/000040 | C90: 45663 | D90: Prachi Signal -CR | E90: =_xlfn.TEXTBEFORE(D90,"-") -> Prachi Signal | F90: #N/A | G90: D - Delhi | H90: Purchase Order-Del | I90: 1044835 Neetu Prakash Poojary | J90: SB 22267 | K90: Direct Expense | L90: Invoices for inward supply from unregistered person | N90: 6 | O90: Immediate | P90: Pending Approval | Q90: BU North | R90: Event Management | S90: Delhi | T90: TRUE | U90: Nexus-Delhi | V90: Indian Rupee | W90: CONVEYANCE - EVENTS (DE) | X90: Conveyance | Y90: 1 | Z90: 617 | AA90: PRACHI SIGNAL | AB90: 1141542 Prachi Singal | AC90: #N/A
A91: D/2025/PO/000041 | B91: D/2025/PO/000041 | C91: 45663 | D91: Priyanka Nagi -CR | E91: =_xlfn.TEXTBEFORE(D91,"-") -> Priyanka Nagi | F91: #N/A | G91: D - Delhi | H91: Purchase Order-Del | I91: 1044835 Neetu Prakash Poojary | J91: SB 22266 | K91: Direct Expense | L91: Invoices for inward supply from unregistered person | N91: 6 | O91: Immediate | P91: Pending Approval | Q91: BU North | R91: Event Management | S91: Delhi | T91: TRUE | U91: Nexus-Delhi | V91: Indian Rupee | W91: CONVEYANCE - EVENTS (DE) | X91: Conveyance | Y91: 1 | Z91: 2078 | AA91: PRIYANKA NAGI | AB91: 1141333 Priyanka Nagi | AC91: #N/A
A92: D/2025/PO/000042 | B92: D/2025/PO/000042 | C92: 45663 | D92: Sadika Madan -CR | E92: =_xlfn.TEXTBEFORE(D92,"-") -> Sadika Madan | F92: #N/A | G92: D - Delhi | H92: Purchase Order-Del | I92: 1044835 Neetu Prakash Poojary | J92: SB 22159 | K92: Direct Expense | L92: Invoices for inward supply from unregistered person | N92: 6 | O92: Immediate | P92: Pending Approval | Q92: BU North | R92: Event Management | S92: Delhi | T92: TRUE | U92: Nexus-Delhi | V92: Indian Rupee | W92: CONVEYANCE - EVENTS (DE) | X92: Conveyance | Y92: 1 | Z92: 6592 | AA92: SADIKA MADAN | AB92: #N/A | AC92: #N/A
A93: D/2025/PO/000043 | B93: D/2025/PO/000043 | C93: 45663 | D93: Kunwar Singh Chauhan -CR | E93: =_xlfn.TEXTBEFORE(D93,"-") -> Kunwar Singh Chauhan | F93: #N/A | G93: D - Delhi | H93: Purchase Order-Del | I93: 1044835 Neetu Prakash Poojary | J93: SB 22159 | K93: Direct Expense | L93: Invoices for inward supply from unregistered person | N93: 6 | O93: Immediate | P93: Pending Approval | Q93: BU North | R93: Event Management | S93: Delhi | T93: TRUE | U93: Nexus-Delhi | V93: Indian Rupee | W93: EVENT EXPENSES /OTHERS | X93: Event Expenses - Others | Y93: 1 | Z93: 9250 | AA93: KUNWAR SINGH CHAUHAN | AB93: 1141533 Kunwar Singh Chauhan | AC93: #N/A
A94: D/2025/PO/000044 | B94: D/2025/PO/000044 | C94: 45663 | D94: Kunwar Singh Chauhan -CR | E94: =_xlfn.TEXTBEFORE(D94,"-") -> Kunwar Singh Chauhan | F94: #N/A | G94: D - Delhi | H94: Purchase Order-Del | I94: 1044835 Neetu Prakash Poojary | J94: SB 22159 | K94: Direct Expense | L94: Invoices for inward supply from unregistered person | N94: 6 | O94: Immediate | P94: Pending Approval | Q94: BU North | R94: Event Management | S94: Delhi | T94: TRUE | U94: Nexus-Delhi | V94: Indian Rupee | W94: CONVEYANCE - EVENTS (DE) | X94: Conveyance | Y94: 1 | Z94: 2230 | AA94: KUNWAR SINGH CHAUHAN | AB94: 1141533 Kunwar Singh Chauhan | AC94: #N/A
A95: D/2025/PO/000045 | B95: D/2025/PO/000045 | C95: 45663 | D95: Kunwar Singh Chauhan -CR | E95: =_xlfn.TEXTBEFORE(D95,"-") -> Kunwar Singh Chauhan | F95: #N/A | G95: D - Delhi | H95: Purchase Order-Del | I95: 1044835 Neetu Prakash Poojary | J95: SB 22159 | K95: Direct Expense | L95: Invoices for inward supply from unregistered person | N95: 6 | O95: Immediate | P95: Pending Approval | Q95: BU North | R95: Event Management | S95: Delhi | T95: TRUE | U95: Nexus-Delhi | V95: Indian Rupee | W95: SITE EXPENSES - EVENTS | X95: Site Expenses - Events | Y95: 1 | Z95: 670 | AA95: KUNWAR SINGH CHAUHAN | AB95: 1141533 Kunwar Singh Chauhan | AC95: #N/A
A96: D/2025/PO/000046 | B96: D/2025/PO/000046 | C96: 45663 | D96: Kunwar Singh Chauhan -CR | E96: =_xlfn.TEXTBEFORE(D96,"-") -> Kunwar Singh Chauhan | F96: #N/A | G96: D - Delhi | H96: Purchase Order-Del | I96: 1044835 Neetu Prakash Poojary | J96: SB 22159 | K96: Direct Expense | L96: Invoices for inward supply from unregistered person | N96: 6 | O96: Immediate | P96: Pending Approval | Q96: BU North | R96: Event Management | S96: Delhi | T96: TRUE | U96: Nexus-Delhi | V96: Indian Rupee | W96: CONVEYANCE - EVENTS (DE) | X96: Conveyance | Y96: 1 | Z96: 2070 | AA96: KUNWAR SINGH CHAUHAN | AB96: 1141533 Kunwar Singh Chauhan | AC96: #N/A
A97: D/2025/PO/000047 | B97: D/2025/PO/000047 | C97: 45663 | D97: Kunwar Singh Chauhan -CR | E97: =_xlfn.TEXTBEFORE(D97,"-") -> Kunwar Singh Chauhan | F97: #N/A | G97: D - Delhi | H97: Purchase Order-Del | I97: 1044835 Neetu Prakash Poojary | J97: SB 22159 | K97: Direct Expense | L97: Invoices for inward supply from unregistered person | N97: 6 | O97: Immediate | P97: Pending Approval | Q97: BU North | R97: Event Management | S97: Delhi | T97: TRUE | U97: Nexus-Delhi | V97: Indian Rupee | W97: CONVEYANCE - EVENTS (DE) | X97: Conveyance | Y97: 1 | Z97: 3900 | AA97: KUNWAR SINGH CHAUHAN | AB97: 1141533 Kunwar Singh Chauhan | AC97: #N/A
A98: D/2025/PO/000048 | B98: D/2025/PO/000048 | C98: 45663 | D98: Ajeet Singh -CR | E98: =_xlfn.TEXTBEFORE(D98,"-") -> Ajeet Singh | F98: 10519 Ajeet Singh | G98: D - Delhi | H98: Purchase Order-Del | I98: 1044835 Neetu Prakash Poojary | J98: SB 22159 | K98: Direct Expense | L98: Invoices for inward supply from unregistered person | N98: 6 | O98: Immediate | P98: Pending Approval | Q98: BU North | R98: Event Management | S98: Delhi | T98: TRUE | U98: Nexus-Delhi | V98: Indian Rupee | W98: CONVEYANCE - EVENTS (DE) | X98: Conveyance | Y98: 1 | Z98: 4083 | AA98: AJEET SINGH | AB98: 1141982 Ajeet Singh | AC98: #N/A
A99: D/2025/PO/000049 | B99: D/2025/PO/000049 | C99: 45663 | D99: Sidhant Saxena.....-CR | E99: =_xlfn.TEXTBEFORE(D99,"-") -> Sidhant Saxena..... | F99: #N/A | G99: D - Delhi | H99: Purchase Order-Del | I99: 1044835 Neetu Prakash Poojary | J99: SB 22159 | K99: Direct Expense | L99: Invoices for inward supply from unregistered person | N99: 6 | O99: Immediate | P99: Pending Approval | Q99: BU North | R99: Event Management | S99: Delhi | T99: TRUE | U99: Nexus-Delhi | V99: Indian Rupee | W99: CONVEYANCE - EVENTS (DE) | X99: Conveyance | Y99: 1 | Z99: 9144 | AA99: SIDHANT SAXENA | AB99: 1044810 Sidhant Saxena | AC99: #N/A
A100: D/2025/PO/000050 | B100: D/2025/PO/000050 | C100: 45663 | D100: Innovative Gifting Solutions-Del | E100: =_xlfn.TEXTBEFORE(D100,"-") -> Innovative Gifting Solutions | F100: 11264 Innovative Gifting Solutions | G100: D - Delhi | H100: Purchase Order-Del | I100: 1138596 Yogesh A | J100: SB 22279 | K100: Direct Expense | L100: Invoices for inward supply from unregistered person | N100: 6 | O100: 90 Days | P100: Pending Approval | Q100: BU North | R100: Event Management | S100: Delhi | T100: TRUE | U100: Nexus-Delhi | V100: Indian Rupee | W100: EVENT EXPENSES-GIVE AWAYS | X100: Event Expenses - Giveaways | Y100: 1 | Z100: 870000 | AA100: Amarpreet Singh | AB100: 1044857 Amarpreet Singh | AC100: CGST Input for DL (DT) 9%
...

Sheet PO Final
A1: Date | B1: Order | C1: Particulars | D1: Quantity | E1: Unit Price | F1: Branch | G1: Vendor | J1: Branch | K1: Created By | L1: Project | M1: Type of Expense | N1: Nature of Document | O1: Place of Supply | P1: Subsidiary | Q1: Terms | R1: Approval Status | S1: Department | T1: Line of business | U1: Subsidiary Location | V1: Nexus Override | W1: Nexus
B2: B/2025/PO/000001 | C2: Office Rent | D2: 1 | E2: 245446 | F2: 245446 | G2: =VLOOKUP(B2,'PO with created By ASR'!A:C,3,FALSE) -> 45658 | J2: =VLOOKUP(B2,'PO with created By ASR'!A:G,4,FALSE) -> H P Ramareddy-Blr | K2: =VLOOKUP(B2,'PO with created By ASR'!A:I,6,FALSE) -> 11014 H P Ramareddy | L2: =VLOOKUP(B2,'PO with created By ASR'!A:J,7,FALSE) -> B - Bangalore | M2: =VLOOKUP(B2,'PO with created By ASR'!A:K,8,FALSE) -> Purchase Order-Blr | N2: Invoices for inward supply from unregistered person | P2: 6
B3: B/2025/PO/000002 | C3: Office Rent | D3: 1 | E3: 245446 | F3: 245446 | G3: =VLOOKUP(B3,'PO with created By ASR'!A:C,3,FALSE) -> 45658 | J3: =VLOOKUP(B3,'PO with created By ASR'!A:G,4,FALSE) -> A Ramareddy (Rent)-Blr | K3: =VLOOKUP(B3,'PO with created By ASR'!A:I,6,FALSE) -> 11009 A Ramareddy (Rent) | L3: =VLOOKUP(B3,'PO with created By ASR'!A:J,7,FALSE) -> B - Bangalore | M3: =VLOOKUP(B3,'PO with created By ASR'!A:K,8,FALSE) -> Purchase Order-Blr | N3: Invoices for inward supply from unregistered person | P3: 6
B4: B/2025/PO/000003 | C4: Water Charges | D4: 1 | E4: 4000 | F4: 4000 | G4: =VLOOKUP(B4,'PO with created By ASR'!A:C,3,FALSE) -> 45658 | J4: =VLOOKUP(B4,'PO with created By ASR'!A:G,4,FALSE) -> H P Ramareddy Utility-Blr | K4: =VLOOKUP(B4,'PO with created By ASR'!A:I,6,FALSE) -> 11015 H P Ramareddy Utility | L4: =VLOOKUP(B4,'PO with created By ASR'!A:J,7,FALSE) -> B - Bangalore | M4: =VLOOKUP(B4,'PO with created By ASR'!A:K,8,FALSE) -> Purchase Order-Blr | N4: Invoices for inward supply from unregistered person | P4: 6
B5: B/2025/PO/000004 | C5: STAY CHARGES (DE) | D5: 1 | E5: 279000 | F5: 279000 | G5: =VLOOKUP(B5,'PO with created By ASR'!A:C,3,FALSE) -> 45658 | J5: =VLOOKUP(B5,'PO with created By ASR'!A:G,4,FALSE) -> Renaissance Bengaluru Race Course Hotel (Dharampal Satyapal Ltd)-Blr | K5: =VLOOKUP(B5,'PO with created By ASR'!A:I,6,FALSE) -> 10403 Renaissance Bengaluru Race Course Hotel (Dharampal Satyapal Ltd) | L5: =VLOOKUP(B5,'PO with created By ASR'!A:J,7,FALSE) -> B - Bangalore | M5: =VLOOKUP(B5,'PO with created By ASR'!A:K,8,FALSE) -> Purchase Order-Blr | N5: Invoices for inward supply from unregistered person | P5: 6
B6: B/2025/PO/000005 | C6: Electricity Expenses | D6: 1 | E6: 19073 | F6: 19073 | G6: =VLOOKUP(B6,'PO with created By ASR'!A:C,3,FALSE) -> 45658 | J6: =VLOOKUP(B6,'PO with created By ASR'!A:G,4,FALSE) -> H P Ramareddy Utility-Blr | K6: =VLOOKUP(B6,'PO with created By ASR'!A:I,6,FALSE) -> 11015 H P Ramareddy Utility | L6: =VLOOKUP(B6,'PO with created By ASR'!A:J,7,FALSE) -> B - Bangalore | M6: =VLOOKUP(B6,'PO with created By ASR'!A:K,8,FALSE) -> Purchase Order-Blr | N6: Invoices for inward supply from unregistered person | P6: 6
B7: B/2025/PO/000006 | C7: Security Charges | D7: 1 | E7: 48991 | F7: 48991 | G7: =VLOOKUP(B7,'PO with created By ASR'!A:C,3,FALSE) -> 45658 | J7: =VLOOKUP(B7,'PO with created By ASR'!A:G,4,FALSE) -> Lynx Security & Detectives Services (P) Ltd-Blr | K7: =VLOOKUP(B7,'PO with created By ASR'!A:I,6,FALSE) -> 11520 Lynx Security & Detectives Services (P) Ltd | L7: =VLOOKUP(B7,'PO with created By ASR'!A:J,7,FALSE) -> B - Bangalore | M7: =VLOOKUP(B7,'PO with created By ASR'!A:K,8,FALSE) -> Purchase Order-Blr | N7: Invoices for inward supply from unregistered person | P7: 6
B8: B/2025/PO/000006 | C8: Office Maintainance Expenses | D8: 1 | E8: 23151 | F8: 23151 | G8: =VLOOKUP(B8,'PO with created By ASR'!A:C,3,FALSE) -> 45658 | J8: =VLOOKUP(B8,'PO with created By ASR'!A:G,4,FALSE) -> Lynx Security & Detectives Services (P) Ltd-Blr | K8: =VLOOKUP(B8,'PO with created By ASR'!A:I,6,FALSE) -> 11520 Lynx Security & Detectives Services (P) Ltd | L8: =VLOOKUP(B8,'PO with created By ASR'!A:J,7,FALSE) -> B - Bangalore | M8: =VLOOKUP(B8,'PO with created By ASR'!A:K,8,FALSE) -> Purchase Order-Blr | N8: Invoices for inward supply from unregistered person | P8: 6
B9: B/2025/PO/000007 | C9: Water Charges | D9: 1 | E9: 1610 | F9: 1610 | G9: =VLOOKUP(B9,'PO with created By ASR'!A:C,3,FALSE) -> 45658 | J9: =VLOOKUP(B9,'PO with created By ASR'!A:G,4,FALSE) -> Mayur Enterprises-Blr | K9: =VLOOKUP(B9,'PO with created By ASR'!A:I,6,FALSE) -> 11521 Mayur Enterprises | L9: =VLOOKUP(B9,'PO with created By ASR'!A:J,7,FALSE) -> B - Bangalore | M9: =VLOOKUP(B9,'PO with created By ASR'!A:K,8,FALSE) -> Purchase Order-Blr | N9: Invoices for inward supply from unregistered person | P9: 6
B10: B/2025/PO/000007 | C10: Ineligible CGST Input-Gen | D10: 1 | E10: 97 | F10: 97 | G10: =VLOOKUP(B10,'PO with created By ASR'!A:C,3,FALSE) -> 45658 | J10: =VLOOKUP(B10,'PO with created By ASR'!A:G,4,FALSE) -> Mayur Enterprises-Blr | K10: =VLOOKUP(B10,'PO with created By ASR'!A:I,6,FALSE) -> 11521 Mayur Enterprises | L10: =VLOOKUP(B10,'PO with created By ASR'!A:J,7,FALSE) -> B - Bangalore | M10: =VLOOKUP(B10,'PO with created By ASR'!A:K,8,FALSE) -> Purchase Order-Blr | N10: Invoices for inward supply from unregistered person | P10: 6
B11: B/2025/PO/000007 | C11: Ineligible SGST Input-Gen | D11: 1 | E11: 97 | F11: 97 | G11: =VLOOKUP(B11,'PO with created By ASR'!A:C,3,FALSE) -> 45658 | J11: =VLOOKUP(B11,'PO with created By ASR'!A:G,4,FALSE) -> Mayur Enterprises-Blr | K11: =VLOOKUP(B11,'PO with created By ASR'!A:I,6,FALSE) -> 11521 Mayur Enterprises | L11: =VLOOKUP(B11,'PO with created By ASR'!A:J,7,FALSE) -> B - Bangalore | M11: =VLOOKUP(B11,'PO with created By ASR'!A:K,8,FALSE) -> Purchase Order-Blr | N11: Invoices for inward supply from unregistered person | P11: 6
B12: B/2025/PO/000008 | C12: Rent - Storage Room | D12: 1 | E12: 27500 | F12: 27500 | G12: =VLOOKUP(B12,'PO with created By ASR'!A:C,3,FALSE) -> 45658 | J12: =VLOOKUP(B12,'PO with created By ASR'!A:G,4,FALSE) -> K Vishwanath Gouda Rent-Blr | K12: =VLOOKUP(B12,'PO with created By ASR'!A:I,6,FALSE) -> 11016 K Vishwanath Gouda Rent | L12: =VLOOKUP(B12,'PO with created By ASR'!A:J,7,FALSE) -> B - Bangalore | M12: =VLOOKUP(B12,'PO with created By ASR'!A:K,8,FALSE) -> Purchase Order-Blr | N12: Invoices for inward supply from unregistered person | P12: 6
B13: B/2025/PO/000009 | C13: Computer Hire Charges | D13: 1 | E13: 3500 | F13: 3500 | G13: =VLOOKUP(B13,'PO with created By ASR'!A:C,3,FALSE) -> 45658 | J13: =VLOOKUP(B13,'PO with created By ASR'!A:G,4,FALSE) -> K-Corp-Blr | K13: =VLOOKUP(B13,'PO with created By ASR'!A:I,6,FALSE) -> #N/A | L13: =VLOOKUP(B13,'PO with created By ASR'!A:J,7,FALSE) -> B - Bangalore | M13: =VLOOKUP(B13,'PO with created By ASR'!A:K,8,FALSE) -> Purchase Order-Blr | N13: Invoices for inward supply from unregistered person | P13: 6
... B3105: A/2025/PO/000987 | C3105: Air Fare (General) | D3105: 1 | E3105: 29997 | F3105: 29997 | G3105: =VLOOKUP(B3105,'PO with created By ASR'!A:C,3,FALSE) -> 45715 | J3105: =VLOOKUP(B3105,'PO with created By ASR'!A:G,4,FALSE) -> Musafir.Com India Pvt Ltd-Mum | K3105: =VLOOKUP(B3105,'PO with created By ASR'!A:I,6,FALSE) -> 10060 Musafir.Com India Pvt Ltd | L3105: =VLOOKUP(B3105,'PO with created By ASR'!A:J,7,FALSE) -> A - Mumbai | M3105: =VLOOKUP(B3105,'PO with created By ASR'!A:K,8,FALSE) -> Purchase Order-Mum | N3105: Invoices for inward supply from unregistered person | P3105: 6
