Workbook

Sheet April - May All Journal 
A1: Internal ID | B1: Internal ID | C1: Date | D1: Period | E1: Type | F1: Voucher Number | G1: Name | H1: Account | I1: Memo | J1: Amount
A2: 3371 | B2: 3371 | C2: 45748 | D2: Apr 2025 | E2: Journal | F2: A/2025/JV/1525 | G2: 1045050 Padmakar Jadhav | H2: 1252 LOANS, SECURITY & OTHER RECEIVABLES < 1YEAR : OTHER LOANS & ADVANCES : Advance To Employees | J2: 434
A3: 3376 | B3: 3376 | C3: 45776 | D3: Apr 2025 | E3: Journal | F3: A/2025/JV/1981 | G3: 1044833 Nazia M | H3: 10340 LOANS, SECURITY & OTHER RECEIVABLES < 1YEAR : LOANS TO EMPLOYEES | J3: -42000
A4: 3387 | B4: 3387 | C4: 45776 | D4: Apr 2025 | E4: Journal | F4: A/2025/JV/1985 | G4: 1044945 Pravin Mahajan | H4: 1133 STAFF RELATED LIABILITIES (NO BONUSES) : SALARY & WAGES PAYABLE : Reimbursement | I4: Being Provision for Reimbursement for the month of April 2025 | J4: 32500
A5: 3387 | B5: 3387 | C5: 45776 | D5: Apr 2025 | E5: Journal | F5: A/2025/JV/1985 | G5: 1044810 Sidhant Saxena | H5: 1133 STAFF RELATED LIABILITIES (NO BONUSES) : SALARY & WAGES PAYABLE : Reimbursement | I5: Being Provision for Reimbursement for the month of April 2025 | J5: 32500
A6: 3387 | B6: 3387 | C6: 45776 | D6: Apr 2025 | E6: Journal | F6: A/2025/JV/1985 | G6: 1115298 Sony Parikh | H6: 1133 STAFF RELATED LIABILITIES (NO BONUSES) : SALARY & WAGES PAYABLE : Reimbursement | I6: Being Provision for Reimbursement for the month of April 2025 | J6: 30000
A7: 3387 | B7: 3387 | C7: 45776 | D7: Apr 2025 | E7: Journal | F7: A/2025/JV/1985 | G7: 1138617 Tejas Damania | H7: 1133 STAFF RELATED LIABILITIES (NO BONUSES) : SALARY & WAGES PAYABLE : Reimbursement | I7: Being Provision for Reimbursement for the month of April 2025 | J7: 24000
A8: 3390 | B8: 3390 | C8: 45776 | D8: Apr 2025 | E8: Journal | F8: A/2025/JV/1973 | G8: 1143735 Arun Kumar M | H8: 1252 LOANS, SECURITY & OTHER RECEIVABLES < 1YEAR : OTHER LOANS & ADVANCES : Advance To Employees | I8: Being Advance Account Recoverd from Salary for the month of April 2025 | J8: -5291
A9: 3390 | B9: 3390 | C9: 45776 | D9: Apr 2025 | E9: Journal | F9: A/2025/JV/1973 | G9: 1119879 Kapeel Parmekar | H9: 1252 LOANS, SECURITY & OTHER RECEIVABLES < 1YEAR : OTHER LOANS & ADVANCES : Advance To Employees | I9: Being Advance Account Recoverd from Salary for the month of April 2025 | J9: -13398.56
A10: 3390 | B10: 3390 | C10: 45776 | D10: Apr 2025 | E10: Journal | F10: A/2025/JV/1973 | G10: 1144574 Mahesh D | H10: 1252 LOANS, SECURITY & OTHER RECEIVABLES < 1YEAR : OTHER LOANS & ADVANCES : Advance To Employees | I10: Being Advance Account Recoverd from Salary for the month of April 2025 | J10: -1852
A11: 3404 | B11: 3404 | C11: 45748 | D11: Apr 2025 | E11: Journal | F11: A/2025/JV/1534 | G11: 1044950 Santosh Singh | H11: 1252 LOANS, SECURITY & OTHER RECEIVABLES < 1YEAR : OTHER LOANS & ADVANCES : Advance To Employees | I11: Being on Account to Santosh Singh for SB 22540 SAP Now 2025 | J11: 25000
A12: 3458 | B12: 3458 | C12: 45748 | D12: Apr 2025 | E12: Journal | F12: A/2025/JV/1535 | G12: 1126217 Ritu Vohra | H12: 1252 LOANS, SECURITY & OTHER RECEIVABLES < 1YEAR : OTHER LOANS & ADVANCES : Advance To Employees | I12: Being on Account to Ritu Vohra for BU 7 SB 15860 Meeting | J12: 17000
A13: 3459 | B13: 3459 | C13: 45748 | D13: Apr 2025 | E13: Journal | F13: A/2025/JV/1536 | G13: 1133840 Srinivasa Dasari | H13: 1252 LOANS, SECURITY & OTHER RECEIVABLES < 1YEAR : OTHER LOANS & ADVANCES : Advance To Employees | I13: Being on Account to Srinivasa Dasari for BU 9 Bangalore SB 22565 Apparel Fashion Tech World on 04.04.2025 | J13: 13530
A14: 3460 | B14: 3460 | C14: 45748 | D14: Apr 2025 | E14: Journal | F14: A/2025/JV/1537 | G14: 1044966 Harshit Jain | H14: 1252 LOANS, SECURITY & OTHER RECEIVABLES < 1YEAR : OTHER LOANS & ADVANCES : Advance To Employees | I14: Being on Account to Harshit Jain for SB 22344 BU 7 A Github Galaxy 2025 | J14: 100000
A15: 3461 | B15: 3461 | C15: 45748 | D15: Apr 2025 | E15: Journal | F15: A/2025/JV/1538 | G15: 1044826 Hazarat Ansari | H15: 1252 LOANS, SECURITY & OTHER RECEIVABLES < 1YEAR : OTHER LOANS & ADVANCES : Advance To Employees | I15: Being On Account to Hazarat Ansari for BU 1 Rajesh SB 22511 Accenture Interns Welcome Networking Dinner. | J15: 10000
... A215: 4696 | B215: 4696 | C215: 45764 | D215: Apr 2025 | E215: Journal | F215: A/2025/JV/1730 | G215: 1044827 Abdul Rahman | H215: 1252 LOANS, SECURITY & OTHER RECEIVABLES < 1YEAR : OTHER LOANS & ADVANCES : Advance To Employees | I215: Being On Account to Abdul Rehman for SB 22559 HPE Cloud Connect. | J215: 10000
A216: 4697 | B216: 4697 | C216: 45748 | D216: Apr 2025 | E216: Journal | F216: A/2025/JV/1515/Rev | G216: 13128 Credit Card Dues (MIS) Credit Card Dues (MIS) | H216: Accounts Payable | J216: -26496206
A217: 4698 | B217: 4698 | C217: 45764 | D217: Apr 2025 | E217: Journal | F217: A/2025/JV/1731 | G217: 1137927 Chahek Poddar | H217: 1252 LOANS, SECURITY & OTHER RECEIVABLES < 1YEAR : OTHER LOANS & ADVANCES : Advance To Employees | I217: Being Fund Transfer to Chahek Poddar for Credit Balance. | J217: 25244.38
A218: 4699 | B218: 4699 | C218: 45764 | D218: Apr 2025 | E218: Journal | F218: A/2025/JV/1732 | G218: 1044898 Hari Bailwal | H218: 1252 LOANS, SECURITY & OTHER RECEIVABLES < 1YEAR : OTHER LOANS & ADVANCES : Advance To Employees | I218: Being Fund Transfer to Hari Bailwal for Credit Balance. | J218: 36228.94
A219: 4700 | B219: 4700 | C219: 45764 | D219: Apr 2025 | E219: Journal | F219: A/2025/JV/1733 | G219: 1044806 Mangesh Waghmare | H219: 1252 LOANS, SECURITY & OTHER RECEIVABLES < 1YEAR : OTHER LOANS & ADVANCES : Advance To Employees | I219: Being Fund transfer to Mangesh Waghmare for Credit Balance. | J219: 3562
A220: 4701 | B220: 4701 | C220: 45764 | D220: Apr 2025 | E220: Journal | F220: A/2025/JV/1734 | G220: 1143742 Mohammad Danish | H220: 1252 LOANS, SECURITY & OTHER RECEIVABLES < 1YEAR : OTHER LOANS & ADVANCES : Advance To Employees | I220: Being Fund Transfer to Mohammad Danish for Credit Balance. | J220: 10412
A221: 4702 | B221: 4702 | C221: 45764 | D221: Apr 2025 | E221: Journal | F221: A/2025/JV/1735 | G221: 1133034 Pinky Sharma | H221: 1252 LOANS, SECURITY & OTHER RECEIVABLES < 1YEAR : OTHER LOANS & ADVANCES : Advance To Employees | I221: Being Fund Transfer to Pinky Sharma for Credit Balance. | J221: 1300
A222: 4703 | B222: 4703 | C222: 45764 | D222: Apr 2025 | E222: Journal | F222: A/2025/JV/1736 | G222: 1044950 Santosh Singh | H222: 1252 LOANS, SECURITY & OTHER RECEIVABLES < 1YEAR : OTHER LOANS & ADVANCES : Advance To Employees | I222: Being fund transfer to Santosh Singh for Credit Balance. | J222: 20471
A223: 4704 | B223: 4704 | C223: 45764 | D223: Apr 2025 | E223: Journal | F223: A/2025/JV/1737 | G223: 1140518 Tapish Gupta | H223: 1252 LOANS, SECURITY & OTHER RECEIVABLES < 1YEAR : OTHER LOANS & ADVANCES : Advance To Employees | I223: Being fund transfer to Tapish Gupta for Credit Balance. | J223: 5394.87
A224: 4705 | B224: 4705 | C224: 45764 | D224: Apr 2025 | E224: Journal | F224: A/2025/JV/1738 | G224: 1138730 Bitu Kumar | H224: 1252 LOANS, SECURITY & OTHER RECEIVABLES < 1YEAR : OTHER LOANS & ADVANCES : Advance To Employees | I224: Being On Account to Bitu Kumar for SB 15860 . | J224: 10000
A225: 4706 | B225: 4706 | C225: 45764 | D225: Apr 2025 | E225: Journal | F225: A/2025/JV/1739 | G225: 1131024 Anurama V | H225: 1252 LOANS, SECURITY & OTHER RECEIVABLES < 1YEAR : OTHER LOANS & ADVANCES : Advance To Employees | I225: Being On Account to Anurama V for Geberal Expenses. | J225: 1913
A226: 4707 | B226: 4707 | C226: 45764 | D226: Apr 2025 | E226: Journal | F226: A/2025/JV/1740 | G226: 1044863 Sunil Sawant | H226: 1252 LOANS, SECURITY & OTHER RECEIVABLES < 1YEAR : OTHER LOANS & ADVANCES : Advance To Employees | I226: Being On Account to Sunil Sawant for SB 22606 TCS W10K 2025. | J226: 40000
A227: 4708 | B227: 4708 | C227: 45764 | D227: Apr 2025 | E227: Journal | F227: A/2025/JV/1741 | G227: 1045047 Sanil Thombare | H227: 1252 LOANS, SECURITY & OTHER RECEIVABLES < 1YEAR : OTHER LOANS & ADVANCES : Advance To Employees | I227: Being On Account to Sanil Thombare for SB 20100 General Expenses. | J227: 5000
A228: 4709 | B228: 4709 | C228: 45765 | D228: Apr 2025 | E228: Journal | F228: A/2025/JV/1742 | G228: 1044942 Ashwath Rao | H228: 1252 LOANS, SECURITY & OTHER RECEIVABLES < 1YEAR : OTHER LOANS & ADVANCES : Advance To Employees | I228: Being On Account to Ashwath TV for SB 22617 Cognizant NW visit. | J228: 3000
... A234: 4718 | B234: 4718 | C234: 45766 | D234: Apr 2025 | E234: Journal | F234: A/2025/JV/1749 | G234: 1138930 Anandan R | H234: 1252 LOANS, SECURITY & OTHER RECEIVABLES < 1YEAR : OTHER LOANS & ADVANCES : Advance To Employees | I234: Being On Account to R Anandan for BU 8 Chennai SB 22627 Natwest Nasscom GCC Summit 2025. | J234: 27500
A235: 4784 | B235: 4784 | C235: 45777 | D235: Apr 2025 | E235: Journal | F235: A/2025/JV/2032 | G235: 13128 Credit Card Dues (MIS) Credit Card Dues (MIS) | H235: Accounts Payable | J235: 23042960
A236: 4811 | B236: 4811 | C236: 45789 | D236: May 2025 | E236: Journal | F236: A/2025/JV/2143 | G236: 1044808 Sarita Stokes | H236: 1252 LOANS, SECURITY & OTHER RECEIVABLES < 1YEAR : OTHER LOANS & ADVANCES : Advance To Employees | I236: Being On Account to Atish Pawar for SB 20190 EC Expenses Submited to be Sarita Stokes | J236: 8000
A237: 4947 | B237: 4947 | C237: 45794 | D237: May 2025 | E237: Journal | F237: A/2025/JV/2189 | G237: 1136203 Sumit Sangle | H237: 1252 LOANS, SECURITY & OTHER RECEIVABLES < 1YEAR : OTHER LOANS & ADVANCES : Advance To Employees | I237: Being on Account to Sumit Sangle for BU 6 Pravin SB 22691 HUL Dove Scalp Launch Event. | J237: 65000
A238: 4948 | B238: 4948 | C238: 45794 | D238: May 2025 | E238: Journal | F238: A/2025/JV/2190 | G238: 1143165 Karan Nischal | H238: 1252 LOANS, SECURITY & OTHER RECEIVABLES < 1YEAR : OTHER LOANS & ADVANCES : Advance To Employees | I238: Being On Account to Karan Nichal for SB 22561 Dell - Indian Express events in May - 21. | J238: 10000
A239: 4949 | B239: 4949 | C239: 45794 | D239: May 2025 | E239: Journal | F239: A/2025/JV/2191 | G239: 1140645 Seemant Mahalwal | H239: 1252 LOANS, SECURITY & OTHER RECEIVABLES < 1YEAR : OTHER LOANS & ADVANCES : Advance To Employees | I239: Being on Account to Seemant Mahalwal for BU 7 A SB 22657 Google YT Shopping Lifestyle edition. | J239: 5000
A240: 4950 | B240: 4950 | C240: 45794 | D240: May 2025 | E240: Journal | F240: A/2025/JV/2192 | G240: 1045051 Suresh Pardale | H240: 1252 LOANS, SECURITY & OTHER RECEIVABLES < 1YEAR : OTHER LOANS & ADVANCES : Advance To Employees | I240: Being On Account to Suresh Pardale for SB 20100 General Expenses. | J240: 10000
A241: 4951 | B241: 4951 | C241: 45794 | D241: May 2025 | E241: Journal | F241: A/2025/JV/2193 | G241: 1139551 Kapoor Samarth | H241: 1252 LOANS, SECURITY & OTHER RECEIVABLES < 1YEAR : OTHER LOANS & ADVANCES : Advance To Employees | I241: Being On Account to Samarth Kapoor for BU 7 A SB 22690 Vast Data Swags. | J241: 20000
A242: 4952 | B242: 4952 | C242: 45794 | D242: May 2025 | E242: Journal | F242: A/2025/JV/2194 | G242: 1139551 Kapoor Samarth | H242: 1252 LOANS, SECURITY & OTHER RECEIVABLES < 1YEAR : OTHER LOANS & ADVANCES : Advance To Employees | I242: Being on Account to Samarth Kapoor for BU 7 A SB 22690 Vast Data Swags. | J242: 5000
A243: 4953 | B243: 4953 | C243: 45794 | D243: May 2025 | E243: Journal | F243: A/2025/JV/2195 | G243: 1141533 Kunwar Singh Chauhan | H243: 1252 LOANS, SECURITY & OTHER RECEIVABLES < 1YEAR : OTHER LOANS & ADVANCES : Advance To Employees | I243: Being On Account to Kunwar Singh Chauhan for BU 7A SB 22664 Amway BBS Multicity events. | J243: 20500
A244: 4954 | B244: 4954 | C244: 45794 | D244: May 2025 | E244: Journal | F244: A/2025/JV/2196 | G244: 1138381 Naveen Mandal | H244: 1252 LOANS, SECURITY & OTHER RECEIVABLES < 1YEAR : OTHER LOANS & ADVANCES : Advance To Employees | I244: Being On Account to Naveen Mandal for BU 7A SB 22664 Amway BBS Multicity events. | J244: 10000
A245: 4955 | B245: 4955 | C245: 45794 | D245: May 2025 | E245: Journal | F245: A/2025/JV/2197 | G245: 1138730 Bitu Kumar | H245: 1252 LOANS, SECURITY & OTHER RECEIVABLES < 1YEAR : OTHER LOANS & ADVANCES : Advance To Employees | I245: Being on Account to Bitu Kumar for BU 7A SB 22664 Amway BBS Multicity events. | J245: 2000
A246: 4956 | B246: 4956 | C246: 45767 | D246: Apr 2025 | E246: Journal | F246: A/2025/JV/1750 | G246: 1044814 Nandini Nair | H246: 1252 LOANS, SECURITY & OTHER RECEIVABLES < 1YEAR : OTHER LOANS & ADVANCES : Advance To Employees | I246: Being On Account to Nandini Nair for BU 9 Bangalore SB 22629 STT Advantage Employee offsite. | J246: 20000
A247: 4957 | B247: 4957 | C247: 45767 | D247: Apr 2025 | E247: Journal | F247: A/2025/JV/1751 | G247: 1044814 Nandini Nair | H247: 1252 LOANS, SECURITY & OTHER RECEIVABLES < 1YEAR : OTHER LOANS & ADVANCES : Advance To Employees | I247: Being on Account to Nanndini Nair for BU 9 Bangalore SB 22629 STT Advantage Employee offsite. | J247: 30000
... A507: 6465 | B507: 6465 | C507: 45800 | D507: May 2025 | E507: Journal | F507: A/2025/JV/2275 | G507: 1045047 Sanil Thombare | H507: 1252 LOANS, SECURITY & OTHER RECEIVABLES < 1YEAR : OTHER LOANS & ADVANCES : Advance To Employees | I507: Being on account for Sanil Thombare for Siemen Event SB No 22653 | J507: 5000
A508: 6534 | B508: 6534 | C508: 45751 | D508: Apr 2025 | E508: Journal | F508: A/2025/JV/2110837101 | G508: 11508 Bisleri International Pvt Ltd Bisleri International Pvt Ltd | H508: 10208 PROVISION FOR DOUBTFUL RECEIVABLES AND INVENTORIES : MISCELLANEOUS EXPENSES WRITTEN OFF | J508: -0.01
A509: 6534 | B509: 6534 | C509: 45751 | D509: Apr 2025 | E509: Journal | F509: A/2025/JV/2110837101 | G509: 11508 Bisleri International Pvt Ltd Bisleri International Pvt Ltd | H509: Accounts Payable | J509: -0.01
A510: 6535 | B510: 6535 | C510: 45751 | D510: Apr 2025 | E510: Journal | F510: A/2025/JV/2110837102 | G510: 12840 Shah Jaju & Associates Shah Jaju & Associates | H510: 10208 PROVISION FOR DOUBTFUL RECEIVABLES AND INVENTORIES : MISCELLANEOUS EXPENSES WRITTEN OFF | J510: 0.16
A511: 6535 | B511: 6535 | C511: 45751 | D511: Apr 2025 | E511: Journal | F511: A/2025/JV/2110837102 | G511: 12840 Shah Jaju & Associates Shah Jaju & Associates | H511: Accounts Payable | J511: 0.16
A512: 6536 | B512: 6536 | C512: 45752 | D512: Apr 2025 | E512: Journal | F512: A/2025/JV/2110837103 | G512: 12067 Jyoti Fire Services Jyoti Fire Services | H512: 10208 PROVISION FOR DOUBTFUL RECEIVABLES AND INVENTORIES : MISCELLANEOUS EXPENSES WRITTEN OFF | J512: 0.2
A513: 6536 | B513: 6536 | C513: 45752 | D513: Apr 2025 | E513: Journal | F513: A/2025/JV/2110837103 | G513: 12067 Jyoti Fire Services Jyoti Fire Services | H513: Accounts Payable | J513: 0.2
A514: 6537 | B514: 6537 | C514: 45755 | D514: Apr 2025 | E514: Journal | F514: A/2025/JV/2110837104 | G514: 12422 Sneha Hospitality Services Pvt Ltd Sneha Hospitality Services Pvt Ltd | H514: 10208 PROVISION FOR DOUBTFUL RECEIVABLES AND INVENTORIES : MISCELLANEOUS EXPENSES WRITTEN OFF | J514: 0.1
A515: 6537 | B515: 6537 | C515: 45755 | D515: Apr 2025 | E515: Journal | F515: A/2025/JV/2110837104 | G515: 12422 Sneha Hospitality Services Pvt Ltd Sneha Hospitality Services Pvt Ltd | H515: Accounts Payable | J515: 0.1
A516: 6538 | B516: 6538 | C516: 45758 | D516: Apr 2025 | E516: Journal | F516: A/2025/JV/2110837105 | G516: 12394 Shiv Enterprises Shiv Enterprises | H516: 10208 PROVISION FOR DOUBTFUL RECEIVABLES AND INVENTORIES : MISCELLANEOUS EXPENSES WRITTEN OFF | J516: 0.3
A517: 6538 | B517: 6538 | C517: 45758 | D517: Apr 2025 | E517: Journal | F517: A/2025/JV/2110837105 | G517: 12394 Shiv Enterprises Shiv Enterprises | H517: Accounts Payable | J517: 0.3
A518: 6539 | B518: 6539 | C518: 45749 | D518: Apr 2025 | E518: Journal | F518: A/2025/JV/2110837106 | G518: 12317 Rak Lead Events Rak Lead Events | H518: 10208 PROVISION FOR DOUBTFUL RECEIVABLES AND INVENTORIES : MISCELLANEOUS EXPENSES WRITTEN OFF | J518: 0.42
A519: 6539 | B519: 6539 | C519: 45749 | D519: Apr 2025 | E519: Journal | F519: A/2025/JV/2110837106 | G519: 12317 Rak Lead Events Rak Lead Events | H519: Accounts Payable | J519: 0.42
... A649: 6767 | B649: 6767 | C649: 45763 | D649: Apr 2025 | E649: Journal | F649: A/2025/JV/2110837175 | G649: 12106 Login Enterprises Login Enterprises | H649: Accounts Payable | J649: 0.12
A650: 6779 | B650: 6779 | C650: 45801 | D650: May 2025 | E650: Journal | F650: A/2025/JV/2280 | G650: 1141982 Ajeet Singh | H650: 1252 LOANS, SECURITY & OTHER RECEIVABLES < 1YEAR : OTHER LOANS & ADVANCES : Advance To Employees | I650: Being Amount Pool Back from Ajeet Singh Happay A/c. | J650: -1735.71
A651: 6780 | B651: 6780 | C651: 45801 | D651: May 2025 | E651: Journal | F651: A/2025/JV/2281 | G651: 1044808 Sarita Stokes | H651: 1252 LOANS, SECURITY & OTHER RECEIVABLES < 1YEAR : OTHER LOANS & ADVANCES : Advance To Employees | I651: Being On Account to Atish Pawar for ECExpenses Submited to be Sarita Stokes. | J651: 6000
A652: 6781 | B652: 6781 | C652: 45801 | D652: May 2025 | E652: Journal | F652: A/2025/JV/2282 | G652: 1044903 Pankaj Kumar Mishra | H652: 1252 LOANS, SECURITY & OTHER RECEIVABLES < 1YEAR : OTHER LOANS & ADVANCES : Advance To Employees | I652: Being On Account to Pankaj Kumar Mishra for BU 7 A SB 22657 Google YT Shopping Lifestyle edition. | J652: 700
A653: 6782 | B653: 6782 | C653: 45801 | D653: May 2025 | E653: Journal | F653: A/2025/JV/2283 | G653: 1139551 Kapoor Samarth | H653: 1252 LOANS, SECURITY & OTHER RECEIVABLES < 1YEAR : OTHER LOANS & ADVANCES : Advance To Employees | I653: Being On Account to Samarth Kapoor for BU 7 A SB 22704 HPE Aruba CXO Meetup. | J653: 25000
A654: 6783 | B654: 6783 | C654: 45801 | D654: May 2025 | E654: Journal | F654: A/2025/JV/2284 | G654: 1045047 Sanil Thombare | H654: 1252 LOANS, SECURITY & OTHER RECEIVABLES < 1YEAR : OTHER LOANS & ADVANCES : Advance To Employees | I654: Being On Account to Sanil Thombare for BU 6 Pravin SB 22725 siemens PMO visit. | J654: 25000
A655: 6784 | B655: 6784 | C655: 45801 | D655: May 2025 | E655: Journal | F655: A/2025/JV/2285 | G655: 1137927 Chahek Poddar | H655: 1252 LOANS, SECURITY & OTHER RECEIVABLES < 1YEAR : OTHER LOANS & ADVANCES : Advance To Employees | I655: Being On Account to Chahek Poddar for BU 1 Rajesh SB 22710 South Aisa Innovation Awards. | J655: 8000
A656: 6785 | B656: 6785 | C656: 45801 | D656: May 2025 | E656: Journal | F656: A/2025/JV/2286 | G656: 1136203 Sumit Sangle | H656: 1252 LOANS, SECURITY & OTHER RECEIVABLES < 1YEAR : OTHER LOANS & ADVANCES : Advance To Employees | I656: Being On Account to Sumit Sangle for BU 6 Pravin SB 22719 CLPL - Yezdi Adventure Launch 2025. | J656: 5000
A657: 6786 | B657: 6786 | C657: 45801 | D657: May 2025 | E657: Journal | F657: A/2025/JV/2287 | G657: 1044878 Ravi Kumar Lal | H657: 1252 LOANS, SECURITY & OTHER RECEIVABLES < 1YEAR : OTHER LOANS & ADVANCES : Advance To Employees | I657: Being On Account to Ravi for BU 7 A SB 22657 Google YT Shopping Lifestyle edition. | J657: 2000
A658: 6787 | B658: 6787 | C658: 45801 | D658: May 2025 | E658: Journal | F658: A/2025/JV/2288 | G658: 1142458 Bharat Sharma | H658: 1252 LOANS, SECURITY & OTHER RECEIVABLES < 1YEAR : OTHER LOANS & ADVANCES : Advance To Employees | I658: Being On Account to Bharat Sharma for BU 7 A SB 22664 Amway BBS Multicity events. | J658: 7500
A659: 6788 | B659: 6788 | C659: 45801 | D659: May 2025 | E659: Journal | F659: A/2025/JV/2289 | G659: 1044908 Lokesh Sonar | H659: 1252 LOANS, SECURITY & OTHER RECEIVABLES < 1YEAR : OTHER LOANS & ADVANCES : Advance To Employees | I659: Being On Account to Lokesh Sonar for BU 6 Pravin SB 22645 Hul Shiva's Farewell Event. | J659: 25000
A660: 6790 | B660: 6790 | C660: 45775 | D660: Apr 2025 | E660: Journal | F660: D/2025/JV/2110837176 | G660: 11734 Black Pearl Production Pvt Ltd Black Pearl Production Pvt Ltd | H660: 10208 PROVISION FOR DOUBTFUL RECEIVABLES AND INVENTORIES : MISCELLANEOUS EXPENSES WRITTEN OFF | J660: -0.4
A661: 6790 | B661: 6790 | C661: 45775 | D661: Apr 2025 | E661: Journal | F661: D/2025/JV/2110837176 | G661: 11734 Black Pearl Production Pvt Ltd Black Pearl Production Pvt Ltd | H661: Accounts Payable | J661: -0.4
A662: 6899 | B662: 6899 | C662: 45749 | D662: Apr 2025 | E662: Journal | F662: D/2025/JV/2110837178 | G662: 11162 M/S Artworks M/S Artworks | H662: 10208 PROVISION FOR DOUBTFUL RECEIVABLES AND INVENTORIES : MISCELLANEOUS EXPENSES WRITTEN OFF | J662: -0.3
A663: 6899 | B663: 6899 | C663: 45749 | D663: Apr 2025 | E663: Journal | F663: D/2025/JV/2110837178 | G663: 11162 M/S Artworks M/S Artworks | H663: Accounts Payable | J663: -0.3
A664: 6960 | B664: 6960 | C664: 45772 | D664: Apr 2025 | E664: Journal | F664: D/2025/JV/2110837181 | G664: 12812 Royal Vacations Corporate Planners Royal Vacations Corporate Planners | H664: 10208 PROVISION FOR DOUBTFUL RECEIVABLES AND INVENTORIES : MISCELLANEOUS EXPENSES WRITTEN OFF | J664: -0.4
A665: 6960 | B665: 6960 | C665: 45772 | D665: Apr 2025 | E665: Journal | F665: D/2025/JV/2110837181 | G665: 12812 Royal Vacations Corporate Planners Royal Vacations Corporate Planners | H665: Accounts Payable | J665: -0.4
A666: 6970 | B666: 6970 | C666: 45757 | D666: Apr 2025 | E666: Journal | F666: D/2025/JV/0224 | G666: 10457 The Oberoi New Delhi (EIH Ltd) The Oberoi New Delhi (EIH Ltd) | H666: Accounts Payable | I666: Being amnount paid by sameer tobaccowala oberoi delhi | J666: -169825.6
A667: 6970 | B667: 6970 | C667: 45757 | D667: Apr 2025 | E667: Journal | F667: D/2025/JV/0224 | G667: 1045038 Sameer Tobaccowala | H667: 1252 LOANS, SECURITY & OTHER RECEIVABLES < 1YEAR : OTHER LOANS & ADVANCES : Advance To Employees | I667: Being amnount paid by sameer tobaccowala oberoi delhi | J667: -169825.6
A668: 6985 | B668: 6985 | C668: 45754 | D668: Apr 2025 | E668: Journal | F668: D/2025/JV/2110837184 | G668: 11790 Corporate Gift Corporate Gift | H668: 10208 PROVISION FOR DOUBTFUL RECEIVABLES AND INVENTORIES : MISCELLANEOUS EXPENSES WRITTEN OFF | J668: -0.16
A669: 6985 | B669: 6985 | C669: 45754 | D669: Apr 2025 | E669: Journal | F669: D/2025/JV/2110837184 | G669: 11790 Corporate Gift Corporate Gift | H669: Accounts Payable | J669: -0.16
A670: 6987 | B670: 6987 | C670: 45782 | D670: May 2025 | E670: Journal | F670: A/2025/JV/2110837185 | G670: 12299 Pyramid Production Pyramid Production | H670: 10208 PROVISION FOR DOUBTFUL RECEIVABLES AND INVENTORIES : MISCELLANEOUS EXPENSES WRITTEN OFF | J670: 0.4
A671: 6987 | B671: 6987 | C671: 45782 | D671: May 2025 | E671: Journal | F671: A/2025/JV/2110837185 | G671: 12299 Pyramid Production Pyramid Production | H671: Accounts Payable | J671: 0.4
A672: 7105 | B672: 7105 | C672: 45755 | D672: Apr 2025 | E672: Journal | F672: D/2025/JV/2110837187 | G672: 12028 M/S Inked M/S Inked | H672: 10208 PROVISION FOR DOUBTFUL RECEIVABLES AND INVENTORIES : MISCELLANEOUS EXPENSES WRITTEN OFF | J672: 0.28
A673: 7105 | B673: 7105 | C673: 45755 | D673: Apr 2025 | E673: Journal | F673: D/2025/JV/2110837187 | G673: 12028 M/S Inked M/S Inked | H673: Accounts Payable | J673: 0.28
A674: 7107 | B674: 7107 | C674: 45769 | D674: Apr 2025 | E674: Journal | F674: A/2025/JV/2110837188 | G674: 12570 Uneecops Workplace Solutions Pvt Ltd Uneecops Workplace Solutions Pvt Ltd | H674: 10208 PROVISION FOR DOUBTFUL RECEIVABLES AND INVENTORIES : MISCELLANEOUS EXPENSES WRITTEN OFF | J674: -0.4
A675: 7107 | B675: 7107 | C675: 45769 | D675: Apr 2025 | E675: Journal | F675: A/2025/JV/2110837188 | G675: 12570 Uneecops Workplace Solutions Pvt Ltd Uneecops Workplace Solutions Pvt Ltd | H675: Accounts Payable | J675: -0.4
A676: 7109 | B676: 7109 | C676: 45771 | D676: Apr 2025 | E676: Journal | F676: B/2025/JV/2110837189 | G676: 12920 Qutab Entertainment Pvt Ltd Qutab Entertainment Pvt Ltd | H676: 10208 PROVISION FOR DOUBTFUL RECEIVABLES AND INVENTORIES : MISCELLANEOUS EXPENSES WRITTEN OFF | J676: 0.21
A677: 7109 | B677: 7109 | C677: 45771 | D677: Apr 2025 | E677: Journal | F677: B/2025/JV/2110837189 | G677: 12920 Qutab Entertainment Pvt Ltd Qutab Entertainment Pvt Ltd | H677: Accounts Payable | J677: 0.21
A678: 7128 | B678: 7128 | C678: 45769 | D678: Apr 2025 | E678: Journal | F678: A/2025/JV/2110837190 | G678: 11067 MTNL Mumbai MTNL Mumbai | H678: 10208 PROVISION FOR DOUBTFUL RECEIVABLES AND INVENTORIES : MISCELLANEOUS EXPENSES WRITTEN OFF | J678: -23.9
A679: 7128 | B679: 7128 | C679: 45769 | D679: Apr 2025 | E679: Journal | F679: A/2025/JV/2110837190 | G679: 11067 MTNL Mumbai MTNL Mumbai | H679: Accounts Payable | J679: -23.9
... A687: 7157 | B687: 7157 | C687: 45772 | D687: Apr 2025 | E687: Journal | F687: A/2025/JV/2110837194 | G687: 12468 Success Gift Solutions Success Gift Solutions | H687: Accounts Payable | J687: -0.2
A688: 7406 | B688: 7406 | C688: 45802 | D688: May 2025 | E688: Journal | F688: A/2025/JV/2291 | G688: 1044999 Puneet Kumar | H688: 1252 LOANS, SECURITY & OTHER RECEIVABLES < 1YEAR : OTHER LOANS & ADVANCES : Advance To Employees | I688: Being On Account to Puneet Kumar for BU 7 A SB 22664 Amway BBS Multicity events. | J688: 25000
A689: 7407 | B689: 7407 | C689: 45802 | D689: May 2025 | E689: Journal | F689: A/2025/JV/2292 | G689: 1044827 Abdul Rahman | H689: 1252 LOANS, SECURITY & OTHER RECEIVABLES < 1YEAR : OTHER LOANS & ADVANCES : Advance To Employees | I689: Being on Account to Abdul Rehman for BU 7 A SB 22704 HPE Aruba CXO Meetup. | J689: 30000
A690: 7408 | B690: 7408 | C690: 45802 | D690: May 2025 | E690: Journal | F690: A/2025/JV/2293 | G690: 1045065 Mahendra Mane | H690: 1252 LOANS, SECURITY & OTHER RECEIVABLES < 1YEAR : OTHER LOANS & ADVANCES : Advance To Employees | I690: Being On Account to Mahendra Mane for BU 6 Pravin SB 22725 siemens PMO visit. | J690: 5000
A691: 7409 | B691: 7409 | C691: 45802 | D691: May 2025 | E691: Journal | F691: A/2025/JV/2294 | G691: 1132253 Rahul Luthra | H691: 1252 LOANS, SECURITY & OTHER RECEIVABLES < 1YEAR : OTHER LOANS & ADVANCES : Advance To Employees | I691: Being On Account to Rahul Luthra for BU 7 A SB 22704 HPE Aruba CXO Meetup. | J691: 50000
A692: 7410 | B692: 7410 | C692: 45802 | D692: May 2025 | E692: Journal | F692: A/2025/JV/2295 | G692: 1138054 Brijesh CL | H692: 1252 LOANS, SECURITY & OTHER RECEIVABLES < 1YEAR : OTHER LOANS & ADVANCES : Advance To Employees | I692: Being On Account to Brijesh l for BU 9 Bangalore SB 22635 Amazon BOX Installation. | J692: 5000
A693: 7411 | B693: 7411 | C693: 45802 | D693: May 2025 | E693: Journal | F693: A/2025/JV/2296 | G693: 1135929 Farhan Shariff | H693: 1252 LOANS, SECURITY & OTHER RECEIVABLES < 1YEAR : OTHER LOANS & ADVANCES : Advance To Employees | I693: Being On Account to Farhan Shariff for BU 9 Bangalore SB 22699 Amazon PXT Offsite. | J693: 99990
A694: 7412 | B694: 7412 | C694: 45802 | D694: May 2025 | E694: Journal | F694: A/2025/JV/2297 | G694: 1143682 Ashok Raj | H694: 1252 LOANS, SECURITY & OTHER RECEIVABLES < 1YEAR : OTHER LOANS & ADVANCES : Advance To Employees | I694: Being On Account to Ashok Raj for BU 9 Bangalore SB 22711 Glance AI Launch. | J694: 86128
A695: 7413 | B695: 7413 | C695: 45802 | D695: May 2025 | E695: Journal | F695: A/2025/JV/2298 | G695: 1143682 Ashok Raj | H695: 1252 LOANS, SECURITY & OTHER RECEIVABLES < 1YEAR : OTHER LOANS & ADVANCES : Advance To Employees | I695: Being On Account to Ashok Raj for BU 9 Bangalore SB 22659 Amazon Day One at Work. | J695: 10000
A696: 7414 | B696: 7414 | C696: 45802 | D696: May 2025 | E696: Journal | F696: A/2025/JV/2299 | G696: 1138381 Naveen Mandal | H696: 1252 LOANS, SECURITY & OTHER RECEIVABLES < 1YEAR : OTHER LOANS & ADVANCES : Advance To Employees | I696: Being On Account to Naveen Mandal for BU 7 A SB 22679 Amway Artistry Serum Launch. | J696: 10000
A697: 7415 | B697: 7415 | C697: 45803 | D697: May 2025 | E697: Journal | F697: A/2025/JV/2300 | G697: 1139551 Kapoor Samarth | H697: 1252 LOANS, SECURITY & OTHER RECEIVABLES < 1YEAR : OTHER LOANS & ADVANCES : Advance To Employees | I697: Being On Account to Samarth Kapoor for BU 7 A SB 22704 HPE Aruba CXO Meetup. | J697: 50000
A698: 7447 | B698: 7447 | C698: 45771 | D698: Apr 2025 | E698: Journal | F698: D/2025/JV/2110837195 | G698: 12028 M/S Inked M/S Inked | H698: 10208 PROVISION FOR DOUBTFUL RECEIVABLES AND INVENTORIES : MISCELLANEOUS EXPENSES WRITTEN OFF | J698: -0.4
A699: 7447 | B699: 7447 | C699: 45771 | D699: Apr 2025 | E699: Journal | F699: D/2025/JV/2110837195 | G699: 12028 M/S Inked M/S Inked | H699: Accounts Payable | J699: -0.4
...

Sheet April - May Applied Journal 
A1: Internal ID | B1: Date | C1: Period | D1: Type | E1: Voucher Number | F1: Name | G1: Account | H1: Memo | I1: Amount | J1: Type | K1: Journal ID | L1: Journal voucher no | M1: Journal Name | N1: Journal account | O1: Journal amount | P1: Journal Pattern | Q1: Journal voucher no
A2: 7749 | B2: 45751 | C2: Apr 2025 | D2: Bill Payment | E2: A/2025/VP/000942 | F2: 12840 Shah Jaju & Associates Shah Jaju & Associates | G2: Accounts Payable | I2: -15388 | J2: Journal | K2: 6535 | L2: A/2025/JV/2110837102 | M2: 12840 Shah Jaju & Associates Shah Jaju & Associates | N2: Accounts Payable | O2: 0.16 | P2: =_xlfn.CONCAT(K2,M2,N2,O2) -> 653512840 Shah Jaju & Associates Shah Jaju & AssociatesAccounts Payable0.16 | Q2: A/2025/JV/2110837102
A3: 7758 | B3: 45756 | C3: Apr 2025 | D3: Bill Payment | E3: A/2025/VP/001008 | F3: 12244 Pcss Solutions Pvt Ltd Pcss Solutions Pvt Ltd | G3: Accounts Payable | I3: -281604 | J3: Journal | K3: 6562 | L3: A/2025/JV/2110837129 | M3: 12244 Pcss Solutions Pvt Ltd Pcss Solutions Pvt Ltd | N3: Accounts Payable | O3: 0.01 | P3: =_xlfn.CONCAT(K3,M3,N3,O3) -> 656212244 Pcss Solutions Pvt Ltd Pcss Solutions Pvt LtdAccounts Payable0.01 | Q3: A/2025/JV/2110837129
A4: 8791 | B4: 45761 | C4: Apr 2025 | D4: Bill Payment | E4: A/2025/VP/001052 | F4: 10229 Tata Teleservices (Mahrashtra) Ltd Tata Teleservices (Mahrashtra) Ltd | G4: Accounts Payable | I4: -2359 | J4: Journal | K4: 7787 | L4: A/2025/JV/2110837208 | M4: 10229 Tata Teleservices (Mahrashtra) Ltd Tata Teleservices (Mahrashtra) Ltd | N4: Accounts Payable | O4: 0.18 | P4: =_xlfn.CONCAT(K4,M4,N4,O4) -> 778710229 Tata Teleservices (Mahrashtra) Ltd Tata Teleservices (Mahrashtra) LtdAccounts Payable0.18 | Q4: A/2025/JV/2110837208
A5: 8822 | B5: 45775 | C5: Apr 2025 | D5: Bill Payment | E5: A/2025/VP/001255 | F5: 10200 Protean eGov Technologies Ltd Protean eGov Technologies Ltd | G5: Accounts Payable | I5: -419 | J5: Journal | K5: 7837 | L5: A/2025/JV/2110837215 | M5: 10200 Protean eGov Technologies Ltd Protean eGov Technologies Ltd | N5: Accounts Payable | O5: 0.39 | P5: =_xlfn.CONCAT(K5,M5,N5,O5) -> 783710200 Protean eGov Technologies Ltd Protean eGov Technologies LtdAccounts Payable0.39 | Q5: A/2025/JV/2110837215
A6: 9175 | B6: 45762 | C6: Apr 2025 | D6: Bill Payment | E6: A/2025/VP/001093 | F6: 11008 Zinia Natasha Fernandes Zinia Natasha Fernandes | G6: 10530 ACCOUNTS PAYABLE : ACCOUNTS PAYABLE | I6: -46800 | J6: Journal | K6: 9090 | L6: A/2025/JV/1565 | M6: 11008 Zinia Natasha Fernandes Zinia Natasha Fernandes | N6: 10530 ACCOUNTS PAYABLE : ACCOUNTS PAYABLE | O6: 28800 | P6: =_xlfn.CONCAT(K6,M6,N6,O6) -> 909011008 Zinia Natasha Fernandes Zinia Natasha Fernandes10530 ACCOUNTS PAYABLE : ACCOUNTS PAYABLE28800 | Q6: A/2025/JV/1565
A7: 9312 | B7: 45758 | C7: Apr 2025 | D7: Bill Payment | E7: B/2025/VP/000467 | F7: 11520 Lynx Security & Detectives Services (P) Ltd Lynx Security & Detectives Services (P) Ltd | G7: Accounts Payable | I7: -26856 | J7: Journal | K7: 8932 | L7: B/2025/JV/2110837301 | M7: 11520 Lynx Security & Detectives Services (P) Ltd Lynx Security & Detectives Services (P) Ltd | N7: Accounts Payable | O7: 0.82 | P7: =_xlfn.CONCAT(K7,M7,N7,O7) -> 893211520 Lynx Security & Detectives Services (P) Ltd Lynx Security & Detectives Services (P) LtdAccounts Payable0.82 | Q7: B/2025/JV/2110837301
A8: 10803 | B8: 45785 | C8: May 2025 | D8: Bill Payment | E8: A/2025/VP/001345 | F8: 10222 S P Sanghi Airconditioning Pvt Ltd S P Sanghi Airconditioning Pvt Ltd | G8: Accounts Payable | I8: -72890 | J8: Journal | K8: 9818 | L8: A/2025/JV/2110837332 | M8: 10222 S P Sanghi Airconditioning Pvt Ltd S P Sanghi Airconditioning Pvt Ltd | N8: Accounts Payable | O8: 0.16 | P8: =_xlfn.CONCAT(K8,M8,N8,O8) -> 981810222 S P Sanghi Airconditioning Pvt Ltd S P Sanghi Airconditioning Pvt LtdAccounts Payable0.16 | Q8: A/2025/JV/2110837332
A9: 10803 | B9: 45785 | C9: May 2025 | D9: Bill Payment | E9: A/2025/VP/001345 | F9: 10222 S P Sanghi Airconditioning Pvt Ltd S P Sanghi Airconditioning Pvt Ltd | G9: Accounts Payable | I9: -72890 | J9: Journal | K9: 12509 | L9: A/2025/JV/2110837422 | M9: 10222 S P Sanghi Airconditioning Pvt Ltd S P Sanghi Airconditioning Pvt Ltd | N9: Accounts Payable | O9: 0.2 | P9: =_xlfn.CONCAT(K9,M9,N9,O9) -> 1250910222 S P Sanghi Airconditioning Pvt Ltd S P Sanghi Airconditioning Pvt LtdAccounts Payable0.2 | Q9: A/2025/JV/2110837422
A10: 10841 | B10: 45791 | C10: May 2025 | D10: Bill Payment | E10: A/2025/VP/001386 | F10: 12067 Jyoti Fire Services Jyoti Fire Services | G10: Accounts Payable | I10: -4142 | J10: Journal | K10: 6536 | L10: A/2025/JV/2110837103 | M10: 12067 Jyoti Fire Services Jyoti Fire Services | N10: Accounts Payable | O10: 0.2 | P10: =_xlfn.CONCAT(K10,M10,N10,O10) -> 653612067 Jyoti Fire Services Jyoti Fire ServicesAccounts Payable0.2 | Q10: A/2025/JV/2110837103
A11: 10925 | B11: 45768 | C11: Apr 2025 | D11: Bill Payment | E11: D/2025/VP/000713 | F11: 11509 Blue Dart Express Ltd Blue Dart Express Ltd | G11: Accounts Payable | I11: -10006 | J11: Journal | K11: 7488 | L11: D/2025/JV/2110837197 | M11: 11509 Blue Dart Express Ltd Blue Dart Express Ltd | N11: Accounts Payable | O11: 0.29 | P11: =_xlfn.CONCAT(K11,M11,N11,O11) -> 748811509 Blue Dart Express Ltd Blue Dart Express LtdAccounts Payable0.29 | Q11: D/2025/JV/2110837197
A12: 11695 | B12: 45750 | C12: Apr 2025 | D12: Bill Payment | E12: D/2025/VP/000582 | F12: 11533 Vinod Gupta Vinod Gupta | G12: Accounts Payable | I12: -264111 | J12: Journal | K12: 8129 | L12: D/2025/JV/2110837255 | M12: 11533 Vinod Gupta Vinod Gupta | N12: Accounts Payable | O12: 0.12 | P12: =_xlfn.CONCAT(K12,M12,N12,O12) -> 812911533 Vinod Gupta Vinod GuptaAccounts Payable0.12 | Q12: D/2025/JV/2110837255
A13: 12451 | B13: 45763 | C13: Apr 2025 | D13: Receipt | E13: SEC/A/RVA/2025/0476 | F13: 10619 Singapore Investcorp India Pvt Ltd | G13: 10364 TRADE NOTES AND ACCOUNTS RECEIVABLE : SUNDRY DEBTORS | I13: -377464 | J13: Journal | K13: 6554 | L13: A/2025/JV/2110837121 | M13: 10619 Singapore Investcorp India Pvt Ltd | N13: 10364 TRADE NOTES AND ACCOUNTS RECEIVABLE : SUNDRY DEBTORS | O13: 0.46 | P13: =_xlfn.CONCAT(K13,M13,N13,O13) -> 655410619 Singapore Investcorp India Pvt Ltd10364 TRADE NOTES AND ACCOUNTS RECEIVABLE : SUNDRY DEBTORS0.46 | Q13: A/2025/JV/2110837121
... A62: 21665 | B62: 45790 | C62: May 2025 | D62: Bill Payment | E62: A/2025/VP/001378 | F62: 11069 Dell International Services India Pvt Ltd Dell International Services India Pvt Ltd | G62: Accounts Payable | I62: -604215 | J62: Journal | K62: 26856 | L62: A/2025/JV/2110838515 | M62: 11069 Dell International Services India Pvt Ltd Dell International Services India Pvt Ltd | N62: Accounts Payable | O62: 0.2 | P62: =_xlfn.CONCAT(K62,M62,N62,O62) -> 2685611069 Dell International Services India Pvt Ltd Dell International Services India Pvt LtdAccounts Payable0.2 | Q62: A/2025/JV/2110838515
A63: 22328 | B63: 45799 | C63: May 2025 | D63: Receipt | E63: SEC/A/RVA/2025/0651 | F63: 10246 Metro Cash & Carry India Pvt Ltd | G63: 10364 TRADE NOTES AND ACCOUNTS RECEIVABLE : SUNDRY DEBTORS | H63: A/2025/IN/0595 | I63: -400797.72 | J63: Journal | K63: 8088 | L63: A/2025/JV/2110837253 | M63: 10246 Metro Cash & Carry India Pvt Ltd | N63: 10364 TRADE NOTES AND ACCOUNTS RECEIVABLE : SUNDRY DEBTORS | O63: 0.28 | P63: =_xlfn.CONCAT(K63,M63,N63,O63) -> 808810246 Metro Cash & Carry India Pvt Ltd10364 TRADE NOTES AND ACCOUNTS RECEIVABLE : SUNDRY DEBTORS0.28 | Q63: A/2025/JV/2110837253
A64: 22548 | B64: 45807 | C64: May 2025 | D64: Receipt | E64: SEC/B/RVA/2025/0036 | F64: 10731 Bengaluru Airport Services Ltd | G64: Accounts Receivable | H64: A/2025/IN/0584 Tds 10% | I64: -1935371 | J64: Journal | K64: 24070 | L64: A/2025/JV/2110838192 | M64: 10731 Bengaluru Airport Services Ltd | N64: Accounts Receivable | O64: 0.2 | P64: =_xlfn.CONCAT(K64,M64,N64,O64) -> 2407010731 Bengaluru Airport Services LtdAccounts Receivable0.2 | Q64: A/2025/JV/2110838192
A65: 22897 | B65: 45811 | C65: Jun 2025 | D65: Receipt | E65: SEC/D/RVA/2025/0135 | F65: 10426 Microsoft Corporation (I) Pvt Ltd | G65: Accounts Receivable | H65: D/2025/SB/0153 | I65: -505056.57 | J65: Journal | K65: 17178 | L65: D/2025/JV/2110837741 | M65: 10426 Microsoft Corporation (I) Pvt Ltd | N65: Accounts Receivable | O65: 0.3 | P65: =_xlfn.CONCAT(K65,M65,N65,O65) -> 1717810426 Microsoft Corporation (I) Pvt LtdAccounts Receivable0.3 | Q65: D/2025/JV/2110837741
A66: 23125 | B66: 45814 | C66: Jun 2025 | D66: Receipt | E66: SEC/A/RVA/2025/0715 | F66: 10469 Amway India Enterprises Pvt Ltd Amway India Enterprises Pvt Ltd | G66: 10364 TRADE NOTES AND ACCOUNTS RECEIVABLE : SUNDRY DEBTORS | H66: A/2025/IN/0586 Tds 2% | I66: -9002125.5 | J66: Journal | K66: 8079 | L66: A/2025/JV/2110837250 | M66: 10469 Amway India Enterprises Pvt Ltd Amway India Enterprises Pvt Ltd | N66: 10364 TRADE NOTES AND ACCOUNTS RECEIVABLE : SUNDRY DEBTORS | O66: 0.46 | P66: =_xlfn.CONCAT(K66,M66,N66,O66) -> 807910469 Amway India Enterprises Pvt Ltd Amway India Enterprises Pvt Ltd10364 TRADE NOTES AND ACCOUNTS RECEIVABLE : SUNDRY DEBTORS0.46 | Q66: A/2025/JV/2110837250
A67: 23415 | B67: 45820 | C67: Jun 2025 | D67: Receipt | E67: SEC/A/RVA/2025/0750 | F67: 10262 Renault Nissan Technology & Business Centre India Pvt Ltd | G67: 10364 TRADE NOTES AND ACCOUNTS RECEIVABLE : SUNDRY DEBTORS | H67: A/2025/IN/0626,A/2025/IN/0627 Tds 10% | I67: -962945.2 | J67: Journal | K67: 11732 | L67: A/2025/JV/2110837399 | M67: 10262 Renault Nissan Technology & Business Centre India Pvt Ltd | N67: 10364 TRADE NOTES AND ACCOUNTS RECEIVABLE : SUNDRY DEBTORS | O67: 0.2 | P67: =_xlfn.CONCAT(K67,M67,N67,O67) -> 1173210262 Renault Nissan Technology & Business Centre India Pvt Ltd10364 TRADE NOTES AND ACCOUNTS RECEIVABLE : SUNDRY DEBTORS0.2 | Q67: A/2025/JV/2110837399
A68: 23426 | B68: 45820 | C68: Jun 2025 | D68: Receipt | E68: SEC/A/RVA/2025/0764 | F68: 10583 Hitachi Vantara India Pvt Ltd Hitachi Vantara India Pvt Ltd | G68: 10364 TRADE NOTES AND ACCOUNTS RECEIVABLE : SUNDRY DEBTORS | H68: A/2025/IN/0607 Tds 10% | I68: -3780022.4 | J68: Journal | K68: 10910 | L68: A/2025/JV/2110837376 | M68: 10583 Hitachi Vantara India Pvt Ltd Hitachi Vantara India Pvt Ltd | N68: 10364 TRADE NOTES AND ACCOUNTS RECEIVABLE : SUNDRY DEBTORS | O68: 0.4 | P68: =_xlfn.CONCAT(K68,M68,N68,O68) -> 1091010583 Hitachi Vantara India Pvt Ltd Hitachi Vantara India Pvt Ltd10364 TRADE NOTES AND ACCOUNTS RECEIVABLE : SUNDRY DEBTORS0.4 | Q68: A/2025/JV/2110837376
A69: 23434 | B69: 45820 | C69: Jun 2025 | D69: Receipt | E69: SEC/A/RVA/2025/0765 | F69: 10385 Bangalore International Airport Ltd | G69: Accounts Receivable | H69: A/2025/IN/0650 Tds 10% | I69: -5054476 | J69: Journal | K69: 16156 | L69: B/2025/JV/2110837665 | M69: 10385 Bangalore International Airport Ltd | N69: Accounts Receivable | O69: 0.4 | P69: =_xlfn.CONCAT(K69,M69,N69,O69) -> 1615610385 Bangalore International Airport LtdAccounts Receivable0.4 | Q69: B/2025/JV/2110837665
A70: 23710 | B70: 45800 | C70: May 2025 | D70: Receipt | E70: SEC/B/RVA/2025/0032 | F70: 10221 Dbs Bank India Ltd | G70: 10364 TRADE NOTES AND ACCOUNTS RECEIVABLE : SUNDRY DEBTORS | I70: -1078822.8 | J70: Journal | K70: 12497 | L70: B/2025/JV/2110837418 | M70: 10221 Dbs Bank India Ltd | N70: 10364 TRADE NOTES AND ACCOUNTS RECEIVABLE : SUNDRY DEBTORS | O70: 0.2 | P70: =_xlfn.CONCAT(K70,M70,N70,O70) -> 1249710221 Dbs Bank India Ltd10364 TRADE NOTES AND ACCOUNTS RECEIVABLE : SUNDRY DEBTORS0.2 | Q70: B/2025/JV/2110837418
A71: 24111 | B71: 45839 | C71: Jul 2025 | D71: Bill Payment | E71: A/2025/VP/001820 | F71: 13170 Mera Prints Solutions Mera Prints Solutions | G71: Accounts Payable | I71: -26403 | J71: Journal | K71: 22810 | L71: A/2025/JV/2110838131 | M71: 13170 Mera Prints Solutions Mera Prints Solutions | N71: Accounts Payable | O71: 0.5 | P71: =_xlfn.CONCAT(K71,M71,N71,O71) -> 2281013170 Mera Prints Solutions Mera Prints SolutionsAccounts Payable0.5 | Q71: A/2025/JV/2110838131
A72: 24116 | B72: 45842 | C72: Jul 2025 | D72: Bill Payment | E72: A/2025/VP/001865 | F72: 12244 Pcss Solutions Pvt Ltd Pcss Solutions Pvt Ltd | G72: Accounts Payable | I72: -653727 | J72: Journal | K72: 11013 | L72: A/2025/JV/2110837386 | M72: 12244 Pcss Solutions Pvt Ltd Pcss Solutions Pvt Ltd | N72: Accounts Payable | O72: 0.02 | P72: =_xlfn.CONCAT(K72,M72,N72,O72) -> 1101312244 Pcss Solutions Pvt Ltd Pcss Solutions Pvt LtdAccounts Payable0.02 | Q72: A/2025/JV/2110837386
A73: 24362 | B73: 45768 | C73: Apr 2025 | D73: Bill Payment | E73: D/2025/VP/000711 | F73: 11132 Shree Ram Computers Shree Ram Computers | G73: Accounts Payable | I73: -29275 | J73: Journal | K73: 8405 | L73: D/2025/JV/2110837274 | M73: 11132 Shree Ram Computers Shree Ram Computers | N73: Accounts Payable | O73: 0.06 | P73: =_xlfn.CONCAT(K73,M73,N73,O73) -> 840511132 Shree Ram Computers Shree Ram ComputersAccounts Payable0.06 | Q73: D/2025/JV/2110837274
A74: 24362 | B74: 45768 | C74: Apr 2025 | D74: Bill Payment | E74: D/2025/VP/000711 | F74: 11132 Shree Ram Computers Shree Ram Computers | G74: Accounts Payable | I74: -29275 | J74: Journal | K74: 8374 | L74: D/2025/JV/2110837271 | M74: 11132 Shree Ram Computers Shree Ram Computers | N74: Accounts Payable | O74: 0.36 | P74: =_xlfn.CONCAT(K74,M74,N74,O74) -> 837411132 Shree Ram Computers Shree Ram ComputersAccounts Payable0.36 | Q74: D/2025/JV/2110837271
A75: 24647 | B75: 45804 | C75: May 2025 | D75: Bill Payment | E75: B/2025/VP/000681 | F75: 12133 M/S Megascule M/S Megascule | G75: Accounts Payable | I75: -304978 | J75: Journal | K75: 23850 | L75: B/2025/JV/2110838169 | M75: 12133 M/S Megascule M/S Megascule | N75: Accounts Payable | O75: 0.5 | P75: =_xlfn.CONCAT(K75,M75,N75,O75) -> 2385012133 M/S Megascule M/S MegasculeAccounts Payable0.5 | Q75: B/2025/JV/2110838169
A76: 24660 | B76: 45805 | C76: May 2025 | D76: Bill Payment | E76: B/2025/VP/000688 | F76: 12286 Print With Me Pvt Ltd Print With Me Pvt Ltd | G76: Accounts Payable | I76: -37535 | J76: Journal | K76: 10204 | L76: B/2025/JV/2110837355 | M76: 12286 Print With Me Pvt Ltd Print With Me Pvt Ltd | N76: Accounts Payable | O76: 0.46 | P76: =_xlfn.CONCAT(K76,M76,N76,O76) -> 1020412286 Print With Me Pvt Ltd Print With Me Pvt LtdAccounts Payable0.46 | Q76: B/2025/JV/2110837355
A77: 24663 | B77: 45805 | C77: May 2025 | D77: Bill Payment | E77: B/2025/VP/000690 | F77: 12133 M/S Megascule M/S Megascule | G77: Accounts Payable | I77: -33188 | J77: Journal | K77: 10190 | L77: B/2025/JV/2110837352 | M77: 12133 M/S Megascule M/S Megascule | N77: Accounts Payable | O77: 0.5 | P77: =_xlfn.CONCAT(K77,M77,N77,O77) -> 1019012133 M/S Megascule M/S MegasculeAccounts Payable0.5 | Q77: B/2025/JV/2110837352
A78: 24673 | B78: 45806 | C78: May 2025 | D78: Bill Payment | E78: B/2025/VP/000693 | F78: 11795 Courier International Services Courier International Services | G78: Accounts Payable | I78: -87560 | J78: Journal | K78: 20611 | L78: B/2025/JV/2110837982 | M78: 11795 Courier International Services Courier International Services | N78: Accounts Payable | O78: 0.4 | P78: =_xlfn.CONCAT(K78,M78,N78,O78) -> 2061111795 Courier International Services Courier International ServicesAccounts Payable0.4 | Q78: B/2025/JV/2110837982
A79: 24673 | B79: 45806 | C79: May 2025 | D79: Bill Payment | E79: B/2025/VP/000693 | F79: 11795 Courier International Services Courier International Services | G79: Accounts Payable | I79: -87560 | J79: Journal | K79: 19628 | L79: B/2025/JV/2110837931 | M79: 11795 Courier International Services Courier International Services | N79: Accounts Payable | O79: 0.5 | P79: =_xlfn.CONCAT(K79,M79,N79,O79) -> 1962811795 Courier International Services Courier International ServicesAccounts Payable0.5 | Q79: B/2025/JV/2110837931
A80: 24702 | B80: 45805 | C80: May 2025 | D80: Bill Payment | E80: C/2025/VP/000239 | F80: 11915 Fiesta Car Rentals & Logistics Pvt Ltd Fiesta Car Rentals & Logistics Pvt Ltd | G80: Accounts Payable | I80: -1838 | J80: Journal | K80: 8457 | L80: C/2025/JV/2110837276 | M80: 11915 Fiesta Car Rentals & Logistics Pvt Ltd Fiesta Car Rentals & Logistics Pvt Ltd | N80: Accounts Payable | O80: 0.5 | P80: =_xlfn.CONCAT(K80,M80,N80,O80) -> 845711915 Fiesta Car Rentals & Logistics Pvt Ltd Fiesta Car Rentals & Logistics Pvt LtdAccounts Payable0.5 | Q80: C/2025/JV/2110837276
A81: 24706 | B81: 45811 | C81: Jun 2025 | D81: Bill Payment | E81: C/2025/VP/000243 | F81: 13117 Shellcode Pvt Ltd Shellcode Pvt Ltd | G81: Accounts Payable | I81: -23742 | J81: Journal | K81: 23508 | L81: A/2025/JV/2110838154 | M81: 13117 Shellcode Pvt Ltd Shellcode Pvt Ltd | N81: Accounts Payable | O81: 0.26 | P81: =_xlfn.CONCAT(K81,M81,N81,O81) -> 2350813117 Shellcode Pvt Ltd Shellcode Pvt LtdAccounts Payable0.26 | Q81: A/2025/JV/2110838154
... A109: 32305 | B109: 45825 | C109: Jun 2025 | D109: Bill Payment | E109: D/2025/VP/001063 | F109: 11774 M/S Cockpitmarx M/S Cockpitmarx | G109: Accounts Payable | I109: -402768 | J109: Journal | K109: 27629 | L109: D/2025/JV/2110838634 | M109: 11774 M/S Cockpitmarx M/S Cockpitmarx | N109: Accounts Payable | O109: 0.46 | P109: =_xlfn.CONCAT(K109,M109,N109,O109) -> 2762911774 M/S Cockpitmarx M/S CockpitmarxAccounts Payable0.46 | Q109: D/2025/JV/2110838634
A110: 34050 | B110: 45819 | C110: Jun 2025 | D110: Receipt | E110: SEC/A/RVA/2025/0753 | F110: 10592 Kotak Mahindra Bank Ltd | G110: Accounts Receivable | H110: A/2025/IN/0651 Tds 2% | I110: -857450 | J110: Journal | K110: 14369 | L110: A/2025/JV/2110837603 | M110: 10592 Kotak Mahindra Bank Ltd | N110: Accounts Receivable | O110: 0.24 | P110: =_xlfn.CONCAT(K110,M110,N110,O110) -> 1436910592 Kotak Mahindra Bank LtdAccounts Receivable0.24 | Q110: A/2025/JV/2110837603
A111: 34065 | B111: 45827 | C111: Jun 2025 | D111: Receipt | E111: SEC/A/RVA/2025/0785 | F111: 10642 Amazon Seller Services India Pvt Ltd | G111: Accounts Receivable | H111: A/2025/IN/0667 Tds 2% | I111: -506988.44 | J111: Journal | K111: 16173 | L111: A/2025/JV/2110837669 | M111: 10642 Amazon Seller Services India Pvt Ltd | N111: Accounts Receivable | O111: 0.33 | P111: =_xlfn.CONCAT(K111,M111,N111,O111) -> 1617310642 Amazon Seller Services India Pvt LtdAccounts Receivable0.33 | Q111: A/2025/JV/2110837669
A112: 34096 | B112: 45828 | C112: Jun 2025 | D112: Receipt | E112: SEC/A/RVA/2025/0792 | F112: 10141 Google India Pvt Ltd | G112: 10364 TRADE NOTES AND ACCOUNTS RECEIVABLE : SUNDRY DEBTORS | H112: A/2025/IN/0614 | I112: -289466 | J112: Journal | K112: 10945 | L112: A/2025/JV/2110837382 | M112: 10141 Google India Pvt Ltd | N112: 10364 TRADE NOTES AND ACCOUNTS RECEIVABLE : SUNDRY DEBTORS | O112: 0.2 | P112: =_xlfn.CONCAT(K112,M112,N112,O112) -> 1094510141 Google India Pvt Ltd10364 TRADE NOTES AND ACCOUNTS RECEIVABLE : SUNDRY DEBTORS0.2 | Q112: A/2025/JV/2110837382
A113: 34325 | B113: 45838 | C113: Jun 2025 | D113: Receipt | E113: SEC/A/RVA/2025/0824 | F113: 10181 Siemens Ltd | G113: 10364 TRADE NOTES AND ACCOUNTS RECEIVABLE : SUNDRY DEBTORS | H113: A/2025/IN/0573 Tds 10% | I113: -309809 | J113: Journal | K113: 8632 | L113: A/2025/JV/2110837285 | M113: 10181 Siemens Ltd | N113: 10364 TRADE NOTES AND ACCOUNTS RECEIVABLE : SUNDRY DEBTORS | O113: 0.22 | P113: =_xlfn.CONCAT(K113,M113,N113,O113) -> 863210181 Siemens Ltd10364 TRADE NOTES AND ACCOUNTS RECEIVABLE : SUNDRY DEBTORS0.22 | Q113: A/2025/JV/2110837285
A114: 34338 | B114: 45838 | C114: Jun 2025 | D114: Receipt | E114: SEC/A/RVA/2025/0829 | F114: 10397 Dell International Services India Pvt Ltd | G114: Accounts Receivable | H114: A/2025/IN/0659,A/2025/IN/0660,A/2025/IN/0661,A/2025/IN/0662 Tds 10% | I114: -19590414 | J114: Journal | K114: 18248 | L114: D/2025/JV/2110837793 | M114: 10397 Dell International Services India Pvt Ltd | N114: Accounts Receivable | O114: 0.4 | P114: =_xlfn.CONCAT(K114,M114,N114,O114) -> 1824810397 Dell International Services India Pvt LtdAccounts Receivable0.4 | Q114: D/2025/JV/2110837793
A115: 34442 | B115: 45839 | C115: Jul 2025 | D115: Receipt | E115: SEC/A/RVA/2025/0834 | F115: 10412 Hindustan Unilever Ltd | G115: Accounts Receivable | H115: A/2025/IN/0663 Tds 1.90% | I115: -1039150.8 | J115: Journal | K115: 18254 | L115: A/2025/JV/2110837796 | M115: 10412 Hindustan Unilever Ltd | N115: Accounts Receivable | O115: 0.23 | P115: =_xlfn.CONCAT(K115,M115,N115,O115) -> 1825410412 Hindustan Unilever LtdAccounts Receivable0.23 | Q115: A/2025/JV/2110837796
A116: 34513 | B116: 45843 | C116: Jul 2025 | D116: Receipt | E116: SEC/A/RVA/2025/0852 | F116: 10412 Hindustan Unilever Ltd | G116: Accounts Receivable | H116: A/2025/IN/0685,A/2025/IN/0655 Tds 2% A/2025/IN/0663,A/2025/IN/0668,A/2025/IN/0673 as per payment advice old Tds deduct | I116: -224478.24 | J116: Journal | K116: 20714 | L116: A/2025/JV/2110837994 | M116: 10412 Hindustan Unilever Ltd | N116: Accounts Receivable | O116: 0.16 | P116: =_xlfn.CONCAT(K116,M116,N116,O116) -> 2071410412 Hindustan Unilever LtdAccounts Receivable0.16 | Q116: A/2025/JV/2110837994
A117: 34522 | B117: 45846 | C117: Jul 2025 | D117: Receipt | E117: SEC/A/RVA/2025/0855 | F117: 10412 Hindustan Unilever Ltd | G117: Accounts Receivable | H117: A/2025/IN/0686 Tds 2% | I117: -199344.82 | J117: Journal | K117: 20719 | L117: A/2025/JV/2110837995 | M117: 10412 Hindustan Unilever Ltd | N117: Accounts Receivable | O117: 0.18 | P117: =_xlfn.CONCAT(K117,M117,N117,O117) -> 2071910412 Hindustan Unilever LtdAccounts Receivable0.18 | Q117: A/2025/JV/2110837995
A118: 34820 | B118: 45849 | C118: Jul 2025 | D118: Receipt | E118: SEC/A/RVA/2025/0872 | F118: 10181 Siemens Ltd | G118: Accounts Receivable | H118: A/2025/IN/0690 Tds 10% | I118: -611391 | J118: Journal | K118: 20731 | L118: A/2025/JV/2110837998 | M118: 10181 Siemens Ltd | N118: Accounts Receivable | O118: 0.01 | P118: =_xlfn.CONCAT(K118,M118,N118,O118) -> 2073110181 Siemens LtdAccounts Receivable0.01 | Q118: A/2025/JV/2110837998
A119: 34833 | B119: 45849 | C119: Jul 2025 | D119: Receipt | E119: SEC/A/RVA/2025/0875 | F119: 10735 Equinox Business Parks Pvt Ltd | G119: 10364 TRADE NOTES AND ACCOUNTS RECEIVABLE : SUNDRY DEBTORS | H119: A/2025/IN/0514 TDS 10% | I119: -982109 | J119: Journal | K119: 6558 | L119: A/2025/JV/2110837125 | M119: 10735 Equinox Business Parks Pvt Ltd | N119: 10364 TRADE NOTES AND ACCOUNTS RECEIVABLE : SUNDRY DEBTORS | O119: 0.2 | P119: =_xlfn.CONCAT(K119,M119,N119,O119) -> 655810735 Equinox Business Parks Pvt Ltd10364 TRADE NOTES AND ACCOUNTS RECEIVABLE : SUNDRY DEBTORS0.2 | Q119: A/2025/JV/2110837125
A120: 34838 | B120: 45849 | C120: Jul 2025 | D120: Receipt | E120: SEC/A/RVA/2025/0877 | F120: 10141 Google India Pvt Ltd | G120: Accounts Receivable | H120: A/2025/IN/0694 tDS 1.7% | I120: -1912585 | J120: Journal | K120: 32861 | L120: A/2025/JV/2110839015 | M120: 10141 Google India Pvt Ltd | N120: Accounts Receivable | O120: 0.14 | P120: =_xlfn.CONCAT(K120,M120,N120,O120) -> 3286110141 Google India Pvt LtdAccounts Receivable0.14 | Q120: A/2025/JV/2110839015
A121: 34845 | B121: 45852 | C121: Jul 2025 | D121: Receipt | E121: SEC/A/RVA/2025/0879 | F121: 10188 TATA Consultancy Services Ltd | G121: 10364 TRADE NOTES AND ACCOUNTS RECEIVABLE : SUNDRY DEBTORS | H121: A/2025/IN/0243 | I121: -352510.52 | J121: Journal | K121: 7956 | L121: A/2025/JV/2110837231 | M121: 10188 TATA Consultancy Services Ltd | N121: 10364 TRADE NOTES AND ACCOUNTS RECEIVABLE : SUNDRY DEBTORS | O121: 0.36 | P121: =_xlfn.CONCAT(K121,M121,N121,O121) -> 795610188 TATA Consultancy Services Ltd10364 TRADE NOTES AND ACCOUNTS RECEIVABLE : SUNDRY DEBTORS0.36 | Q121: A/2025/JV/2110837231
A122: 35243 | B122: 45797 | C122: May 2025 | D122: Bill Payment | E122: A/2025/VP/001461 | F122: 12391 Shivam Logistics Shivam Logistics | G122: Accounts Payable | I122: -87422.8 | J122: Journal | K122: 28081 | L122: A/2025/JV/2110838643 | M122: 12391 Shivam Logistics Shivam Logistics | N122: Accounts Payable | O122: 0.2 | P122: =_xlfn.CONCAT(K122,M122,N122,O122) -> 2808112391 Shivam Logistics Shivam LogisticsAccounts Payable0.2 | Q122: A/2025/JV/2110838643
A123: 35245 | B123: 45786 | C123: May 2025 | D123: Bill Payment | E123: A/2025/VP/001360 | F123: 10874 Sahil Ruke Sahil Ruke | G123: Accounts Payable | I123: -165972 | J123: Journal | K123: 26181 | L123: A/2025/JV/2110838383 | M123: 10874 Sahil Ruke Sahil Ruke | N123: Accounts Payable | O123: 0.3 | P123: =_xlfn.CONCAT(K123,M123,N123,O123) -> 2618110874 Sahil Ruke Sahil RukeAccounts Payable0.3 | Q123: A/2025/JV/2110838383
A124: 35248 | B124: 45792 | C124: May 2025 | D124: Bill Payment | E124: A/2025/VP/001402 | F124: 12317 Rak Lead Events Rak Lead Events | G124: Accounts Payable | I124: -554136.69 | J124: Journal | K124: 6542 | L124: A/2025/JV/2110837109 | M124: 12317 Rak Lead Events Rak Lead Events | N124: Accounts Payable | O124: 0.24 | P124: =_xlfn.CONCAT(K124,M124,N124,O124) -> 654212317 Rak Lead Events Rak Lead EventsAccounts Payable0.24 | Q124: A/2025/JV/2110837109
A125: 35248 | B125: 45792 | C125: May 2025 | D125: Bill Payment | E125: A/2025/VP/001402 | F125: 12317 Rak Lead Events Rak Lead Events | G125: Accounts Payable | I125: -554136.69 | J125: Journal | K125: 6541 | L125: A/2025/JV/2110837108 | M125: 12317 Rak Lead Events Rak Lead Events | N125: Accounts Payable | O125: 0.4 | P125: =_xlfn.CONCAT(K125,M125,N125,O125) -> 654112317 Rak Lead Events Rak Lead EventsAccounts Payable0.4 | Q125: A/2025/JV/2110837108
A126: 35248 | B126: 45792 | C126: May 2025 | D126: Bill Payment | E126: A/2025/VP/001402 | F126: 12317 Rak Lead Events Rak Lead Events | G126: Accounts Payable | I126: -554136.69 | J126: Journal | K126: 6548 | L126: C/2025/JV/2110837115 | M126: 12317 Rak Lead Events Rak Lead Events | N126: Accounts Payable | O126: 0.02 | P126: =_xlfn.CONCAT(K126,M126,N126,O126) -> 654812317 Rak Lead Events Rak Lead EventsAccounts Payable0.02 | Q126: C/2025/JV/2110837115
A127: 35777 | B127: 45852 | C127: Jul 2025 | D127: Receipt | E127: SEC/A/RVA/2025/0881 | F127: 10181 Siemens Ltd | G127: Accounts Receivable | H127: A/2025/IN/0637,A/2025/IN/0681,A/2025/IN/0695 Tds 10% | I127: -152041 | J127: Journal | K127: 20758 | L127: A/2025/JV/2110838000 | M127: 10181 Siemens Ltd | N127: Accounts Receivable | O127: 0.44 | P127: =_xlfn.CONCAT(K127,M127,N127,O127) -> 2075810181 Siemens LtdAccounts Receivable0.44 | Q127: A/2025/JV/2110838000
A128: 35812 | B128: 45855 | C128: Jul 2025 | D128: Receipt | E128: SEC/A/RVA/2025/0892 | F128: 10412 Hindustan Unilever Ltd | G128: 10364 TRADE NOTES AND ACCOUNTS RECEIVABLE : SUNDRY DEBTORS | H128: A/2025/IN/0560 Tds 2% | I128: -928191.88 | J128: Journal | K128: 6574 | L128: A/2025/JV/2110837142 | M128: 10412 Hindustan Unilever Ltd | N128: 10364 TRADE NOTES AND ACCOUNTS RECEIVABLE : SUNDRY DEBTORS | O128: 0.12 | P128: =_xlfn.CONCAT(K128,M128,N128,O128) -> 657410412 Hindustan Unilever Ltd10364 TRADE NOTES AND ACCOUNTS RECEIVABLE : SUNDRY DEBTORS0.12 | Q128: A/2025/JV/2110837142
A129: 36762 | B129: 45779 | C129: May 2025 | D129: Bill Payment | E129: D/2025/VP/000789 | F129: 12550 M/S Travelnama M/S Travelnama | G129: Accounts Payable | I129: -377105 | J129: Journal | K129: 7804 | L129: D/2025/JV/2110837211 | M129: 12550 M/S Travelnama M/S Travelnama | N129: Accounts Payable | O129: 0.04 | P129: =_xlfn.CONCAT(K129,M129,N129,O129) -> 780412550 M/S Travelnama M/S TravelnamaAccounts Payable0.04 | Q129: D/2025/JV/2110837211
A130: 36802 | B130: 45870 | C130: Aug 2025 | D130: Receipt | E130: SEC/A/RVA/2025/0934 | F130: 10764 TechnoBind Solutions Pvt Ltd | G130: 10364 TRADE NOTES AND ACCOUNTS RECEIVABLE : SUNDRY DEBTORS | I130: -1243627 | J130: Journal | K130: 6565 | L130: A/2025/JV/2110837132 | M130: 10764 TechnoBind Solutions Pvt Ltd | N130: 10364 TRADE NOTES AND ACCOUNTS RECEIVABLE : SUNDRY DEBTORS | O130: 0.5 | P130: =_xlfn.CONCAT(K130,M130,N130,O130) -> 656510764 TechnoBind Solutions Pvt Ltd10364 TRADE NOTES AND ACCOUNTS RECEIVABLE : SUNDRY DEBTORS0.5 | Q130: A/2025/JV/2110837132
A131: 36817 | B131: 45870 | C131: Aug 2025 | D131: Receipt | E131: SEC/A/RVA/2025/0940 | F131: 10264 SAP Labs India Pvt Ltd SAP Labs India Pvt Ltd | G131: 10364 TRADE NOTES AND ACCOUNTS RECEIVABLE : SUNDRY DEBTORS | I131: -747618.04 | J131: Journal | K131: 6573 | L131: A/2025/JV/2110837140 | M131: 10264 SAP Labs India Pvt Ltd SAP Labs India Pvt Ltd | N131: 10364 TRADE NOTES AND ACCOUNTS RECEIVABLE : SUNDRY DEBTORS | O131: 0.36 | P131: =_xlfn.CONCAT(K131,M131,N131,O131) -> 657310264 SAP Labs India Pvt Ltd SAP Labs India Pvt Ltd10364 TRADE NOTES AND ACCOUNTS RECEIVABLE : SUNDRY DEBTORS0.36 | Q131: A/2025/JV/2110837140
A132: 36964 | B132: 45782 | C132: May 2025 | D132: Receipt | E132: SEC/A/RVA/2025/0553 | F132: 10306 Cognizant Technology Solutions India Pvt Ltd Cognizant Technology Solutions India Pvt Ltd | G132: 10364 TRADE NOTES AND ACCOUNTS RECEIVABLE : SUNDRY DEBTORS | H132: A/2025/IN/0506,A/2025/IN/0468,A/2025/IN/0469 Tds 10% | I132: -584935.26 | J132: Journal | K132: 23768 | L132: A/2025/JV/2110838158 | M132: 10306 Cognizant Technology Solutions India Pvt Ltd Cognizant Technology Solutions India Pvt Ltd | N132: 10364 TRADE NOTES AND ACCOUNTS RECEIVABLE : SUNDRY DEBTORS | O132: 0.2 | P132: =_xlfn.CONCAT(K132,M132,N132,O132) -> 2376810306 Cognizant Technology Solutions India Pvt Ltd Cognizant Technology Solutions India Pvt Ltd10364 TRADE NOTES AND ACCOUNTS RECEIVABLE : SUNDRY DEBTORS0.2 | Q132: A/2025/JV/2110838158
A133: 37096 | B133: 45786 | C133: May 2025 | D133: Receipt | E133: SEC/A/RVA/2025/0586 | F133: 10706 Skyflow Labs India Pvt Ltd | G133: 10364 TRADE NOTES AND ACCOUNTS RECEIVABLE : SUNDRY DEBTORS | H133: A/2025/IN/0593 Tds 2% | I133: -228687 | J133: Journal | K133: 8081 | L133: A/2025/JV/2110837251 | M133: 10706 Skyflow Labs India Pvt Ltd | N133: 10364 TRADE NOTES AND ACCOUNTS RECEIVABLE : SUNDRY DEBTORS | O133: 0.08 | P133: =_xlfn.CONCAT(K133,M133,N133,O133) -> 808110706 Skyflow Labs India Pvt Ltd10364 TRADE NOTES AND ACCOUNTS RECEIVABLE : SUNDRY DEBTORS0.08 | Q133: A/2025/JV/2110837251
A134: 37115 | B134: 45790 | C134: May 2025 | D134: Receipt | E134: SEC/A/RVA/2025/0590 | F134: 10412 Hindustan Unilever Ltd | G134: 10364 TRADE NOTES AND ACCOUNTS RECEIVABLE : SUNDRY DEBTORS | H134: A/2025/IN/0475,A/2025/IN/0476,A/2025/IN/0477,A/2025/IN/0483,A/2025/IN/0496 Tds 1.90% | I134: -22408183 | J134: Journal | K134: 7921 | L134: A/2025/JV/2110837223 | M134: 10412 Hindustan Unilever Ltd | N134: 10364 TRADE NOTES AND ACCOUNTS RECEIVABLE : SUNDRY DEBTORS | O134: 0.02 | P134: =_xlfn.CONCAT(K134,M134,N134,O134) -> 792110412 Hindustan Unilever Ltd10364 TRADE NOTES AND ACCOUNTS RECEIVABLE : SUNDRY DEBTORS0.02 | Q134: A/2025/JV/2110837223
A135: 37115 | B135: 45790 | C135: May 2025 | D135: Receipt | E135: SEC/A/RVA/2025/0590 | F135: 10412 Hindustan Unilever Ltd | G135: 10364 TRADE NOTES AND ACCOUNTS RECEIVABLE : SUNDRY DEBTORS | H135: A/2025/IN/0475,A/2025/IN/0476,A/2025/IN/0477,A/2025/IN/0483,A/2025/IN/0496 Tds 1.90% | I135: -22408183 | J135: Journal | K135: 7946 | L135: A/2025/JV/2110837228 | M135: 10412 Hindustan Unilever Ltd | N135: 10364 TRADE NOTES AND ACCOUNTS RECEIVABLE : SUNDRY DEBTORS | O135: 0.5 | P135: =_xlfn.CONCAT(K135,M135,N135,O135) -> 794610412 Hindustan Unilever Ltd10364 TRADE NOTES AND ACCOUNTS RECEIVABLE : SUNDRY DEBTORS0.5 | Q135: A/2025/JV/2110837228
A136: 37115 | B136: 45790 | C136: May 2025 | D136: Receipt | E136: SEC/A/RVA/2025/0590 | F136: 10412 Hindustan Unilever Ltd | G136: 10364 TRADE NOTES AND ACCOUNTS RECEIVABLE : SUNDRY DEBTORS | H136: A/2025/IN/0475,A/2025/IN/0476,A/2025/IN/0477,A/2025/IN/0483,A/2025/IN/0496 Tds 1.90% | I136: -22408183 | J136: Journal | K136: 7967 | L136: A/2025/JV/2110837233 | M136: 10412 Hindustan Unilever Ltd | N136: 10364 TRADE NOTES AND ACCOUNTS RECEIVABLE : SUNDRY DEBTORS | O136: 0.26 | P136: =_xlfn.CONCAT(K136,M136,N136,O136) -> 796710412 Hindustan Unilever Ltd10364 TRADE NOTES AND ACCOUNTS RECEIVABLE : SUNDRY DEBTORS0.26 | Q136: A/2025/JV/2110837233
A137: 37380 | B137: 45793 | C137: May 2025 | D137: Receipt | E137: SEC/A/RVA/2025/0610 | F137: 10306 Cognizant Technology Solutions India Pvt Ltd Cognizant Technology Solutions India Pvt Ltd | G137: 10364 TRADE NOTES AND ACCOUNTS RECEIVABLE : SUNDRY DEBTORS | H137: A/2025/IN/0543,A/2025/IN/0542 Tds 10% | I137: -708771.78 | J137: Journal | K137: 6566 | L137: A/2025/JV/2110837133 | M137: 10306 Cognizant Technology Solutions India Pvt Ltd Cognizant Technology Solutions India Pvt Ltd | N137: 10364 TRADE NOTES AND ACCOUNTS RECEIVABLE : SUNDRY DEBTORS | O137: 0.4 | P137: =_xlfn.CONCAT(K137,M137,N137,O137) -> 656610306 Cognizant Technology Solutions India Pvt Ltd Cognizant Technology Solutions India Pvt Ltd10364 TRADE NOTES AND ACCOUNTS RECEIVABLE : SUNDRY DEBTORS0.4 | Q137: A/2025/JV/2110837133
A138: 37383 | B138: 45794 | C138: May 2025 | D138: Receipt | E138: SEC/B/RVA/2025/0028 | F138: 10088 CIO Association CIO Association | G138: 10364 TRADE NOTES AND ACCOUNTS RECEIVABLE : SUNDRY DEBTORS | H138: B/2025/SB/0047 Tds 2% | I138: -203164.72 | J138: Journal | K138: 12684 | L138: B/2025/JV/2110837431 | M138: 10088 CIO Association CIO Association | N138: 10364 TRADE NOTES AND ACCOUNTS RECEIVABLE : SUNDRY DEBTORS | O138: 0.44 | P138: =_xlfn.CONCAT(K138,M138,N138,O138) -> 1268410088 CIO Association CIO Association10364 TRADE NOTES AND ACCOUNTS RECEIVABLE : SUNDRY DEBTORS0.44 | Q138: B/2025/JV/2110837431
A139: 37394 | B139: 45798 | C139: May 2025 | D139: Receipt | E139: SEC/B/RVA/2025/0030 | F139: 10221 Dbs Bank India Ltd | G139: 10364 TRADE NOTES AND ACCOUNTS RECEIVABLE : SUNDRY DEBTORS | H139: B/2025/SB/0046 Tds 10% | I139: -995519.16 | J139: Journal | K139: 13667 | L139: B/2025/JV/2110837539 | M139: 10221 Dbs Bank India Ltd | N139: 10364 TRADE NOTES AND ACCOUNTS RECEIVABLE : SUNDRY DEBTORS | O139: 0.14 | P139: =_xlfn.CONCAT(K139,M139,N139,O139) -> 1366710221 Dbs Bank India Ltd10364 TRADE NOTES AND ACCOUNTS RECEIVABLE : SUNDRY DEBTORS0.14 | Q139: B/2025/JV/2110837539
A140: 37423 | B140: 45796 | C140: May 2025 | D140: Bill Payment | E140: D/2025/VP/000929 | F140: 11132 Shree Ram Computers Shree Ram Computers | G140: Accounts Payable | I140: -23663 | J140: Journal | K140: 37421 | L140: D/2025/JV/2110839283 | M140: 11132 Shree Ram Computers Shree Ram Computers | N140: Accounts Payable | O140: 0.4 | P140: =_xlfn.CONCAT(K140,M140,N140,O140) -> 3742111132 Shree Ram Computers Shree Ram ComputersAccounts Payable0.4 | Q140: D/2025/JV/2110839283
A141: 37423 | B141: 45796 | C141: May 2025 | D141: Bill Payment | E141: D/2025/VP/000929 | F141: 11132 Shree Ram Computers Shree Ram Computers | G141: Accounts Payable | I141: -23663 | J141: Journal | K141: 14231 | L141: D/2025/JV/2110837585 | M141: 11132 Shree Ram Computers Shree Ram Computers | N141: Accounts Payable | O141: 0.06 | P141: =_xlfn.CONCAT(K141,M141,N141,O141) -> 1423111132 Shree Ram Computers Shree Ram ComputersAccounts Payable0.06 | Q141: D/2025/JV/2110837585
A142: 37426 | B142: 45800 | C142: May 2025 | D142: Receipt | E142: SEC/B/RVA/2025/0033 | F142: 10451 Takasago International India Pvt Ltd | G142: Accounts Receivable | H142: B/2025/SB/0051 Tds 2% | I142: -25010 | J142: Journal | K142: 21602 | L142: B/2025/JV/2110838030 | M142: 10451 Takasago International India Pvt Ltd | N142: Accounts Receivable | O142: 0.2 | P142: =_xlfn.CONCAT(K142,M142,N142,O142) -> 2160210451 Takasago International India Pvt LtdAccounts Receivable0.2 | Q142: B/2025/JV/2110838030
A143: 37432 | B143: 45800 | C143: May 2025 | D143: Receipt | E143: SEC/A/RVA/2025/0657 | F143: 10469 Amway India Enterprises Pvt Ltd Amway India Enterprises Pvt Ltd | G143: 10364 TRADE NOTES AND ACCOUNTS RECEIVABLE : SUNDRY DEBTORS | H143: A/2025/IN/0526 Tds 2% | I143: -6163773.6 | J143: Journal | K143: 8020 | L143: D/2025/JV/2110837243 | M143: 10469 Amway India Enterprises Pvt Ltd Amway India Enterprises Pvt Ltd | N143: 10364 TRADE NOTES AND ACCOUNTS RECEIVABLE : SUNDRY DEBTORS | O143: 0.36 | P143: =_xlfn.CONCAT(K143,M143,N143,O143) -> 802010469 Amway India Enterprises Pvt Ltd Amway India Enterprises Pvt Ltd10364 TRADE NOTES AND ACCOUNTS RECEIVABLE : SUNDRY DEBTORS0.36 | Q143: D/2025/JV/2110837243
A144: 37738 | B144: 45803 | C144: May 2025 | D144: Receipt | E144: SEC/A/RVA/2025/0661 | F144: 10664 GitHub India Pvt Ltd | G144: 10364 TRADE NOTES AND ACCOUNTS RECEIVABLE : SUNDRY DEBTORS | I144: -13275301 | J144: Journal | K144: 23776 | L144: D/2025/JV/2110838159 | M144: 10664 GitHub India Pvt Ltd | N144: 10364 TRADE NOTES AND ACCOUNTS RECEIVABLE : SUNDRY DEBTORS | O144: 0.32 | P144: =_xlfn.CONCAT(K144,M144,N144,O144) -> 2377610664 GitHub India Pvt Ltd10364 TRADE NOTES AND ACCOUNTS RECEIVABLE : SUNDRY DEBTORS0.32 | Q144: D/2025/JV/2110838159
A145: 37738 | B145: 45803 | C145: May 2025 | D145: Receipt | E145: SEC/A/RVA/2025/0661 | F145: 10664 GitHub India Pvt Ltd | G145: 10364 TRADE NOTES AND ACCOUNTS RECEIVABLE : SUNDRY DEBTORS | I145: -13275301 | J145: Journal | K145: 23779 | L145: D/2025/JV/2110838162 | M145: 10664 GitHub India Pvt Ltd | N145: 10364 TRADE NOTES AND ACCOUNTS RECEIVABLE : SUNDRY DEBTORS | O145: 0.42 | P145: =_xlfn.CONCAT(K145,M145,N145,O145) -> 2377910664 GitHub India Pvt Ltd10364 TRADE NOTES AND ACCOUNTS RECEIVABLE : SUNDRY DEBTORS0.42 | Q145: D/2025/JV/2110838162
A146: 37738 | B146: 45803 | C146: May 2025 | D146: Receipt | E146: SEC/A/RVA/2025/0661 | F146: 10664 GitHub India Pvt Ltd | G146: 10364 TRADE NOTES AND ACCOUNTS RECEIVABLE : SUNDRY DEBTORS | I146: -13275301 | J146: Journal | K146: 23778 | L146: D/2025/JV/2110838161 | M146: 10664 GitHub India Pvt Ltd | N146: 10364 TRADE NOTES AND ACCOUNTS RECEIVABLE : SUNDRY DEBTORS | O146: 0.1 | P146: =_xlfn.CONCAT(K146,M146,N146,O146) -> 2377810664 GitHub India Pvt Ltd10364 TRADE NOTES AND ACCOUNTS RECEIVABLE : SUNDRY DEBTORS0.1 | Q146: D/2025/JV/2110838161
A147: 37766 | B147: 45807 | C147: May 2025 | D147: Receipt | E147: SEC/A/RVA/2025/0690 | F147: 10593 Lenovo (India) Pvt Ltd | G147: 10364 TRADE NOTES AND ACCOUNTS RECEIVABLE : SUNDRY DEBTORS | I147: -1077425.9 | J147: Journal | K147: 8066 | L147: A/2025/JV/2110837247 | M147: 10593 Lenovo (India) Pvt Ltd | N147: 10364 TRADE NOTES AND ACCOUNTS RECEIVABLE : SUNDRY DEBTORS | O147: 0.12 | P147: =_xlfn.CONCAT(K147,M147,N147,O147) -> 806610593 Lenovo (India) Pvt Ltd10364 TRADE NOTES AND ACCOUNTS RECEIVABLE : SUNDRY DEBTORS0.12 | Q147: A/2025/JV/2110837247
A148: 38125 | B148: 45800 | C148: May 2025 | D148: Receipt | E148: SEC/A/RVA/2025/0648 | F148: 10306 Cognizant Technology Solutions India Pvt Ltd Cognizant Technology Solutions India Pvt Ltd | G148: 10364 TRADE NOTES AND ACCOUNTS RECEIVABLE : SUNDRY DEBTORS | H148: A/2025/IN/0581,A/2025/IN/0500,A/2025/IN/0502,A/2025/IN/0504 Tds 10% | I148: -3948803.2 | J148: Journal | K148: 8491 | L148: A/2025/JV/2110837278 | M148: 10306 Cognizant Technology Solutions India Pvt Ltd Cognizant Technology Solutions India Pvt Ltd | N148: 10364 TRADE NOTES AND ACCOUNTS RECEIVABLE : SUNDRY DEBTORS | O148: 0.2 | P148: =_xlfn.CONCAT(K148,M148,N148,O148) -> 849110306 Cognizant Technology Solutions India Pvt Ltd Cognizant Technology Solutions India Pvt Ltd10364 TRADE NOTES AND ACCOUNTS RECEIVABLE : SUNDRY DEBTORS0.2 | Q148: A/2025/JV/2110837278
A149: 38125 | B149: 45800 | C149: May 2025 | D149: Receipt | E149: SEC/A/RVA/2025/0648 | F149: 10306 Cognizant Technology Solutions India Pvt Ltd Cognizant Technology Solutions India Pvt Ltd | G149: 10364 TRADE NOTES AND ACCOUNTS RECEIVABLE : SUNDRY DEBTORS | H149: A/2025/IN/0581,A/2025/IN/0500,A/2025/IN/0502,A/2025/IN/0504 Tds 10% | I149: -3948803.2 | J149: Journal | K149: 7981 | L149: A/2025/JV/2110837236 | M149: 10306 Cognizant Technology Solutions India Pvt Ltd Cognizant Technology Solutions India Pvt Ltd | N149: 10364 TRADE NOTES AND ACCOUNTS RECEIVABLE : SUNDRY DEBTORS | O149: 0.28 | P149: =_xlfn.CONCAT(K149,M149,N149,O149) -> 798110306 Cognizant Technology Solutions India Pvt Ltd Cognizant Technology Solutions India Pvt Ltd10364 TRADE NOTES AND ACCOUNTS RECEIVABLE : SUNDRY DEBTORS0.28 | Q149: A/2025/JV/2110837236
A150: 38125 | B150: 45800 | C150: May 2025 | D150: Receipt | E150: SEC/A/RVA/2025/0648 | F150: 10306 Cognizant Technology Solutions India Pvt Ltd Cognizant Technology Solutions India Pvt Ltd | G150: 10364 TRADE NOTES AND ACCOUNTS RECEIVABLE : SUNDRY DEBTORS | H150: A/2025/IN/0581,A/2025/IN/0500,A/2025/IN/0502,A/2025/IN/0504 Tds 10% | I150: -3948803.2 | J150: Journal | K150: 15951 | L150: C/2025/JV/2110837658 | M150: 10306 Cognizant Technology Solutions India Pvt Ltd Cognizant Technology Solutions India Pvt Ltd | N150: 10364 TRADE NOTES AND ACCOUNTS RECEIVABLE : SUNDRY DEBTORS | O150: 0.08 | P150: =_xlfn.CONCAT(K150,M150,N150,O150) -> 1595110306 Cognizant Technology Solutions India Pvt Ltd Cognizant Technology Solutions India Pvt Ltd10364 TRADE NOTES AND ACCOUNTS RECEIVABLE : SUNDRY DEBTORS0.08 | Q150: C/2025/JV/2110837658
A151: 38125 | B151: 45800 | C151: May 2025 | D151: Receipt | E151: SEC/A/RVA/2025/0648 | F151: 10306 Cognizant Technology Solutions India Pvt Ltd Cognizant Technology Solutions India Pvt Ltd | G151: 10364 TRADE NOTES AND ACCOUNTS RECEIVABLE : SUNDRY DEBTORS | H151: A/2025/IN/0581,A/2025/IN/0500,A/2025/IN/0502,A/2025/IN/0504 Tds 10% | I151: -3948803.2 | J151: Journal | K151: 6553 | L151: A/2025/JV/2110837120 | M151: 10306 Cognizant Technology Solutions India Pvt Ltd Cognizant Technology Solutions India Pvt Ltd | N151: 10364 TRADE NOTES AND ACCOUNTS RECEIVABLE : SUNDRY DEBTORS | O151: 0.26 | P151: =_xlfn.CONCAT(K151,M151,N151,O151) -> 655310306 Cognizant Technology Solutions India Pvt Ltd Cognizant Technology Solutions India Pvt Ltd10364 TRADE NOTES AND ACCOUNTS RECEIVABLE : SUNDRY DEBTORS0.26 | Q151: A/2025/JV/2110837120
A152: 38586 | B152: 45834 | C152: Jun 2025 | D152: Receipt | E152: SEC/B/RVA/2025/0044 | F152: 10533 Softcell Technologies Global Pvt Ltd | G152: 10364 TRADE NOTES AND ACCOUNTS RECEIVABLE : SUNDRY DEBTORS | H152: B/2025/SB/0045 Tds 10% | I152: -342553 | J152: Journal | K152: 12681 | L152: B/2025/JV/2110837429 | M152: 10533 Softcell Technologies Global Pvt Ltd | N152: 10364 TRADE NOTES AND ACCOUNTS RECEIVABLE : SUNDRY DEBTORS | O152: 0.49 | P152: =_xlfn.CONCAT(K152,M152,N152,O152) -> 1268110533 Softcell Technologies Global Pvt Ltd10364 TRADE NOTES AND ACCOUNTS RECEIVABLE : SUNDRY DEBTORS0.49 | Q152: B/2025/JV/2110837429
A153: 38591 | B153: 45831 | C153: Jun 2025 | D153: Receipt | E153: SEC/C/RVA/2025/0018 | F153: 10249 NatWest Digital Services India Pvt Ltd (RBS Services India Pvt Ltd) NatWest Digital Services India Pvt Ltd (RBS Services India Pvt Ltd) | G153: Accounts Receivable | H153: C/2025/SB/0021 Tds 10% | I153: -425793.24 | J153: Journal | K153: 20953 | L153: C/2025/JV/2110838010 | M153: 10249 NatWest Digital Services India Pvt Ltd (RBS Services India Pvt Ltd) NatWest Digital Services India Pvt Ltd (RBS Services India Pvt Ltd) | N153: Accounts Receivable | O153: 0.46 | P153: =_xlfn.CONCAT(K153,M153,N153,O153) -> 2095310249 NatWest Digital Services India Pvt Ltd (RBS Services India Pvt Ltd) NatWest Digital Services India Pvt Ltd (RBS Services India Pvt Ltd)Accounts Receivable0.46 | Q153: C/2025/JV/2110838010
A154: 38600 | B154: 45821 | C154: Jun 2025 | D154: Receipt | E154: SEC/D/RVA/2025/0142 | F154: 10043 Kiran Nadar Museum of Art Kiran Nadar Museum of Art | G154: Accounts Receivable | H154: D/2025/SB/0158 TDS 2% | I154: -1928349 | J154: Journal | K154: 16777 | L154: D/2025/JV/2110837723 | M154: 10043 Kiran Nadar Museum of Art Kiran Nadar Museum of Art | N154: Accounts Receivable | O154: 0.4 | P154: =_xlfn.CONCAT(K154,M154,N154,O154) -> 1677710043 Kiran Nadar Museum of Art Kiran Nadar Museum of ArtAccounts Receivable0.4 | Q154: D/2025/JV/2110837723
A155: 38891 | B155: 45835 | C155: Jun 2025 | D155: Receipt | E155: SEC/D/RVA/2025/0153 | F155: 10763 PMG Integrated Communications Pvt Ltd | G155: 10364 TRADE NOTES AND ACCOUNTS RECEIVABLE : SUNDRY DEBTORS | H155: D/2025/SB/0128 Tds 2% | I155: -1819754 | J155: Journal | K155: 6546 | L155: D/2025/JV/2110837113 | M155: 10763 PMG Integrated Communications Pvt Ltd | N155: 10364 TRADE NOTES AND ACCOUNTS RECEIVABLE : SUNDRY DEBTORS | O155: 0.46 | P155: =_xlfn.CONCAT(K155,M155,N155,O155) -> 654610763 PMG Integrated Communications Pvt Ltd10364 TRADE NOTES AND ACCOUNTS RECEIVABLE : SUNDRY DEBTORS0.46 | Q155: D/2025/JV/2110837113
A156: 39258 | B156: 45791 | C156: May 2025 | D156: Bill Payment | E156: D/2025/VP/000873 | F156: 11774 M/S Cockpitmarx M/S Cockpitmarx | G156: Accounts Payable | I156: -273384 | J156: Journal | K156: 8394 | L156: D/2025/JV/2110837273 | M156: 11774 M/S Cockpitmarx M/S Cockpitmarx | N156: Accounts Payable | O156: 0.2 | P156: =_xlfn.CONCAT(K156,M156,N156,O156) -> 839411774 M/S Cockpitmarx M/S CockpitmarxAccounts Payable0.2 | Q156: D/2025/JV/2110837273
A157: 39363 | B157: 45785 | C157: May 2025 | D157: Bill Payment | E157: A/2025/VP/001582 | F157: 13237 Elite International Elite International | G157: Accounts Payable | I157: -14606 | J157: Journal | K157: 32805 | L157: A/2025/JV/2110839009 | M157: 13237 Elite International Elite International | N157: Accounts Payable | O157: 0.36 | P157: =_xlfn.CONCAT(K157,M157,N157,O157) -> 3280513237 Elite International Elite InternationalAccounts Payable0.36 | Q157: A/2025/JV/2110839009
A158: 39608 | B158: 45769 | C158: Apr 2025 | D158: Bill Payment | E158: D/2025/VP/000715 | F158: 11132 Shree Ram Computers Shree Ram Computers | G158: Accounts Payable | I158: -122300 | J158: Journal | K158: 8661 | L158: D/2025/JV/2110837291 | M158: 11132 Shree Ram Computers Shree Ram Computers | N158: Accounts Payable | O158: 0.02 | P158: =_xlfn.CONCAT(K158,M158,N158,O158) -> 866111132 Shree Ram Computers Shree Ram ComputersAccounts Payable0.02 | Q158: D/2025/JV/2110837291
A159: 39608 | B159: 45769 | C159: Apr 2025 | D159: Bill Payment | E159: D/2025/VP/000715 | F159: 11132 Shree Ram Computers Shree Ram Computers | G159: Accounts Payable | I159: -122300 | J159: Journal | K159: 7873 | L159: D/2025/JV/2110837220 | M159: 11132 Shree Ram Computers Shree Ram Computers | N159: Accounts Payable | O159: 0.4 | P159: =_xlfn.CONCAT(K159,M159,N159,O159) -> 787311132 Shree Ram Computers Shree Ram ComputersAccounts Payable0.4 | Q159: D/2025/JV/2110837220
A160: 39610 | B160: 45828 | C160: Jun 2025 | D160: Bill Payment | E160: D/2025/VP/001104 | F160: 13104 Driveassist Technologies India Pvt Ltd Driveassist Technologies India Pvt Ltd | G160: Accounts Payable | I160: -5534 | J160: Journal | K160: 17380 | L160: D/2025/JV/2110837748 | M160: 13104 Driveassist Technologies India Pvt Ltd Driveassist Technologies India Pvt Ltd | N160: Accounts Payable | O160: 0.5 | P160: =_xlfn.CONCAT(K160,M160,N160,O160) -> 1738013104 Driveassist Technologies India Pvt Ltd Driveassist Technologies India Pvt LtdAccounts Payable0.5 | Q160: D/2025/JV/2110837748
A161: 40336 | B161: 45891 | C161: Aug 2025 | D161: Bill Payment | E161: D/2025/VP/001460 | F161: 11790 Corporate Gift Corporate Gift | G161: Accounts Payable | I161: -143998 | J161: Journal | K161: 30330 | L161: D/2025/JV/2110838842 | M161: 11790 Corporate Gift Corporate Gift | N161: Accounts Payable | O161: 0.5 | P161: =_xlfn.CONCAT(K161,M161,N161,O161) -> 3033011790 Corporate Gift Corporate GiftAccounts Payable0.5 | Q161: D/2025/JV/2110838842
A162: 40574 | B162: 45814 | C162: Jun 2025 | D162: Receipt | E162: SEC/A/RVA/2025/0719 | F162: 10306 Cognizant Technology Solutions India Pvt Ltd Cognizant Technology Solutions India Pvt Ltd | G162: Accounts Receivable | H162: A/2025/IN/0631,A/2025/IN/0282,A/2025/IN/0285,A/2025/IN/0286,A/2025/IN/0292 Tds 10% | I162: -772192.57 | J162: Journal | K162: 13948 | L162: C/2025/JV/2110837571 | M162: 10306 Cognizant Technology Solutions India Pvt Ltd Cognizant Technology Solutions India Pvt Ltd | N162: Accounts Receivable | O162: 0.2 | P162: =_xlfn.CONCAT(K162,M162,N162,O162) -> 1394810306 Cognizant Technology Solutions India Pvt Ltd Cognizant Technology Solutions India Pvt LtdAccounts Receivable0.2 | Q162: C/2025/JV/2110837571
A163: 40589 | B163: 45818 | C163: Jun 2025 | D163: Receipt | E163: SEC/A/RVA/2025/0736 | F163: 10412 Hindustan Unilever Ltd | G163: Accounts Receivable | H163: A/2025/IN/0605,A/2025/IN/0605 Tds 1.90% | I163: -3241504.5 | J163: Journal | K163: 10906 | L163: A/2025/JV/2110837374 | M163: 10412 Hindustan Unilever Ltd | N163: Accounts Receivable | O163: 0.04 | P163: =_xlfn.CONCAT(K163,M163,N163,O163) -> 1090610412 Hindustan Unilever LtdAccounts Receivable0.04 | Q163: A/2025/JV/2110837374
A164: 40589 | B164: 45818 | C164: Jun 2025 | D164: Receipt | E164: SEC/A/RVA/2025/0736 | F164: 10412 Hindustan Unilever Ltd | G164: Accounts Receivable | H164: A/2025/IN/0605,A/2025/IN/0605 Tds 1.90% | I164: -3241504.5 | J164: Journal | K164: 23223 | L164: A/2025/JV/2110838138 | M164: 10412 Hindustan Unilever Ltd | N164: Accounts Receivable | O164: 0.44 | P164: =_xlfn.CONCAT(K164,M164,N164,O164) -> 2322310412 Hindustan Unilever LtdAccounts Receivable0.44 | Q164: A/2025/JV/2110838138
A165: 40624 | B165: 45897 | C165: Aug 2025 | D165: Bill Payment | E165: D/2025/VP/001493 | F165: 12319 Rastey Commuting Services Pvt Ltd Rastey Commuting Services Pvt Ltd | G165: Accounts Payable | I165: -264886 | J165: Journal | K165: 27543 | L165: A/2025/JV/2110838626 | M165: 12319 Rastey Commuting Services Pvt Ltd Rastey Commuting Services Pvt Ltd | N165: Accounts Payable | O165: 0.4 | P165: =_xlfn.CONCAT(K165,M165,N165,O165) -> 2754312319 Rastey Commuting Services Pvt Ltd Rastey Commuting Services Pvt LtdAccounts Payable0.4 | Q165: A/2025/JV/2110838626
A166: 41251 | B166: 45805 | C166: May 2025 | D166: Bill Payment | E166: A/2025/VP/001559 | F166: 12106 Login Enterprises Login Enterprises | G166: Accounts Payable | I166: -74308 | J166: Journal | K166: 6594 | L166: A/2025/JV/2110837162 | M166: 12106 Login Enterprises Login Enterprises | N166: Accounts Payable | O166: 0.15 | P166: =_xlfn.CONCAT(K166,M166,N166,O166) -> 659412106 Login Enterprises Login EnterprisesAccounts Payable0.15 | Q166: A/2025/JV/2110837162
A167: 41251 | B167: 45805 | C167: May 2025 | D167: Bill Payment | E167: A/2025/VP/001559 | F167: 12106 Login Enterprises Login Enterprises | G167: Accounts Payable | I167: -74308 | J167: Journal | K167: 6767 | L167: A/2025/JV/2110837175 | M167: 12106 Login Enterprises Login Enterprises | N167: Accounts Payable | O167: 0.12 | P167: =_xlfn.CONCAT(K167,M167,N167,O167) -> 676712106 Login Enterprises Login EnterprisesAccounts Payable0.12 | Q167: A/2025/JV/2110837175
A168: 41619 | B168: 45779 | C168: May 2025 | D168: Bill Payment | E168: D/2025/VP/000805 | F168: 12319 Rastey Commuting Services Pvt Ltd Rastey Commuting Services Pvt Ltd | G168: 10530 ACCOUNTS PAYABLE : ACCOUNTS PAYABLE | I168: -159198 | J168: Journal | K168: 14026 | L168: D/2025/JV/0288 | M168: 12319 Rastey Commuting Services Pvt Ltd Rastey Commuting Services Pvt Ltd | N168: 10530 ACCOUNTS PAYABLE : ACCOUNTS PAYABLE | O168: 0.2 | P168: =_xlfn.CONCAT(K168,M168,N168,O168) -> 1402612319 Rastey Commuting Services Pvt Ltd Rastey Commuting Services Pvt Ltd10530 ACCOUNTS PAYABLE : ACCOUNTS PAYABLE0.2 | Q168: D/2025/JV/0288
A169: 42621 | B169: 45780 | C169: May 2025 | D169: Receipt | E169: SEC/A/RVA/2025/0551 | F169: 10566 Clarivate Analytics India Pvt Ltd Clarivate Analytics India Pvt Ltd | G169: 10364 TRADE NOTES AND ACCOUNTS RECEIVABLE : SUNDRY DEBTORS | H169: A/2025/IN/0521 Tds 2% | I169: -894447 | J169: Journal | K169: 23765 | L169: A/2025/JV/2110838157 | M169: 10566 Clarivate Analytics India Pvt Ltd Clarivate Analytics India Pvt Ltd | N169: 10364 TRADE NOTES AND ACCOUNTS RECEIVABLE : SUNDRY DEBTORS | O169: 0.5 | P169: =_xlfn.CONCAT(K169,M169,N169,O169) -> 2376510566 Clarivate Analytics India Pvt Ltd Clarivate Analytics India Pvt Ltd10364 TRADE NOTES AND ACCOUNTS RECEIVABLE : SUNDRY DEBTORS0.5 | Q169: A/2025/JV/2110838157
A170: 42623 | B170: 45782 | C170: May 2025 | D170: Receipt | E170: SEC/A/RVA/2025/0554 | F170: 10306 Cognizant Technology Solutions India Pvt Ltd Cognizant Technology Solutions India Pvt Ltd | G170: 10364 TRADE NOTES AND ACCOUNTS RECEIVABLE : SUNDRY DEBTORS | H170: A/2025/IN/0505 Tds 10% | I170: -161805.6 | J170: Journal | K170: 6555 | L170: A/2025/JV/2110837122 | M170: 10306 Cognizant Technology Solutions India Pvt Ltd Cognizant Technology Solutions India Pvt Ltd | N170: 10364 TRADE NOTES AND ACCOUNTS RECEIVABLE : SUNDRY DEBTORS | O170: 0.4 | P170: =_xlfn.CONCAT(K170,M170,N170,O170) -> 655510306 Cognizant Technology Solutions India Pvt Ltd Cognizant Technology Solutions India Pvt Ltd10364 TRADE NOTES AND ACCOUNTS RECEIVABLE : SUNDRY DEBTORS0.4 | Q170: A/2025/JV/2110837122
A171: 42625 | B171: 45782 | C171: May 2025 | D171: Receipt | E171: SEC/A/RVA/2025/0555 | F171: 10306 Cognizant Technology Solutions India Pvt Ltd Cognizant Technology Solutions India Pvt Ltd | G171: 10364 TRADE NOTES AND ACCOUNTS RECEIVABLE : SUNDRY DEBTORS | H171: A/2025/IN/0507,A/2025/IN/0508 Tds 10% | I171: -1801898.5 | J171: Journal | K171: 8164 | L171: A/2025/JV/2110837257 | M171: 10306 Cognizant Technology Solutions India Pvt Ltd Cognizant Technology Solutions India Pvt Ltd | N171: 10364 TRADE NOTES AND ACCOUNTS RECEIVABLE : SUNDRY DEBTORS | O171: 0.5 | P171: =_xlfn.CONCAT(K171,M171,N171,O171) -> 816410306 Cognizant Technology Solutions India Pvt Ltd Cognizant Technology Solutions India Pvt Ltd10364 TRADE NOTES AND ACCOUNTS RECEIVABLE : SUNDRY DEBTORS0.5 | Q171: A/2025/JV/2110837257
A172: 42640 | B172: 45790 | C172: May 2025 | D172: Receipt | E172: SEC/A/RVA/2025/0596 | F172: 10196 Tvs Srichakra Ltd | G172: 10364 TRADE NOTES AND ACCOUNTS RECEIVABLE : SUNDRY DEBTORS | H172: A/2025/IN/0519 Tds 10% | I172: -17416 | J172: Journal | K172: 8014 | L172: A/2025/JV/2110837242 | M172: 10196 Tvs Srichakra Ltd | N172: 10364 TRADE NOTES AND ACCOUNTS RECEIVABLE : SUNDRY DEBTORS | O172: 0.5 | P172: =_xlfn.CONCAT(K172,M172,N172,O172) -> 801410196 Tvs Srichakra Ltd10364 TRADE NOTES AND ACCOUNTS RECEIVABLE : SUNDRY DEBTORS0.5 | Q172: A/2025/JV/2110837242
A173: 43076 | B173: 45841 | C173: Jul 2025 | D173: Bill Payment | E173: B/2025/VP/000822 | F173: 11685 Ashik Mobile Generator Ashik Mobile Generator | G173: Accounts Payable | I173: -12138 | J173: Journal | K173: 23409 | L173: B/2025/JV/2110838145 | M173: 11685 Ashik Mobile Generator Ashik Mobile Generator | N173: Accounts Payable | O173: 0.66 | P173: =_xlfn.CONCAT(K173,M173,N173,O173) -> 2340911685 Ashik Mobile Generator Ashik Mobile GeneratorAccounts Payable0.66 | Q173: B/2025/JV/2110838145
A174: 43141 | B174: 45888 | C174: Aug 2025 | D174: Bill Payment | E174: A/2025/VP/002304 | F174: 12422 Sneha Hospitality Services Pvt Ltd Sneha Hospitality Services Pvt Ltd | G174: Accounts Payable | I174: -122162 | J174: Journal | K174: 6537 | L174: A/2025/JV/2110837104 | M174: 12422 Sneha Hospitality Services Pvt Ltd Sneha Hospitality Services Pvt Ltd | N174: Accounts Payable | O174: 0.1 | P174: =_xlfn.CONCAT(K174,M174,N174,O174) -> 653712422 Sneha Hospitality Services Pvt Ltd Sneha Hospitality Services Pvt LtdAccounts Payable0.1 | Q174: A/2025/JV/2110837104
A175: 47811 | B175: 45916 | C175: Sep 2025 | D175: Bill Payment | E175: A/2025/VP/002629 | F175: 10151 Havas Worldwide India Pvt Ltd Havas Worldwide India Pvt Ltd | G175: 10530 ACCOUNTS PAYABLE : ACCOUNTS PAYABLE | I175: -3196860 | J175: Journal | K175: 11571 | L175: B/2025/JV/2110837394 | M175: 10151 Havas Worldwide India Pvt Ltd Havas Worldwide India Pvt Ltd | N175: 10530 ACCOUNTS PAYABLE : ACCOUNTS PAYABLE | O175: 0.46 | P175: =_xlfn.CONCAT(K175,M175,N175,O175) -> 1157110151 Havas Worldwide India Pvt Ltd Havas Worldwide India Pvt Ltd10530 ACCOUNTS PAYABLE : ACCOUNTS PAYABLE0.46 | Q175: B/2025/JV/2110837394
...

Sheet April - May Not Applied Matchin
A1: Internal ID | B1: Date | C1: Period | D1: Type | E1: Voucher Number | F1: Name | G1: Account | H1: Memo | I1: Amount | J1: Journal Pattern
A2: 3371 | B2: 45748 | C2: Apr 2025 | D2: Journal | E2: A/2025/JV/1525 | F2: 1045050 Padmakar Jadhav | G2: 1252 LOANS, SECURITY & OTHER RECEIVABLES < 1YEAR : OTHER LOANS & ADVANCES : Advance To Employees | I2: 434 | J2: =_xlfn.CONCAT(A2,F2,G2,I2) -> 33711045050 Padmakar Jadhav1252 LOANS, SECURITY & OTHER RECEIVABLES < 1YEAR : OTHER LOANS & ADVANCES : Advance To Employees434 | K2: =VLOOKUP(J2,'April - May Applied Journal '!P:Q,2,FALSE) -> #N/A
A3: 3376 | B3: 45776 | C3: Apr 2025 | D3: Journal | E3: A/2025/JV/1981 | F3: 1044833 Nazia M | G3: 10340 LOANS, SECURITY & OTHER RECEIVABLES < 1YEAR : LOANS TO EMPLOYEES | I3: -42000 | J3: =_xlfn.CONCAT(A3,F3,G3,I3) -> 33761044833 Nazia M10340 LOANS, SECURITY & OTHER RECEIVABLES < 1YEAR : LOANS TO EMPLOYEES-42000 | K3: =VLOOKUP(J3,'April - May Applied Journal '!P:Q,2,FALSE) -> #N/A
A4: 3387 | B4: 45776 | C4: Apr 2025 | D4: Journal | E4: A/2025/JV/1985 | F4: 1044945 Pravin Mahajan | G4: 1133 STAFF RELATED LIABILITIES (NO BONUSES) : SALARY & WAGES PAYABLE : Reimbursement | H4: Being Provision for Reimbursement for the month of April 2025 | I4: 32500 | J4: =_xlfn.CONCAT(A4,F4,G4,I4) -> 33871044945 Pravin Mahajan1133 STAFF RELATED LIABILITIES (NO BONUSES) : SALARY & WAGES PAYABLE : Reimbursement32500 | K4: =VLOOKUP(J4,'April - May Applied Journal '!P:Q,2,FALSE) -> #N/A
A5: 3387 | B5: 45776 | C5: Apr 2025 | D5: Journal | E5: A/2025/JV/1985 | F5: 1044810 Sidhant Saxena | G5: 1133 STAFF RELATED LIABILITIES (NO BONUSES) : SALARY & WAGES PAYABLE : Reimbursement | H5: Being Provision for Reimbursement for the month of April 2025 | I5: 32500 | J5: =_xlfn.CONCAT(A5,F5,G5,I5) -> 33871044810 Sidhant Saxena1133 STAFF RELATED LIABILITIES (NO BONUSES) : SALARY & WAGES PAYABLE : Reimbursement32500 | K5: =VLOOKUP(J5,'April - May Applied Journal '!P:Q,2,FALSE) -> #N/A
A6: 3387 | B6: 45776 | C6: Apr 2025 | D6: Journal | E6: A/2025/JV/1985 | F6: 1115298 Sony Parikh | G6: 1133 STAFF RELATED LIABILITIES (NO BONUSES) : SALARY & WAGES PAYABLE : Reimbursement | H6: Being Provision for Reimbursement for the month of April 2025 | I6: 30000 | J6: =_xlfn.CONCAT(A6,F6,G6,I6) -> 33871115298 Sony Parikh1133 STAFF RELATED LIABILITIES (NO BONUSES) : SALARY & WAGES PAYABLE : Reimbursement30000 | K6: =VLOOKUP(J6,'April - May Applied Journal '!P:Q,2,FALSE) -> #N/A
A7: 3387 | B7: 45776 | C7: Apr 2025 | D7: Journal | E7: A/2025/JV/1985 | F7: 1138617 Tejas Damania | G7: 1133 STAFF RELATED LIABILITIES (NO BONUSES) : SALARY & WAGES PAYABLE : Reimbursement | H7: Being Provision for Reimbursement for the month of April 2025 | I7: 24000 | J7: =_xlfn.CONCAT(A7,F7,G7,I7) -> 33871138617 Tejas Damania1133 STAFF RELATED LIABILITIES (NO BONUSES) : SALARY & WAGES PAYABLE : Reimbursement24000 | K7: =VLOOKUP(J7,'April - May Applied Journal '!P:Q,2,FALSE) -> #N/A
A8: 3390 | B8: 45776 | C8: Apr 2025 | D8: Journal | E8: A/2025/JV/1973 | F8: 1143735 Arun Kumar M | G8: 1252 LOANS, SECURITY & OTHER RECEIVABLES < 1YEAR : OTHER LOANS & ADVANCES : Advance To Employees | H8: Being Advance Account Recoverd from Salary for the month of April 2025 | I8: -5291 | J8: =_xlfn.CONCAT(A8,F8,G8,I8) -> 33901143735 Arun Kumar M1252 LOANS, SECURITY & OTHER RECEIVABLES < 1YEAR : OTHER LOANS & ADVANCES : Advance To Employees-5291 | K8: =VLOOKUP(J8,'April - May Applied Journal '!P:Q,2,FALSE) -> #N/A
A9: 3390 | B9: 45776 | C9: Apr 2025 | D9: Journal | E9: A/2025/JV/1973 | F9: 1119879 Kapeel Parmekar | G9: 1252 LOANS, SECURITY & OTHER RECEIVABLES < 1YEAR : OTHER LOANS & ADVANCES : Advance To Employees | H9: Being Advance Account Recoverd from Salary for the month of April 2025 | I9: -13398.56 | J9: =_xlfn.CONCAT(A9,F9,G9,I9) -> 33901119879 Kapeel Parmekar1252 LOANS, SECURITY & OTHER RECEIVABLES < 1YEAR : OTHER LOANS & ADVANCES : Advance To Employees-13398.56 | K9: =VLOOKUP(J9,'April - May Applied Journal '!P:Q,2,FALSE) -> #N/A
A10: 3390 | B10: 45776 | C10: Apr 2025 | D10: Journal | E10: A/2025/JV/1973 | F10: 1144574 Mahesh D | G10: 1252 LOANS, SECURITY & OTHER RECEIVABLES < 1YEAR : OTHER LOANS & ADVANCES : Advance To Employees | H10: Being Advance Account Recoverd from Salary for the month of April 2025 | I10: -1852 | J10: =_xlfn.CONCAT(A10,F10,G10,I10) -> 33901144574 Mahesh D1252 LOANS, SECURITY & OTHER RECEIVABLES < 1YEAR : OTHER LOANS & ADVANCES : Advance To Employees-1852 | K10: =VLOOKUP(J10,'April - May Applied Journal '!P:Q,2,FALSE) -> #N/A
A11: 3404 | B11: 45748 | C11: Apr 2025 | D11: Journal | E11: A/2025/JV/1534 | F11: 1044950 Santosh Singh | G11: 1252 LOANS, SECURITY & OTHER RECEIVABLES < 1YEAR : OTHER LOANS & ADVANCES : Advance To Employees | H11: Being on Account to Santosh Singh for SB 22540 SAP Now 2025 | I11: 25000 | J11: =_xlfn.CONCAT(A11,F11,G11,I11) -> 34041044950 Santosh Singh1252 LOANS, SECURITY & OTHER RECEIVABLES < 1YEAR : OTHER LOANS & ADVANCES : Advance To Employees25000 | K11: =VLOOKUP(J11,'April - May Applied Journal '!P:Q,2,FALSE) -> #N/A
A12: 3458 | B12: 45748 | C12: Apr 2025 | D12: Journal | E12: A/2025/JV/1535 | F12: 1126217 Ritu Vohra | G12: 1252 LOANS, SECURITY & OTHER RECEIVABLES < 1YEAR : OTHER LOANS & ADVANCES : Advance To Employees | H12: Being on Account to Ritu Vohra for BU 7 SB 15860 Meeting | I12: 17000 | J12: =_xlfn.CONCAT(A12,F12,G12,I12) -> 34581126217 Ritu Vohra1252 LOANS, SECURITY & OTHER RECEIVABLES < 1YEAR : OTHER LOANS & ADVANCES : Advance To Employees17000 | K12: =VLOOKUP(J12,'April - May Applied Journal '!P:Q,2,FALSE) -> #N/A
A13: 3459 | B13: 45748 | C13: Apr 2025 | D13: Journal | E13: A/2025/JV/1536 | F13: 1133840 Srinivasa Dasari | G13: 1252 LOANS, SECURITY & OTHER RECEIVABLES < 1YEAR : OTHER LOANS & ADVANCES : Advance To Employees | H13: Being on Account to Srinivasa Dasari for BU 9 Bangalore SB 22565 Apparel Fashion Tech World on 04.04.2025 | I13: 13530 | J13: =_xlfn.CONCAT(A13,F13,G13,I13) -> 34591133840 Srinivasa Dasari1252 LOANS, SECURITY & OTHER RECEIVABLES < 1YEAR : OTHER LOANS & ADVANCES : Advance To Employees13530 | K13: =VLOOKUP(J13,'April - May Applied Journal '!P:Q,2,FALSE) -> #N/A
A14: 3460 | B14: 45748 | C14: Apr 2025 | D14: Journal | E14: A/2025/JV/1537 | F14: 1044966 Harshit Jain | G14: 1252 LOANS, SECURITY & OTHER RECEIVABLES < 1YEAR : OTHER LOANS & ADVANCES : Advance To Employees | H14: Being on Account to Harshit Jain for SB 22344 BU 7 A Github Galaxy 2025 | I14: 100000 | J14: =_xlfn.CONCAT(A14,F14,G14,I14) -> 34601044966 Harshit Jain1252 LOANS, SECURITY & OTHER RECEIVABLES < 1YEAR : OTHER LOANS & ADVANCES : Advance To Employees100000 | K14: =VLOOKUP(J14,'April - May Applied Journal '!P:Q,2,FALSE) -> #N/A
A15: 3461 | B15: 45748 | C15: Apr 2025 | D15: Journal | E15: A/2025/JV/1538 | F15: 1044826 Hazarat Ansari | G15: 1252 LOANS, SECURITY & OTHER RECEIVABLES < 1YEAR : OTHER LOANS & ADVANCES : Advance To Employees | H15: Being On Account to Hazarat Ansari for BU 1 Rajesh SB 22511 Accenture Interns Welcome Networking Dinner. | I15: 10000 | J15: =_xlfn.CONCAT(A15,F15,G15,I15) -> 34611044826 Hazarat Ansari1252 LOANS, SECURITY & OTHER RECEIVABLES < 1YEAR : OTHER LOANS & ADVANCES : Advance To Employees10000 | K15: =VLOOKUP(J15,'April - May Applied Journal '!P:Q,2,FALSE) -> #N/A
... A215: 4696 | B215: 45764 | C215: Apr 2025 | D215: Journal | E215: A/2025/JV/1730 | F215: 1044827 Abdul Rahman | G215: 1252 LOANS, SECURITY & OTHER RECEIVABLES < 1YEAR : OTHER LOANS & ADVANCES : Advance To Employees | H215: Being On Account to Abdul Rehman for SB 22559 HPE Cloud Connect. | I215: 10000 | J215: =_xlfn.CONCAT(A215,F215,G215,I215) -> 46961044827 Abdul Rahman1252 LOANS, SECURITY & OTHER RECEIVABLES < 1YEAR : OTHER LOANS & ADVANCES : Advance To Employees10000 | K215: =VLOOKUP(J215,'April - May Applied Journal '!P:Q,2,FALSE) -> #N/A
A216: 4697 | B216: 45748 | C216: Apr 2025 | D216: Journal | E216: A/2025/JV/1515/Rev | F216: 13128 Credit Card Dues (MIS) Credit Card Dues (MIS) | G216: Accounts Payable | I216: -26496206 | J216: =_xlfn.CONCAT(A216,F216,G216,I216) -> 469713128 Credit Card Dues (MIS) Credit Card Dues (MIS)Accounts Payable-26496206.39 | K216: =VLOOKUP(J216,'April - May Applied Journal '!P:Q,2,FALSE) -> #N/A
A217: 4698 | B217: 45764 | C217: Apr 2025 | D217: Journal | E217: A/2025/JV/1731 | F217: 1137927 Chahek Poddar | G217: 1252 LOANS, SECURITY & OTHER RECEIVABLES < 1YEAR : OTHER LOANS & ADVANCES : Advance To Employees | H217: Being Fund Transfer to Chahek Poddar for Credit Balance. | I217: 25244.38 | J217: =_xlfn.CONCAT(A217,F217,G217,I217) -> 46981137927 Chahek Poddar1252 LOANS, SECURITY & OTHER RECEIVABLES < 1YEAR : OTHER LOANS & ADVANCES : Advance To Employees25244.38 | K217: =VLOOKUP(J217,'April - May Applied Journal '!P:Q,2,FALSE) -> #N/A
A218: 4699 | B218: 45764 | C218: Apr 2025 | D218: Journal | E218: A/2025/JV/1732 | F218: 1044898 Hari Bailwal | G218: 1252 LOANS, SECURITY & OTHER RECEIVABLES < 1YEAR : OTHER LOANS & ADVANCES : Advance To Employees | H218: Being Fund Transfer to Hari Bailwal for Credit Balance. | I218: 36228.94 | J218: =_xlfn.CONCAT(A218,F218,G218,I218) -> 46991044898 Hari Bailwal1252 LOANS, SECURITY & OTHER RECEIVABLES < 1YEAR : OTHER LOANS & ADVANCES : Advance To Employees36228.94 | K218: =VLOOKUP(J218,'April - May Applied Journal '!P:Q,2,FALSE) -> #N/A
A219: 4700 | B219: 45764 | C219: Apr 2025 | D219: Journal | E219: A/2025/JV/1733 | F219: 1044806 Mangesh Waghmare | G219: 1252 LOANS, SECURITY & OTHER RECEIVABLES < 1YEAR : OTHER LOANS & ADVANCES : Advance To Employees | H219: Being Fund transfer to Mangesh Waghmare for Credit Balance. | I219: 3562 | J219: =_xlfn.CONCAT(A219,F219,G219,I219) -> 47001044806 Mangesh Waghmare1252 LOANS, SECURITY & OTHER RECEIVABLES < 1YEAR : OTHER LOANS & ADVANCES : Advance To Employees3562 | K219: =VLOOKUP(J219,'April - May Applied Journal '!P:Q,2,FALSE) -> #N/A
A220: 4701 | B220: 45764 | C220: Apr 2025 | D220: Journal | E220: A/2025/JV/1734 | F220: 1143742 Mohammad Danish | G220: 1252 LOANS, SECURITY & OTHER RECEIVABLES < 1YEAR : OTHER LOANS & ADVANCES : Advance To Employees | H220: Being Fund Transfer to Mohammad Danish for Credit Balance. | I220: 10412 | J220: =_xlfn.CONCAT(A220,F220,G220,I220) -> 47011143742 Mohammad Danish1252 LOANS, SECURITY & OTHER RECEIVABLES < 1YEAR : OTHER LOANS & ADVANCES : Advance To Employees10412 | K220: =VLOOKUP(J220,'April - May Applied Journal '!P:Q,2,FALSE) -> #N/A
A221: 4702 | B221: 45764 | C221: Apr 2025 | D221: Journal | E221: A/2025/JV/1735 | F221: 1133034 Pinky Sharma | G221: 1252 LOANS, SECURITY & OTHER RECEIVABLES < 1YEAR : OTHER LOANS & ADVANCES : Advance To Employees | H221: Being Fund Transfer to Pinky Sharma for Credit Balance. | I221: 1300 | J221: =_xlfn.CONCAT(A221,F221,G221,I221) -> 47021133034 Pinky Sharma1252 LOANS, SECURITY & OTHER RECEIVABLES < 1YEAR : OTHER LOANS & ADVANCES : Advance To Employees1300 | K221: =VLOOKUP(J221,'April - May Applied Journal '!P:Q,2,FALSE) -> #N/A
A222: 4703 | B222: 45764 | C222: Apr 2025 | D222: Journal | E222: A/2025/JV/1736 | F222: 1044950 Santosh Singh | G222: 1252 LOANS, SECURITY & OTHER RECEIVABLES < 1YEAR : OTHER LOANS & ADVANCES : Advance To Employees | H222: Being fund transfer to Santosh Singh for Credit Balance. | I222: 20471 | J222: =_xlfn.CONCAT(A222,F222,G222,I222) -> 47031044950 Santosh Singh1252 LOANS, SECURITY & OTHER RECEIVABLES < 1YEAR : OTHER LOANS & ADVANCES : Advance To Employees20471 | K222: =VLOOKUP(J222,'April - May Applied Journal '!P:Q,2,FALSE) -> #N/A
A223: 4704 | B223: 45764 | C223: Apr 2025 | D223: Journal | E223: A/2025/JV/1737 | F223: 1140518 Tapish Gupta | G223: 1252 LOANS, SECURITY & OTHER RECEIVABLES < 1YEAR : OTHER LOANS & ADVANCES : Advance To Employees | H223: Being fund transfer to Tapish Gupta for Credit Balance. | I223: 5394.87 | J223: =_xlfn.CONCAT(A223,F223,G223,I223) -> 47041140518 Tapish Gupta1252 LOANS, SECURITY & OTHER RECEIVABLES < 1YEAR : OTHER LOANS & ADVANCES : Advance To Employees5394.87 | K223: =VLOOKUP(J223,'April - May Applied Journal '!P:Q,2,FALSE) -> #N/A
A224: 4705 | B224: 45764 | C224: Apr 2025 | D224: Journal | E224: A/2025/JV/1738 | F224: 1138730 Bitu Kumar | G224: 1252 LOANS, SECURITY & OTHER RECEIVABLES < 1YEAR : OTHER LOANS & ADVANCES : Advance To Employees | H224: Being On Account to Bitu Kumar for SB 15860 . | I224: 10000 | J224: =_xlfn.CONCAT(A224,F224,G224,I224) -> 47051138730 Bitu Kumar1252 LOANS, SECURITY & OTHER RECEIVABLES < 1YEAR : OTHER LOANS & ADVANCES : Advance To Employees10000 | K224: =VLOOKUP(J224,'April - May Applied Journal '!P:Q,2,FALSE) -> #N/A
A225: 4706 | B225: 45764 | C225: Apr 2025 | D225: Journal | E225: A/2025/JV/1739 | F225: 1131024 Anurama V | G225: 1252 LOANS, SECURITY & OTHER RECEIVABLES < 1YEAR : OTHER LOANS & ADVANCES : Advance To Employees | H225: Being On Account to Anurama V for Geberal Expenses. | I225: 1913 | J225: =_xlfn.CONCAT(A225,F225,G225,I225) -> 47061131024 Anurama V1252 LOANS, SECURITY & OTHER RECEIVABLES < 1YEAR : OTHER LOANS & ADVANCES : Advance To Employees1913 | K225: =VLOOKUP(J225,'April - May Applied Journal '!P:Q,2,FALSE) -> #N/A
A226: 4707 | B226: 45764 | C226: Apr 2025 | D226: Journal | E226: A/2025/JV/1740 | F226: 1044863 Sunil Sawant | G226: 1252 LOANS, SECURITY & OTHER RECEIVABLES < 1YEAR : OTHER LOANS & ADVANCES : Advance To Employees | H226: Being On Account to Sunil Sawant for SB 22606 TCS W10K 2025. | I226: 40000 | J226: =_xlfn.CONCAT(A226,F226,G226,I226) -> 47071044863 Sunil Sawant1252 LOANS, SECURITY & OTHER RECEIVABLES < 1YEAR : OTHER LOANS & ADVANCES : Advance To Employees40000 | K226: =VLOOKUP(J226,'April - May Applied Journal '!P:Q,2,FALSE) -> #N/A
A227: 4708 | B227: 45764 | C227: Apr 2025 | D227: Journal | E227: A/2025/JV/1741 | F227: 1045047 Sanil Thombare | G227: 1252 LOANS, SECURITY & OTHER RECEIVABLES < 1YEAR : OTHER LOANS & ADVANCES : Advance To Employees | H227: Being On Account to Sanil Thombare for SB 20100 General Expenses. | I227: 5000 | J227: =_xlfn.CONCAT(A227,F227,G227,I227) -> 47081045047 Sanil Thombare1252 LOANS, SECURITY & OTHER RECEIVABLES < 1YEAR : OTHER LOANS & ADVANCES : Advance To Employees5000 | K227: =VLOOKUP(J227,'April - May Applied Journal '!P:Q,2,FALSE) -> #N/A
A228: 4709 | B228: 45765 | C228: Apr 2025 | D228: Journal | E228: A/2025/JV/1742 | F228: 1044942 Ashwath Rao | G228: 1252 LOANS, SECURITY & OTHER RECEIVABLES < 1YEAR : OTHER LOANS & ADVANCES : Advance To Employees | H228: Being On Account to Ashwath TV for SB 22617 Cognizant NW visit. | I228: 3000 | J228: =_xlfn.CONCAT(A228,F228,G228,I228) -> 47091044942 Ashwath Rao1252 LOANS, SECURITY & OTHER RECEIVABLES < 1YEAR : OTHER LOANS & ADVANCES : Advance To Employees3000 | K228: =VLOOKUP(J228,'April - May Applied Journal '!P:Q,2,FALSE) -> #N/A
... A234: 4718 | B234: 45766 | C234: Apr 2025 | D234: Journal | E234: A/2025/JV/1749 | F234: 1138930 Anandan R | G234: 1252 LOANS, SECURITY & OTHER RECEIVABLES < 1YEAR : OTHER LOANS & ADVANCES : Advance To Employees | H234: Being On Account to R Anandan for BU 8 Chennai SB 22627 Natwest Nasscom GCC Summit 2025. | I234: 27500 | J234: =_xlfn.CONCAT(A234,F234,G234,I234) -> 47181138930 Anandan R1252 LOANS, SECURITY & OTHER RECEIVABLES < 1YEAR : OTHER LOANS & ADVANCES : Advance To Employees27500 | K234: =VLOOKUP(J234,'April - May Applied Journal '!P:Q,2,FALSE) -> #N/A
A235: 4784 | B235: 45777 | C235: Apr 2025 | D235: Journal | E235: A/2025/JV/2032 | F235: 13128 Credit Card Dues (MIS) Credit Card Dues (MIS) | G235: Accounts Payable | I235: 23042960 | J235: =_xlfn.CONCAT(A235,F235,G235,I235) -> 478413128 Credit Card Dues (MIS) Credit Card Dues (MIS)Accounts Payable23042959.73 | K235: =VLOOKUP(J235,'April - May Applied Journal '!P:Q,2,FALSE) -> #N/A
A236: 4785 | B236: 45778 | C236: May 2025 | D236: Journal | E236: A/2025/JV/2032 | F236: 13128 Credit Card Dues (MIS) Credit Card Dues (MIS) | G236: Accounts Payable | I236: -23042960 | J236: =_xlfn.CONCAT(A236,F236,G236,I236) -> 478513128 Credit Card Dues (MIS) Credit Card Dues (MIS)Accounts Payable-23042959.73 | K236: =VLOOKUP(J236,'April - May Applied Journal '!P:Q,2,FALSE) -> #N/A
A237: 4811 | B237: 45789 | C237: May 2025 | D237: Journal | E237: A/2025/JV/2143 | F237: 1044808 Sarita Stokes | G237: 1252 LOANS, SECURITY & OTHER RECEIVABLES < 1YEAR : OTHER LOANS & ADVANCES : Advance To Employees | H237: Being On Account to Atish Pawar for SB 20190 EC Expenses Submited to be Sarita Stokes | I237: 8000 | J237: =_xlfn.CONCAT(A237,F237,G237,I237) -> 48111044808 Sarita Stokes1252 LOANS, SECURITY & OTHER RECEIVABLES < 1YEAR : OTHER LOANS & ADVANCES : Advance To Employees8000 | K237: =VLOOKUP(J237,'April - May Applied Journal '!P:Q,2,FALSE) -> #N/A
A238: 4947 | B238: 45794 | C238: May 2025 | D238: Journal | E238: A/2025/JV/2189 | F238: 1136203 Sumit Sangle | G238: 1252 LOANS, SECURITY & OTHER RECEIVABLES < 1YEAR : OTHER LOANS & ADVANCES : Advance To Employees | H238: Being on Account to Sumit Sangle for BU 6 Pravin SB 22691 HUL Dove Scalp Launch Event. | I238: 65000 | J238: =_xlfn.CONCAT(A238,F238,G238,I238) -> 49471136203 Sumit Sangle1252 LOANS, SECURITY & OTHER RECEIVABLES < 1YEAR : OTHER LOANS & ADVANCES : Advance To Employees65000 | K238: =VLOOKUP(J238,'April - May Applied Journal '!P:Q,2,FALSE) -> #N/A
A239: 4948 | B239: 45794 | C239: May 2025 | D239: Journal | E239: A/2025/JV/2190 | F239: 1143165 Karan Nischal | G239: 1252 LOANS, SECURITY & OTHER RECEIVABLES < 1YEAR : OTHER LOANS & ADVANCES : Advance To Employees | H239: Being On Account to Karan Nichal for SB 22561 Dell - Indian Express events in May - 21. | I239: 10000 | J239: =_xlfn.CONCAT(A239,F239,G239,I239) -> 49481143165 Karan Nischal1252 LOANS, SECURITY & OTHER RECEIVABLES < 1YEAR : OTHER LOANS & ADVANCES : Advance To Employees10000 | K239: =VLOOKUP(J239,'April - May Applied Journal '!P:Q,2,FALSE) -> #N/A
A240: 4949 | B240: 45794 | C240: May 2025 | D240: Journal | E240: A/2025/JV/2191 | F240: 1140645 Seemant Mahalwal | G240: 1252 LOANS, SECURITY & OTHER RECEIVABLES < 1YEAR : OTHER LOANS & ADVANCES : Advance To Employees | H240: Being on Account to Seemant Mahalwal for BU 7 A SB 22657 Google YT Shopping Lifestyle edition. | I240: 5000 | J240: =_xlfn.CONCAT(A240,F240,G240,I240) -> 49491140645 Seemant Mahalwal1252 LOANS, SECURITY & OTHER RECEIVABLES < 1YEAR : OTHER LOANS & ADVANCES : Advance To Employees5000 | K240: =VLOOKUP(J240,'April - May Applied Journal '!P:Q,2,FALSE) -> #N/A
A241: 4950 | B241: 45794 | C241: May 2025 | D241: Journal | E241: A/2025/JV/2192 | F241: 1045051 Suresh Pardale | G241: 1252 LOANS, SECURITY & OTHER RECEIVABLES < 1YEAR : OTHER LOANS & ADVANCES : Advance To Employees | H241: Being On Account to Suresh Pardale for SB 20100 General Expenses. | I241: 10000 | J241: =_xlfn.CONCAT(A241,F241,G241,I241) -> 49501045051 Suresh Pardale1252 LOANS, SECURITY & OTHER RECEIVABLES < 1YEAR : OTHER LOANS & ADVANCES : Advance To Employees10000 | K241: =VLOOKUP(J241,'April - May Applied Journal '!P:Q,2,FALSE) -> #N/A
A242: 4951 | B242: 45794 | C242: May 2025 | D242: Journal | E242: A/2025/JV/2193 | F242: 1139551 Kapoor Samarth | G242: 1252 LOANS, SECURITY & OTHER RECEIVABLES < 1YEAR : OTHER LOANS & ADVANCES : Advance To Employees | H242: Being On Account to Samarth Kapoor for BU 7 A SB 22690 Vast Data Swags. | I242: 20000 | J242: =_xlfn.CONCAT(A242,F242,G242,I242) -> 49511139551 Kapoor Samarth1252 LOANS, SECURITY & OTHER RECEIVABLES < 1YEAR : OTHER LOANS & ADVANCES : Advance To Employees20000 | K242: =VLOOKUP(J242,'April - May Applied Journal '!P:Q,2,FALSE) -> #N/A
A243: 4952 | B243: 45794 | C243: May 2025 | D243: Journal | E243: A/2025/JV/2194 | F243: 1139551 Kapoor Samarth | G243: 1252 LOANS, SECURITY & OTHER RECEIVABLES < 1YEAR : OTHER LOANS & ADVANCES : Advance To Employees | H243: Being on Account to Samarth Kapoor for BU 7 A SB 22690 Vast Data Swags. | I243: 5000 | J243: =_xlfn.CONCAT(A243,F243,G243,I243) -> 49521139551 Kapoor Samarth1252 LOANS, SECURITY & OTHER RECEIVABLES < 1YEAR : OTHER LOANS & ADVANCES : Advance To Employees5000 | K243: =VLOOKUP(J243,'April - May Applied Journal '!P:Q,2,FALSE) -> #N/A
A244: 4953 | B244: 45794 | C244: May 2025 | D244: Journal | E244: A/2025/JV/2195 | F244: 1141533 Kunwar Singh Chauhan | G244: 1252 LOANS, SECURITY & OTHER RECEIVABLES < 1YEAR : OTHER LOANS & ADVANCES : Advance To Employees | H244: Being On Account to Kunwar Singh Chauhan for BU 7A SB 22664 Amway BBS Multicity events. | I244: 20500 | J244: =_xlfn.CONCAT(A244,F244,G244,I244) -> 49531141533 Kunwar Singh Chauhan1252 LOANS, SECURITY & OTHER RECEIVABLES < 1YEAR : OTHER LOANS & ADVANCES : Advance To Employees20500 | K244: =VLOOKUP(J244,'April - May Applied Journal '!P:Q,2,FALSE) -> #N/A
A245: 4954 | B245: 45794 | C245: May 2025 | D245: Journal | E245: A/2025/JV/2196 | F245: 1138381 Naveen Mandal | G245: 1252 LOANS, SECURITY & OTHER RECEIVABLES < 1YEAR : OTHER LOANS & ADVANCES : Advance To Employees | H245: Being On Account to Naveen Mandal for BU 7A SB 22664 Amway BBS Multicity events. | I245: 10000 | J245: =_xlfn.CONCAT(A245,F245,G245,I245) -> 49541138381 Naveen Mandal1252 LOANS, SECURITY & OTHER RECEIVABLES < 1YEAR : OTHER LOANS & ADVANCES : Advance To Employees10000 | K245: =VLOOKUP(J245,'April - May Applied Journal '!P:Q,2,FALSE) -> #N/A
A246: 4955 | B246: 45794 | C246: May 2025 | D246: Journal | E246: A/2025/JV/2197 | F246: 1138730 Bitu Kumar | G246: 1252 LOANS, SECURITY & OTHER RECEIVABLES < 1YEAR : OTHER LOANS & ADVANCES : Advance To Employees | H246: Being on Account to Bitu Kumar for BU 7A SB 22664 Amway BBS Multicity events. | I246: 2000 | J246: =_xlfn.CONCAT(A246,F246,G246,I246) -> 49551138730 Bitu Kumar1252 LOANS, SECURITY & OTHER RECEIVABLES < 1YEAR : OTHER LOANS & ADVANCES : Advance To Employees2000 | K246: =VLOOKUP(J246,'April - May Applied Journal '!P:Q,2,FALSE) -> #N/A
A247: 4956 | B247: 45767 | C247: Apr 2025 | D247: Journal | E247: A/2025/JV/1750 | F247: 1044814 Nandini Nair | G247: 1252 LOANS, SECURITY & OTHER RECEIVABLES < 1YEAR : OTHER LOANS & ADVANCES : Advance To Employees | H247: Being On Account to Nandini Nair for BU 9 Bangalore SB 22629 STT Advantage Employee offsite. | I247: 20000 | J247: =_xlfn.CONCAT(A247,F247,G247,I247) -> 49561044814 Nandini Nair1252 LOANS, SECURITY & OTHER RECEIVABLES < 1YEAR : OTHER LOANS & ADVANCES : Advance To Employees20000 | K247: =VLOOKUP(J247,'April - May Applied Journal '!P:Q,2,FALSE) -> #N/A
A248: 4957 | B248: 45767 | C248: Apr 2025 | D248: Journal | E248: A/2025/JV/1751 | F248: 1044814 Nandini Nair | G248: 1252 LOANS, SECURITY & OTHER RECEIVABLES < 1YEAR : OTHER LOANS & ADVANCES : Advance To Employees | H248: Being on Account to Nanndini Nair for BU 9 Bangalore SB 22629 STT Advantage Employee offsite. | I248: 30000 | J248: =_xlfn.CONCAT(A248,F248,G248,I248) -> 49571044814 Nandini Nair1252 LOANS, SECURITY & OTHER RECEIVABLES < 1YEAR : OTHER LOANS & ADVANCES : Advance To Employees30000 | K248: =VLOOKUP(J248,'April - May Applied Journal '!P:Q,2,FALSE) -> #N/A
... A508: 6465 | B508: 45800 | C508: May 2025 | D508: Journal | E508: A/2025/JV/2275 | F508: 1045047 Sanil Thombare | G508: 1252 LOANS, SECURITY & OTHER RECEIVABLES < 1YEAR : OTHER LOANS & ADVANCES : Advance To Employees | H508: Being on account for Sanil Thombare for Siemen Event SB No 22653 | I508: 5000 | J508: =_xlfn.CONCAT(A508,F508,G508,I508) -> 64651045047 Sanil Thombare1252 LOANS, SECURITY & OTHER RECEIVABLES < 1YEAR : OTHER LOANS & ADVANCES : Advance To Employees5000 | K508: =VLOOKUP(J508,'April - May Applied Journal '!P:Q,2,FALSE) -> #N/A
A509: 6534 | B509: 45751 | C509: Apr 2025 | D509: Journal | E509: A/2025/JV/2110837101 | F509: 11508 Bisleri International Pvt Ltd Bisleri International Pvt Ltd | G509: 10208 PROVISION FOR DOUBTFUL RECEIVABLES AND INVENTORIES : MISCELLANEOUS EXPENSES WRITTEN OFF | I509: -0.01 | J509: =_xlfn.CONCAT(A509,F509,G509,I509) -> 653411508 Bisleri International Pvt Ltd Bisleri International Pvt Ltd10208 PROVISION FOR DOUBTFUL RECEIVABLES AND INVENTORIES : MISCELLANEOUS EXPENSES WRITTEN OFF-0.01 | K509: =VLOOKUP(J509,'April - May Applied Journal '!P:Q,2,FALSE) -> #N/A
A510: 6534 | B510: 45751 | C510: Apr 2025 | D510: Journal | E510: A/2025/JV/2110837101 | F510: 11508 Bisleri International Pvt Ltd Bisleri International Pvt Ltd | G510: Accounts Payable | I510: -0.01 | J510: =_xlfn.CONCAT(A510,F510,G510,I510) -> 653411508 Bisleri International Pvt Ltd Bisleri International Pvt LtdAccounts Payable-0.01 | K510: =VLOOKUP(J510,'April - May Applied Journal '!P:Q,2,FALSE) -> #N/A
A511: 6535 | B511: 45751 | C511: Apr 2025 | D511: Journal | E511: A/2025/JV/2110837102 | F511: 12840 Shah Jaju & Associates Shah Jaju & Associates | G511: 10208 PROVISION FOR DOUBTFUL RECEIVABLES AND INVENTORIES : MISCELLANEOUS EXPENSES WRITTEN OFF | I511: 0.16 | J511: =_xlfn.CONCAT(A511,F511,G511,I511) -> 653512840 Shah Jaju & Associates Shah Jaju & Associates10208 PROVISION FOR DOUBTFUL RECEIVABLES AND INVENTORIES : MISCELLANEOUS EXPENSES WRITTEN OFF0.16 | K511: =VLOOKUP(J511,'April - May Applied Journal '!P:Q,2,FALSE) -> #N/A
A512: 6535 | B512: 45751 | C512: Apr 2025 | D512: Journal | E512: A/2025/JV/2110837102 | F512: 12840 Shah Jaju & Associates Shah Jaju & Associates | G512: Accounts Payable | I512: 0.16 | J512: =_xlfn.CONCAT(A512,F512,G512,I512) -> 653512840 Shah Jaju & Associates Shah Jaju & AssociatesAccounts Payable0.16 | K512: =VLOOKUP(J512,'April - May Applied Journal '!P:Q,2,FALSE) -> A/2025/JV/2110837102
A513: 6536 | B513: 45752 | C513: Apr 2025 | D513: Journal | E513: A/2025/JV/2110837103 | F513: 12067 Jyoti Fire Services Jyoti Fire Services | G513: 10208 PROVISION FOR DOUBTFUL RECEIVABLES AND INVENTORIES : MISCELLANEOUS EXPENSES WRITTEN OFF | I513: 0.2 | J513: =_xlfn.CONCAT(A513,F513,G513,I513) -> 653612067 Jyoti Fire Services Jyoti Fire Services10208 PROVISION FOR DOUBTFUL RECEIVABLES AND INVENTORIES : MISCELLANEOUS EXPENSES WRITTEN OFF0.2 | K513: =VLOOKUP(J513,'April - May Applied Journal '!P:Q,2,FALSE) -> #N/A
A514: 6536 | B514: 45752 | C514: Apr 2025 | D514: Journal | E514: A/2025/JV/2110837103 | F514: 12067 Jyoti Fire Services Jyoti Fire Services | G514: Accounts Payable | I514: 0.2 | J514: =_xlfn.CONCAT(A514,F514,G514,I514) -> 653612067 Jyoti Fire Services Jyoti Fire ServicesAccounts Payable0.2 | K514: =VLOOKUP(J514,'April - May Applied Journal '!P:Q,2,FALSE) -> A/2025/JV/2110837103
A515: 6537 | B515: 45755 | C515: Apr 2025 | D515: Journal | E515: A/2025/JV/2110837104 | F515: 12422 Sneha Hospitality Services Pvt Ltd Sneha Hospitality Services Pvt Ltd | G515: 10208 PROVISION FOR DOUBTFUL RECEIVABLES AND INVENTORIES : MISCELLANEOUS EXPENSES WRITTEN OFF | I515: 0.1 | J515: =_xlfn.CONCAT(A515,F515,G515,I515) -> 653712422 Sneha Hospitality Services Pvt Ltd Sneha Hospitality Services Pvt Ltd10208 PROVISION FOR DOUBTFUL RECEIVABLES AND INVENTORIES : MISCELLANEOUS EXPENSES WRITTEN OFF0.1 | K515: =VLOOKUP(J515,'April - May Applied Journal '!P:Q,2,FALSE) -> #N/A
A516: 6537 | B516: 45755 | C516: Apr 2025 | D516: Journal | E516: A/2025/JV/2110837104 | F516: 12422 Sneha Hospitality Services Pvt Ltd Sneha Hospitality Services Pvt Ltd | G516: Accounts Payable | I516: 0.1 | J516: =_xlfn.CONCAT(A516,F516,G516,I516) -> 653712422 Sneha Hospitality Services Pvt Ltd Sneha Hospitality Services Pvt LtdAccounts Payable0.1 | K516: =VLOOKUP(J516,'April - May Applied Journal '!P:Q,2,FALSE) -> A/2025/JV/2110837104
A517: 6538 | B517: 45758 | C517: Apr 2025 | D517: Journal | E517: A/2025/JV/2110837105 | F517: 12394 Shiv Enterprises Shiv Enterprises | G517: 10208 PROVISION FOR DOUBTFUL RECEIVABLES AND INVENTORIES : MISCELLANEOUS EXPENSES WRITTEN OFF | I517: 0.3 | J517: =_xlfn.CONCAT(A517,F517,G517,I517) -> 653812394 Shiv Enterprises Shiv Enterprises10208 PROVISION FOR DOUBTFUL RECEIVABLES AND INVENTORIES : MISCELLANEOUS EXPENSES WRITTEN OFF0.3 | K517: =VLOOKUP(J517,'April - May Applied Journal '!P:Q,2,FALSE) -> #N/A
A518: 6538 | B518: 45758 | C518: Apr 2025 | D518: Journal | E518: A/2025/JV/2110837105 | F518: 12394 Shiv Enterprises Shiv Enterprises | G518: Accounts Payable | I518: 0.3 | J518: =_xlfn.CONCAT(A518,F518,G518,I518) -> 653812394 Shiv Enterprises Shiv EnterprisesAccounts Payable0.3 | K518: =VLOOKUP(J518,'April - May Applied Journal '!P:Q,2,FALSE) -> A/2025/JV/2110837105
A519: 6539 | B519: 45749 | C519: Apr 2025 | D519: Journal | E519: A/2025/JV/2110837106 | F519: 12317 Rak Lead Events Rak Lead Events | G519: 10208 PROVISION FOR DOUBTFUL RECEIVABLES AND INVENTORIES : MISCELLANEOUS EXPENSES WRITTEN OFF | I519: 0.42 | J519: =_xlfn.CONCAT(A519,F519,G519,I519) -> 653912317 Rak Lead Events Rak Lead Events10208 PROVISION FOR DOUBTFUL RECEIVABLES AND INVENTORIES : MISCELLANEOUS EXPENSES WRITTEN OFF0.42 | K519: =VLOOKUP(J519,'April - May Applied Journal '!P:Q,2,FALSE) -> #N/A
A520: 6539 | B520: 45749 | C520: Apr 2025 | D520: Journal | E520: A/2025/JV/2110837106 | F520: 12317 Rak Lead Events Rak Lead Events | G520: Accounts Payable | I520: 0.42 | J520: =_xlfn.CONCAT(A520,F520,G520,I520) -> 653912317 Rak Lead Events Rak Lead EventsAccounts Payable0.42 | K520: =VLOOKUP(J520,'April - May Applied Journal '!P:Q,2,FALSE) -> #N/A
... A650: 6767 | B650: 45763 | C650: Apr 2025 | D650: Journal | E650: A/2025/JV/2110837175 | F650: 12106 Login Enterprises Login Enterprises | G650: Accounts Payable | I650: 0.12 | J650: =_xlfn.CONCAT(A650,F650,G650,I650) -> 676712106 Login Enterprises Login EnterprisesAccounts Payable0.12 | K650: =VLOOKUP(J650,'April - May Applied Journal '!P:Q,2,FALSE) -> A/2025/JV/2110837175
A651: 6779 | B651: 45801 | C651: May 2025 | D651: Journal | E651: A/2025/JV/2280 | F651: 1141982 Ajeet Singh | G651: 1252 LOANS, SECURITY & OTHER RECEIVABLES < 1YEAR : OTHER LOANS & ADVANCES : Advance To Employees | H651: Being Amount Pool Back from Ajeet Singh Happay A/c. | I651: -1735.71 | J651: =_xlfn.CONCAT(A651,F651,G651,I651) -> 67791141982 Ajeet Singh1252 LOANS, SECURITY & OTHER RECEIVABLES < 1YEAR : OTHER LOANS & ADVANCES : Advance To Employees-1735.71 | K651: =VLOOKUP(J651,'April - May Applied Journal '!P:Q,2,FALSE) -> #N/A
A652: 6780 | B652: 45801 | C652: May 2025 | D652: Journal | E652: A/2025/JV/2281 | F652: 1044808 Sarita Stokes | G652: 1252 LOANS, SECURITY & OTHER RECEIVABLES < 1YEAR : OTHER LOANS & ADVANCES : Advance To Employees | H652: Being On Account to Atish Pawar for ECExpenses Submited to be Sarita Stokes. | I652: 6000 | J652: =_xlfn.CONCAT(A652,F652,G652,I652) -> 67801044808 Sarita Stokes1252 LOANS, SECURITY & OTHER RECEIVABLES < 1YEAR : OTHER LOANS & ADVANCES : Advance To Employees6000 | K652: =VLOOKUP(J652,'April - May Applied Journal '!P:Q,2,FALSE) -> #N/A
A653: 6781 | B653: 45801 | C653: May 2025 | D653: Journal | E653: A/2025/JV/2282 | F653: 1044903 Pankaj Kumar Mishra | G653: 1252 LOANS, SECURITY & OTHER RECEIVABLES < 1YEAR : OTHER LOANS & ADVANCES : Advance To Employees | H653: Being On Account to Pankaj Kumar Mishra for BU 7 A SB 22657 Google YT Shopping Lifestyle edition. | I653: 700 | J653: =_xlfn.CONCAT(A653,F653,G653,I653) -> 67811044903 Pankaj Kumar Mishra1252 LOANS, SECURITY & OTHER RECEIVABLES < 1YEAR : OTHER LOANS & ADVANCES : Advance To Employees700 | K653: =VLOOKUP(J653,'April - May Applied Journal '!P:Q,2,FALSE) -> #N/A
A654: 6782 | B654: 45801 | C654: May 2025 | D654: Journal | E654: A/2025/JV/2283 | F654: 1139551 Kapoor Samarth | G654: 1252 LOANS, SECURITY & OTHER RECEIVABLES < 1YEAR : OTHER LOANS & ADVANCES : Advance To Employees | H654: Being On Account to Samarth Kapoor for BU 7 A SB 22704 HPE Aruba CXO Meetup. | I654: 25000 | J654: =_xlfn.CONCAT(A654,F654,G654,I654) -> 67821139551 Kapoor Samarth1252 LOANS, SECURITY & OTHER RECEIVABLES < 1YEAR : OTHER LOANS & ADVANCES : Advance To Employees25000 | K654: =VLOOKUP(J654,'April - May Applied Journal '!P:Q,2,FALSE) -> #N/A
A655: 6783 | B655: 45801 | C655: May 2025 | D655: Journal | E655: A/2025/JV/2284 | F655: 1045047 Sanil Thombare | G655: 1252 LOANS, SECURITY & OTHER RECEIVABLES < 1YEAR : OTHER LOANS & ADVANCES : Advance To Employees | H655: Being On Account to Sanil Thombare for BU 6 Pravin SB 22725 siemens PMO visit. | I655: 25000 | J655: =_xlfn.CONCAT(A655,F655,G655,I655) -> 67831045047 Sanil Thombare1252 LOANS, SECURITY & OTHER RECEIVABLES < 1YEAR : OTHER LOANS & ADVANCES : Advance To Employees25000 | K655: =VLOOKUP(J655,'April - May Applied Journal '!P:Q,2,FALSE) -> #N/A
A656: 6784 | B656: 45801 | C656: May 2025 | D656: Journal | E656: A/2025/JV/2285 | F656: 1137927 Chahek Poddar | G656: 1252 LOANS, SECURITY & OTHER RECEIVABLES < 1YEAR : OTHER LOANS & ADVANCES : Advance To Employees | H656: Being On Account to Chahek Poddar for BU 1 Rajesh SB 22710 South Aisa Innovation Awards. | I656: 8000 | J656: =_xlfn.CONCAT(A656,F656,G656,I656) -> 67841137927 Chahek Poddar1252 LOANS, SECURITY & OTHER RECEIVABLES < 1YEAR : OTHER LOANS & ADVANCES : Advance To Employees8000 | K656: =VLOOKUP(J656,'April - May Applied Journal '!P:Q,2,FALSE) -> #N/A
A657: 6785 | B657: 45801 | C657: May 2025 | D657: Journal | E657: A/2025/JV/2286 | F657: 1136203 Sumit Sangle | G657: 1252 LOANS, SECURITY & OTHER RECEIVABLES < 1YEAR : OTHER LOANS & ADVANCES : Advance To Employees | H657: Being On Account to Sumit Sangle for BU 6 Pravin SB 22719 CLPL - Yezdi Adventure Launch 2025. | I657: 5000 | J657: =_xlfn.CONCAT(A657,F657,G657,I657) -> 67851136203 Sumit Sangle1252 LOANS, SECURITY & OTHER RECEIVABLES < 1YEAR : OTHER LOANS & ADVANCES : Advance To Employees5000 | K657: =VLOOKUP(J657,'April - May Applied Journal '!P:Q,2,FALSE) -> #N/A
A658: 6786 | B658: 45801 | C658: May 2025 | D658: Journal | E658: A/2025/JV/2287 | F658: 1044878 Ravi Kumar Lal | G658: 1252 LOANS, SECURITY & OTHER RECEIVABLES < 1YEAR : OTHER LOANS & ADVANCES : Advance To Employees | H658: Being On Account to Ravi for BU 7 A SB 22657 Google YT Shopping Lifestyle edition. | I658: 2000 | J658: =_xlfn.CONCAT(A658,F658,G658,I658) -> 67861044878 Ravi Kumar Lal1252 LOANS, SECURITY & OTHER RECEIVABLES < 1YEAR : OTHER LOANS & ADVANCES : Advance To Employees2000 | K658: =VLOOKUP(J658,'April - May Applied Journal '!P:Q,2,FALSE) -> #N/A
A659: 6787 | B659: 45801 | C659: May 2025 | D659: Journal | E659: A/2025/JV/2288 | F659: 1142458 Bharat Sharma | G659: 1252 LOANS, SECURITY & OTHER RECEIVABLES < 1YEAR : OTHER LOANS & ADVANCES : Advance To Employees | H659: Being On Account to Bharat Sharma for BU 7 A SB 22664 Amway BBS Multicity events. | I659: 7500 | J659: =_xlfn.CONCAT(A659,F659,G659,I659) -> 67871142458 Bharat Sharma1252 LOANS, SECURITY & OTHER RECEIVABLES < 1YEAR : OTHER LOANS & ADVANCES : Advance To Employees7500 | K659: =VLOOKUP(J659,'April - May Applied Journal '!P:Q,2,FALSE) -> #N/A
A660: 6788 | B660: 45801 | C660: May 2025 | D660: Journal | E660: A/2025/JV/2289 | F660: 1044908 Lokesh Sonar | G660: 1252 LOANS, SECURITY & OTHER RECEIVABLES < 1YEAR : OTHER LOANS & ADVANCES : Advance To Employees | H660: Being On Account to Lokesh Sonar for BU 6 Pravin SB 22645 Hul Shiva's Farewell Event. | I660: 25000 | J660: =_xlfn.CONCAT(A660,F660,G660,I660) -> 67881044908 Lokesh Sonar1252 LOANS, SECURITY & OTHER RECEIVABLES < 1YEAR : OTHER LOANS & ADVANCES : Advance To Employees25000 | K660: =VLOOKUP(J660,'April - May Applied Journal '!P:Q,2,FALSE) -> #N/A
A661: 6790 | B661: 45775 | C661: Apr 2025 | D661: Journal | E661: D/2025/JV/2110837176 | F661: 11734 Black Pearl Production Pvt Ltd Black Pearl Production Pvt Ltd | G661: 10208 PROVISION FOR DOUBTFUL RECEIVABLES AND INVENTORIES : MISCELLANEOUS EXPENSES WRITTEN OFF | I661: -0.4 | J661: =_xlfn.CONCAT(A661,F661,G661,I661) -> 679011734 Black Pearl Production Pvt Ltd Black Pearl Production Pvt Ltd10208 PROVISION FOR DOUBTFUL RECEIVABLES AND INVENTORIES : MISCELLANEOUS EXPENSES WRITTEN OFF-0.4 | K661: =VLOOKUP(J661,'April - May Applied Journal '!P:Q,2,FALSE) -> #N/A
A662: 6790 | B662: 45775 | C662: Apr 2025 | D662: Journal | E662: D/2025/JV/2110837176 | F662: 11734 Black Pearl Production Pvt Ltd Black Pearl Production Pvt Ltd | G662: Accounts Payable | I662: -0.4 | J662: =_xlfn.CONCAT(A662,F662,G662,I662) -> 679011734 Black Pearl Production Pvt Ltd Black Pearl Production Pvt LtdAccounts Payable-0.4 | K662: =VLOOKUP(J662,'April - May Applied Journal '!P:Q,2,FALSE) -> #N/A
A663: 6899 | B663: 45749 | C663: Apr 2025 | D663: Journal | E663: D/2025/JV/2110837178 | F663: 11162 M/S Artworks M/S Artworks | G663: 10208 PROVISION FOR DOUBTFUL RECEIVABLES AND INVENTORIES : MISCELLANEOUS EXPENSES WRITTEN OFF | I663: -0.3 | J663: =_xlfn.CONCAT(A663,F663,G663,I663) -> 689911162 M/S Artworks M/S Artworks10208 PROVISION FOR DOUBTFUL RECEIVABLES AND INVENTORIES : MISCELLANEOUS EXPENSES WRITTEN OFF-0.3 | K663: =VLOOKUP(J663,'April - May Applied Journal '!P:Q,2,FALSE) -> #N/A
A664: 6899 | B664: 45749 | C664: Apr 2025 | D664: Journal | E664: D/2025/JV/2110837178 | F664: 11162 M/S Artworks M/S Artworks | G664: Accounts Payable | I664: -0.3 | J664: =_xlfn.CONCAT(A664,F664,G664,I664) -> 689911162 M/S Artworks M/S ArtworksAccounts Payable-0.3 | K664: =VLOOKUP(J664,'April - May Applied Journal '!P:Q,2,FALSE) -> #N/A
A665: 6960 | B665: 45772 | C665: Apr 2025 | D665: Journal | E665: D/2025/JV/2110837181 | F665: 12812 Royal Vacations Corporate Planners Royal Vacations Corporate Planners | G665: 10208 PROVISION FOR DOUBTFUL RECEIVABLES AND INVENTORIES : MISCELLANEOUS EXPENSES WRITTEN OFF | I665: -0.4 | J665: =_xlfn.CONCAT(A665,F665,G665,I665) -> 696012812 Royal Vacations Corporate Planners Royal Vacations Corporate Planners10208 PROVISION FOR DOUBTFUL RECEIVABLES AND INVENTORIES : MISCELLANEOUS EXPENSES WRITTEN OFF-0.4 | K665: =VLOOKUP(J665,'April - May Applied Journal '!P:Q,2,FALSE) -> #N/A
A666: 6960 | B666: 45772 | C666: Apr 2025 | D666: Journal | E666: D/2025/JV/2110837181 | F666: 12812 Royal Vacations Corporate Planners Royal Vacations Corporate Planners | G666: Accounts Payable | I666: -0.4 | J666: =_xlfn.CONCAT(A666,F666,G666,I666) -> 696012812 Royal Vacations Corporate Planners Royal Vacations Corporate PlannersAccounts Payable-0.4 | K666: =VLOOKUP(J666,'April - May Applied Journal '!P:Q,2,FALSE) -> #N/A
A667: 6970 | B667: 45757 | C667: Apr 2025 | D667: Journal | E667: D/2025/JV/0224 | F667: 10457 The Oberoi New Delhi (EIH Ltd) The Oberoi New Delhi (EIH Ltd) | G667: Accounts Payable | H667: Being amnount paid by sameer tobaccowala oberoi delhi | I667: -169825.6 | J667: =_xlfn.CONCAT(A667,F667,G667,I667) -> 697010457 The Oberoi New Delhi (EIH Ltd) The Oberoi New Delhi (EIH Ltd)Accounts Payable-169825.6 | K667: =VLOOKUP(J667,'April - May Applied Journal '!P:Q,2,FALSE) -> #N/A
A668: 6970 | B668: 45757 | C668: Apr 2025 | D668: Journal | E668: D/2025/JV/0224 | F668: 1045038 Sameer Tobaccowala | G668: 1252 LOANS, SECURITY & OTHER RECEIVABLES < 1YEAR : OTHER LOANS & ADVANCES : Advance To Employees | H668: Being amnount paid by sameer tobaccowala oberoi delhi | I668: -169825.6 | J668: =_xlfn.CONCAT(A668,F668,G668,I668) -> 69701045038 Sameer Tobaccowala1252 LOANS, SECURITY & OTHER RECEIVABLES < 1YEAR : OTHER LOANS & ADVANCES : Advance To Employees-169825.6 | K668: =VLOOKUP(J668,'April - May Applied Journal '!P:Q,2,FALSE) -> #N/A
A669: 6985 | B669: 45754 | C669: Apr 2025 | D669: Journal | E669: D/2025/JV/2110837184 | F669: 11790 Corporate Gift Corporate Gift | G669: 10208 PROVISION FOR DOUBTFUL RECEIVABLES AND INVENTORIES : MISCELLANEOUS EXPENSES WRITTEN OFF | I669: -0.16 | J669: =_xlfn.CONCAT(A669,F669,G669,I669) -> 698511790 Corporate Gift Corporate Gift10208 PROVISION FOR DOUBTFUL RECEIVABLES AND INVENTORIES : MISCELLANEOUS EXPENSES WRITTEN OFF-0.16 | K669: =VLOOKUP(J669,'April - May Applied Journal '!P:Q,2,FALSE) -> #N/A
A670: 6985 | B670: 45754 | C670: Apr 2025 | D670: Journal | E670: D/2025/JV/2110837184 | F670: 11790 Corporate Gift Corporate Gift | G670: Accounts Payable | I670: -0.16 | J670: =_xlfn.CONCAT(A670,F670,G670,I670) -> 698511790 Corporate Gift Corporate GiftAccounts Payable-0.16 | K670: =VLOOKUP(J670,'April - May Applied Journal '!P:Q,2,FALSE) -> #N/A
A671: 6987 | B671: 45782 | C671: May 2025 | D671: Journal | E671: A/2025/JV/2110837185 | F671: 12299 Pyramid Production Pyramid Production | G671: 10208 PROVISION FOR DOUBTFUL RECEIVABLES AND INVENTORIES : MISCELLANEOUS EXPENSES WRITTEN OFF | I671: 0.4 | J671: =_xlfn.CONCAT(A671,F671,G671,I671) -> 698712299 Pyramid Production Pyramid Production10208 PROVISION FOR DOUBTFUL RECEIVABLES AND INVENTORIES : MISCELLANEOUS EXPENSES WRITTEN OFF0.4 | K671: =VLOOKUP(J671,'April - May Applied Journal '!P:Q,2,FALSE) -> #N/A
A672: 6987 | B672: 45782 | C672: May 2025 | D672: Journal | E672: A/2025/JV/2110837185 | F672: 12299 Pyramid Production Pyramid Production | G672: Accounts Payable | I672: 0.4 | J672: =_xlfn.CONCAT(A672,F672,G672,I672) -> 698712299 Pyramid Production Pyramid ProductionAccounts Payable0.4 | K672: =VLOOKUP(J672,'April - May Applied Journal '!P:Q,2,FALSE) -> A/2025/JV/2110837185
A673: 7105 | B673: 45755 | C673: Apr 2025 | D673: Journal | E673: D/2025/JV/2110837187 | F673: 12028 M/S Inked M/S Inked | G673: 10208 PROVISION FOR DOUBTFUL RECEIVABLES AND INVENTORIES : MISCELLANEOUS EXPENSES WRITTEN OFF | I673: 0.28 | J673: =_xlfn.CONCAT(A673,F673,G673,I673) -> 710512028 M/S Inked M/S Inked10208 PROVISION FOR DOUBTFUL RECEIVABLES AND INVENTORIES : MISCELLANEOUS EXPENSES WRITTEN OFF0.28 | K673: =VLOOKUP(J673,'April - May Applied Journal '!P:Q,2,FALSE) -> #N/A
A674: 7105 | B674: 45755 | C674: Apr 2025 | D674: Journal | E674: D/2025/JV/2110837187 | F674: 12028 M/S Inked M/S Inked | G674: Accounts Payable | I674: 0.28 | J674: =_xlfn.CONCAT(A674,F674,G674,I674) -> 710512028 M/S Inked M/S InkedAccounts Payable0.28 | K674: =VLOOKUP(J674,'April - May Applied Journal '!P:Q,2,FALSE) -> D/2025/JV/2110837187
A675: 7107 | B675: 45769 | C675: Apr 2025 | D675: Journal | E675: A/2025/JV/2110837188 | F675: 12570 Uneecops Workplace Solutions Pvt Ltd Uneecops Workplace Solutions Pvt Ltd | G675: 10208 PROVISION FOR DOUBTFUL RECEIVABLES AND INVENTORIES : MISCELLANEOUS EXPENSES WRITTEN OFF | I675: -0.4 | J675: =_xlfn.CONCAT(A675,F675,G675,I675) -> 710712570 Uneecops Workplace Solutions Pvt Ltd Uneecops Workplace Solutions Pvt Ltd10208 PROVISION FOR DOUBTFUL RECEIVABLES AND INVENTORIES : MISCELLANEOUS EXPENSES WRITTEN OFF-0.4 | K675: =VLOOKUP(J675,'April - May Applied Journal '!P:Q,2,FALSE) -> #N/A
A676: 7107 | B676: 45769 | C676: Apr 2025 | D676: Journal | E676: A/2025/JV/2110837188 | F676: 12570 Uneecops Workplace Solutions Pvt Ltd Uneecops Workplace Solutions Pvt Ltd | G676: Accounts Payable | I676: -0.4 | J676: =_xlfn.CONCAT(A676,F676,G676,I676) -> 710712570 Uneecops Workplace Solutions Pvt Ltd Uneecops Workplace Solutions Pvt LtdAccounts Payable-0.4 | K676: =VLOOKUP(J676,'April - May Applied Journal '!P:Q,2,FALSE) -> #N/A
A677: 7109 | B677: 45771 | C677: Apr 2025 | D677: Journal | E677: B/2025/JV/2110837189 | F677: 12920 Qutab Entertainment Pvt Ltd Qutab Entertainment Pvt Ltd | G677: 10208 PROVISION FOR DOUBTFUL RECEIVABLES AND INVENTORIES : MISCELLANEOUS EXPENSES WRITTEN OFF | I677: 0.21 | J677: =_xlfn.CONCAT(A677,F677,G677,I677) -> 710912920 Qutab Entertainment Pvt Ltd Qutab Entertainment Pvt Ltd10208 PROVISION FOR DOUBTFUL RECEIVABLES AND INVENTORIES : MISCELLANEOUS EXPENSES WRITTEN OFF0.21 | K677: =VLOOKUP(J677,'April - May Applied Journal '!P:Q,2,FALSE) -> #N/A
A678: 7109 | B678: 45771 | C678: Apr 2025 | D678: Journal | E678: B/2025/JV/2110837189 | F678: 12920 Qutab Entertainment Pvt Ltd Qutab Entertainment Pvt Ltd | G678: Accounts Payable | I678: 0.21 | J678: =_xlfn.CONCAT(A678,F678,G678,I678) -> 710912920 Qutab Entertainment Pvt Ltd Qutab Entertainment Pvt LtdAccounts Payable0.21 | K678: =VLOOKUP(J678,'April - May Applied Journal '!P:Q,2,FALSE) -> #N/A
A679: 7128 | B679: 45769 | C679: Apr 2025 | D679: Journal | E679: A/2025/JV/2110837190 | F679: 11067 MTNL Mumbai MTNL Mumbai | G679: 10208 PROVISION FOR DOUBTFUL RECEIVABLES AND INVENTORIES : MISCELLANEOUS EXPENSES WRITTEN OFF | I679: -23.9 | J679: =_xlfn.CONCAT(A679,F679,G679,I679) -> 712811067 MTNL Mumbai MTNL Mumbai10208 PROVISION FOR DOUBTFUL RECEIVABLES AND INVENTORIES : MISCELLANEOUS EXPENSES WRITTEN OFF-23.9 | K679: =VLOOKUP(J679,'April - May Applied Journal '!P:Q,2,FALSE) -> #N/A
A680: 7128 | B680: 45769 | C680: Apr 2025 | D680: Journal | E680: A/2025/JV/2110837190 | F680: 11067 MTNL Mumbai MTNL Mumbai | G680: Accounts Payable | I680: -23.9 | J680: =_xlfn.CONCAT(A680,F680,G680,I680) -> 712811067 MTNL Mumbai MTNL MumbaiAccounts Payable-23.9 | K680: =VLOOKUP(J680,'April - May Applied Journal '!P:Q,2,FALSE) -> #N/A
... A688: 7157 | B688: 45772 | C688: Apr 2025 | D688: Journal | E688: A/2025/JV/2110837194 | F688: 12468 Success Gift Solutions Success Gift Solutions | G688: Accounts Payable | I688: -0.2 | J688: =_xlfn.CONCAT(A688,F688,G688,I688) -> 715712468 Success Gift Solutions Success Gift SolutionsAccounts Payable-0.2 | K688: =VLOOKUP(J688,'April - May Applied Journal '!P:Q,2,FALSE) -> #N/A
A689: 7406 | B689: 45802 | C689: May 2025 | D689: Journal | E689: A/2025/JV/2291 | F689: 1044999 Puneet Kumar | G689: 1252 LOANS, SECURITY & OTHER RECEIVABLES < 1YEAR : OTHER LOANS & ADVANCES : Advance To Employees | H689: Being On Account to Puneet Kumar for BU 7 A SB 22664 Amway BBS Multicity events. | I689: 25000 | J689: =_xlfn.CONCAT(A689,F689,G689,I689) -> 74061044999 Puneet Kumar1252 LOANS, SECURITY & OTHER RECEIVABLES < 1YEAR : OTHER LOANS & ADVANCES : Advance To Employees25000 | K689: =VLOOKUP(J689,'April - May Applied Journal '!P:Q,2,FALSE) -> #N/A
A690: 7407 | B690: 45802 | C690: May 2025 | D690: Journal | E690: A/2025/JV/2292 | F690: 1044827 Abdul Rahman | G690: 1252 LOANS, SECURITY & OTHER RECEIVABLES < 1YEAR : OTHER LOANS & ADVANCES : Advance To Employees | H690: Being on Account to Abdul Rehman for BU 7 A SB 22704 HPE Aruba CXO Meetup. | I690: 30000 | J690: =_xlfn.CONCAT(A690,F690,G690,I690) -> 74071044827 Abdul Rahman1252 LOANS, SECURITY & OTHER RECEIVABLES < 1YEAR : OTHER LOANS & ADVANCES : Advance To Employees30000 | K690: =VLOOKUP(J690,'April - May Applied Journal '!P:Q,2,FALSE) -> #N/A
A691: 7408 | B691: 45802 | C691: May 2025 | D691: Journal | E691: A/2025/JV/2293 | F691: 1045065 Mahendra Mane | G691: 1252 LOANS, SECURITY & OTHER RECEIVABLES < 1YEAR : OTHER LOANS & ADVANCES : Advance To Employees | H691: Being On Account to Mahendra Mane for BU 6 Pravin SB 22725 siemens PMO visit. | I691: 5000 | J691: =_xlfn.CONCAT(A691,F691,G691,I691) -> 74081045065 Mahendra Mane1252 LOANS, SECURITY & OTHER RECEIVABLES < 1YEAR : OTHER LOANS & ADVANCES : Advance To Employees5000 | K691: =VLOOKUP(J691,'April - May Applied Journal '!P:Q,2,FALSE) -> #N/A
A692: 7409 | B692: 45802 | C692: May 2025 | D692: Journal | E692: A/2025/JV/2294 | F692: 1132253 Rahul Luthra | G692: 1252 LOANS, SECURITY & OTHER RECEIVABLES < 1YEAR : OTHER LOANS & ADVANCES : Advance To Employees | H692: Being On Account to Rahul Luthra for BU 7 A SB 22704 HPE Aruba CXO Meetup. | I692: 50000 | J692: =_xlfn.CONCAT(A692,F692,G692,I692) -> 74091132253 Rahul Luthra1252 LOANS, SECURITY & OTHER RECEIVABLES < 1YEAR : OTHER LOANS & ADVANCES : Advance To Employees50000 | K692: =VLOOKUP(J692,'April - May Applied Journal '!P:Q,2,FALSE) -> #N/A
A693: 7410 | B693: 45802 | C693: May 2025 | D693: Journal | E693: A/2025/JV/2295 | F693: 1138054 Brijesh CL | G693: 1252 LOANS, SECURITY & OTHER RECEIVABLES < 1YEAR : OTHER LOANS & ADVANCES : Advance To Employees | H693: Being On Account to Brijesh l for BU 9 Bangalore SB 22635 Amazon BOX Installation. | I693: 5000 | J693: =_xlfn.CONCAT(A693,F693,G693,I693) -> 74101138054 Brijesh CL1252 LOANS, SECURITY & OTHER RECEIVABLES < 1YEAR : OTHER LOANS & ADVANCES : Advance To Employees5000 | K693: =VLOOKUP(J693,'April - May Applied Journal '!P:Q,2,FALSE) -> #N/A
A694: 7411 | B694: 45802 | C694: May 2025 | D694: Journal | E694: A/2025/JV/2296 | F694: 1135929 Farhan Shariff | G694: 1252 LOANS, SECURITY & OTHER RECEIVABLES < 1YEAR : OTHER LOANS & ADVANCES : Advance To Employees | H694: Being On Account to Farhan Shariff for BU 9 Bangalore SB 22699 Amazon PXT Offsite. | I694: 99990 | J694: =_xlfn.CONCAT(A694,F694,G694,I694) -> 74111135929 Farhan Shariff1252 LOANS, SECURITY & OTHER RECEIVABLES < 1YEAR : OTHER LOANS & ADVANCES : Advance To Employees99990 | K694: =VLOOKUP(J694,'April - May Applied Journal '!P:Q,2,FALSE) -> #N/A
A695: 7412 | B695: 45802 | C695: May 2025 | D695: Journal | E695: A/2025/JV/2297 | F695: 1143682 Ashok Raj | G695: 1252 LOANS, SECURITY & OTHER RECEIVABLES < 1YEAR : OTHER LOANS & ADVANCES : Advance To Employees | H695: Being On Account to Ashok Raj for BU 9 Bangalore SB 22711 Glance AI Launch. | I695: 86128 | J695: =_xlfn.CONCAT(A695,F695,G695,I695) -> 74121143682 Ashok Raj1252 LOANS, SECURITY & OTHER RECEIVABLES < 1YEAR : OTHER LOANS & ADVANCES : Advance To Employees86128 | K695: =VLOOKUP(J695,'April - May Applied Journal '!P:Q,2,FALSE) -> #N/A
A696: 7413 | B696: 45802 | C696: May 2025 | D696: Journal | E696: A/2025/JV/2298 | F696: 1143682 Ashok Raj | G696: 1252 LOANS, SECURITY & OTHER RECEIVABLES < 1YEAR : OTHER LOANS & ADVANCES : Advance To Employees | H696: Being On Account to Ashok Raj for BU 9 Bangalore SB 22659 Amazon Day One at Work. | I696: 10000 | J696: =_xlfn.CONCAT(A696,F696,G696,I696) -> 74131143682 Ashok Raj1252 LOANS, SECURITY & OTHER RECEIVABLES < 1YEAR : OTHER LOANS & ADVANCES : Advance To Employees10000 | K696: =VLOOKUP(J696,'April - May Applied Journal '!P:Q,2,FALSE) -> #N/A
A697: 7414 | B697: 45802 | C697: May 2025 | D697: Journal | E697: A/2025/JV/2299 | F697: 1138381 Naveen Mandal | G697: 1252 LOANS, SECURITY & OTHER RECEIVABLES < 1YEAR : OTHER LOANS & ADVANCES : Advance To Employees | H697: Being On Account to Naveen Mandal for BU 7 A SB 22679 Amway Artistry Serum Launch. | I697: 10000 | J697: =_xlfn.CONCAT(A697,F697,G697,I697) -> 74141138381 Naveen Mandal1252 LOANS, SECURITY & OTHER RECEIVABLES < 1YEAR : OTHER LOANS & ADVANCES : Advance To Employees10000 | K697: =VLOOKUP(J697,'April - May Applied Journal '!P:Q,2,FALSE) -> #N/A
A698: 7415 | B698: 45803 | C698: May 2025 | D698: Journal | E698: A/2025/JV/2300 | F698: 1139551 Kapoor Samarth | G698: 1252 LOANS, SECURITY & OTHER RECEIVABLES < 1YEAR : OTHER LOANS & ADVANCES : Advance To Employees | H698: Being On Account to Samarth Kapoor for BU 7 A SB 22704 HPE Aruba CXO Meetup. | I698: 50000 | J698: =_xlfn.CONCAT(A698,F698,G698,I698) -> 74151139551 Kapoor Samarth1252 LOANS, SECURITY & OTHER RECEIVABLES < 1YEAR : OTHER LOANS & ADVANCES : Advance To Employees50000 | K698: =VLOOKUP(J698,'April - May Applied Journal '!P:Q,2,FALSE) -> #N/A
A699: 7447 | B699: 45771 | C699: Apr 2025 | D699: Journal | E699: D/2025/JV/2110837195 | F699: 12028 M/S Inked M/S Inked | G699: 10208 PROVISION FOR DOUBTFUL RECEIVABLES AND INVENTORIES : MISCELLANEOUS EXPENSES WRITTEN OFF | I699: -0.4 | J699: =_xlfn.CONCAT(A699,F699,G699,I699) -> 744712028 M/S Inked M/S Inked10208 PROVISION FOR DOUBTFUL RECEIVABLES AND INVENTORIES : MISCELLANEOUS EXPENSES WRITTEN OFF-0.4 | K699: =VLOOKUP(J699,'April - May Applied Journal '!P:Q,2,FALSE) -> #N/A
...

Sheet April - May Not Applied Journal
A1: Internal ID | B1: Date | C1: Period | D1: Type | E1: Voucher Number | F1: Name | G1: Account | H1: Memo | I1: Amount | J1: Journal Pattern
A2: 3371 | B2: 45748 | C2: Apr 2025 | D2: Journal | E2: A/2025/JV/1525 | F2: 1045050 Padmakar Jadhav | G2: 1252 LOANS, SECURITY & OTHER RECEIVABLES < 1YEAR : OTHER LOANS & ADVANCES : Advance To Employees | I2: 434 | J2: 33711045050 Padmakar Jadhav1252 LOANS, SECURITY & OTHER RECEIVABLES < 1YEAR : OTHER LOANS & ADVANCES : Advance To Employees434 | K2: #N/A
A3: 3376 | B3: 45776 | C3: Apr 2025 | D3: Journal | E3: A/2025/JV/1981 | F3: 1044833 Nazia M | G3: 10340 LOANS, SECURITY & OTHER RECEIVABLES < 1YEAR : LOANS TO EMPLOYEES | I3: -42000 | J3: 33761044833 Nazia M10340 LOANS, SECURITY & OTHER RECEIVABLES < 1YEAR : LOANS TO EMPLOYEES-42000 | K3: #N/A
A4: 3387 | B4: 45776 | C4: Apr 2025 | D4: Journal | E4: A/2025/JV/1985 | F4: 1044945 Pravin Mahajan | G4: 1133 STAFF RELATED LIABILITIES (NO BONUSES) : SALARY & WAGES PAYABLE : Reimbursement | H4: Being Provision for Reimbursement for the month of April 2025 | I4: 32500 | J4: 33871044945 Pravin Mahajan1133 STAFF RELATED LIABILITIES (NO BONUSES) : SALARY & WAGES PAYABLE : Reimbursement32500 | K4: #N/A
A5: 3387 | B5: 45776 | C5: Apr 2025 | D5: Journal | E5: A/2025/JV/1985 | F5: 1044810 Sidhant Saxena | G5: 1133 STAFF RELATED LIABILITIES (NO BONUSES) : SALARY & WAGES PAYABLE : Reimbursement | H5: Being Provision for Reimbursement for the month of April 2025 | I5: 32500 | J5: 33871044810 Sidhant Saxena1133 STAFF RELATED LIABILITIES (NO BONUSES) : SALARY & WAGES PAYABLE : Reimbursement32500 | K5: #N/A
A6: 3387 | B6: 45776 | C6: Apr 2025 | D6: Journal | E6: A/2025/JV/1985 | F6: 1115298 Sony Parikh | G6: 1133 STAFF RELATED LIABILITIES (NO BONUSES) : SALARY & WAGES PAYABLE : Reimbursement | H6: Being Provision for Reimbursement for the month of April 2025 | I6: 30000 | J6: 33871115298 Sony Parikh1133 STAFF RELATED LIABILITIES (NO BONUSES) : SALARY & WAGES PAYABLE : Reimbursement30000 | K6: #N/A
A7: 3387 | B7: 45776 | C7: Apr 2025 | D7: Journal | E7: A/2025/JV/1985 | F7: 1138617 Tejas Damania | G7: 1133 STAFF RELATED LIABILITIES (NO BONUSES) : SALARY & WAGES PAYABLE : Reimbursement | H7: Being Provision for Reimbursement for the month of April 2025 | I7: 24000 | J7: 33871138617 Tejas Damania1133 STAFF RELATED LIABILITIES (NO BONUSES) : SALARY & WAGES PAYABLE : Reimbursement24000 | K7: #N/A
A8: 3390 | B8: 45776 | C8: Apr 2025 | D8: Journal | E8: A/2025/JV/1973 | F8: 1143735 Arun Kumar M | G8: 1252 LOANS, SECURITY & OTHER RECEIVABLES < 1YEAR : OTHER LOANS & ADVANCES : Advance To Employees | H8: Being Advance Account Recoverd from Salary for the month of April 2025 | I8: -5291 | J8: 33901143735 Arun Kumar M1252 LOANS, SECURITY & OTHER RECEIVABLES < 1YEAR : OTHER LOANS & ADVANCES : Advance To Employees-5291 | K8: #N/A
A9: 3390 | B9: 45776 | C9: Apr 2025 | D9: Journal | E9: A/2025/JV/1973 | F9: 1119879 Kapeel Parmekar | G9: 1252 LOANS, SECURITY & OTHER RECEIVABLES < 1YEAR : OTHER LOANS & ADVANCES : Advance To Employees | H9: Being Advance Account Recoverd from Salary for the month of April 2025 | I9: -13398.56 | J9: 33901119879 Kapeel Parmekar1252 LOANS, SECURITY & OTHER RECEIVABLES < 1YEAR : OTHER LOANS & ADVANCES : Advance To Employees-13398.56 | K9: #N/A
A10: 3390 | B10: 45776 | C10: Apr 2025 | D10: Journal | E10: A/2025/JV/1973 | F10: 1144574 Mahesh D | G10: 1252 LOANS, SECURITY & OTHER RECEIVABLES < 1YEAR : OTHER LOANS & ADVANCES : Advance To Employees | H10: Being Advance Account Recoverd from Salary for the month of April 2025 | I10: -1852 | J10: 33901144574 Mahesh D1252 LOANS, SECURITY & OTHER RECEIVABLES < 1YEAR : OTHER LOANS & ADVANCES : Advance To Employees-1852 | K10: #N/A
A11: 3404 | B11: 45748 | C11: Apr 2025 | D11: Journal | E11: A/2025/JV/1534 | F11: 1044950 Santosh Singh | G11: 1252 LOANS, SECURITY & OTHER RECEIVABLES < 1YEAR : OTHER LOANS & ADVANCES : Advance To Employees | H11: Being on Account to Santosh Singh for SB 22540 SAP Now 2025 | I11: 25000 | J11: 34041044950 Santosh Singh1252 LOANS, SECURITY & OTHER RECEIVABLES < 1YEAR : OTHER LOANS & ADVANCES : Advance To Employees25000 | K11: #N/A
A12: 3458 | B12: 45748 | C12: Apr 2025 | D12: Journal | E12: A/2025/JV/1535 | F12: 1126217 Ritu Vohra | G12: 1252 LOANS, SECURITY & OTHER RECEIVABLES < 1YEAR : OTHER LOANS & ADVANCES : Advance To Employees | H12: Being on Account to Ritu Vohra for BU 7 SB 15860 Meeting | I12: 17000 | J12: 34581126217 Ritu Vohra1252 LOANS, SECURITY & OTHER RECEIVABLES < 1YEAR : OTHER LOANS & ADVANCES : Advance To Employees17000 | K12: #N/A
A13: 3459 | B13: 45748 | C13: Apr 2025 | D13: Journal | E13: A/2025/JV/1536 | F13: 1133840 Srinivasa Dasari | G13: 1252 LOANS, SECURITY & OTHER RECEIVABLES < 1YEAR : OTHER LOANS & ADVANCES : Advance To Employees | H13: Being on Account to Srinivasa Dasari for BU 9 Bangalore SB 22565 Apparel Fashion Tech World on 04.04.2025 | I13: 13530 | J13: 34591133840 Srinivasa Dasari1252 LOANS, SECURITY & OTHER RECEIVABLES < 1YEAR : OTHER LOANS & ADVANCES : Advance To Employees13530 | K13: #N/A
A14: 3460 | B14: 45748 | C14: Apr 2025 | D14: Journal | E14: A/2025/JV/1537 | F14: 1044966 Harshit Jain | G14: 1252 LOANS, SECURITY & OTHER RECEIVABLES < 1YEAR : OTHER LOANS & ADVANCES : Advance To Employees | H14: Being on Account to Harshit Jain for SB 22344 BU 7 A Github Galaxy 2025 | I14: 100000 | J14: 34601044966 Harshit Jain1252 LOANS, SECURITY & OTHER RECEIVABLES < 1YEAR : OTHER LOANS & ADVANCES : Advance To Employees100000 | K14: #N/A
A15: 3461 | B15: 45748 | C15: Apr 2025 | D15: Journal | E15: A/2025/JV/1538 | F15: 1044826 Hazarat Ansari | G15: 1252 LOANS, SECURITY & OTHER RECEIVABLES < 1YEAR : OTHER LOANS & ADVANCES : Advance To Employees | H15: Being On Account to Hazarat Ansari for BU 1 Rajesh SB 22511 Accenture Interns Welcome Networking Dinner. | I15: 10000 | J15: 34611044826 Hazarat Ansari1252 LOANS, SECURITY & OTHER RECEIVABLES < 1YEAR : OTHER LOANS & ADVANCES : Advance To Employees10000 | K15: #N/A
... A215: 4696 | B215: 45764 | C215: Apr 2025 | D215: Journal | E215: A/2025/JV/1730 | F215: 1044827 Abdul Rahman | G215: 1252 LOANS, SECURITY & OTHER RECEIVABLES < 1YEAR : OTHER LOANS & ADVANCES : Advance To Employees | H215: Being On Account to Abdul Rehman for SB 22559 HPE Cloud Connect. | I215: 10000 | J215: 46961044827 Abdul Rahman1252 LOANS, SECURITY & OTHER RECEIVABLES < 1YEAR : OTHER LOANS & ADVANCES : Advance To Employees10000 | K215: #N/A
A216: 4697 | B216: 45748 | C216: Apr 2025 | D216: Journal | E216: A/2025/JV/1515/Rev | F216: 13128 Credit Card Dues (MIS) Credit Card Dues (MIS) | G216: Accounts Payable | I216: -26496206 | J216: 469713128 Credit Card Dues (MIS) Credit Card Dues (MIS)Accounts Payable-26496206.39 | K216: #N/A
A217: 4698 | B217: 45764 | C217: Apr 2025 | D217: Journal | E217: A/2025/JV/1731 | F217: 1137927 Chahek Poddar | G217: 1252 LOANS, SECURITY & OTHER RECEIVABLES < 1YEAR : OTHER LOANS & ADVANCES : Advance To Employees | H217: Being Fund Transfer to Chahek Poddar for Credit Balance. | I217: 25244.38 | J217: 46981137927 Chahek Poddar1252 LOANS, SECURITY & OTHER RECEIVABLES < 1YEAR : OTHER LOANS & ADVANCES : Advance To Employees25244.38 | K217: #N/A
A218: 4699 | B218: 45764 | C218: Apr 2025 | D218: Journal | E218: A/2025/JV/1732 | F218: 1044898 Hari Bailwal | G218: 1252 LOANS, SECURITY & OTHER RECEIVABLES < 1YEAR : OTHER LOANS & ADVANCES : Advance To Employees | H218: Being Fund Transfer to Hari Bailwal for Credit Balance. | I218: 36228.94 | J218: 46991044898 Hari Bailwal1252 LOANS, SECURITY & OTHER RECEIVABLES < 1YEAR : OTHER LOANS & ADVANCES : Advance To Employees36228.94 | K218: #N/A
A219: 4700 | B219: 45764 | C219: Apr 2025 | D219: Journal | E219: A/2025/JV/1733 | F219: 1044806 Mangesh Waghmare | G219: 1252 LOANS, SECURITY & OTHER RECEIVABLES < 1YEAR : OTHER LOANS & ADVANCES : Advance To Employees | H219: Being Fund transfer to Mangesh Waghmare for Credit Balance. | I219: 3562 | J219: 47001044806 Mangesh Waghmare1252 LOANS, SECURITY & OTHER RECEIVABLES < 1YEAR : OTHER LOANS & ADVANCES : Advance To Employees3562 | K219: #N/A
A220: 4701 | B220: 45764 | C220: Apr 2025 | D220: Journal | E220: A/2025/JV/1734 | F220: 1143742 Mohammad Danish | G220: 1252 LOANS, SECURITY & OTHER RECEIVABLES < 1YEAR : OTHER LOANS & ADVANCES : Advance To Employees | H220: Being Fund Transfer to Mohammad Danish for Credit Balance. | I220: 10412 | J220: 47011143742 Mohammad Danish1252 LOANS, SECURITY & OTHER RECEIVABLES < 1YEAR : OTHER LOANS & ADVANCES : Advance To Employees10412 | K220: #N/A
A221: 4702 | B221: 45764 | C221: Apr 2025 | D221: Journal | E221: A/2025/JV/1735 | F221: 1133034 Pinky Sharma | G221: 1252 LOANS, SECURITY & OTHER RECEIVABLES < 1YEAR : OTHER LOANS & ADVANCES : Advance To Employees | H221: Being Fund Transfer to Pinky Sharma for Credit Balance. | I221: 1300 | J221: 47021133034 Pinky Sharma1252 LOANS, SECURITY & OTHER RECEIVABLES < 1YEAR : OTHER LOANS & ADVANCES : Advance To Employees1300 | K221: #N/A
A222: 4703 | B222: 45764 | C222: Apr 2025 | D222: Journal | E222: A/2025/JV/1736 | F222: 1044950 Santosh Singh | G222: 1252 LOANS, SECURITY & OTHER RECEIVABLES < 1YEAR : OTHER LOANS & ADVANCES : Advance To Employees | H222: Being fund transfer to Santosh Singh for Credit Balance. | I222: 20471 | J222: 47031044950 Santosh Singh1252 LOANS, SECURITY & OTHER RECEIVABLES < 1YEAR : OTHER LOANS & ADVANCES : Advance To Employees20471 | K222: #N/A
A223: 4704 | B223: 45764 | C223: Apr 2025 | D223: Journal | E223: A/2025/JV/1737 | F223: 1140518 Tapish Gupta | G223: 1252 LOANS, SECURITY & OTHER RECEIVABLES < 1YEAR : OTHER LOANS & ADVANCES : Advance To Employees | H223: Being fund transfer to Tapish Gupta for Credit Balance. | I223: 5394.87 | J223: 47041140518 Tapish Gupta1252 LOANS, SECURITY & OTHER RECEIVABLES < 1YEAR : OTHER LOANS & ADVANCES : Advance To Employees5394.87 | K223: #N/A
A224: 4705 | B224: 45764 | C224: Apr 2025 | D224: Journal | E224: A/2025/JV/1738 | F224: 1138730 Bitu Kumar | G224: 1252 LOANS, SECURITY & OTHER RECEIVABLES < 1YEAR : OTHER LOANS & ADVANCES : Advance To Employees | H224: Being On Account to Bitu Kumar for SB 15860 . | I224: 10000 | J224: 47051138730 Bitu Kumar1252 LOANS, SECURITY & OTHER RECEIVABLES < 1YEAR : OTHER LOANS & ADVANCES : Advance To Employees10000 | K224: #N/A
A225: 4706 | B225: 45764 | C225: Apr 2025 | D225: Journal | E225: A/2025/JV/1739 | F225: 1131024 Anurama V | G225: 1252 LOANS, SECURITY & OTHER RECEIVABLES < 1YEAR : OTHER LOANS & ADVANCES : Advance To Employees | H225: Being On Account to Anurama V for Geberal Expenses. | I225: 1913 | J225: 47061131024 Anurama V1252 LOANS, SECURITY & OTHER RECEIVABLES < 1YEAR : OTHER LOANS & ADVANCES : Advance To Employees1913 | K225: #N/A
A226: 4707 | B226: 45764 | C226: Apr 2025 | D226: Journal | E226: A/2025/JV/1740 | F226: 1044863 Sunil Sawant | G226: 1252 LOANS, SECURITY & OTHER RECEIVABLES < 1YEAR : OTHER LOANS & ADVANCES : Advance To Employees | H226: Being On Account to Sunil Sawant for SB 22606 TCS W10K 2025. | I226: 40000 | J226: 47071044863 Sunil Sawant1252 LOANS, SECURITY & OTHER RECEIVABLES < 1YEAR : OTHER LOANS & ADVANCES : Advance To Employees40000 | K226: #N/A
A227: 4708 | B227: 45764 | C227: Apr 2025 | D227: Journal | E227: A/2025/JV/1741 | F227: 1045047 Sanil Thombare | G227: 1252 LOANS, SECURITY & OTHER RECEIVABLES < 1YEAR : OTHER LOANS & ADVANCES : Advance To Employees | H227: Being On Account to Sanil Thombare for SB 20100 General Expenses. | I227: 5000 | J227: 47081045047 Sanil Thombare1252 LOANS, SECURITY & OTHER RECEIVABLES < 1YEAR : OTHER LOANS & ADVANCES : Advance To Employees5000 | K227: #N/A
A228: 4709 | B228: 45765 | C228: Apr 2025 | D228: Journal | E228: A/2025/JV/1742 | F228: 1044942 Ashwath Rao | G228: 1252 LOANS, SECURITY & OTHER RECEIVABLES < 1YEAR : OTHER LOANS & ADVANCES : Advance To Employees | H228: Being On Account to Ashwath TV for SB 22617 Cognizant NW visit. | I228: 3000 | J228: 47091044942 Ashwath Rao1252 LOANS, SECURITY & OTHER RECEIVABLES < 1YEAR : OTHER LOANS & ADVANCES : Advance To Employees3000 | K228: #N/A
... A234: 4718 | B234: 45766 | C234: Apr 2025 | D234: Journal | E234: A/2025/JV/1749 | F234: 1138930 Anandan R | G234: 1252 LOANS, SECURITY & OTHER RECEIVABLES < 1YEAR : OTHER LOANS & ADVANCES : Advance To Employees | H234: Being On Account to R Anandan for BU 8 Chennai SB 22627 Natwest Nasscom GCC Summit 2025. | I234: 27500 | J234: 47181138930 Anandan R1252 LOANS, SECURITY & OTHER RECEIVABLES < 1YEAR : OTHER LOANS & ADVANCES : Advance To Employees27500 | K234: #N/A
A235: 4784 | B235: 45777 | C235: Apr 2025 | D235: Journal | E235: A/2025/JV/2032 | F235: 13128 Credit Card Dues (MIS) Credit Card Dues (MIS) | G235: Accounts Payable | I235: 23042960 | J235: 478413128 Credit Card Dues (MIS) Credit Card Dues (MIS)Accounts Payable23042959.73 | K235: #N/A
A236: 4785 | B236: 45778 | C236: May 2025 | D236: Journal | E236: A/2025/JV/2032 | F236: 13128 Credit Card Dues (MIS) Credit Card Dues (MIS) | G236: Accounts Payable | I236: -23042960 | J236: 478513128 Credit Card Dues (MIS) Credit Card Dues (MIS)Accounts Payable-23042959.73 | K236: #N/A
A237: 4811 | B237: 45789 | C237: May 2025 | D237: Journal | E237: A/2025/JV/2143 | F237: 1044808 Sarita Stokes | G237: 1252 LOANS, SECURITY & OTHER RECEIVABLES < 1YEAR : OTHER LOANS & ADVANCES : Advance To Employees | H237: Being On Account to Atish Pawar for SB 20190 EC Expenses Submited to be Sarita Stokes | I237: 8000 | J237: 48111044808 Sarita Stokes1252 LOANS, SECURITY & OTHER RECEIVABLES < 1YEAR : OTHER LOANS & ADVANCES : Advance To Employees8000 | K237: #N/A
A238: 4947 | B238: 45794 | C238: May 2025 | D238: Journal | E238: A/2025/JV/2189 | F238: 1136203 Sumit Sangle | G238: 1252 LOANS, SECURITY & OTHER RECEIVABLES < 1YEAR : OTHER LOANS & ADVANCES : Advance To Employees | H238: Being on Account to Sumit Sangle for BU 6 Pravin SB 22691 HUL Dove Scalp Launch Event. | I238: 65000 | J238: 49471136203 Sumit Sangle1252 LOANS, SECURITY & OTHER RECEIVABLES < 1YEAR : OTHER LOANS & ADVANCES : Advance To Employees65000 | K238: #N/A
A239: 4948 | B239: 45794 | C239: May 2025 | D239: Journal | E239: A/2025/JV/2190 | F239: 1143165 Karan Nischal | G239: 1252 LOANS, SECURITY & OTHER RECEIVABLES < 1YEAR : OTHER LOANS & ADVANCES : Advance To Employees | H239: Being On Account to Karan Nichal for SB 22561 Dell - Indian Express events in May - 21. | I239: 10000 | J239: 49481143165 Karan Nischal1252 LOANS, SECURITY & OTHER RECEIVABLES < 1YEAR : OTHER LOANS & ADVANCES : Advance To Employees10000 | K239: #N/A
A240: 4949 | B240: 45794 | C240: May 2025 | D240: Journal | E240: A/2025/JV/2191 | F240: 1140645 Seemant Mahalwal | G240: 1252 LOANS, SECURITY & OTHER RECEIVABLES < 1YEAR : OTHER LOANS & ADVANCES : Advance To Employees | H240: Being on Account to Seemant Mahalwal for BU 7 A SB 22657 Google YT Shopping Lifestyle edition. | I240: 5000 | J240: 49491140645 Seemant Mahalwal1252 LOANS, SECURITY & OTHER RECEIVABLES < 1YEAR : OTHER LOANS & ADVANCES : Advance To Employees5000 | K240: #N/A
A241: 4950 | B241: 45794 | C241: May 2025 | D241: Journal | E241: A/2025/JV/2192 | F241: 1045051 Suresh Pardale | G241: 1252 LOANS, SECURITY & OTHER RECEIVABLES < 1YEAR : OTHER LOANS & ADVANCES : Advance To Employees | H241: Being On Account to Suresh Pardale for SB 20100 General Expenses. | I241: 10000 | J241: 49501045051 Suresh Pardale1252 LOANS, SECURITY & OTHER RECEIVABLES < 1YEAR : OTHER LOANS & ADVANCES : Advance To Employees10000 | K241: #N/A
A242: 4951 | B242: 45794 | C242: May 2025 | D242: Journal | E242: A/2025/JV/2193 | F242: 1139551 Kapoor Samarth | G242: 1252 LOANS, SECURITY & OTHER RECEIVABLES < 1YEAR : OTHER LOANS & ADVANCES : Advance To Employees | H242: Being On Account to Samarth Kapoor for BU 7 A SB 22690 Vast Data Swags. | I242: 20000 | J242: 49511139551 Kapoor Samarth1252 LOANS, SECURITY & OTHER RECEIVABLES < 1YEAR : OTHER LOANS & ADVANCES : Advance To Employees20000 | K242: #N/A
A243: 4952 | B243: 45794 | C243: May 2025 | D243: Journal | E243: A/2025/JV/2194 | F243: 1139551 Kapoor Samarth | G243: 1252 LOANS, SECURITY & OTHER RECEIVABLES < 1YEAR : OTHER LOANS & ADVANCES : Advance To Employees | H243: Being on Account to Samarth Kapoor for BU 7 A SB 22690 Vast Data Swags. | I243: 5000 | J243: 49521139551 Kapoor Samarth1252 LOANS, SECURITY & OTHER RECEIVABLES < 1YEAR : OTHER LOANS & ADVANCES : Advance To Employees5000 | K243: #N/A
A244: 4953 | B244: 45794 | C244: May 2025 | D244: Journal | E244: A/2025/JV/2195 | F244: 1141533 Kunwar Singh Chauhan | G244: 1252 LOANS, SECURITY & OTHER RECEIVABLES < 1YEAR : OTHER LOANS & ADVANCES : Advance To Employees | H244: Being On Account to Kunwar Singh Chauhan for BU 7A SB 22664 Amway BBS Multicity events. | I244: 20500 | J244: 49531141533 Kunwar Singh Chauhan1252 LOANS, SECURITY & OTHER RECEIVABLES < 1YEAR : OTHER LOANS & ADVANCES : Advance To Employees20500 | K244: #N/A
A245: 4954 | B245: 45794 | C245: May 2025 | D245: Journal | E245: A/2025/JV/2196 | F245: 1138381 Naveen Mandal | G245: 1252 LOANS, SECURITY & OTHER RECEIVABLES < 1YEAR : OTHER LOANS & ADVANCES : Advance To Employees | H245: Being On Account to Naveen Mandal for BU 7A SB 22664 Amway BBS Multicity events. | I245: 10000 | J245: 49541138381 Naveen Mandal1252 LOANS, SECURITY & OTHER RECEIVABLES < 1YEAR : OTHER LOANS & ADVANCES : Advance To Employees10000 | K245: #N/A
A246: 4955 | B246: 45794 | C246: May 2025 | D246: Journal | E246: A/2025/JV/2197 | F246: 1138730 Bitu Kumar | G246: 1252 LOANS, SECURITY & OTHER RECEIVABLES < 1YEAR : OTHER LOANS & ADVANCES : Advance To Employees | H246: Being on Account to Bitu Kumar for BU 7A SB 22664 Amway BBS Multicity events. | I246: 2000 | J246: 49551138730 Bitu Kumar1252 LOANS, SECURITY & OTHER RECEIVABLES < 1YEAR : OTHER LOANS & ADVANCES : Advance To Employees2000 | K246: #N/A
A247: 4956 | B247: 45767 | C247: Apr 2025 | D247: Journal | E247: A/2025/JV/1750 | F247: 1044814 Nandini Nair | G247: 1252 LOANS, SECURITY & OTHER RECEIVABLES < 1YEAR : OTHER LOANS & ADVANCES : Advance To Employees | H247: Being On Account to Nandini Nair for BU 9 Bangalore SB 22629 STT Advantage Employee offsite. | I247: 20000 | J247: 49561044814 Nandini Nair1252 LOANS, SECURITY & OTHER RECEIVABLES < 1YEAR : OTHER LOANS & ADVANCES : Advance To Employees20000 | K247: #N/A
A248: 4957 | B248: 45767 | C248: Apr 2025 | D248: Journal | E248: A/2025/JV/1751 | F248: 1044814 Nandini Nair | G248: 1252 LOANS, SECURITY & OTHER RECEIVABLES < 1YEAR : OTHER LOANS & ADVANCES : Advance To Employees | H248: Being on Account to Nanndini Nair for BU 9 Bangalore SB 22629 STT Advantage Employee offsite. | I248: 30000 | J248: 49571044814 Nandini Nair1252 LOANS, SECURITY & OTHER RECEIVABLES < 1YEAR : OTHER LOANS & ADVANCES : Advance To Employees30000 | K248: #N/A
... A508: 6465 | B508: 45800 | C508: May 2025 | D508: Journal | E508: A/2025/JV/2275 | F508: 1045047 Sanil Thombare | G508: 1252 LOANS, SECURITY & OTHER RECEIVABLES < 1YEAR : OTHER LOANS & ADVANCES : Advance To Employees | H508: Being on account for Sanil Thombare for Siemen Event SB No 22653 | I508: 5000 | J508: 64651045047 Sanil Thombare1252 LOANS, SECURITY & OTHER RECEIVABLES < 1YEAR : OTHER LOANS & ADVANCES : Advance To Employees5000 | K508: #N/A
A509: 6534 | B509: 45751 | C509: Apr 2025 | D509: Journal | E509: A/2025/JV/2110837101 | F509: 11508 Bisleri International Pvt Ltd Bisleri International Pvt Ltd | G509: 10208 PROVISION FOR DOUBTFUL RECEIVABLES AND INVENTORIES : MISCELLANEOUS EXPENSES WRITTEN OFF | I509: -0.01 | J509: 653411508 Bisleri International Pvt Ltd Bisleri International Pvt Ltd10208 PROVISION FOR DOUBTFUL RECEIVABLES AND INVENTORIES : MISCELLANEOUS EXPENSES WRITTEN OFF-0.01 | K509: #N/A
A510: 6534 | B510: 45751 | C510: Apr 2025 | D510: Journal | E510: A/2025/JV/2110837101 | F510: 11508 Bisleri International Pvt Ltd Bisleri International Pvt Ltd | G510: Accounts Payable | I510: -0.01 | J510: 653411508 Bisleri International Pvt Ltd Bisleri International Pvt LtdAccounts Payable-0.01 | K510: #N/A
A511: 6535 | B511: 45751 | C511: Apr 2025 | D511: Journal | E511: A/2025/JV/2110837102 | F511: 12840 Shah Jaju & Associates Shah Jaju & Associates | G511: 10208 PROVISION FOR DOUBTFUL RECEIVABLES AND INVENTORIES : MISCELLANEOUS EXPENSES WRITTEN OFF | I511: 0.16 | J511: 653512840 Shah Jaju & Associates Shah Jaju & Associates10208 PROVISION FOR DOUBTFUL RECEIVABLES AND INVENTORIES : MISCELLANEOUS EXPENSES WRITTEN OFF0.16 | K511: #N/A
A512: 6536 | B512: 45752 | C512: Apr 2025 | D512: Journal | E512: A/2025/JV/2110837103 | F512: 12067 Jyoti Fire Services Jyoti Fire Services | G512: 10208 PROVISION FOR DOUBTFUL RECEIVABLES AND INVENTORIES : MISCELLANEOUS EXPENSES WRITTEN OFF | I512: 0.2 | J512: 653612067 Jyoti Fire Services Jyoti Fire Services10208 PROVISION FOR DOUBTFUL RECEIVABLES AND INVENTORIES : MISCELLANEOUS EXPENSES WRITTEN OFF0.2 | K512: #N/A
A513: 6537 | B513: 45755 | C513: Apr 2025 | D513: Journal | E513: A/2025/JV/2110837104 | F513: 12422 Sneha Hospitality Services Pvt Ltd Sneha Hospitality Services Pvt Ltd | G513: 10208 PROVISION FOR DOUBTFUL RECEIVABLES AND INVENTORIES : MISCELLANEOUS EXPENSES WRITTEN OFF | I513: 0.1 | J513: 653712422 Sneha Hospitality Services Pvt Ltd Sneha Hospitality Services Pvt Ltd10208 PROVISION FOR DOUBTFUL RECEIVABLES AND INVENTORIES : MISCELLANEOUS EXPENSES WRITTEN OFF0.1 | K513: #N/A
A514: 6538 | B514: 45758 | C514: Apr 2025 | D514: Journal | E514: A/2025/JV/2110837105 | F514: 12394 Shiv Enterprises Shiv Enterprises | G514: 10208 PROVISION FOR DOUBTFUL RECEIVABLES AND INVENTORIES : MISCELLANEOUS EXPENSES WRITTEN OFF | I514: 0.3 | J514: 653812394 Shiv Enterprises Shiv Enterprises10208 PROVISION FOR DOUBTFUL RECEIVABLES AND INVENTORIES : MISCELLANEOUS EXPENSES WRITTEN OFF0.3 | K514: #N/A
A515: 6539 | B515: 45749 | C515: Apr 2025 | D515: Journal | E515: A/2025/JV/2110837106 | F515: 12317 Rak Lead Events Rak Lead Events | G515: 10208 PROVISION FOR DOUBTFUL RECEIVABLES AND INVENTORIES : MISCELLANEOUS EXPENSES WRITTEN OFF | I515: 0.42 | J515: 653912317 Rak Lead Events Rak Lead Events10208 PROVISION FOR DOUBTFUL RECEIVABLES AND INVENTORIES : MISCELLANEOUS EXPENSES WRITTEN OFF0.42 | K515: #N/A
A516: 6539 | B516: 45749 | C516: Apr 2025 | D516: Journal | E516: A/2025/JV/2110837106 | F516: 12317 Rak Lead Events Rak Lead Events | G516: Accounts Payable | I516: 0.42 | J516: 653912317 Rak Lead Events Rak Lead EventsAccounts Payable0.42 | K516: #N/A
A517: 6540 | B517: 45749 | C517: Apr 2025 | D517: Journal | E517: A/2025/JV/2110837107 | F517: 11206 Devoba Arts Frame Makers Devoba Arts Frame Makers | G517: 10208 PROVISION FOR DOUBTFUL RECEIVABLES AND INVENTORIES : MISCELLANEOUS EXPENSES WRITTEN OFF | I517: -0.4 | J517: 654011206 Devoba Arts Frame Makers Devoba Arts Frame Makers10208 PROVISION FOR DOUBTFUL RECEIVABLES AND INVENTORIES : MISCELLANEOUS EXPENSES WRITTEN OFF-0.4 | K517: #N/A
A518: 6540 | B518: 45749 | C518: Apr 2025 | D518: Journal | E518: A/2025/JV/2110837107 | F518: 11206 Devoba Arts Frame Makers Devoba Arts Frame Makers | G518: Accounts Payable | I518: -0.4 | J518: 654011206 Devoba Arts Frame Makers Devoba Arts Frame MakersAccounts Payable-0.4 | K518: #N/A
A519: 6541 | B519: 45749 | C519: Apr 2025 | D519: Journal | E519: A/2025/JV/2110837108 | F519: 12317 Rak Lead Events Rak Lead Events | G519: 10208 PROVISION FOR DOUBTFUL RECEIVABLES AND INVENTORIES : MISCELLANEOUS EXPENSES WRITTEN OFF | I519: 0.4 | J519: 654112317 Rak Lead Events Rak Lead Events10208 PROVISION FOR DOUBTFUL RECEIVABLES AND INVENTORIES : MISCELLANEOUS EXPENSES WRITTEN OFF0.4 | K519: #N/A
A520: 6542 | B520: 45750 | C520: Apr 2025 | D520: Journal | E520: A/2025/JV/2110837109 | F520: 12317 Rak Lead Events Rak Lead Events | G520: 10208 PROVISION FOR DOUBTFUL RECEIVABLES AND INVENTORIES : MISCELLANEOUS EXPENSES WRITTEN OFF | I520: 0.24 | J520: 654212317 Rak Lead Events Rak Lead Events10208 PROVISION FOR DOUBTFUL RECEIVABLES AND INVENTORIES : MISCELLANEOUS EXPENSES WRITTEN OFF0.24 | K520: #N/A
... A624: 6767 | B624: 45763 | C624: Apr 2025 | D624: Journal | E624: A/2025/JV/2110837175 | F624: 12106 Login Enterprises Login Enterprises | G624: 10208 PROVISION FOR DOUBTFUL RECEIVABLES AND INVENTORIES : MISCELLANEOUS EXPENSES WRITTEN OFF | I624: 0.12 | J624: 676712106 Login Enterprises Login Enterprises10208 PROVISION FOR DOUBTFUL RECEIVABLES AND INVENTORIES : MISCELLANEOUS EXPENSES WRITTEN OFF0.12 | K624: #N/A
A625: 6779 | B625: 45801 | C625: May 2025 | D625: Journal | E625: A/2025/JV/2280 | F625: 1141982 Ajeet Singh | G625: 1252 LOANS, SECURITY & OTHER RECEIVABLES < 1YEAR : OTHER LOANS & ADVANCES : Advance To Employees | H625: Being Amount Pool Back from Ajeet Singh Happay A/c. | I625: -1735.71 | J625: 67791141982 Ajeet Singh1252 LOANS, SECURITY & OTHER RECEIVABLES < 1YEAR : OTHER LOANS & ADVANCES : Advance To Employees-1735.71 | K625: #N/A
A626: 6780 | B626: 45801 | C626: May 2025 | D626: Journal | E626: A/2025/JV/2281 | F626: 1044808 Sarita Stokes | G626: 1252 LOANS, SECURITY & OTHER RECEIVABLES < 1YEAR : OTHER LOANS & ADVANCES : Advance To Employees | H626: Being On Account to Atish Pawar for ECExpenses Submited to be Sarita Stokes. | I626: 6000 | J626: 67801044808 Sarita Stokes1252 LOANS, SECURITY & OTHER RECEIVABLES < 1YEAR : OTHER LOANS & ADVANCES : Advance To Employees6000 | K626: #N/A
A627: 6781 | B627: 45801 | C627: May 2025 | D627: Journal | E627: A/2025/JV/2282 | F627: 1044903 Pankaj Kumar Mishra | G627: 1252 LOANS, SECURITY & OTHER RECEIVABLES < 1YEAR : OTHER LOANS & ADVANCES : Advance To Employees | H627: Being On Account to Pankaj Kumar Mishra for BU 7 A SB 22657 Google YT Shopping Lifestyle edition. | I627: 700 | J627: 67811044903 Pankaj Kumar Mishra1252 LOANS, SECURITY & OTHER RECEIVABLES < 1YEAR : OTHER LOANS & ADVANCES : Advance To Employees700 | K627: #N/A
A628: 6782 | B628: 45801 | C628: May 2025 | D628: Journal | E628: A/2025/JV/2283 | F628: 1139551 Kapoor Samarth | G628: 1252 LOANS, SECURITY & OTHER RECEIVABLES < 1YEAR : OTHER LOANS & ADVANCES : Advance To Employees | H628: Being On Account to Samarth Kapoor for BU 7 A SB 22704 HPE Aruba CXO Meetup. | I628: 25000 | J628: 67821139551 Kapoor Samarth1252 LOANS, SECURITY & OTHER RECEIVABLES < 1YEAR : OTHER LOANS & ADVANCES : Advance To Employees25000 | K628: #N/A
A629: 6783 | B629: 45801 | C629: May 2025 | D629: Journal | E629: A/2025/JV/2284 | F629: 1045047 Sanil Thombare | G629: 1252 LOANS, SECURITY & OTHER RECEIVABLES < 1YEAR : OTHER LOANS & ADVANCES : Advance To Employees | H629: Being On Account to Sanil Thombare for BU 6 Pravin SB 22725 siemens PMO visit. | I629: 25000 | J629: 67831045047 Sanil Thombare1252 LOANS, SECURITY & OTHER RECEIVABLES < 1YEAR : OTHER LOANS & ADVANCES : Advance To Employees25000 | K629: #N/A
A630: 6784 | B630: 45801 | C630: May 2025 | D630: Journal | E630: A/2025/JV/2285 | F630: 1137927 Chahek Poddar | G630: 1252 LOANS, SECURITY & OTHER RECEIVABLES < 1YEAR : OTHER LOANS & ADVANCES : Advance To Employees | H630: Being On Account to Chahek Poddar for BU 1 Rajesh SB 22710 South Aisa Innovation Awards. | I630: 8000 | J630: 67841137927 Chahek Poddar1252 LOANS, SECURITY & OTHER RECEIVABLES < 1YEAR : OTHER LOANS & ADVANCES : Advance To Employees8000 | K630: #N/A
A631: 6785 | B631: 45801 | C631: May 2025 | D631: Journal | E631: A/2025/JV/2286 | F631: 1136203 Sumit Sangle | G631: 1252 LOANS, SECURITY & OTHER RECEIVABLES < 1YEAR : OTHER LOANS & ADVANCES : Advance To Employees | H631: Being On Account to Sumit Sangle for BU 6 Pravin SB 22719 CLPL - Yezdi Adventure Launch 2025. | I631: 5000 | J631: 67851136203 Sumit Sangle1252 LOANS, SECURITY & OTHER RECEIVABLES < 1YEAR : OTHER LOANS & ADVANCES : Advance To Employees5000 | K631: #N/A
A632: 6786 | B632: 45801 | C632: May 2025 | D632: Journal | E632: A/2025/JV/2287 | F632: 1044878 Ravi Kumar Lal | G632: 1252 LOANS, SECURITY & OTHER RECEIVABLES < 1YEAR : OTHER LOANS & ADVANCES : Advance To Employees | H632: Being On Account to Ravi for BU 7 A SB 22657 Google YT Shopping Lifestyle edition. | I632: 2000 | J632: 67861044878 Ravi Kumar Lal1252 LOANS, SECURITY & OTHER RECEIVABLES < 1YEAR : OTHER LOANS & ADVANCES : Advance To Employees2000 | K632: #N/A
A633: 6787 | B633: 45801 | C633: May 2025 | D633: Journal | E633: A/2025/JV/2288 | F633: 1142458 Bharat Sharma | G633: 1252 LOANS, SECURITY & OTHER RECEIVABLES < 1YEAR : OTHER LOANS & ADVANCES : Advance To Employees | H633: Being On Account to Bharat Sharma for BU 7 A SB 22664 Amway BBS Multicity events. | I633: 7500 | J633: 67871142458 Bharat Sharma1252 LOANS, SECURITY & OTHER RECEIVABLES < 1YEAR : OTHER LOANS & ADVANCES : Advance To Employees7500 | K633: #N/A
A634: 6788 | B634: 45801 | C634: May 2025 | D634: Journal | E634: A/2025/JV/2289 | F634: 1044908 Lokesh Sonar | G634: 1252 LOANS, SECURITY & OTHER RECEIVABLES < 1YEAR : OTHER LOANS & ADVANCES : Advance To Employees | H634: Being On Account to Lokesh Sonar for BU 6 Pravin SB 22645 Hul Shiva's Farewell Event. | I634: 25000 | J634: 67881044908 Lokesh Sonar1252 LOANS, SECURITY & OTHER RECEIVABLES < 1YEAR : OTHER LOANS & ADVANCES : Advance To Employees25000 | K634: #N/A
A635: 6790 | B635: 45775 | C635: Apr 2025 | D635: Journal | E635: D/2025/JV/2110837176 | F635: 11734 Black Pearl Production Pvt Ltd Black Pearl Production Pvt Ltd | G635: 10208 PROVISION FOR DOUBTFUL RECEIVABLES AND INVENTORIES : MISCELLANEOUS EXPENSES WRITTEN OFF | I635: -0.4 | J635: 679011734 Black Pearl Production Pvt Ltd Black Pearl Production Pvt Ltd10208 PROVISION FOR DOUBTFUL RECEIVABLES AND INVENTORIES : MISCELLANEOUS EXPENSES WRITTEN OFF-0.4 | K635: #N/A
A636: 6790 | B636: 45775 | C636: Apr 2025 | D636: Journal | E636: D/2025/JV/2110837176 | F636: 11734 Black Pearl Production Pvt Ltd Black Pearl Production Pvt Ltd | G636: Accounts Payable | I636: -0.4 | J636: 679011734 Black Pearl Production Pvt Ltd Black Pearl Production Pvt LtdAccounts Payable-0.4 | K636: #N/A
A637: 6899 | B637: 45749 | C637: Apr 2025 | D637: Journal | E637: D/2025/JV/2110837178 | F637: 11162 M/S Artworks M/S Artworks | G637: 10208 PROVISION FOR DOUBTFUL RECEIVABLES AND INVENTORIES : MISCELLANEOUS EXPENSES WRITTEN OFF | I637: -0.3 | J637: 689911162 M/S Artworks M/S Artworks10208 PROVISION FOR DOUBTFUL RECEIVABLES AND INVENTORIES : MISCELLANEOUS EXPENSES WRITTEN OFF-0.3 | K637: #N/A
A638: 6899 | B638: 45749 | C638: Apr 2025 | D638: Journal | E638: D/2025/JV/2110837178 | F638: 11162 M/S Artworks M/S Artworks | G638: Accounts Payable | I638: -0.3 | J638: 689911162 M/S Artworks M/S ArtworksAccounts Payable-0.3 | K638: #N/A
A639: 6960 | B639: 45772 | C639: Apr 2025 | D639: Journal | E639: D/2025/JV/2110837181 | F639: 12812 Royal Vacations Corporate Planners Royal Vacations Corporate Planners | G639: 10208 PROVISION FOR DOUBTFUL RECEIVABLES AND INVENTORIES : MISCELLANEOUS EXPENSES WRITTEN OFF | I639: -0.4 | J639: 696012812 Royal Vacations Corporate Planners Royal Vacations Corporate Planners10208 PROVISION FOR DOUBTFUL RECEIVABLES AND INVENTORIES : MISCELLANEOUS EXPENSES WRITTEN OFF-0.4 | K639: #N/A
A640: 6960 | B640: 45772 | C640: Apr 2025 | D640: Journal | E640: D/2025/JV/2110837181 | F640: 12812 Royal Vacations Corporate Planners Royal Vacations Corporate Planners | G640: Accounts Payable | I640: -0.4 | J640: 696012812 Royal Vacations Corporate Planners Royal Vacations Corporate PlannersAccounts Payable-0.4 | K640: #N/A
A641: 6970 | B641: 45757 | C641: Apr 2025 | D641: Journal | E641: D/2025/JV/0224 | F641: 10457 The Oberoi New Delhi (EIH Ltd) The Oberoi New Delhi (EIH Ltd) | G641: Accounts Payable | H641: Being amnount paid by sameer tobaccowala oberoi delhi | I641: -169825.6 | J641: 697010457 The Oberoi New Delhi (EIH Ltd) The Oberoi New Delhi (EIH Ltd)Accounts Payable-169825.6 | K641: #N/A
A642: 6970 | B642: 45757 | C642: Apr 2025 | D642: Journal | E642: D/2025/JV/0224 | F642: 1045038 Sameer Tobaccowala | G642: 1252 LOANS, SECURITY & OTHER RECEIVABLES < 1YEAR : OTHER LOANS & ADVANCES : Advance To Employees | H642: Being amnount paid by sameer tobaccowala oberoi delhi | I642: -169825.6 | J642: 69701045038 Sameer Tobaccowala1252 LOANS, SECURITY & OTHER RECEIVABLES < 1YEAR : OTHER LOANS & ADVANCES : Advance To Employees-169825.6 | K642: #N/A
A643: 6985 | B643: 45754 | C643: Apr 2025 | D643: Journal | E643: D/2025/JV/2110837184 | F643: 11790 Corporate Gift Corporate Gift | G643: 10208 PROVISION FOR DOUBTFUL RECEIVABLES AND INVENTORIES : MISCELLANEOUS EXPENSES WRITTEN OFF | I643: -0.16 | J643: 698511790 Corporate Gift Corporate Gift10208 PROVISION FOR DOUBTFUL RECEIVABLES AND INVENTORIES : MISCELLANEOUS EXPENSES WRITTEN OFF-0.16 | K643: #N/A
A644: 6985 | B644: 45754 | C644: Apr 2025 | D644: Journal | E644: D/2025/JV/2110837184 | F644: 11790 Corporate Gift Corporate Gift | G644: Accounts Payable | I644: -0.16 | J644: 698511790 Corporate Gift Corporate GiftAccounts Payable-0.16 | K644: #N/A
A645: 6987 | B645: 45782 | C645: May 2025 | D645: Journal | E645: A/2025/JV/2110837185 | F645: 12299 Pyramid Production Pyramid Production | G645: 10208 PROVISION FOR DOUBTFUL RECEIVABLES AND INVENTORIES : MISCELLANEOUS EXPENSES WRITTEN OFF | I645: 0.4 | J645: 698712299 Pyramid Production Pyramid Production10208 PROVISION FOR DOUBTFUL RECEIVABLES AND INVENTORIES : MISCELLANEOUS EXPENSES WRITTEN OFF0.4 | K645: #N/A
A646: 7105 | B646: 45755 | C646: Apr 2025 | D646: Journal | E646: D/2025/JV/2110837187 | F646: 12028 M/S Inked M/S Inked | G646: 10208 PROVISION FOR DOUBTFUL RECEIVABLES AND INVENTORIES : MISCELLANEOUS EXPENSES WRITTEN OFF | I646: 0.28 | J646: 710512028 M/S Inked M/S Inked10208 PROVISION FOR DOUBTFUL RECEIVABLES AND INVENTORIES : MISCELLANEOUS EXPENSES WRITTEN OFF0.28 | K646: #N/A
A647: 7107 | B647: 45769 | C647: Apr 2025 | D647: Journal | E647: A/2025/JV/2110837188 | F647: 12570 Uneecops Workplace Solutions Pvt Ltd Uneecops Workplace Solutions Pvt Ltd | G647: 10208 PROVISION FOR DOUBTFUL RECEIVABLES AND INVENTORIES : MISCELLANEOUS EXPENSES WRITTEN OFF | I647: -0.4 | J647: 710712570 Uneecops Workplace Solutions Pvt Ltd Uneecops Workplace Solutions Pvt Ltd10208 PROVISION FOR DOUBTFUL RECEIVABLES AND INVENTORIES : MISCELLANEOUS EXPENSES WRITTEN OFF-0.4 | K647: #N/A
A648: 7107 | B648: 45769 | C648: Apr 2025 | D648: Journal | E648: A/2025/JV/2110837188 | F648: 12570 Uneecops Workplace Solutions Pvt Ltd Uneecops Workplace Solutions Pvt Ltd | G648: Accounts Payable | I648: -0.4 | J648: 710712570 Uneecops Workplace Solutions Pvt Ltd Uneecops Workplace Solutions Pvt LtdAccounts Payable-0.4 | K648: #N/A
A649: 7109 | B649: 45771 | C649: Apr 2025 | D649: Journal | E649: B/2025/JV/2110837189 | F649: 12920 Qutab Entertainment Pvt Ltd Qutab Entertainment Pvt Ltd | G649: 10208 PROVISION FOR DOUBTFUL RECEIVABLES AND INVENTORIES : MISCELLANEOUS EXPENSES WRITTEN OFF | I649: 0.21 | J649: 710912920 Qutab Entertainment Pvt Ltd Qutab Entertainment Pvt Ltd10208 PROVISION FOR DOUBTFUL RECEIVABLES AND INVENTORIES : MISCELLANEOUS EXPENSES WRITTEN OFF0.21 | K649: #N/A
A650: 7109 | B650: 45771 | C650: Apr 2025 | D650: Journal | E650: B/2025/JV/2110837189 | F650: 12920 Qutab Entertainment Pvt Ltd Qutab Entertainment Pvt Ltd | G650: Accounts Payable | I650: 0.21 | J650: 710912920 Qutab Entertainment Pvt Ltd Qutab Entertainment Pvt LtdAccounts Payable0.21 | K650: #N/A
A651: 7128 | B651: 45769 | C651: Apr 2025 | D651: Journal | E651: A/2025/JV/2110837190 | F651: 11067 MTNL Mumbai MTNL Mumbai | G651: 10208 PROVISION FOR DOUBTFUL RECEIVABLES AND INVENTORIES : MISCELLANEOUS EXPENSES WRITTEN OFF | I651: -23.9 | J651: 712811067 MTNL Mumbai MTNL Mumbai10208 PROVISION FOR DOUBTFUL RECEIVABLES AND INVENTORIES : MISCELLANEOUS EXPENSES WRITTEN OFF-23.9 | K651: #N/A
A652: 7128 | B652: 45769 | C652: Apr 2025 | D652: Journal | E652: A/2025/JV/2110837190 | F652: 11067 MTNL Mumbai MTNL Mumbai | G652: Accounts Payable | I652: -23.9 | J652: 712811067 MTNL Mumbai MTNL MumbaiAccounts Payable-23.9 | K652: #N/A
A653: 7131 | B653: 45755 | C653: Apr 2025 | D653: Journal | E653: D/2025/JV/2110837191 | F653: 12236 Pandey Print Services Pandey Print Services | G653: 10208 PROVISION FOR DOUBTFUL RECEIVABLES AND INVENTORIES : MISCELLANEOUS EXPENSES WRITTEN OFF | I653: 0.4 | J653: 713112236 Pandey Print Services Pandey Print Services10208 PROVISION FOR DOUBTFUL RECEIVABLES AND INVENTORIES : MISCELLANEOUS EXPENSES WRITTEN OFF0.4 | K653: #N/A
A654: 7133 | B654: 45790 | C654: May 2025 | D654: Journal | E654: A/2025/JV/2110837192 | F654: 11155 Ambika Print Solutions Ambika Print Solutions | G654: 10208 PROVISION FOR DOUBTFUL RECEIVABLES AND INVENTORIES : MISCELLANEOUS EXPENSES WRITTEN OFF | I654: 0.24 | J654: 713311155 Ambika Print Solutions Ambika Print Solutions10208 PROVISION FOR DOUBTFUL RECEIVABLES AND INVENTORIES : MISCELLANEOUS EXPENSES WRITTEN OFF0.24 | K654: #N/A
... A658: 7157 | B658: 45772 | C658: Apr 2025 | D658: Journal | E658: A/2025/JV/2110837194 | F658: 12468 Success Gift Solutions Success Gift Solutions | G658: Accounts Payable | I658: -0.2 | J658: 715712468 Success Gift Solutions Success Gift SolutionsAccounts Payable-0.2 | K658: #N/A
A659: 7406 | B659: 45802 | C659: May 2025 | D659: Journal | E659: A/2025/JV/2291 | F659: 1044999 Puneet Kumar | G659: 1252 LOANS, SECURITY & OTHER RECEIVABLES < 1YEAR : OTHER LOANS & ADVANCES : Advance To Employees | H659: Being On Account to Puneet Kumar for BU 7 A SB 22664 Amway BBS Multicity events. | I659: 25000 | J659: 74061044999 Puneet Kumar1252 LOANS, SECURITY & OTHER RECEIVABLES < 1YEAR : OTHER LOANS & ADVANCES : Advance To Employees25000 | K659: #N/A
A660: 7407 | B660: 45802 | C660: May 2025 | D660: Journal | E660: A/2025/JV/2292 | F660: 1044827 Abdul Rahman | G660: 1252 LOANS, SECURITY & OTHER RECEIVABLES < 1YEAR : OTHER LOANS & ADVANCES : Advance To Employees | H660: Being on Account to Abdul Rehman for BU 7 A SB 22704 HPE Aruba CXO Meetup. | I660: 30000 | J660: 74071044827 Abdul Rahman1252 LOANS, SECURITY & OTHER RECEIVABLES < 1YEAR : OTHER LOANS & ADVANCES : Advance To Employees30000 | K660: #N/A
A661: 7408 | B661: 45802 | C661: May 2025 | D661: Journal | E661: A/2025/JV/2293 | F661: 1045065 Mahendra Mane | G661: 1252 LOANS, SECURITY & OTHER RECEIVABLES < 1YEAR : OTHER LOANS & ADVANCES : Advance To Employees | H661: Being On Account to Mahendra Mane for BU 6 Pravin SB 22725 siemens PMO visit. | I661: 5000 | J661: 74081045065 Mahendra Mane1252 LOANS, SECURITY & OTHER RECEIVABLES < 1YEAR : OTHER LOANS & ADVANCES : Advance To Employees5000 | K661: #N/A
A662: 7409 | B662: 45802 | C662: May 2025 | D662: Journal | E662: A/2025/JV/2294 | F662: 1132253 Rahul Luthra | G662: 1252 LOANS, SECURITY & OTHER RECEIVABLES < 1YEAR : OTHER LOANS & ADVANCES : Advance To Employees | H662: Being On Account to Rahul Luthra for BU 7 A SB 22704 HPE Aruba CXO Meetup. | I662: 50000 | J662: 74091132253 Rahul Luthra1252 LOANS, SECURITY & OTHER RECEIVABLES < 1YEAR : OTHER LOANS & ADVANCES : Advance To Employees50000 | K662: #N/A
A663: 7410 | B663: 45802 | C663: May 2025 | D663: Journal | E663: A/2025/JV/2295 | F663: 1138054 Brijesh CL | G663: 1252 LOANS, SECURITY & OTHER RECEIVABLES < 1YEAR : OTHER LOANS & ADVANCES : Advance To Employees | H663: Being On Account to Brijesh l for BU 9 Bangalore SB 22635 Amazon BOX Installation. | I663: 5000 | J663: 74101138054 Brijesh CL1252 LOANS, SECURITY & OTHER RECEIVABLES < 1YEAR : OTHER LOANS & ADVANCES : Advance To Employees5000 | K663: #N/A
A664: 7411 | B664: 45802 | C664: May 2025 | D664: Journal | E664: A/2025/JV/2296 | F664: 1135929 Farhan Shariff | G664: 1252 LOANS, SECURITY & OTHER RECEIVABLES < 1YEAR : OTHER LOANS & ADVANCES : Advance To Employees | H664: Being On Account to Farhan Shariff for BU 9 Bangalore SB 22699 Amazon PXT Offsite. | I664: 99990 | J664: 74111135929 Farhan Shariff1252 LOANS, SECURITY & OTHER RECEIVABLES < 1YEAR : OTHER LOANS & ADVANCES : Advance To Employees99990 | K664: #N/A
A665: 7412 | B665: 45802 | C665: May 2025 | D665: Journal | E665: A/2025/JV/2297 | F665: 1143682 Ashok Raj | G665: 1252 LOANS, SECURITY & OTHER RECEIVABLES < 1YEAR : OTHER LOANS & ADVANCES : Advance To Employees | H665: Being On Account to Ashok Raj for BU 9 Bangalore SB 22711 Glance AI Launch. | I665: 86128 | J665: 74121143682 Ashok Raj1252 LOANS, SECURITY & OTHER RECEIVABLES < 1YEAR : OTHER LOANS & ADVANCES : Advance To Employees86128 | K665: #N/A
A666: 7413 | B666: 45802 | C666: May 2025 | D666: Journal | E666: A/2025/JV/2298 | F666: 1143682 Ashok Raj | G666: 1252 LOANS, SECURITY & OTHER RECEIVABLES < 1YEAR : OTHER LOANS & ADVANCES : Advance To Employees | H666: Being On Account to Ashok Raj for BU 9 Bangalore SB 22659 Amazon Day One at Work. | I666: 10000 | J666: 74131143682 Ashok Raj1252 LOANS, SECURITY & OTHER RECEIVABLES < 1YEAR : OTHER LOANS & ADVANCES : Advance To Employees10000 | K666: #N/A
A667: 7414 | B667: 45802 | C667: May 2025 | D667: Journal | E667: A/2025/JV/2299 | F667: 1138381 Naveen Mandal | G667: 1252 LOANS, SECURITY & OTHER RECEIVABLES < 1YEAR : OTHER LOANS & ADVANCES : Advance To Employees | H667: Being On Account to Naveen Mandal for BU 7 A SB 22679 Amway Artistry Serum Launch. | I667: 10000 | J667: 74141138381 Naveen Mandal1252 LOANS, SECURITY & OTHER RECEIVABLES < 1YEAR : OTHER LOANS & ADVANCES : Advance To Employees10000 | K667: #N/A
A668: 7415 | B668: 45803 | C668: May 2025 | D668: Journal | E668: A/2025/JV/2300 | F668: 1139551 Kapoor Samarth | G668: 1252 LOANS, SECURITY & OTHER RECEIVABLES < 1YEAR : OTHER LOANS & ADVANCES : Advance To Employees | H668: Being On Account to Samarth Kapoor for BU 7 A SB 22704 HPE Aruba CXO Meetup. | I668: 50000 | J668: 74151139551 Kapoor Samarth1252 LOANS, SECURITY & OTHER RECEIVABLES < 1YEAR : OTHER LOANS & ADVANCES : Advance To Employees50000 | K668: #N/A
A669: 7447 | B669: 45771 | C669: Apr 2025 | D669: Journal | E669: D/2025/JV/2110837195 | F669: 12028 M/S Inked M/S Inked | G669: 10208 PROVISION FOR DOUBTFUL RECEIVABLES AND INVENTORIES : MISCELLANEOUS EXPENSES WRITTEN OFF | I669: -0.4 | J669: 744712028 M/S Inked M/S Inked10208 PROVISION FOR DOUBTFUL RECEIVABLES AND INVENTORIES : MISCELLANEOUS EXPENSES WRITTEN OFF-0.4 | K669: #N/A
...

Sheet Customer
A1: Internal ID | B1: Internal ID | C1: Date | D1: Period | E1: Type | F1: Voucher Number | G1: Name | H1: Account | I1: Memo | J1: Amount
A2: 6546 | B2: 6546 | C2: 45748 | D2: Apr 2025 | E2: Journal | F2: D/2025/JV/2110837113 | G2: 10763 PMG Integrated Communications Pvt Ltd | H2: 10208 PROVISION FOR DOUBTFUL RECEIVABLES AND INVENTORIES : MISCELLANEOUS EXPENSES WRITTEN OFF | J2: -0.46
A3: 6546 | B3: 6546 | C3: 45748 | D3: Apr 2025 | E3: Journal | F3: D/2025/JV/2110837113 | G3: 10763 PMG Integrated Communications Pvt Ltd | H3: 10364 TRADE NOTES AND ACCOUNTS RECEIVABLE : SUNDRY DEBTORS | J3: 0.46
A4: 6549 | B4: 6549 | C4: 45750 | D4: Apr 2025 | E4: Journal | F4: A/2025/JV/2110837116 | G4: 10177 SAP India Pvt Ltd SAP India Pvt Ltd | H4: 10208 PROVISION FOR DOUBTFUL RECEIVABLES AND INVENTORIES : MISCELLANEOUS EXPENSES WRITTEN OFF | J4: 0.3
A5: 6549 | B5: 6549 | C5: 45750 | D5: Apr 2025 | E5: Journal | F5: A/2025/JV/2110837116 | G5: 10177 SAP India Pvt Ltd SAP India Pvt Ltd | H5: 10364 TRADE NOTES AND ACCOUNTS RECEIVABLE : SUNDRY DEBTORS | J5: -0.3
A6: 6550 | B6: 6550 | C6: 45750 | D6: Apr 2025 | E6: Journal | F6: A/2025/JV/2110837117 | G6: 10728 Arliga Ecoworld Infrastructure Pvt Ltd | H6: 10208 PROVISION FOR DOUBTFUL RECEIVABLES AND INVENTORIES : MISCELLANEOUS EXPENSES WRITTEN OFF | J6: 0.04
A7: 6550 | B7: 6550 | C7: 45750 | D7: Apr 2025 | E7: Journal | F7: A/2025/JV/2110837117 | G7: 10728 Arliga Ecoworld Infrastructure Pvt Ltd | H7: 10364 TRADE NOTES AND ACCOUNTS RECEIVABLE : SUNDRY DEBTORS | J7: -0.04
A8: 6551 | B8: 6551 | C8: 45750 | D8: Apr 2025 | E8: Journal | F8: A/2025/JV/2110837118 | G8: 10203 Accenture Solutions Pvt Ltd Accenture Solutions Pvt Ltd | H8: 10208 PROVISION FOR DOUBTFUL RECEIVABLES AND INVENTORIES : MISCELLANEOUS EXPENSES WRITTEN OFF | J8: -0.44
A9: 6551 | B9: 6551 | C9: 45750 | D9: Apr 2025 | E9: Journal | F9: A/2025/JV/2110837118 | G9: 10203 Accenture Solutions Pvt Ltd Accenture Solutions Pvt Ltd | H9: 10364 TRADE NOTES AND ACCOUNTS RECEIVABLE : SUNDRY DEBTORS | J9: 0.44
A10: 6552 | B10: 6552 | C10: 45750 | D10: Apr 2025 | E10: Journal | F10: A/2025/JV/2110837119 | G10: 10764 TechnoBind Solutions Pvt Ltd | H10: 10208 PROVISION FOR DOUBTFUL RECEIVABLES AND INVENTORIES : MISCELLANEOUS EXPENSES WRITTEN OFF | J10: 0.24
A11: 6552 | B11: 6552 | C11: 45750 | D11: Apr 2025 | E11: Journal | F11: A/2025/JV/2110837119 | G11: 10764 TechnoBind Solutions Pvt Ltd | H11: 10364 TRADE NOTES AND ACCOUNTS RECEIVABLE : SUNDRY DEBTORS | J11: -0.24
A12: 6553 | B12: 6553 | C12: 45751 | D12: Apr 2025 | E12: Journal | F12: A/2025/JV/2110837120 | G12: 10306 Cognizant Technology Solutions India Pvt Ltd Cognizant Technology Solutions India Pvt Ltd | H12: 10208 PROVISION FOR DOUBTFUL RECEIVABLES AND INVENTORIES : MISCELLANEOUS EXPENSES WRITTEN OFF | J12: -0.26
A13: 6553 | B13: 6553 | C13: 45751 | D13: Apr 2025 | E13: Journal | F13: A/2025/JV/2110837120 | G13: 10306 Cognizant Technology Solutions India Pvt Ltd Cognizant Technology Solutions India Pvt Ltd | H13: 10364 TRADE NOTES AND ACCOUNTS RECEIVABLE : SUNDRY DEBTORS | J13: 0.26
... A252: 12716 | B252: 12716 | C252: 45775 | D252: Apr 2025 | E252: Journal | F252: D/2025/JV/0267 | G252: 10390 Candor Gurgaon One Realty Projects Pvt Ltd | H252: Accounts Receivable | J252: -55000
A253: 12728 | B253: 12728 | C253: 45777 | D253: Apr 2025 | E253: Journal | F253: A/2025/JV/2044 | G253: 10766 Shobiz Experiential Communications Pvt Ltd-Del | H253: Accounts Receivable | I253: Being Inter office Credit Balance Transfer | J253: -8042974
A254: 12728 | B254: 12728 | C254: 45777 | D254: Apr 2025 | E254: Journal | F254: A/2025/JV/2044 | G254: 10765 Shobiz Experiential Communications Pvt Ltd-Mum | H254: Accounts Receivable | I254: Being Inter office Credit Balance Transfer | J254: -53149148
A255: 12728 | B255: 12728 | C255: 45777 | D255: Apr 2025 | E255: Journal | F255: A/2025/JV/2044 | G255: 10768 Shobiz Experiential Communications Pvt Ltd-Blr | H255: Accounts Receivable | I255: Being Inter office Credit Balance Transfer | J255: -267085
A256: 12728 | B256: 12728 | C256: 45777 | D256: Apr 2025 | E256: Journal | F256: A/2025/JV/2044 | G256: 10766 Shobiz Experiential Communications Pvt Ltd-Del | H256: Accounts Receivable | I256: Being Inter office Credit Balance Transfer | J256: -3711693
A257: 12728 | B257: 12728 | C257: 45777 | D257: Apr 2025 | E257: Journal | F257: A/2025/JV/2044 | G257: 10765 Shobiz Experiential Communications Pvt Ltd-Mum | H257: Accounts Receivable | I257: Being Inter office Credit Balance Transfer | J257: -15218340
A258: 12728 | B258: 12728 | C258: 45777 | D258: Apr 2025 | E258: Journal | F258: A/2025/JV/2044 | G258: 10768 Shobiz Experiential Communications Pvt Ltd-Blr | H258: Accounts Receivable | I258: Being Inter office Credit Balance Transfer | J258: -816497
A259: 12728 | B259: 12728 | C259: 45777 | D259: Apr 2025 | E259: Journal | F259: A/2025/JV/2044 | G259: 10767 Shobiz Experiential Communications Pvt Ltd-Che | H259: Accounts Receivable | I259: Being Inter office Credit Balance Transfer | J259: -657878
A260: 12728 | B260: 12728 | C260: 45777 | D260: Apr 2025 | E260: Journal | F260: A/2025/JV/2044 | G260: 10765 Shobiz Experiential Communications Pvt Ltd-Mum | H260: Accounts Receivable | I260: Being Inter office Credit Balance Transfer | J260: -134879985
A261: 12728 | B261: 12728 | C261: 45777 | D261: Apr 2025 | E261: Journal | F261: A/2025/JV/2044 | G261: 10768 Shobiz Experiential Communications Pvt Ltd-Blr | H261: Accounts Receivable | I261: Being Inter office Credit Balance Transfer | J261: -8947662
A262: 12728 | B262: 12728 | C262: 45777 | D262: Apr 2025 | E262: Journal | F262: A/2025/JV/2044 | G262: 10767 Shobiz Experiential Communications Pvt Ltd-Che | H262: Accounts Receivable | I262: Being Inter office Credit Balance Transfer | J262: -2023671
A263: 12728 | B263: 12728 | C263: 45777 | D263: Apr 2025 | E263: Journal | F263: A/2025/JV/2044 | G263: 10766 Shobiz Experiential Communications Pvt Ltd-Del | H263: Accounts Receivable | I263: Being Inter office Credit Balance Transfer | J263: -66994968
A264: 12779 | B264: 12779 | C264: 45748 | D264: Apr 2025 | E264: Journal | F264: A/2025/JV/1558/Rev | G264: 10264 SAP Labs India Pvt Ltd SAP Labs India Pvt Ltd | H264: Accounts Receivable | J264: -327419.86
A265: 12779 | B265: 12779 | C265: 45748 | D265: Apr 2025 | E265: Journal | F265: A/2025/JV/1558/Rev | G265: 10140 GlaxoSmithKline Consumer Pvt Ltd GlaxoSmithKline Consumer Pvt Ltd | H265: Accounts Receivable | J265: -12960
A266: 13230 | B266: 13230 | C266: 45748 | D266: Apr 2025 | E266: Journal | F266: A/2025/JV/1524/Rev | G266: 10469 Amway India Enterprises Pvt Ltd Amway India Enterprises Pvt Ltd | H266: Accounts Receivable | I266: Clients Credit Balance March 2025 | J266: -7500000
A267: 13230 | B267: 13230 | C267: 45748 | D267: Apr 2025 | E267: Journal | F267: A/2025/JV/1524/Rev | G267: 10383 Apparel Resources Pvt Ltd | H267: Accounts Receivable | I267: Clients Credit Balance March 2025 | J267: -137328
A268: 13230 | B268: 13230 | C268: 45748 | D268: Apr 2025 | E268: Journal | F268: A/2025/JV/1524/Rev | G268: 10008 Asia Pacific Travel Retail Association | H268: Accounts Receivable | I268: Clients Credit Balance March 2025 | J268: -3027125
A269: 13230 | B269: 13230 | C269: 45748 | D269: Apr 2025 | E269: Journal | F269: A/2025/JV/1524/Rev | G269: 10665 Godrej Properties Ltd | H269: Accounts Receivable | I269: Clients Credit Balance March 2025 | J269: -29087.46
A270: 13230 | B270: 13230 | C270: 45748 | D270: Apr 2025 | E270: Journal | F270: A/2025/JV/1524/Rev | G270: 10422 Loreal India Pvt Ltd | H270: Accounts Receivable | I270: Clients Credit Balance March 2025 | J270: -212400
A271: 13230 | B271: 13230 | C271: 45748 | D271: Apr 2025 | E271: Journal | F271: A/2025/JV/1524/Rev | G271: 10058 M/S RainFocus | H271: Accounts Receivable | I271: Clients Credit Balance March 2025 | J271: -124733.34
A272: 13230 | B272: 13230 | C272: 45748 | D272: Apr 2025 | E272: Journal | F272: A/2025/JV/1524/Rev | G272: 10177 SAP India Pvt Ltd SAP India Pvt Ltd | H272: Accounts Receivable | I272: Clients Credit Balance March 2025 | J272: -301478.34
A273: 13230 | B273: 13230 | C273: 45748 | D273: Apr 2025 | E273: Journal | F273: A/2025/JV/1524/Rev | G273: Suspens A/C .. Dr. | H273: Accounts Receivable | I273: Clients Credit Balance March 2025 | J273: -398012
A274: 13230 | B274: 13230 | C274: 45748 | D274: Apr 2025 | E274: Journal | F274: A/2025/JV/1524/Rev | G274: 10626 Tata Motors Passenger Vehicles Ltd Tata Motors Passenger Vehicles Ltd | H274: Accounts Receivable | I274: Clients Credit Balance March 2025 | J274: -3947130
A275: 13230 | B275: 13230 | C275: 45748 | D275: Apr 2025 | E275: Journal | F275: A/2025/JV/1524/Rev | G275: 10285 Vivo Mobile India Pvt Ltd | H275: Accounts Receivable | I275: Clients Credit Balance March 2025 | J275: -8260000
A276: 13667 | B276: 13667 | C276: 45761 | D276: Apr 2025 | E276: Journal | F276: B/2025/JV/2110837539 | G276: 10221 Dbs Bank India Ltd | H276: 10208 PROVISION FOR DOUBTFUL RECEIVABLES AND INVENTORIES : MISCELLANEOUS EXPENSES WRITTEN OFF | J276: -0.14
A277: 13667 | B277: 13667 | C277: 45761 | D277: Apr 2025 | E277: Journal | F277: B/2025/JV/2110837539 | G277: 10221 Dbs Bank India Ltd | H277: 10364 TRADE NOTES AND ACCOUNTS RECEIVABLE : SUNDRY DEBTORS | J277: 0.14
A278: 13730 | B278: 13730 | C278: 45748 | D278: Apr 2025 | E278: Journal | F278: A/2025/JV/1522/Rev | G278: 10766 Shobiz Experiential Communications Pvt Ltd-Del | H278: Accounts Receivable | I278: Being Inter office Credit Balance Transfer | J278: 5098440
A279: 13730 | B279: 13730 | C279: 45748 | D279: Apr 2025 | E279: Journal | F279: A/2025/JV/1522/Rev | G279: 10765 Shobiz Experiential Communications Pvt Ltd-Mum | H279: Accounts Receivable | I279: Being Inter office Credit Balance Transfer | J279: 18091845
A280: 13730 | B280: 13730 | C280: 45748 | D280: Apr 2025 | E280: Journal | F280: A/2025/JV/1522/Rev | G280: 10768 Shobiz Experiential Communications Pvt Ltd-Blr | H280: Accounts Receivable | I280: Being Inter office Credit Balance Transfer | J280: 49764
A281: 13730 | B281: 13730 | C281: 45748 | D281: Apr 2025 | E281: Journal | F281: A/2025/JV/1522/Rev | G281: 10766 Shobiz Experiential Communications Pvt Ltd-Del | H281: Accounts Receivable | I281: Being Inter office Credit Balance Transfer | J281: 2558388
A282: 13730 | B282: 13730 | C282: 45748 | D282: Apr 2025 | E282: Journal | F282: A/2025/JV/1522/Rev | G282: 10765 Shobiz Experiential Communications Pvt Ltd-Mum | H282: Accounts Receivable | I282: Being Inter office Credit Balance Transfer | J282: 3485111
A283: 13730 | B283: 13730 | C283: 45748 | D283: Apr 2025 | E283: Journal | F283: A/2025/JV/1522/Rev | G283: 10765 Shobiz Experiential Communications Pvt Ltd-Mum | H283: Accounts Receivable | I283: Being Inter office Credit Balance Transfer | J283: 64534902
A284: 13730 | B284: 13730 | C284: 45748 | D284: Apr 2025 | E284: Journal | F284: A/2025/JV/1522/Rev | G284: 10768 Shobiz Experiential Communications Pvt Ltd-Blr | H284: Accounts Receivable | I284: Being Inter office Credit Balance Transfer | J284: 6474557
A285: 13730 | B285: 13730 | C285: 45748 | D285: Apr 2025 | E285: Journal | F285: A/2025/JV/1522/Rev | G285: 10767 Shobiz Experiential Communications Pvt Ltd-Che | H285: Accounts Receivable | I285: Being Inter office Credit Balance Transfer | J285: 2023671
A286: 13730 | B286: 13730 | C286: 45748 | D286: Apr 2025 | E286: Journal | F286: A/2025/JV/1522/Rev | G286: 10766 Shobiz Experiential Communications Pvt Ltd-Del | H286: Accounts Receivable | I286: Being Inter office Credit Balance Transfer | J286: 48783686
A287: 13948 | B287: 13948 | C287: 45786 | D287: May 2025 | E287: Journal | F287: C/2025/JV/2110837571 | G287: 10306 Cognizant Technology Solutions India Pvt Ltd Cognizant Technology Solutions India Pvt Ltd | H287: 10208 PROVISION FOR DOUBTFUL RECEIVABLES AND INVENTORIES : MISCELLANEOUS EXPENSES WRITTEN OFF | J287: -0.2
A288: 13948 | B288: 13948 | C288: 45786 | D288: May 2025 | E288: Journal | F288: C/2025/JV/2110837571 | G288: 10306 Cognizant Technology Solutions India Pvt Ltd Cognizant Technology Solutions India Pvt Ltd | H288: Accounts Receivable | J288: 0.2
A289: 13964 | B289: 13964 | C289: 45788 | D289: May 2025 | E289: Journal | F289: A/2025/JV/2110837572 | G289: 10412 Hindustan Unilever Ltd | H289: 10208 PROVISION FOR DOUBTFUL RECEIVABLES AND INVENTORIES : MISCELLANEOUS EXPENSES WRITTEN OFF | J289: -0.23
A290: 13964 | B290: 13964 | C290: 45788 | D290: May 2025 | E290: Journal | F290: A/2025/JV/2110837572 | G290: 10412 Hindustan Unilever Ltd | H290: Accounts Receivable | J290: 0.23
A291: 13966 | B291: 13966 | C291: 45788 | D291: May 2025 | E291: Journal | F291: A/2025/JV/2110837573 | G291: 10412 Hindustan Unilever Ltd | H291: 10208 PROVISION FOR DOUBTFUL RECEIVABLES AND INVENTORIES : MISCELLANEOUS EXPENSES WRITTEN OFF | J291: -0.26
A292: 13966 | B292: 13966 | C292: 45788 | D292: May 2025 | E292: Journal | F292: A/2025/JV/2110837573 | G292: 10412 Hindustan Unilever Ltd | H292: Accounts Receivable | J292: 0.26
A293: 13968 | B293: 13968 | C293: 45788 | D293: May 2025 | E293: Journal | F293: A/2025/JV/2110837574 | G293: 10181 Siemens Ltd | H293: 10208 PROVISION FOR DOUBTFUL RECEIVABLES AND INVENTORIES : MISCELLANEOUS EXPENSES WRITTEN OFF | J293: 0.1
A294: 13968 | B294: 13968 | C294: 45788 | D294: May 2025 | E294: Journal | F294: A/2025/JV/2110837574 | G294: 10181 Siemens Ltd | H294: Accounts Receivable | J294: -0.1
A295: 13974 | B295: 13974 | C295: 45790 | D295: May 2025 | E295: Journal | F295: A/2025/JV/2110837575 | G295: 10642 Amazon Seller Services India Pvt Ltd | H295: 10208 PROVISION FOR DOUBTFUL RECEIVABLES AND INVENTORIES : MISCELLANEOUS EXPENSES WRITTEN OFF | J295: 0.2
A296: 13974 | B296: 13974 | C296: 45790 | D296: May 2025 | E296: Journal | F296: A/2025/JV/2110837575 | G296: 10642 Amazon Seller Services India Pvt Ltd | H296: Accounts Receivable | J296: -0.2
A297: 14318 | B297: 14318 | C297: 45790 | D297: May 2025 | E297: Journal | F297: A/2025/JV/2110837594 | G297: 10648 BP Exploration Alpha Ltd | H297: 10208 PROVISION FOR DOUBTFUL RECEIVABLES AND INVENTORIES : MISCELLANEOUS EXPENSES WRITTEN OFF | J297: 0.1
A298: 14318 | B298: 14318 | C298: 45790 | D298: May 2025 | E298: Journal | F298: A/2025/JV/2110837594 | G298: 10648 BP Exploration Alpha Ltd | H298: Accounts Receivable | J298: -0.1
... A424: 20975 | B424: 20975 | C424: 45768 | D424: Apr 2025 | E424: Journal | F424: A/2025/CN/0038 | G424: 10046 Lightspeed India Partners Advisors LLP Lightspeed India Partners Advisors LLP | H424: 10364 TRADE NOTES AND ACCOUNTS RECEIVABLE : SUNDRY DEBTORS | J424: -0.2
A425: 20976 | B425: 20976 | C425: 45808 | D425: May 2025 | E425: Journal | F425: A/2025/JV/2462 | G425: 10768 Shobiz Experiential Communications Pvt Ltd-Blr | H425: Accounts Receivable | I425: Being Inter office Credit Balance Transfer | J425: -147648
A426: 20976 | B426: 20976 | C426: 45808 | D426: May 2025 | E426: Journal | F426: A/2025/JV/2462 | G426: 10768 Shobiz Experiential Communications Pvt Ltd-Blr | H426: Accounts Receivable | I426: Being Inter office Credit Balance Transfer | J426: -2051624
A427: 20976 | B427: 20976 | C427: 45808 | D427: May 2025 | E427: Journal | F427: A/2025/JV/2462 | G427: 10767 Shobiz Experiential Communications Pvt Ltd-Che | H427: Accounts Receivable | I427: Being Inter office Credit Balance Transfer | J427: -22066
A428: 20976 | B428: 20976 | C428: 45808 | D428: May 2025 | E428: Journal | F428: A/2025/JV/2462 | G428: 10767 Shobiz Experiential Communications Pvt Ltd-Che | H428: Accounts Receivable | I428: Being Inter office Credit Balance Transfer | J428: -394203
A429: 20976 | B429: 20976 | C429: 45808 | D429: May 2025 | E429: Journal | F429: A/2025/JV/2462 | G429: 10767 Shobiz Experiential Communications Pvt Ltd-Che | H429: Accounts Receivable | I429: Being Inter office Credit Balance Transfer | J429: -201190
A430: 20976 | B430: 20976 | C430: 45808 | D430: May 2025 | E430: Journal | F430: A/2025/JV/2462 | G430: 10766 Shobiz Experiential Communications Pvt Ltd-Del | H430: Accounts Receivable | I430: Being Inter office Credit Balance Transfer | J430: -603479
A431: 20976 | B431: 20976 | C431: 45808 | D431: May 2025 | E431: Journal | F431: A/2025/JV/2462 | G431: 10766 Shobiz Experiential Communications Pvt Ltd-Del | H431: Accounts Receivable | I431: Being Inter office Credit Balance Transfer | J431: -719741
A432: 20976 | B432: 20976 | C432: 45808 | D432: May 2025 | E432: Journal | F432: A/2025/JV/2462 | G432: 10766 Shobiz Experiential Communications Pvt Ltd-Del | H432: Accounts Receivable | I432: Being Inter office Credit Balance Transfer | J432: -13339180
A433: 20976 | B433: 20976 | C433: 45808 | D433: May 2025 | E433: Journal | F433: A/2025/JV/2462 | G433: 10765 Shobiz Experiential Communications Pvt Ltd-Mum | H433: Accounts Receivable | I433: Being Inter office Credit Balance Transfer | J433: -17417122
A434: 20976 | B434: 20976 | C434: 45808 | D434: May 2025 | E434: Journal | F434: A/2025/JV/2462 | G434: 10765 Shobiz Experiential Communications Pvt Ltd-Mum | H434: Accounts Receivable | I434: Being Inter office Credit Balance Transfer | J434: -7742331
A435: 20976 | B435: 20976 | C435: 45808 | D435: May 2025 | E435: Journal | F435: A/2025/JV/2462 | G435: 10765 Shobiz Experiential Communications Pvt Ltd-Mum | H435: Accounts Receivable | I435: Being Inter office Credit Balance Transfer | J435: -46557321
A436: 21579 | B436: 21579 | C436: 45805 | D436: May 2025 | E436: Journal | F436: A/2025/JV/2110838027 | G436: 10181 Siemens Ltd | H436: 10208 PROVISION FOR DOUBTFUL RECEIVABLES AND INVENTORIES : MISCELLANEOUS EXPENSES WRITTEN OFF | J436: 0.21
A437: 21579 | B437: 21579 | C437: 45805 | D437: May 2025 | E437: Journal | F437: A/2025/JV/2110838027 | G437: 10181 Siemens Ltd | H437: Accounts Receivable | J437: -0.21
A438: 21598 | B438: 21598 | C438: 45779 | D438: May 2025 | E438: Journal | F438: B/2025/JV/2110838028 | G438: 10203 Accenture Solutions Pvt Ltd Accenture Solutions Pvt Ltd | H438: 10208 PROVISION FOR DOUBTFUL RECEIVABLES AND INVENTORIES : MISCELLANEOUS EXPENSES WRITTEN OFF | J438: 0.25
A439: 21598 | B439: 21598 | C439: 45779 | D439: May 2025 | E439: Journal | F439: B/2025/JV/2110838028 | G439: 10203 Accenture Solutions Pvt Ltd Accenture Solutions Pvt Ltd | H439: Accounts Receivable | J439: -0.25
A440: 21600 | B440: 21600 | C440: 45786 | D440: May 2025 | E440: Journal | F440: B/2025/JV/2110838029 | G440: 10324 IKEA India Pvt Ltd IKEA India Pvt Ltd | H440: 10208 PROVISION FOR DOUBTFUL RECEIVABLES AND INVENTORIES : MISCELLANEOUS EXPENSES WRITTEN OFF | J440: 0.4
A441: 21600 | B441: 21600 | C441: 45786 | D441: May 2025 | E441: Journal | F441: B/2025/JV/2110838029 | G441: 10324 IKEA India Pvt Ltd IKEA India Pvt Ltd | H441: Accounts Receivable | J441: -0.4
A442: 21602 | B442: 21602 | C442: 45798 | D442: May 2025 | E442: Journal | F442: B/2025/JV/2110838030 | G442: 10451 Takasago International India Pvt Ltd | H442: 10208 PROVISION FOR DOUBTFUL RECEIVABLES AND INVENTORIES : MISCELLANEOUS EXPENSES WRITTEN OFF | J442: -0.2
A443: 21602 | B443: 21602 | C443: 45798 | D443: May 2025 | E443: Journal | F443: B/2025/JV/2110838030 | G443: 10451 Takasago International India Pvt Ltd | H443: Accounts Receivable | J443: 0.2
A444: 21604 | B444: 21604 | C444: 45804 | D444: May 2025 | E444: Journal | F444: B/2025/JV/2110838031 | G444: 10049 Megagrow Business Solutions LLP | H444: 10208 PROVISION FOR DOUBTFUL RECEIVABLES AND INVENTORIES : MISCELLANEOUS EXPENSES WRITTEN OFF | J444: 0.24
A445: 21604 | B445: 21604 | C445: 45804 | D445: May 2025 | E445: Journal | F445: B/2025/JV/2110838031 | G445: 10049 Megagrow Business Solutions LLP | H445: Accounts Receivable | J445: -0.24
A446: 21606 | B446: 21606 | C446: 45806 | D446: May 2025 | E446: Journal | F446: A/2025/JV/2110838032 | G446: 10221 Dbs Bank India Ltd | H446: 10208 PROVISION FOR DOUBTFUL RECEIVABLES AND INVENTORIES : MISCELLANEOUS EXPENSES WRITTEN OFF | J446: 0.2
A447: 21606 | B447: 21606 | C447: 45806 | D447: May 2025 | E447: Journal | F447: A/2025/JV/2110838032 | G447: 10221 Dbs Bank India Ltd | H447: Accounts Receivable | J447: -0.2
... A539: 40851 | B539: 40851 | C539: 45750 | D539: Apr 2025 | E539: Journal | F539: C/2025/JV/2110839429 | G539: 10297 Astrazeneca India Pvt Ltd | H539: 10364 TRADE NOTES AND ACCOUNTS RECEIVABLE : SUNDRY DEBTORS | J539: 0.04

Sheet Vendor
A1: Internal ID | B1: Internal ID | C1: Date | D1: Period | E1: Type | F1: Voucher Number | G1: Name | H1: Account | I1: Memo | J1: Amount
A2: 4058 | B2: 4058 | C2: 45791 | D2: May 2025 | E2: Journal | F2: A/2025/JV/2166 | G2: 10112 Airtel Ltd(Bill Booking) Airtel Ltd(Bill Booking) | H2: 10530 ACCOUNTS PAYABLE : ACCOUNTS PAYABLE | I2: Being Airtel dongle Monthly Bill NO 7304905026/7304901565.7304901765/9004847183/9004813950/9987154590/8433940473 dated 7/5/2025. | J2: -7189.74
A3: 4697 | B3: 4697 | C3: 45748 | D3: Apr 2025 | E3: Journal | F3: A/2025/JV/1515/Rev | G3: 13128 Credit Card Dues (MIS) Credit Card Dues (MIS) | H3: Accounts Payable | J3: -26496206
A4: 4784 | B4: 4784 | C4: 45777 | D4: Apr 2025 | E4: Journal | F4: A/2025/JV/2032 | G4: 13128 Credit Card Dues (MIS) Credit Card Dues (MIS) | H4: Accounts Payable | J4: 23042960
A5: 6534 | B5: 6534 | C5: 45751 | D5: Apr 2025 | E5: Journal | F5: A/2025/JV/2110837101 | G5: 11508 Bisleri International Pvt Ltd Bisleri International Pvt Ltd | H5: 10208 PROVISION FOR DOUBTFUL RECEIVABLES AND INVENTORIES : MISCELLANEOUS EXPENSES WRITTEN OFF | J5: -0.01
A6: 6534 | B6: 6534 | C6: 45751 | D6: Apr 2025 | E6: Journal | F6: A/2025/JV/2110837101 | G6: 11508 Bisleri International Pvt Ltd Bisleri International Pvt Ltd | H6: Accounts Payable | J6: -0.01
A7: 6535 | B7: 6535 | C7: 45751 | D7: Apr 2025 | E7: Journal | F7: A/2025/JV/2110837102 | G7: 12840 Shah Jaju & Associates Shah Jaju & Associates | H7: 10208 PROVISION FOR DOUBTFUL RECEIVABLES AND INVENTORIES : MISCELLANEOUS EXPENSES WRITTEN OFF | J7: 0.16
A8: 6535 | B8: 6535 | C8: 45751 | D8: Apr 2025 | E8: Journal | F8: A/2025/JV/2110837102 | G8: 12840 Shah Jaju & Associates Shah Jaju & Associates | H8: Accounts Payable | J8: 0.16
A9: 6536 | B9: 6536 | C9: 45752 | D9: Apr 2025 | E9: Journal | F9: A/2025/JV/2110837103 | G9: 12067 Jyoti Fire Services Jyoti Fire Services | H9: 10208 PROVISION FOR DOUBTFUL RECEIVABLES AND INVENTORIES : MISCELLANEOUS EXPENSES WRITTEN OFF | J9: 0.2
A10: 6536 | B10: 6536 | C10: 45752 | D10: Apr 2025 | E10: Journal | F10: A/2025/JV/2110837103 | G10: 12067 Jyoti Fire Services Jyoti Fire Services | H10: Accounts Payable | J10: 0.2
A11: 6537 | B11: 6537 | C11: 45755 | D11: Apr 2025 | E11: Journal | F11: A/2025/JV/2110837104 | G11: 12422 Sneha Hospitality Services Pvt Ltd Sneha Hospitality Services Pvt Ltd | H11: 10208 PROVISION FOR DOUBTFUL RECEIVABLES AND INVENTORIES : MISCELLANEOUS EXPENSES WRITTEN OFF | J11: 0.1
A12: 6537 | B12: 6537 | C12: 45755 | D12: Apr 2025 | E12: Journal | F12: A/2025/JV/2110837104 | G12: 12422 Sneha Hospitality Services Pvt Ltd Sneha Hospitality Services Pvt Ltd | H12: Accounts Payable | J12: 0.1
